Workbook

Sheet Main Center
AF2: Summary Table
D4: Year 00 | E4: Year 01 | F4: Year 02 | G4: Year 03 | H4: Year 04 | I4: Year 05 | J4: Year 06 | K4: Year 07 | L4: Year 08 | M4: Year 09 | N4: Year 10 | O4: Year 11 | P4: Year 12 | Q4: Year 13 | R4: Year 14 | S4: Year 15 | T4: Year 16 | U4: Year 17 | V4: Year 18 | W4: Year 19 | X4: Year 20 | AE4: Year 00 - Year 05 | AF4: Year 06 - Year 10 | AG4: Year 11 - Year 15 | AH4: Year 16 - Year 20
A5: Assumptions
A6: Number of Centers | D6: 1 | AD6: Sales | AE6: =SUM(D23:I23) -> 33003.496 | AF6: =SUM(J23:N23) -> 71306.604 | AG6: =SUM(O23:S23) -> 124220.5 | AH6: =SUM(T23:X23) -> 172839.27
A7: Costs of Center Setup (Investment) | B7: Gross Profit (USD) | D7: =2000000/D13 -> 14814.815 | AD7: Revenue | AE7: =SUM(D28:I28) -> 19.395702 | AF7: =SUM(J28:N28) -> 61.466229 | AG7: =SUM(O28:S28) -> 156.95018 | AH7: =SUM(T28:X28) -> 322.88972
A8: Sales Volumes | E8: 4435 | AD8: Expenses | AE8: =SUM(D30:I30) -> 15.516561 | AF8: =SUM(J30:N30) -> 49.172983 | AG8: =SUM(O30:S30) -> 125.56015 | AH8: =SUM(T30:X30) -> 258.31177
A9: Sales Growth | C9: 0.1 | E9: 0.2 | F9: =E9 -> 0.2 | G9: =F9 -> 0.2 | H9: =G9 -> 0.2 | I9: =H9 -> 0.2 | J9: 0.15 | K9: =J9 -> 0.15 | L9: =K9 -> 0.15 | M9: =L9 -> 0.15 | N9: =M9 -> 0.15 | O9: 0.1 | P9: =O9 -> 0.1 | Q9: =P9 -> 0.1 | R9: =Q9 -> 0.1 | S9: =R9 -> 0.1 | T9: 0.05 | U9: =T9 -> 0.05 | V9: =U9 -> 0.05 | W9: =V9 -> 0.05 | X9: =W9 -> 0.05 | AD9: EBITDA | AE9: =SUM(D43:I43) -> -25.48329 | AF9: =SUM(J43:N43) -> -18.22336 | AG9: =SUM(O43:S43) -> 13.683013 | AH9: =SUM(T43:X43) -> 77.7606
A10: Price Increase | E10: 0.16 | F10: 0.086687643 | G10: 0.087072291 | H10: 0.090769398 | I10: 0.078758145 | J10: 0.07905988 | K10: 0.079373414 | L10: 0.079699048 | M10: 0.080037074 | N10: 0.080387773 | O10: 0.080751414 | P10: 0.08112825 | Q10: 0.081518518 | R10: 0.081922436 | S10: 0.082340198 | T10: 0.082771977 | U10: 0.083217919 | V10: 0.08367814 | W10: 0.084152725 | X10: 0.084641726 | AD10: Net Profit/Loss | AE10: =SUM(D51:I51) -> -27.48329 | AF10: =SUM(J51:N51) -> -18.22336 | AG10: =SUM(O51:S51) -> 13.683013 | AH10: =SUM(T51:X51) -> 77.7606
A11: Salary Increase | E11: 0.16 | F11: 0.1 | G11: 0.1 | H11: 0.11 | I11: 0.07 | J11: 0.07 | K11: 0.07 | L11: 0.07 | M11: 0.07 | N11: 0.07 | O11: 0.07 | P11: 0.07 | Q11: 0.07 | R11: 0.07 | S11: 0.07 | T11: 0.07 | U11: 0.07 | V11: 0.07 | W11: 0.07 | X11: 0.07
A12: Local Inflation | E12: 0.16 | F12: 0.07 | G12: 0.07 | H12: 0.07 | I12: 0.07 | J12: 0.07 | K12: 0.07 | L12: 0.07 | M12: 0.07 | N12: 0.07 | O12: 0.07 | P12: 0.07 | Q12: 0.07 | R12: 0.07 | S12: 0.07 | T12: 0.07 | U12: 0.07 | V12: 0.07 | W12: 0.07 | X12: 0.07
A13: Re. / $ Parity | D13: 135 | E13: 141.75 | F13: 148.8375 | G13: 156.27938 | H13: 164.09334 | I13: 172.29801 | J13: 180.91291 | K13: 189.95856 | L13: 199.45648 | M13: 209.42931 | N13: 219.90077 | O13: 230.89581 | P13: 242.4406 | Q13: 254.56263 | R13: 267.29077 | S13: 280.6553 | T13: 294.68807 | U13: 309.42247 | V13: 324.8936 | W13: 341.13828 | X13: 358.19519
A14: Rent Inflation | E14: 0.1 | F14: =E14 -> 0.1 | G14: =F14 -> 0.1 | H14: =G14 -> 0.1 | I14: =H14 -> 0.1 | J14: =I14 -> 0.1 | K14: =J14 -> 0.1 | L14: =K14 -> 0.1 | M14: =L14 -> 0.1 | ... X14: =W14 -> 0.1
A15: Reagents/Consumables Inflation | E15: 0.09889959 | F15: 0.075175 | G15: 0.075175 | H15: 0.075175 | I15: 0.075175 | J15: 0.075175 | K15: 0.075175 | L15: 0.075175 | M15: 0.075175 | N15: 0.075175 | O15: 0.075175 | P15: 0.075175 | Q15: 0.075175 | R15: 0.075175 | S15: 0.075175 | T15: 0.075175 | U15: 0.075175 | V15: 0.075175 | W15: 0.075175 | X15: 0.075175
A16: Number of FTEs | C16: =COUNT('Staff Costs'!C4:C10) -> 7 | E16: =$C$16*$D$6 -> 7 | F16: =$C$16*$D$6 -> 7 | G16: =$C$16*$D$6 -> 7 | H16: =$C$16*$D$6 -> 7 | I16: =$C$16*$D$6 -> 7 | J16: =$C$16*$D$6 -> 7 | K16: =$C$16*$D$6 -> 7 | L16: =$C$16*$D$6 -> 7 | ... X16: =$C$16*$D$6 -> 7
A17: Salary including Fringe | C17: ='Staff Costs'!D11/1.1/C16 -> 28607.143 | E17: =C17*(1+E11) -> 33184.286 | F17: =E17*(1+F11) -> 36502.714 | G17: =F17*(1+G11) -> 40152.986 | H17: =G17*(1+H11) -> 44569.814 | I17: =H17*(1+I11) -> 47689.701 | J17: =I17*(1+J11) -> 51027.98 | K17: =J17*(1+K11) -> 54599.939 | L17: =K17*(1+L11) -> 58421.935 | M17: =L17*(1+M11) -> 62511.47 | ... X17: =W17*(1+X11) -> 131577.39
A18: =A36 -> Supplies | B18: Supplies | C18: =SUMIF('Overhead Costs'!$B$3:$B$14,'Main Center'!B18,'Overhead Costs'!$C$3:$C$14) -> 31660 | E18: =C18*(1+E12) -> 36725.6 | F18: =E18*(1+F12) -> 39296.392 | G18: =F18*(1+G12) -> 42047.139 | H18: =G18*(1+H12) -> 44990.439 | I18: =H18*(1+I12) -> 48139.77 | J18: =I18*(1+J12) -> 51509.554 | K18: =J18*(1+K12) -> 55115.223 | L18: =K18*(1+L12) -> 58973.288 | M18: =L18*(1+M12) -> 63101.418 | ... X18: =W18*(1+X12) -> 132819.14
A19: =A37 -> Utilities | B19: Utilities | C19: =SUMIF('Overhead Costs'!$B$3:$B$14,'Main Center'!B19,'Overhead Costs'!$C$3:$C$14) -> 29370 | E19: =C19*(1+E12) -> 34069.2 | F19: =E19*(1+F12) -> 36454.044 | G19: =F19*(1+G12) -> 39005.827 | H19: =G19*(1+H12) -> 41736.235 | I19: =H19*(1+I12) -> 44657.771 | J19: =I19*(1+J12) -> 47783.815 | K19: =J19*(1+K12) -> 51128.683 | L19: =K19*(1+L12) -> 54707.69 | M19: =L19*(1+M12) -> 58537.229 | ... X19: =W19*(1+X12) -> 123212.2
A20: SG&A | B20: SG&A | C20: ='Overhead Costs'!C15-'Main Center'!C19-'Main Center'!C18 -> 171995 | E20: =C20*(((1+E14)+(1+E12))/2) -> 194354.35 | F20: =E20*(((1+F14)+(1+F12))/2) -> 210874.47 | G20: =F20*(((1+G14)+(1+G12))/2) -> 228798.8 | H20: =G20*(((1+H14)+(1+H12))/2) -> 248246.7 | I20: =H20*(((1+I14)+(1+I12))/2) -> 269347.67 | J20: =I20*(((1+J14)+(1+J12))/2) -> 292242.22 | K20: =J20*(((1+K14)+(1+K12))/2) -> 317082.81 | L20: =K20*(((1+L14)+(1+L12))/2) -> 344034.85 | M20: =L20*(((1+M14)+(1+M12))/2) -> 373277.81 | ... X20: =W20*(((1+X14)+(1+X12))/2) -> 915712.81
B21: =C21-'Overhead Costs'!C15 -> 0 | C21: =SUM(C18:C20) -> 233025
A22: Stats
A23: Volumes | B23: Laboratory Volumes (`000) | E23: =E8*D6 -> 4435 | F23: =E23*(1+F9) -> 5322 | G23: =F23*(1+G9) -> 6386.4 | H23: =G23*(1+H9) -> 7663.68 | I23: =H23*(1+I9) -> 9196.416 | J23: =I23*(1+J9) -> 10575.878 | K23: =J23*(1+K9) -> 12162.26 | L23: =K23*(1+L9) -> 13986.599 | M23: =L23*(1+M9) -> 16084.589 | ... X23: =W23*(1+X9) -> 38020.492
A24: Average Charge | C24: =Average_charge_3_Main_centers!B9 -> 413.65962 | E24: =C24*(1+E10) -> 479.84516 | F24: =E24*(1+F10) -> 521.44181 | G24: =F24*(1+G10) -> 566.84494 | H24: =G24*(1+H10) -> 618.29711 | I24: =H24*(1+I10) -> 666.99304 | J24: =I24*(1+J10) -> 719.72543 | K24: =J24*(1+K10) -> 776.8525 | L24: =K24*(1+L10) -> 838.7669 | M24: =L24*(1+M10) -> 905.89935 | ... X24: =W24*(1+X10) -> 2164.6438
A27: Financials | C27: 1
A28: Gross Revenue | B28: Outpatient | E28: =E24*E23/1000000 -> 2.1281133 | F28: =F24*F23/1000000 -> 2.7751133 | G28: =G24*G23/1000000 -> 3.6200985 | H28: =H24*H23/1000000 -> 4.7384312 | I28: =I24*I23/1000000 -> 6.1339455 | J28: =J24*J23/1000000 -> 7.6117287 | K28: =K24*K23/1000000 -> 9.4482822 | L28: =L24*L23/1000000 -> 11.731496 | ... X28: =X24*X23/1000000 -> 82.300822
A29: Discount/Referral Incentive | B29: Discounts | C29: -0.2 | E29: =$C$29*E28 -> -0.42562266 | F29: =$C$29*F28 -> -0.55502266 | G29: =$C$29*G28 -> -0.7240197 | H29: =$C$29*H28 -> -0.94768624 | I29: =$C$29*I28 -> -1.2267891 | J29: =$C$29*J28 -> -1.5223457 | K29: =$C$29*K28 -> -1.8896564 | L29: =$C$29*L28 -> -2.3462993 | ... X29: =$C$29*X28 -> -16.460164
A30: Net Revenue | D30: =SUM(D28:D29) -> 0 | E30: =SUM(E28:E29) -> 1.7024906 | F30: =SUM(F28:F29) -> 2.2200906 | G30: =SUM(G28:G29) -> 2.8960788 | H30: =SUM(H28:H29) -> 3.790745 | I30: =SUM(I28:I29) -> 4.9071564 | J30: =SUM(J28:J29) -> 6.0893829 | K30: =SUM(K28:K29) -> 7.5586258 | ... X30: =SUM(X28:X29) -> 65.840658
A32: Expenses
A34: Staff Cost | B34: Staff | E34: =E17*E16*12/1000000 -> 2.78748 | F34: =F17*F16*12/1000000 -> 3.066228 | G34: =G17*G16*12/1000000 -> 3.3728508 | H34: =H17*H16*12/1000000 -> 3.7438644 | I34: =I17*I16*12/1000000 -> 4.0059349 | J34: =J17*J16*12/1000000 -> 4.2863503 | K34: =K17*K16*12/1000000 -> 4.5863949 | L34: =L17*L16*12/1000000 -> 4.9074425 | ... X34: =X17*X16*12/1000000 -> 11.052501
A35: Reagents/Consumables | B35: Reagents/Consumables | C35: =Reagent_Costing!BK39 -> 0.23000483 | E35: =$C$35*E28 -> 0.48947634 | F35: =E35*(1+F9)*(1+F15) -> 0.63152726 | G35: =F35*(1+G9)*(1+G15) -> 0.81480279 | H35: =G35*(1+H9)*(1+H15) -> 1.0512667 | I35: =H35*(1+I9)*(1+I15) -> 1.3563548 | J35: =I35*(1+J9)*(1+J15) -> 1.6770666 | K35: =J35*(1+K9)*(1+K15) -> 2.0736111 | L35: =K35*(1+L9)*(1+L15) -> 2.563919 | M35: =L35*(1+M9)*(1+M15) -> 3.1701609 | ... X35: =W35*(1+X9)*(1+X15) -> 16.632587
A36: Supplies | B36: Supplies | E36: =E18*$D$6/1000000*12 -> 0.4407072 | F36: =F18*$D$6/1000000*12 -> 0.4715567 | G36: =G18*$D$6/1000000*12 -> 0.50456567 | H36: =H18*$D$6/1000000*12 -> 0.53988527 | I36: =I18*$D$6/1000000*12 -> 0.57767724 | J36: =J18*$D$6/1000000*12 -> 0.61811465 | K36: =K18*$D$6/1000000*12 -> 0.66138267 | L36: =L18*$D$6/1000000*12 -> 0.70767946 | ... X36: =X18*$D$6/1000000*12 -> 1.5938297
A37: Utilities | B37: Utilities | E37: =E19*$D$6/1000000*12 -> 0.4088304 | F37: =F19*$D$6/1000000*12 -> 0.43744853 | G37: =G19*$D$6/1000000*12 -> 0.46806992 | H37: =H19*$D$6/1000000*12 -> 0.50083482 | I37: =I19*$D$6/1000000*12 -> 0.53589326 | J37: =J19*$D$6/1000000*12 -> 0.57340579 | K37: =K19*$D$6/1000000*12 -> 0.61354419 | L37: =L19*$D$6/1000000*12 -> 0.65649228 | ... X37: =X19*$D$6/1000000*12 -> 1.4785464
A38: SG&A | B38: General / Administration | E38: =(E20*$D$6/1000000*12) -> 2.3322522 | F38: =(F20*$D$6/1000000*12) -> 2.5304936 | G38: =(G20*$D$6/1000000*12) -> 2.7455856 | H38: =(H20*$D$6/1000000*12) -> 2.9789604 | I38: =(I20*$D$6/1000000*12) -> 3.232172 | J38: =(J20*$D$6/1000000*12) -> 3.5069066 | K38: =(K20*$D$6/1000000*12) -> 3.8049937 | L38: =(L20*$D$6/1000000*12) -> 4.1284182 | ... X38: =(X20*$D$6/1000000*12) -> 10.988554
A39: Central Support | B39: Central Support Services Costs | E39: =(('Central _support'!D10/1000000))/31 -> 0.13583923 | F39: =E39*(1+F12) -> 0.14534797 | G39: =F39*(1+G12) -> 0.15552233 | H39: =G39*(1+H12) -> 0.16640889 | I39: =H39*(1+I12) -> 0.17805752 | J39: =I39*(1+J12) -> 0.19052154 | K39: =J39*(1+K12) -> 0.20385805 | L39: =K39*(1+L12) -> 0.21812811 | M39: =L39*(1+M12) -> 0.23339708 | ... X39: =W39*(1+X12) -> 0.4912663
A40: Marketing | B40: General / Administration | C40: =1% -> 0.01 | E40: =+($C$40*E28) -> 0.021281133 | F40: =+($C$40*F28) -> 0.027751133 | G40: =+($C$40*G28) -> 0.036200985 | H40: =+($C$40*H28) -> 0.047384312 | I40: =+($C$40*I28) -> 0.061339455 | J40: =+($C$40*J28) -> 0.076117287 | K40: =+($C$40*K28) -> 0.094482822 | L40: =+($C$40*L28) -> 0.11731496 | ... X40: =+($C$40*X28) -> 0.82300822
A41: Total Expenses | D41: =SUM(D34:D40) -> 0 | E41: =SUM(E34:E40) -> 6.6158665 | F41: =SUM(F34:F40) -> 7.3103532 | G41: =SUM(G34:G40) -> 8.0975981 | H41: =SUM(H34:H40) -> 9.0286048 | I41: =SUM(I34:I40) -> 9.9474292 | J41: =SUM(J34:J40) -> 10.928483 | K41: =SUM(K34:K40) -> 12.038267 | ... X41: =SUM(X34:X40) -> 43.060292
A43: Earning / (Deficit) before Interest & Depreciation | C43: Rs. | D43: =D30-D41 -> 0 | E43: =E30-E41 -> -4.9133759 | F43: =F30-F41 -> -5.0902626 | G43: =G30-G41 -> -5.2015193 | H43: =H30-H41 -> -5.2378598 | I43: =I30-I41 -> -5.0402728 | J43: =J30-J41 -> -4.8390999 | K43: =K30-K41 -> -4.4796416 | ... X43: =X30-X41 -> 22.780366
C44: $ | D44: 0 | E44: =E43/E13 -> -0.034662264 | F44: =F43/F13 -> -0.034200135 | G44: =G43/G13 -> -0.033283466 | H44: =H43/H13 -> -0.031920002 | I44: =I43/I13 -> -0.029253227 | J44: =J43/J13 -> -0.026748228 | K44: =K43/K13 -> -0.023582205 | L44: =L43/L13 -> -0.019624317 | ... X44: =X43/X13 -> 0.063597631
A46: EBITDA Margin | D46: 0 | E46: =E43/E28 -> -2.3087943 | F46: =F43/F28 -> -1.834254 | G46: =G43/G28 -> -1.4368447 | H46: =H43/H28 -> -1.1053996 | I46: =I43/I28 -> -0.82170159 | J46: =J43/J28 -> -0.63574256 | K46: =K43/K28 -> -0.47412234 | L46: =L43/L28 -> -0.3336486 | ... X46: =X43/X28 -> 0.2767939
A48: Sales Tax | C48: 0 | D48: =D49*D13 -> -2 | E48: =$C$48*E28 -> 0 | F48: =$C$48*F28 -> 0 | G48: =$C$48*G28 -> 0 | H48: =$C$48*H28 -> 0 | I48: =$C$48*I28 -> 0 | J48: =$C$48*J28 -> 0 | K48: =$C$48*K28 -> 0 | L48: =$C$48*L28 -> 0 | ... X48: =$C$48*X28 -> 0
A49: Depreciation | B49: Ongoing Capital Equipment | C49: $ | D49: =-D6*D7/1000000 -> -0.014814815 | E49: =-E6*E7/1000000 -> 0 | F49: =-F6*F7/1000000 -> 0 | G49: =-G6*G7/1000000 -> 0 | H49: =-H6*H7/1000000 -> 0 | I49: =-I6*I7/1000000 -> 0 | J49: =-J6*J7/1000000 -> 0 | K49: =-K6*K7/1000000 -> 0 | ... X49: =-X6*X7/1000000 -> 0 | Y49: =SUM(D49:X49) -> -0.014814815
A51: Excess / (Shortfall) of Revenues over Expenditure before Depreciation | C51: Rs. | D51: =+D43+D48 -> -2 | E51: =+E43+E48 -> -4.9133759 | F51: =+F43+F48 -> -5.0902626 | G51: =+G43+G48 -> -5.2015193 | H51: =+H43+H48 -> -5.2378598 | I51: =+I43+I48 -> -5.0402728 | J51: =+J43+J48 -> -4.8390999 | K51: =+K43+K48 -> -4.4796416 | ... X51: =+X43+X48 -> 22.780366 | Y51: =SUM(D51:X51) -> 45.736962 | Z51: =Y51/20 -> 2.2868481
A52: Excess / (Shortfall) of Revenues over Expenditure before Depreciation | C52: $ | D52: =+D44+D49 -> -0.014814815 | E52: =+E44+E49 -> -0.034662264 | F52: =+F44+F49 -> -0.034200135 | G52: =+G44+G49 -> -0.033283466 | H52: =+H44+H49 -> -0.031920002 | I52: =+I44+I49 -> -0.029253227 | J52: =+J44+J49 -> -0.026748228 | K52: =+K44+K49 -> -0.023582205 | ... X52: =+X44+X49 -> 0.063597631 | Y52: =SUM(D52:X52) -> 0.013443715
A55: NPV in Rs | B55: Discount Rate | C55: 0.128267 | D55: =NPV(C55,E51:X51)+D51 -> -16.423424 | E55: =D55*1000000 -> -16423424
A56: NPV in $ | D56: =D55/E13 -> -0.1158619 | E56: =D56*1000000 -> -115861.9
A57: IRR (%) | D57: =IRR(D51:X51) -> 0.053815637
A58: Annualized RoI (%) | D58: =(((Y52*1000000)/D7)^(1/20))-1 -> -0.0048440269
A59: Payback | D59: =MATCH(1,E61:X61,0) -> 17 | E59: Years | F59: =-ROUND(INDEX(E60:X60,MATCH(1,E61:X61,0))/INDEX(E51:X51,MATCH(1,E61:X61,0)+1)*12,0) -> 8 | G59: Months
E60: =SUM($D51:E51) -> -6.9133759 | F60: =SUM($D51:F51) -> -12.003638 | G60: =SUM($D51:G51) -> -17.205158 | H60: =SUM($D51:H51) -> -22.443018 | I60: =SUM($D51:I51) -> -27.48329 | J60: =SUM($D51:J51) -> -32.32239 | K60: =SUM($D51:K51) -> -36.802032 | L60: =SUM($D51:L51) -> -40.716229 | ... X60: =SUM($D51:X51) -> 45.736962
E61: =IF(AND(E60<0,F60>0),1,"") | F61: =IF(AND(F60<0,G60>0),1,"") | G61: =IF(AND(G60<0,H60>0),1,"") | H61: =IF(AND(H60<0,I60>0),1,"") | I61: =IF(AND(I60<0,J60>0),1,"") | J61: =IF(AND(J60<0,K60>0),1,"") | K61: =IF(AND(K60<0,L60>0),1,"") | L61: =IF(AND(L60<0,M60>0),1,"") | ... X61: =IF(AND(X60<0,Y60>0),1,"")
A63: Revenue per day | E63: =E28*1000000/300 -> 7093.7109 | F63: =F28*1000000/300 -> 9250.3776 | G63: =G28*1000000/300 -> 12066.995 | H63: =H28*1000000/300 -> 15794.771 | I63: =I28*1000000/300 -> 20446.485 | J63: =J28*1000000/300 -> 25372.429 | K63: =K28*1000000/300 -> 31494.274 | L63: =L28*1000000/300 -> 39104.988 | ... X63: =X28*1000000/300 -> 274336.07
A64: Revenue per month | E64: =E63*25 -> 177342.77 | F64: =F63*25 -> 231259.44 | G64: =G63*25 -> 301674.88 | H64: =H63*25 -> 394869.27 | I64: =I63*25 -> 511162.13 | J64: =J63*25 -> 634310.72 | K64: =K63*25 -> 787356.85 | L64: =L63*25 -> 977624.71 | ... X64: =X63*25 -> 6858401.9
C70: 2021 - 20205 | D70: 2026 - 2030 | E70: 2031- 2035 | F70: 2035 - 2040
B71: Summary Income Statements
B72: Revenue | C72: =SUM(E28:I28) -> 19.395702 | D72: =SUM(J28:N28) -> 61.466229 | E72: =SUM(O28:S28) -> 156.95018 | F72: =SUM(T28:X28) -> 322.88972
B73: Gross Profit | C73: =SUM(E30:I30) -> 15.516561 | D73: =SUM(J30:N30) -> 49.172983 | E73: =SUM(O30:S30) -> 125.56015 | F73: =SUM(T30:X30) -> 258.31177
B74: Operating Expenses | C74: =SUM(E41:I41) -> 40.999852 | D74: =SUM(J41:N41) -> 67.396343 | E74: =SUM(O41:S41) -> 111.87713 | F74: =SUM(T41:X41) -> 180.55117
B75: Net Profit/Loss | C75: =SUM(E51:I51) -> -25.48329 | D75: =SUM(J51:N51) -> -18.22336 | E75: =SUM(O51:O51) -> -0.85674648 | F75: =SUM(T51:X51) -> 77.7606
B76: USD (M)
B77: Revenue | C77: =C72/153 -> 0.12676929 | D77: =D72/153 -> 0.40174006 | E77: =E72/153 -> 1.0258182 | F77: =F72/153 -> 2.1103903
B78: Gross Profit | C78: =C73/153 -> 0.10141543 | D78: =D73/153 -> 0.32139205 | E78: =E73/153 -> 0.82065455 | F78: =F73/153 -> 1.6883122
B79: Operating Expenses | C79: =C74/153 -> 0.26797289 | D79: =D74/153 -> 0.44049898 | E79: =E74/153 -> 0.73122309 | F79: =F74/153 -> 1.180073
B80: Net Profit/Loss | C80: =C75/153 -> -0.16655745 | D80: =D75/153 -> -0.11910693 | E80: =E75/153 -> -0.0055996502 | F80: =F75/153 -> 0.50823921
B81: USD
B82: Revenue | C82: =C77*1000000 -> 126769.29 | D82: =D77*1000000 -> 401740.06 | E82: =E77*1000000 -> 1025818.2 | F82: =F77*1000000 -> 2110390.3
B83: Gross Profit | C83: =C78*1000000 -> 101415.43 | D83: =D78*1000000 -> 321392.05 | E83: =E78*1000000 -> 820654.55 | F83: =F78*1000000 -> 1688312.2
B84: Operating Expenses | C84: =C79*1000000 -> 267972.89 | D84: =D79*1000000 -> 440498.98 | E84: =E79*1000000 -> 731223.09 | F84: =F79*1000000 -> 1180073
B85: Net Profit/Loss | C85: =C80*1000000 -> -166557.45 | D85: =D80*1000000 -> -119106.93 | E85: =E80*1000000 -> -5599.6502 | F85: =F80*1000000 -> 508239.21
C86: =C81*1000000 -> 0 | D86: =D81*1000000 -> 0 | E86: =E81*1000000 -> 0 | F86: =F81*1000000 -> 0

Sheet Satellite Centers
AF2: Summary Table
A4: South Karachi | D4: Satellite Center | E4: Year 01 | F4: Year 02 | G4: Year 03 | H4: Year 04 | I4: Year 05 | J4: Year 06 | K4: Year 07 | L4: Year 08 | M4: Year 09 | N4: Year 10 | O4: Year 11 | P4: Year 12 | Q4: Year 13 | R4: Year 14 | S4: Year 15 | T4: Year 16 | U4: Year 17 | V4: Year 18 | W4: Year 19 | X4: Year 20 | AE4: Year 00 - Year 05 | AF4: Year 06 - Year 10 | AG4: Year 11 - Year 15 | AH4: Year 16 - Year 20
A5: Assumptions
A6: Number of Centers | D6: 1 | AD6: Sales | AE6: =SUM(D23:I23) -> 33003.496 | AF6: =SUM(J23:N23) -> 71306.604 | AG6: =SUM(O23:S23) -> 124220.5 | AH6: =SUM(T23:X23) -> 172839.27
A7: Costs of Center Setup (Investment) | D7: =1000000/D13 -> 7407.4074 | AD7: Revenue | AE7: =SUM(D28:I28) -> 19.395702 | AF7: =SUM(J28:N28) -> 61.466229 | AG7: =SUM(O28:S28) -> 156.95018 | AH7: =SUM(T28:X28) -> 322.88972
A8: Sales Volumes | E8: 4435 | AD8: Expenses | AE8: =SUM(D30:I30) -> 15.516561 | AF8: =SUM(J30:N30) -> 49.172983 | AG8: =SUM(O30:S30) -> 125.56015 | AH8: =SUM(T30:X30) -> 258.31177
A9: Sales Growth | E9: 0.2 | F9: =E9 -> 0.2 | G9: =F9 -> 0.2 | H9: =G9 -> 0.2 | I9: =H9 -> 0.2 | J9: 0.15 | K9: =J9 -> 0.15 | L9: =K9 -> 0.15 | M9: =L9 -> 0.15 | N9: =M9 -> 0.15 | O9: 0.1 | P9: =O9 -> 0.1 | Q9: =P9 -> 0.1 | R9: =Q9 -> 0.1 | S9: =R9 -> 0.1 | T9: 0.05 | U9: =T9 -> 0.05 | V9: =U9 -> 0.05 | W9: =V9 -> 0.05 | X9: =W9 -> 0.05 | AD9: EBITDA | AE9: =SUM(D43:I43) -> -15.449774 | AF9: =SUM(J43:N43) -> -4.591185 | AG9: =SUM(O43:S43) -> 31.800559 | AH9: =SUM(T43:X43) -> 101.33271
A10: Price Increase | E10: 0.16 | F10: 0.086687643 | G10: 0.087072291 | H10: 0.090769398 | I10: 0.078758145 | J10: 0.07905988 | K10: 0.079373414 | L10: 0.079699048 | M10: 0.080037074 | N10: 0.080387773 | O10: 0.080751414 | P10: 0.08112825 | Q10: 0.081518518 | R10: 0.081922436 | S10: 0.082340198 | T10: 0.082771977 | U10: 0.083217919 | V10: 0.08367814 | W10: 0.084152725 | X10: 0.084641726 | AD10: Net Profit/Loss | AE10: =SUM(D51:I51) -> -16.449774 | AF10: =SUM(J51:N51) -> -4.591185 | AG10: =SUM(O51:S51) -> 31.800559 | AH10: =SUM(T51:X51) -> 101.33271
A11: Salary Increase | E11: 0.16 | F11: 0.1 | G11: 0.1 | H11: 0.11 | I11: 0.07 | J11: 0.07 | K11: 0.07 | L11: 0.07 | M11: 0.07 | N11: 0.07 | O11: 0.07 | P11: 0.07 | Q11: 0.07 | R11: 0.07 | S11: 0.07 | T11: 0.07 | U11: 0.07 | V11: 0.07 | W11: 0.07 | X11: 0.07
A12: Local Inflation | E12: 0.16 | F12: 0.07 | G12: 0.07 | H12: 0.07 | I12: 0.07 | J12: 0.07 | K12: 0.07 | L12: 0.07 | M12: 0.07 | N12: 0.07 | O12: 0.07 | P12: 0.07 | Q12: 0.07 | R12: 0.07 | S12: 0.07 | T12: 0.07 | U12: 0.07 | V12: 0.07 | W12: 0.07 | X12: 0.07
A13: Re. / $ Parity | D13: 135 | E13: 141.75 | F13: 148.8375 | G13: 156.27938 | H13: 164.09334 | I13: 172.29801 | J13: 180.91291 | K13: 189.95856 | L13: 199.45648 | M13: 209.42931 | N13: 219.90077 | O13: 230.89581 | P13: 242.4406 | Q13: 254.56263 | R13: 267.29077 | S13: 280.6553 | T13: 294.68807 | U13: 309.42247 | V13: 324.8936 | W13: 341.13828 | X13: 358.19519
A14: Rent Inflation | E14: 0.13 | F14: 0.13 | G14: 0.13 | H14: 0.13 | I14: 0.13 | J14: 0.13 | K14: 0.13 | L14: 0.13 | M14: 0.13 | N14: 0.13 | O14: 0.13 | P14: 0.13 | Q14: 0.13 | R14: 0.13 | S14: 0.13 | T14: 0.13 | U14: 0.13 | V14: 0.13 | W14: 0.13 | X14: 0.13
A15: Reagents/Consumables Inflation | E15: 0.09889959 | F15: 0.075175 | G15: 0.075175 | H15: 0.075175 | I15: 0.075175 | J15: 0.075175 | K15: 0.075175 | L15: 0.075175 | M15: 0.075175 | N15: 0.075175 | O15: 0.075175 | P15: 0.075175 | Q15: 0.075175 | R15: 0.075175 | S15: 0.075175 | T15: 0.075175 | U15: 0.075175 | V15: 0.075175 | W15: 0.075175 | X15: 0.075175
A16: Number of FTEs | C16: =COUNT('Staff Costs'!C15:C20) -> 6 | E16: =$C$16*$D$6 -> 6 | F16: =$C$16*$D$6 -> 6 | G16: =$C$16*$D$6 -> 6 | H16: =$C$16*$D$6 -> 6 | I16: =$C$16*$D$6 -> 6 | J16: =$C$16*$D$6 -> 6 | K16: =$C$16*$D$6 -> 6 | L16: =$C$16*$D$6 -> 6 | ... X16: =$C$16*$D$6 -> 6
A17: Salary including Fringe | C17: ='Staff Costs'!D21/1.1/C16 -> 29825.152 | E17: =C17*(1+E11) -> 34597.176 | F17: =E17*(1+F11) -> 38056.893 | G17: =F17*(1+G11) -> 41862.583 | H17: =G17*(1+H11) -> 46467.467 | I17: =H17*(1+I11) -> 49720.189 | J17: =I17*(1+J11) -> 53200.603 | K17: =J17*(1+K11) -> 56924.645 | L17: =K17*(1+L11) -> 60909.37 | M17: =L17*(1+M11) -> 65173.026 | ... X17: =W17*(1+X11) -> 137179.57
A18: Supplies | B18: Supplies | C18: =SUMIF('Overhead Costs'!$B$19:$B$31,'Main Center'!B18,'Overhead Costs'!$C$19:$C$31) -> 1308 | E18: =C18*(1+E12) -> 1517.28 | F18: =E18*(1+F12) -> 1623.4896 | G18: =F18*(1+G12) -> 1737.1339 | H18: =G18*(1+H12) -> 1858.7332 | I18: =H18*(1+I12) -> 1988.8446 | J18: =I18*(1+J12) -> 2128.0637 | K18: =J18*(1+K12) -> 2277.0281 | L18: =K18*(1+L12) -> 2436.4201 | M18: =L18*(1+M12) -> 2606.9695 | ... X18: =W18*(1+X12) -> 5487.2849
A19: Utilities | B19: Utilities | C19: =SUMIF('Overhead Costs'!$B$19:$B$31,'Main Center'!B19,'Overhead Costs'!$C$19:$C$31) -> 13826 | E19: =C19*(1+E12) -> 16038.16 | F19: =E19*(1+F12) -> 17160.831 | G19: =F19*(1+G12) -> 18362.089 | H19: =G19*(1+H12) -> 19647.436 | I19: =H19*(1+I12) -> 21022.756 | J19: =I19*(1+J12) -> 22494.349 | K19: =J19*(1+K12) -> 24068.953 | L19: =K19*(1+L12) -> 25753.78 | M19: =L19*(1+M12) -> 27556.545 | ... X19: =W19*(1+X12) -> 58002.447
A20: SG&A | B20: SG&A | C20: ='Overhead Costs'!C32-'Satellite Centers'!C18-'Satellite Centers'!C19 -> 110457 | E20: =C20*(((1+E14)+(1+E12))/2) -> 126473.26 | F20: =E20*(((1+F14)+(1+F12))/2) -> 139120.59 | G20: =F20*(((1+G14)+(1+G12))/2) -> 153032.65 | H20: =G20*(((1+H14)+(1+H12))/2) -> 168335.92 | I20: =H20*(((1+I14)+(1+I12))/2) -> 185169.51 | J20: =I20*(((1+J14)+(1+J12))/2) -> 203686.46 | K20: =J20*(((1+K14)+(1+K12))/2) -> 224055.1 | L20: =K20*(((1+L14)+(1+L12))/2) -> 246460.61 | M20: =L20*(((1+M14)+(1+M12))/2) -> 271106.68 | ... X20: =W20*(((1+X14)+(1+X12))/2) -> 773498.99
A22: Stats
A23: Volumes | B23: Laboratory Volumes (`000) | E23: =E8*D6 -> 4435 | F23: =E23*(1+F9) -> 5322 | G23: =F23*(1+G9) -> 6386.4 | H23: =G23*(1+H9) -> 7663.68 | I23: =H23*(1+I9) -> 9196.416 | J23: =I23*(1+J9) -> 10575.878 | K23: =J23*(1+K9) -> 12162.26 | L23: =K23*(1+L9) -> 13986.599 | M23: =L23*(1+M9) -> 16084.589 | ... X23: =W23*(1+X9) -> 38020.492 | Z23: =(X23-E23)/E23 -> 7.5728279
A24: Average Revenue | C24: ='Main Center'!C24 -> 413.65962 | E24: =C24*(1+E10) -> 479.84516 | F24: =E24*(1+F10) -> 521.44181 | G24: =F24*(1+G10) -> 566.84494 | H24: =G24*(1+H10) -> 618.29711 | I24: =H24*(1+I10) -> 666.99304 | J24: =I24*(1+J10) -> 719.72543 | K24: =J24*(1+K10) -> 776.8525 | L24: =K24*(1+L10) -> 838.7669 | M24: =L24*(1+M10) -> 905.89935 | ... X24: =W24*(1+X10) -> 2164.6438
A27: Financials
A28: Gross Revenue | B28: Outpatient | E28: =E24*E23/1000000 -> 2.1281133 | F28: =F24*F23/1000000 -> 2.7751133 | G28: =G24*G23/1000000 -> 3.6200985 | H28: =H24*H23/1000000 -> 4.7384312 | I28: =I24*I23/1000000 -> 6.1339455 | J28: =J24*J23/1000000 -> 7.6117287 | K28: =K24*K23/1000000 -> 9.4482822 | L28: =L24*L23/1000000 -> 11.731496 | ... X28: =X24*X23/1000000 -> 82.300822
A29: Discount | B29: Discounts | C29: =-20% -> -0.2 | E29: =$C$29*E28 -> -0.42562266 | F29: =$C$29*F28 -> -0.55502266 | G29: =$C$29*G28 -> -0.7240197 | H29: =$C$29*H28 -> -0.94768624 | I29: =$C$29*I28 -> -1.2267891 | J29: =$C$29*J28 -> -1.5223457 | K29: =$C$29*K28 -> -1.8896564 | L29: =$C$29*L28 -> -2.3462993 | ... X29: =$C$29*X28 -> -16.460164
A30: Net Revenue | D30: =SUM(D28:D29) -> 0 | E30: =SUM(E28:E29) -> 1.7024906 | F30: =SUM(F28:F29) -> 2.2200906 | G30: =SUM(G28:G29) -> 2.8960788 | H30: =SUM(H28:H29) -> 3.790745 | I30: =SUM(I28:I29) -> 4.9071564 | J30: =SUM(J28:J29) -> 6.0893829 | K30: =SUM(K28:K29) -> 7.5586258 | ... X30: =SUM(X28:X29) -> 65.840658
A32: Expenses
A34: Staff Cost | B34: Staff | E34: =E17*E16*12/1000000 -> 2.4909967 | F34: =F17*F16*12/1000000 -> 2.7400963 | G34: =G17*G16*12/1000000 -> 3.014106 | H34: =H17*H16*12/1000000 -> 3.3456576 | I34: =I17*I16*12/1000000 -> 3.5798536 | J34: =J17*J16*12/1000000 -> 3.8304434 | K34: =K17*K16*12/1000000 -> 4.0985744 | L34: =L17*L16*12/1000000 -> 4.3854746 | ... X34: =X17*X16*12/1000000 -> 9.8769291
A35: Med Surg | B35: Medical / Surgical | C35: =Reagent_Costing!BK39 -> 0.23000483 | E35: =$C$35*E28 -> 0.48947634 | F35: =E35*(1+F9)*(1+F15) -> 0.63152726 | G35: =F35*(1+G9)*(1+G15) -> 0.81480279 | H35: =G35*(1+H9)*(1+H15) -> 1.0512667 | I35: =H35*(1+I9)*(1+I15) -> 1.3563548 | J35: =I35*(1+J9)*(1+J15) -> 1.6770666 | K35: =J35*(1+K9)*(1+K15) -> 2.0736111 | L35: =K35*(1+L9)*(1+L15) -> 2.563919 | M35: =L35*(1+M9)*(1+M15) -> 3.1701609 | ... X35: =W35*(1+X9)*(1+X15) -> 16.632587
A36: Supplies | B36: Supplies | E36: =E18*$D$6/1000000*12 -> 0.01820736 | F36: =F18*$D$6/1000000*12 -> 0.019481875 | G36: =G18*$D$6/1000000*12 -> 0.020845606 | H36: =H18*$D$6/1000000*12 -> 0.022304799 | I36: =I18*$D$6/1000000*12 -> 0.023866135 | J36: =J18*$D$6/1000000*12 -> 0.025536764 | K36: =K18*$D$6/1000000*12 -> 0.027324338 | L36: =L18*$D$6/1000000*12 -> 0.029237041 | ... X36: =X18*$D$6/1000000*12 -> 0.065847419
A37: Utilities | B37: Utilities | E37: =E19*$D$6/1000000*12 -> 0.19245792 | F37: =F19*$D$6/1000000*12 -> 0.20592997 | G37: =G19*$D$6/1000000*12 -> 0.22034507 | H37: =H19*$D$6/1000000*12 -> 0.23576923 | I37: =I19*$D$6/1000000*12 -> 0.25227307 | J37: =J19*$D$6/1000000*12 -> 0.26993219 | K37: =K19*$D$6/1000000*12 -> 0.28882744 | L37: =L19*$D$6/1000000*12 -> 0.30904536 | ... X37: =X19*$D$6/1000000*12 -> 0.69602937
A38: SG & A | B38: General / Administration | E38: =(E20*$D$6/1000000*12) -> 1.5176792 | F38: =(F20*$D$6/1000000*12) -> 1.6694471 | G38: =(G20*$D$6/1000000*12) -> 1.8363918 | H38: =(H20*$D$6/1000000*12) -> 2.020031 | I38: =(I20*$D$6/1000000*12) -> 2.2220341 | J38: =(J20*$D$6/1000000*12) -> 2.4442375 | K38: =(K20*$D$6/1000000*12) -> 2.6886612 | L38: =(L20*$D$6/1000000*12) -> 2.9575274 | ... X38: =(X20*$D$6/1000000*12) -> 9.2819878
A39: Central Support | B39: Central Support Services Costs | E39: =(('Central _support'!D10/1000000))/31 -> 0.13583923 | F39: =E39*(1+F12) -> 0.14534797 | G39: =F39*(1+G12) -> 0.15552233 | H39: =G39*(1+H12) -> 0.16640889 | I39: =H39*(1+I12) -> 0.17805752 | J39: =I39*(1+J12) -> 0.19052154 | K39: =J39*(1+K12) -> 0.20385805 | L39: =K39*(1+L12) -> 0.21812811 | M39: =L39*(1+M12) -> 0.23339708 | ... X39: =W39*(1+X12) -> 0.4912663
A40: Marketing | B40: General / Administration | C40: =1% -> 0.01 | E40: =+($C$40*E28) -> 0.021281133 | F40: =+($C$40*F28) -> 0.027751133 | G40: =+($C$40*G28) -> 0.036200985 | H40: =+($C$40*H28) -> 0.047384312 | I40: =+($C$40*I28) -> 0.061339455 | J40: =+($C$40*J28) -> 0.076117287 | K40: =+($C$40*K28) -> 0.094482822 | L40: =+($C$40*L28) -> 0.11731496 | ... X40: =+($C$40*X28) -> 0.82300822
A41: Total Expenses | D41: =SUM(D34:D40) -> 0 | E41: =SUM(E34:E40) -> 4.8659378 | F41: =SUM(F34:F40) -> 5.4395816 | G41: =SUM(G34:G40) -> 6.0982145 | H41: =SUM(H34:H40) -> 6.8888225 | I41: =SUM(I34:I40) -> 7.6737787 | J41: =SUM(J34:J40) -> 8.5138553 | K41: =SUM(K34:K40) -> 9.4753394 | ... X41: =SUM(X34:X40) -> 37.867655
A43: Earning / (Deficit) before Interest & Depreciation | C43: Rs. | D43: =D30-D41 -> 0 | E43: =E30-E41 -> -3.1634472 | F43: =F30-F41 -> -3.219491 | G43: =G30-G41 -> -3.2021357 | H43: =H30-H41 -> -3.0980776 | I43: =I30-I41 -> -2.7666223 | J43: =J30-J41 -> -2.4244723 | K43: =K30-K41 -> -1.9167137 | ... X43: =X30-X41 -> 27.973003
C44: $ | D44: 0 | E44: =E43/E13 -> -0.022317088 | F44: =F43/F13 -> -0.021630913 | G44: =G43/G13 -> -0.020489817 | H44: =H43/H13 -> -0.018879971 | I44: =I43/I13 -> -0.016057192 | J44: =J43/J13 -> -0.013401323 | K44: =K43/K13 -> -0.010090168 | L44: =L43/L13 -> -0.0059935346 | ... X44: =X43/X13 -> 0.0780943
A46: EBITDA Margin | D46: 0 | E46: =E43/E28 -> -1.4865032 | F46: =F43/F28 -> -1.1601296 | G46: =G43/G28 -> -0.88454381 | H46: =H43/H28 -> -0.65381926 | I46: =I43/I28 -> -0.45103471 | J46: =J43/J28 -> -0.31851797 | K46: =K43/K28 -> -0.20286372 | L46: =L43/L28 -> -0.10190084 | ... X46: =X43/X28 -> 0.33988728
A48: Sales Tax | C48: 0 | D48: =D49*D13 -> -1 | E48: =$C$48*E28 -> 0 | F48: =$C$48*F28 -> 0 | G48: =$C$48*G28 -> 0 | H48: =$C$48*H28 -> 0 | I48: =$C$48*I28 -> 0 | J48: =$C$48*J28 -> 0 | K48: =$C$48*K28 -> 0 | L48: =$C$48*L28 -> 0 | ... X48: =$C$48*X28 -> 0 | Y48: =SUM(D48:X48) -> -1
A49: Depreciation | B49: Ongoing Capital Equipment | C49: $ | D49: =-D6*D7/1000000 -> -0.0074074074 | K49: =-0.007*0 -> 0 | O49: =D49*0.25 -> -0.0018518519 | P49: =E49*0.25 -> 0 | Q49: =F49*0.25 -> 0 | R49: =G49*0.25 -> 0 | S49: =H49*0.25 -> 0 | T49: =I49*0.25 -> 0 | U49: =J49*0.25 -> 0 | V49: =K49*0.25 -> 0 | ... X49: =M49*0.25 -> 0
A51: Excess / (Shortfall) of Revenues over Expenditure before Depreciation | C51: Rs. | D51: =+D43+D48 -> -1 | E51: =+E43+E48 -> -3.1634472 | F51: =+F43+F48 -> -3.219491 | G51: =+G43+G48 -> -3.2021357 | H51: =+H43+H48 -> -3.0980776 | I51: =+I43+I48 -> -2.7666223 | J51: =+J43+J48 -> -2.4244723 | K51: =+K43+K48 -> -1.9167137 | ... X51: =+X43+X48 -> 27.973003 | Y51: =SUM(D51:X51) -> 112.09231
A52: Excess / (Shortfall) of Revenues over Expenditure before Depreciation | C52: $ | D52: =+D44+D49 -> -0.0074074074 | E52: =+E44+E49 -> -0.022317088 | F52: =+F44+F49 -> -0.021630913 | G52: =+G44+G49 -> -0.020489817 | H52: =+H44+H49 -> -0.018879971 | I52: =+I44+I49 -> -0.016057192 | J52: =+J44+J49 -> -0.013401323 | K52: =+K44+K49 -> -0.010090168 | ... X52: =+X44+X49 -> 0.0780943 | Y52: =SUM(D52:X52) -> 0.29439188
A55: NPV in Rs | B55: Discount Rate | C55: ='Main Center'!C55 -> 0.128267 | D55: =NPV(C55,E51:X51)+D51 -> 3.2166197
A56: NPV in $ | D56: =D55/E13 -> 0.022692203 | E56: =D56*1000000 -> 22692.203
A57: IRR (%) | D57: =IRR(D51:X51) -> 0.14564159
A58: Annualized RoI (%) | D58: =(((Y52*1000000)/D7)^(1/20))-1 -> 0.20216196
A59: Payback | D59: =MATCH(1,E61:X61,0) -> 14 | E59: Years | F59: =-ROUND(INDEX(E60:X60,MATCH(1,E61:X61,0))/INDEX(E51:X51,MATCH(1,E61:X61,0)+1)*12,0) -> 1 | G59: Months
E60: =SUM($D51:E51) -> -4.1634472 | F60: =SUM($D51:F51) -> -7.3829382 | G60: =SUM($D51:G51) -> -10.585074 | H60: =SUM($D51:H51) -> -13.683151 | I60: =SUM($D51:I51) -> -16.449774 | J60: =SUM($D51:J51) -> -18.874246 | K60: =SUM($D51:K51) -> -20.79096 | L60: =SUM($D51:L51) -> -21.986409 | ... X60: =SUM($D51:X51) -> 112.09231
E61: =IF(AND(E60<0,F60>0),1,"") | F61: =IF(AND(F60<0,G60>0),1,"") | G61: =IF(AND(G60<0,H60>0),1,"") | H61: =IF(AND(H60<0,I60>0),1,"") | I61: =IF(AND(I60<0,J60>0),1,"") | J61: =IF(AND(J60<0,K60>0),1,"") | K61: =IF(AND(K60<0,L60>0),1,"") | L61: =IF(AND(L60<0,M60>0),1,"") | ... X61: =IF(AND(X60<0,Y60>0),1,"")
A63: Revenue per day | E63: =E28*1000000/300 -> 7093.7109 | F63: =F28*1000000/300 -> 9250.3776 | G63: =G28*1000000/300 -> 12066.995 | H63: =H28*1000000/300 -> 15794.771 | I63: =I28*1000000/300 -> 20446.485 | J63: =J28*1000000/300 -> 25372.429 | K63: =K28*1000000/300 -> 31494.274 | L63: =L28*1000000/300 -> 39104.988 | ... X63: =X28*1000000/300 -> 274336.07
A64: Revenue per month | E64: =E63*25 -> 177342.77 | F64: =F63*25 -> 231259.44 | G64: =G63*25 -> 301674.88 | H64: =H63*25 -> 394869.27 | I64: =I63*25 -> 511162.13 | J64: =J63*25 -> 634310.72 | K64: =K63*25 -> 787356.85 | L64: =L63*25 -> 977624.71 | ... X64: =X63*25 -> 6858401.9
C70: 2021 - 20205 | D70: 2026 - 2030 | E70: 2031- 2035 | F70: 2035 - 2040
B71: Summary Income Statements
B72: Revenue | C72: =SUM(E28:I28) -> 19.395702 | D72: =SUM(J28:N28) -> 61.466229 | E72: =SUM(O28:S28) -> 156.95018 | F72: =SUM(T28:X28) -> 322.88972
B73: Gross Profit | C73: =SUM(E30:I30) -> 15.516561 | D73: =SUM(J30:N30) -> 49.172983 | E73: =SUM(O30:S30) -> 125.56015 | F73: =SUM(T30:X30) -> 258.31177
B74: Operating Expenses | C74: =SUM(E41:I41) -> 30.966335 | D74: =SUM(J41:N41) -> 53.764168 | E74: =SUM(O41:S41) -> 93.759587 | F74: =SUM(T41:X41) -> 156.97906
B75: Net Profit/Loss | C75: =SUM(E51:I51) -> -15.449774 | D75: =SUM(J51:N51) -> -4.591185 | E75: =SUM(O51:O51) -> 2.3761598 | F75: =SUM(T51:X51) -> 101.33271
B77: Revenue | C77: =C72/153 -> 0.12676929 | D77: =D72/153 -> 0.40174006 | E77: =E72/153 -> 1.0258182 | F77: =F72/153 -> 2.1103903
B78: Gross Profit | C78: =C73/153 -> 0.10141543 | D78: =D73/153 -> 0.32139205 | E78: =E73/153 -> 0.82065455 | F78: =F73/153 -> 1.6883122
B79: Operating Expenses | C79: =C74/153 -> 0.20239435 | D79: =D74/153 -> 0.35139979 | E79: =E74/153 -> 0.61280776 | F79: =F74/153 -> 1.0260069
B80: Net Profit/Loss | C80: =C75/153 -> -0.10097891 | D80: =D75/153 -> -0.030007745 | E80: =E75/153 -> 0.015530456 | F80: =F75/153 -> 0.66230531
B82: Revenue | C82: =C77*1000000 -> 126769.29 | D82: =D77*1000000 -> 401740.06 | E82: =E77*1000000 -> 1025818.2 | F82: =F77*1000000 -> 2110390.3
B83: Gross Profit | C83: =C78*1000000 -> 101415.43 | D83: =D78*1000000 -> 321392.05 | E83: =E78*1000000 -> 820654.55 | F83: =F78*1000000 -> 1688312.2
B84: Operating Expenses | C84: =C79*1000000 -> 202394.35 | D84: =D79*1000000 -> 351399.79 | E84: =E79*1000000 -> 612807.76 | F84: =F79*1000000 -> 1026006.9
B85: Net Profit/Loss | C85: =C80*1000000 -> -100978.91 | D85: =D80*1000000 -> -30007.745 | E85: =E80*1000000 -> 15530.456 | F85: =F80*1000000 -> 662305.31

Sheet Staff Costs
A1: Main Centers
A2: Staff Member | B2: Average Monthly Salary | C2: Fringe Benefits (PKR) | D2: Monthly Total Salary (PKR) | E2: Annual Salary (PKR)
B3: (PKR)
A4: Senior Medical Officer | B4: 65370 | C4: 8059 | D4: 73429 | E4: 881150
A5: Medical Representative | B5: 27540 | C5: 3771 | D5: 31312 | E5: 375743
A6: Centre Technicians | B6: 20330 | C6: 2954 | D6: 23284 | E6: 279409
A7: Screener / Nurse | B7: 20716 | C7: 2998 | D7: 23714 | E7: 284569
A8: Medical Receptionist | B8: 24341 | C8: 3409 | D8: 27750 | E8: 332997
A9: Van Drivers | B9: 20461 | C9: 2969 | D9: 23430 | E9: 281155
A10: Cleaner/Helper | B10: 15006 | C10: 2351 | D10: 17357 | E10: 208283
A11: Total | B11: 193764 | C11: 26511 | D11: 220275 | E11: 2643305
A13: Satellite Centers
A14: Staff Member | B14: Average Monthly Salary (PKR) | C14: Fringe Benefits (PKR) | D14: Monthly Total Salary (PKR) | E14: Annual Salary (PKR)
A15: Senior Medical Officer | B15: 65370 | C15: 8059 | D15: 73429 | E15: 881150
A16: Medical Representative | B16: 27540 | C16: 3771 | D16: 31312 | E16: 375743
A17: Centre Technicians | B17: 20330 | C17: 2954 | D17: 23284 | E17: 279409
A18: Screener / Nurse | B18: 20716 | C18: 2998 | D18: 23714 | E18: 284569
A19: Medical Receptionist | B19: 24341 | C19: 3409 | D19: 27750 | E19: 332997
A20: Cleaner/Helper | B20: 15006 | C20: 2351 | D20: 17357 | E20: 208283
A21: Total | B21: 173304 | C21: 23542 | D21: 196846 | E21: 2362150

Sheet Reagent_Costing
M1: INDIRECT MATERIALS | T1: DIRECT MATERIALS CONSUMABLES | AA1: DIRECT MATERIALS REAGENTS | AH1: TESTS COSTING
A2: Platform | B2: Test | C2: Expected No. of Tests | D2: Tests Conducted | E2: Difference from Target | F2: Cost Efficiency (%) | M2: Cost Item | N2: Quantity in Unit | O2: Units Consumed | P2: Total Quantity | Q2: Total Cost | R2: Per Test | T2: Cost Item | U2: Quantity in Unit | V2: Units Consumed | W2: Total Quantity | X2: Total Cost | Y2: Per Test | AA2: Platform | AB2: Test | AC2: Regents Procured | AD2: Cost per Unit (PKR) | AE2: Total Cost | AF2: Reagent Cost Per Test (PKR) | AH2: Platform | AI2: Test | AJ2: Tests Conducted | AK2: Direct Materials (Reagents) | AL2: Direct Materials (Consumables) | AM2: Indirect Material (Consumables) | AN2: Total Cost (PKR) | AQ2: Platform | AR2: Test | AS2: Price | AT2: Cost (PKR) | AU2: Gross Profit | AV2: Gross Profit (%)
A3: Hematology | B3: Complete Blood Count | C3: 11500 | D3: 8131 | E3: -3369 | F3: 0.71 | Q3: (PKR) | X3: (PKR) | AC3: (Units) | AE3: (PKR) | AH3: Hematology | AI3: Complete Blood Count | AJ3: 8131 | AK3: 33.64 | AL3: =Y21+Y5 -> 25.821029 | AM3: =R8 -> 1.5988193 | AN3: =AK3+AL3+AM3 -> 61.059849 | AQ3: Hematology | AR3: Complete Blood Count | AS3: 380 | AT3: =AN3 -> 61.059849 | AU3: =AS3-AT3 -> 318.94015 | AV3: =AU3/AS3 -> 0.83931619
A4: Biochemistry | B4: Alkaline phosphate | C4: 1950 | D4: 1278 | E4: -672 | F4: 0.66 | M4: Hematology | T4: Hematology | AA4: Hematology | AB4: Complete Blood Count | AC4: 250 | AD4: 3400 | AE4: 273500 | AF4: 30.64 | AH4: Biochemistry | AI4: Alkaline phosphate | AJ4: 1278 | AK4: 17.25 | AL4: =Y21+Y7 -> 22.582925 | AM4: =R18 -> 8.2415805 | AN4: =AK4+AL4+AM4 -> 48.074506 | AQ4: Biochemistry | AR4: Alkaline phosphate | AS4: 290 | AT4: =AN4 -> 48.074506 | AU4: =AS4-AT4 -> 241.92549 | AV4: =AU4/AS4 -> 0.83422584
A5: Biochemistry | B5: Gamma GT | C5: 3000 | D5: 1274 | E5: -1726 | F5: 0.42 | M5: Anitseraset | N5: 1 | O5: 3 | P5: 3 | Q5: 6000 | T5: EDTA Vacutainer (1x100) - Purple | U5: 100 | V5: 129 | W5: 12900 | X5: 93525 | Y5: =X5/AJ3 -> 11.502275 | AB5: (Diluent + Lyse) | AC5: 30 | AD5: 450 | AH5: Biochemistry | AI5: Gamma GT | AJ5: 1274 | AK5: 32.88 | AL5: =AL4 -> 22.582925 | AM5: =AM4 -> 8.2415805 | AN5: =AK5+AL5+AM5 -> 63.704506 | AQ5: Biochemistry | AR5: Gamma GT | AS5: 350 | AT5: =AN5 -> 63.704506 | AU5: =AS5-AT5 -> 286.29549 | AV5: =AU5/AS5 -> 0.81798713
A6: Biochemistry | B6: Bilirubin Total | C6: 2700 | D6: 1274 | E6: -1426 | F6: 0.47 | M6: Eight Calibration Control 1.5 (Normal) | N6: 0 | O6: 0 | P6: - | Q6: 3500 | T6: Biochemistry and HbA1c | AA6: Biochemistry | AB6: Alkaline phosphate | AC6: 26 | AD6: 848 | AE6: 22048 | AF6: 17.25 | AH6: Biochemistry | AI6: Bilirubin Total | AJ6: 1274 | AK6: 12.66 | AL6: =AL5 -> 22.582925 | AM6: =AM5 -> 8.2415805 | AN6: =AK6+AL6+AM6 -> 43.484506 | AQ6: Biochemistry | AR6: Bilirubin Total | AS6: 350 | AT6: =AN6 -> 43.484506 | AU6: =AS6-AT6 -> 306.51549 | AV6: =AU6/AS6 -> 0.87575856
A7: Biochemistry | B7: Bilirubin Direct | C7: 2250 | D7: 1274 | E7: -976 | F7: 0.57 | M7: Eight Calibration Control 1.5 (Low) | N7: 1 | O7: 1 | P7: 1 | Q7: 3500 | T7: Gel Vacutainer (1x100) - Yellow | U7: 100 | V7: 104 | W7: 10400 | X7: 93600 | Y7: =X7/SUM(AJ4:AJ17) -> 8.2641709 | AA7: Biochemistry | AB7: Gamma GT | AC7: 40 | AD7: 1047 | AE7: 41888 | AF7: 32.88 | AH7: Biochemistry | AI7: Bilirubin Direct | AJ7: 1274 | AK7: 10.55 | AL7: =AL6 -> 22.582925 | AM7: =AM6 -> 8.2415805 | AN7: =AK7+AL7+AM7 -> 41.374506 | AQ7: Biochemistry | AR7: Bilirubin Direct | AS7: 350 | AT7: =AN7 -> 41.374506 | AU7: =AS7-AT7 -> 308.62549 | AV7: =AU7/AS7 -> 0.88178713
A8: Biochemistry | B8: Alanine Transferase | C8: 3600 | D8: 1274 | E8: -2326 | F8: 0.35 | M8: Total | Q8: 13000 | R8: =Q8/AJ3 -> 1.5988193 | T8: General Consumables | AA8: Biochemistry | AB8: Bilirubin Total | AC8: 36 | AD8: 448 | AE8: 16128 | AF8: 12.66 | AH8: Biochemistry | AI8: Alanine Transferase | AJ8: 1274 | AK8: 23.31 | AL8: =AL7 -> 22.582925 | AM8: =AM7 -> 8.2415805 | AN8: =AK8+AL8+AM8 -> 54.134506 | AQ8: Biochemistry | AR8: Alanine Transferase | AS8: 330 | AT8: =AN8 -> 54.134506 | AU8: =AS8-AT8 -> 275.86549 | AV8: =AU8/AS8 -> 0.83595604
A9: Biochemistry | B9: HDL Direct | C9: 840 | D9: 194 | E9: -646 | F9: 0.23 | M9: Biochemistry | T9: Syringes | U9: 100 | V9: 256 | W9: 25600 | X9: 152400 | AA9: Biochemistry | AB9: Bilirubin Direct | AC9: 30 | AD9: 448 | AE9: 13440 | AF9: 10.55 | AH9: Biochemistry | AI9: HDL Direct | AJ9: 194 | AK9: 196.29 | AL9: =AL8 -> 22.582925 | AM9: =AM8 -> 8.2415805 | AN9: =AK9+AL9+AM9 -> 227.11451 | AQ9: Biochemistry | AR9: HDL Direct | AS9: 350 | AT9: =AN9 -> 227.11451 | AU9: =AS9-AT9 -> 122.88549 | AV9: =AU9/AS9 -> 0.35110141
A10: Biochemistry | B10: Triglycerides | C10: 975 | D10: 196 | E10: -779 | F10: 0.2 | M10: Eppindrof Cup | N10: 2 | O10: 2 | P10: 4 | Q10: 800 | T10: Alcohol Swab | U10: 200 | V10: 118 | W10: 23600 | X10: 20060 | AA10: Biochemistry | AB10: Alanine Transferase | AC10: 48 | AD10: 619 | AE10: 29702 | AF10: 23.31 | AH10: Biochemistry | AI10: Triglycerides | AJ10: 196 | AK10: 49.52 | AL10: =AL9 -> 22.582925 | AM10: =AM9 -> 8.2415805 | AN10: =AK10+AL10+AM10 -> 80.344506 | AQ10: Biochemistry | AR10: Triglycerides | AS10: 290 | AT10: =AN10 -> 80.344506 | AU10: =AS10-AT10 -> 209.65549 | AV10: =AU10/AS10 -> 0.72294998
A11: Biochemistry | B11: Total Cholesterol | C11: 1275 | D11: 251 | E11: -1024 | F11: 0.2 | M11: Selectra cup | N11: 1 | O11: 1 | P11: 1 | Q11: 5500 | T11: Bandage | U11: 200 | V11: 97 | W11: 19400 | X11: 27370 | AA11: Biochemistry | AB11: HDL Direct | AC11: 14 | AD11: 2720 | AE11: 38080 | AF11: 196.29 | AH11: Biochemistry | AI11: Total Cholesterol | AJ11: 251 | AK11: 87.84 | AL11: =AL10 -> 22.582925 | AM11: =AM10 -> 8.2415805 | AN11: =AK11+AL11+AM11 -> 118.66451 | AQ11: Biochemistry | AR11: Total Cholesterol | AS11: 190 | AT11: =AN11 -> 118.66451 | AU11: =AS11-AT11 -> 71.335494 | AV11: =AU11/AS11 -> 0.37544997
A12: Biochemistry | B12: LDL Direct | C12: 960 | D12: 204 | E12: -756 | F12: 0.21 | M12: D/W Ampule glass | N12: 1 | O12: 1 | P12: 1 | Q12: 2000 | T12: Butterfly needle | U12: 100 | V12: 4 | W12: 400 | X12: 30000 | AA12: Biochemistry | AB12: Triglycerides | AC12: 13 | AD12: 747 | AE12: 9707 | AF12: 49.52 | AH12: Biochemistry | AI12: LDL Direct | AJ12: 204 | AK12: 387.76 | AL12: =AL11 -> 22.582925 | AM12: =AM11 -> 8.2415805 | AN12: =AK12+AL12+AM12 -> 418.58451 | AQ12: Biochemistry | AR12: LDL Direct | AS12: 350 | AT12: =AN12 -> 418.58451 | AU12: =AS12-AT12 -> -68.584506 | AV12: =AU12/AS12 -> -0.19595573
A13: Biochemistry | B13: Uric Acid | C13: 975 | D13: 137 | E13: -838 | F13: 0.14 | M13: Boule Control (Normal) | N13: 1 | O13: 1 | P13: 1 | Q13: 5000 | T13: Vacant Needle Holder | U13: 100 | V13: 138 | W13: 13800 | X13: 13800 | AA13: Biochemistry | AB13: Total Cholesterol | AC13: 17 | AD13: 848 | AE13: 22048 | AF13: 32.96 | AH13: Biochemistry | AI13: Uric Acid | AJ13: 137 | AK13: 49.34 | AL13: =AL12 -> 22.582925 | AM13: =AM12 -> 8.2415805 | AN13: =AK13+AL13+AM13 -> 80.164506 | AQ13: Biochemistry | AR13: Uric Acid | AS13: 290 | AT13: =AN13 -> 80.164506 | AU13: =AS13-AT13 -> 209.83549 | AV13: =AU13/AS13 -> 0.72357067
A14: Biochemistry | B14: Urea UV | C14: 1425 | D14: 409 | E14: -1016 | F14: 0.29 | M14: Cleaning Solution | N14: - | O14: 2 | P14: 2 | Q14: 7140 | T14: Tagging roll | U14: 1 | V14: 60 | W14: 60 | X14: 4800 | AA14: Biochemistry | AB14: LDL Direct | AC14: 16 | AD14: 4944 | AE14: 79104 | AF14: 387.76 | AH14: Biochemistry | AI14: Urea UV | AJ14: 409 | AK14: 15.79 | AL14: =AL13 -> 22.582925 | AM14: =AM13 -> 8.2415805 | AN14: =AK14+AL14+AM14 -> 46.614506 | AQ14: Biochemistry | AR14: Urea UV | AS14: 290 | AT14: =AN14 -> 46.614506 | AU14: =AS14-AT14 -> 243.38549 | AV14: =AU14/AS14 -> 0.83926033
A15: Biochemistry | B15: Glucose PAP | C15: 300 | D15: 771 | E15: 471 | F15: 2.57 | M15: HSN - Normal Calibration | N15: - | O15: 13 | P15: 13 | Q15: 18893 | T15: Blood Tube rack | U15: - | V15: 20 | W15: 20 | X15: 8000 | AA15: Biochemistry | AB15: Uric Acid | AC15: 13 | AD15: 520 | AE15: 6760 | AF15: 49.34 | AH15: Biochemistry | AI15: Glucose PAP | AJ15: 771 | AK15: 0.33 | AL15: =AL14 -> 22.582925 | AM15: =AM14 -> 8.2415805 | AN15: =AK15+AL15+AM15 -> 31.154506 | AQ15: Biochemistry | AR15: Glucose PAP | AS15: 170 | AT15: =AN15 -> 31.154506 | AU15: =AS15-AT15 -> 138.84549 | AV15: =AU15/AS15 -> 0.8167382
A16: Biochemistry | B16: Creatinine | C16: 3375 | D16: 550 | E16: -2825 | F16: 0.17 | M16: HSP - Pathology Calibration | N16: - | O16: 17 | P16: 17 | Q16: 25840 | T16: Danger Box | U16: - | V16: 14 | W16: 14 | X16: 3500 | AA16: Biochemistry | AB16: Urea UV | AC16: 19 | AD16: 340 | AE16: 6460 | AF16: 15.79 | AH16: Biochemistry | AI16: Creatinine | AJ16: 550 | AK16: 23.18 | AL16: =AL15 -> 22.582925 | AM16: =AM15 -> 8.2415805 | AN16: =AK16+AL16+AM16 -> 54.004506 | AQ16: Biochemistry | AR16: Creatinine | AS16: 250 | AT16: =AN16 -> 54.004506 | AU16: =AS16-AT16 -> 195.99549 | AV16: =AU16/AS16 -> 0.78398198
A17: HbA1c | B17: Hemoglobin (A1c) | C17: 300 | D17: 2240 | E17: -712 | F17: 0.76 | M17: System Solution | N17: - | O17: 1.5 | P17: 1.5 | Q17: 9710 | T17: Tourniquet | U17: - | V17: 6 | W17: 6 | X17: 450 | AA17: Biochemistry | AB17: Glucose PAP | AC17: 1 | AD17: 256 | AE17: 256 | AF17: 0.33 | AH17: HbA1c | AI17: Hemoglobin (A1c) | AJ17: 2240 | AK17: 276.79 | AL17: =AL16 -> 22.582925 | AM17: =R22 -> 4.6875 | AN17: =AK17+AL17+AM17 -> 304.06043 | AQ17: HbA1c | AR17: Hemoglobin (A1c) | AS17: 850 | AT17: =AN17 -> 304.06043 | AU17: =AS17-AT17 -> 545.93957 | AV17: =AU17/AS17 -> 0.64228185
A18: Total | C18: =SUM(C3:C17) -> 35425 | D18: =SUM(D3:D17) -> 19457 | E18: =SUM(E3:E17) -> -18620 | F18: =D18/C18 -> 0.54924488 | M18: Total | Q18: 74883 | R18: =Q18/SUM(AJ4:AJ16) -> 8.2415805 | T18: Immersion oil | U18: - | V18: 1 | W18: 1 | X18: 4300 | AA18: Biochemistry | AB18: Creatinine | AC18: 1 | AD18: 283 | AE18: 12750 | AF18: 23.18
M19: HbA1c | T19: Normal Saline | V19: 1 | W19: 1 | X19: 120 | AA19: HbA1c | AB19: Hemoglobin (A1c) | AC19: 31 | AD19: 20000 | AE19: 620000 | AF19: 276.79
M20: Yellow tip | N20: - | O20: 3 | P20: 3 | Q20: 750 | T20: Vacant Needle Holder | U20: - | V20: 100 | W20: 100 | X20: 13800
M21: Plastic tube | N21: - | O21: 15 | P21: 15 | Q21: 9750 | T21: Total | X21: 278600 | Y21: =X21/SUM(AJ3:AJ17) -> 14.318754
M22: Total | Q22: 10500 | R22: =Q22/AJ17 -> 4.6875 | AH22: Q3 TESTS COSTING
AH24: Platform | AI24: Test | AJ24: Tests Conducted | AK24: Direct Materials (Reagents) | AL24: Direct Materials (Consumables) | AM24: Indirect Material (Consumables) | AN24: Total Cost (PKR) | AO24: Q3-Q1 | AQ24: Platform | AR24: Test | AS24: Price | AT24: Cost (PKR) | AU24: Gross Profit | AV24: Gross Profit (%) | AW24: Q3-Q1 | AZ24: No. | BA24: Test | BB24: Test Price | BC24: Per Test Cost (PKR) | BD24: Gross Profit | BE24: Gross Profit (%) | BG24: Test | BH24: Tests Conducted | BI24: Gross Profit | BJ24: Contribution Mix | BK24: Weighted Gross Profit
AH25: Hematology | AI25: Complete Blood Count | AJ25: 5583 | AK25: 51.504567 | AL25: 28.03 | AM25: 10.02 | AN25: =AK25+AL25+AM25 -> 89.554567 | AO25: =AN25-AN3 -> 28.494719 | AQ25: Hematology | AR25: Complete Blood Count | AS25: 380 | AT25: =AN25 -> 89.554567 | AU25: =AS25-AT25 -> 290.44543 | AV25: =AU25/AS25 -> 0.76433009 | AW25: =AV25-AV3 -> -0.074986102 | BB25: (PKR) | BD25: (PKR) | BG25: Complete Blood Count | BH25: 5583 | BI25: 0.76 | BJ25: =BH25/$BH$37 -> 0.35841304 | BK25: =BJ25*BI25 -> 0.27239391
AH26: Biochemistry | AI26: Alkaline phosphate | AJ26: 1147 | AK26: 7.2233653 | AL26: 24.05 | AM26: 5.06 | AN26: =AK26+AL26+AM26 -> 36.333365 | AO26: =AN26-AN4 -> -11.74114 | AQ26: Biochemistry | AR26: Alkaline phosphate | AS26: 290 | AT26: =AN26 -> 36.333365 | AU26: =AS26-AT26 -> 253.66663 | AV26: =AU26/AS26 -> 0.87471253 | AW26: =AV26-AV4 -> 0.040486691 | AZ26: 1 | BA26: Alkaline phosphate | BC26: 36.33 | BG26: Liver Function Tests | BH26: =SUM(AJ26:AJ30) -> 6021 | BI26: 0.8 | BJ26: =BH26/$BH$37 -> 0.38653142 | BK26: =BJ26*BI26 -> 0.30922514
AH27: Biochemistry | AI27: Gamma GT | AJ27: 1147 | AK27: 17.585562 | AL27: =AL26 -> 24.05 | AM27: 5.06 | AN27: =AK27+AL27+AM27 -> 46.695562 | AO27: =AN27-AN5 -> -17.008943 | AQ27: Biochemistry | AR27: Gamma GT | AS27: 350 | AT27: =AN27 -> 46.695562 | AU27: =AS27-AT27 -> 303.30444 | AV27: =AU27/AS27 -> 0.86658411 | AW27: =AV27-AV5 -> 0.048596981 | AZ27: 2 | BA27: Gamma GT | BC27: 46.7 | BG27: Lipid Profie | BH27: =SUM(AJ31:AJ34) -> 1088 | BI27: 0.63 | BJ27: =BH27/$BH$37 -> 0.069846569 | BK27: =BJ27*BI27 -> 0.044003338
AH28: Biochemistry | AI28: Bilirubin Total | AJ28: 1147 | AK28: 6.4680732 | AL28: =AL27 -> 24.05 | AM28: 5.06 | AN28: =AK28+AL28+AM28 -> 35.578073 | AO28: =AN28-AN6 -> -7.9064323 | AQ28: Biochemistry | AR28: Bilirubin Total | AS28: 350 | AT28: =AN28 -> 35.578073 | AU28: =AS28-AT28 -> 314.42193 | AV28: =AU28/AS28 -> 0.89834836 | AW28: =AV28-AV6 -> 0.022589807 | AZ28: 3 | BA28: Bilirubin Total | BC28: 35.58 | BG28: Uric Acid | BH28: 205 | BI28: 0.86113457 | BJ28: =BH28/$BH$37 -> 0.013160429 | BK28: =BJ28*BI28 -> 0.0113329
AH29: Biochemistry | AI29: Bilirubin Direct | AJ29: 1147 | AK29: 6.5149433 | AL29: =AL28 -> 24.05 | AM29: 5.06 | AN29: =AK29+AL29+AM29 -> 35.624943 | AO29: =AN29-AN7 -> -5.7495622 | AQ29: Biochemistry | AR29: Bilirubin Direct | AS29: 350 | AT29: =AN29 -> 35.624943 | AU29: =AS29-AT29 -> 314.37506 | AV29: =AU29/AS29 -> 0.89821445 | AW29: =AV29-AV7 -> 0.016427321 | AZ29: 4 | BA29: Bilirubin Direct | BC29: 35.62 | BG29: Urea UV | BH29: 409 | BI29: 0.87955493 | BJ29: =BH29/$BH$37 -> 0.02625666 | BK29: =BJ29*BI29 -> 0.023094175
AH30: Biochemistry | AI30: Alanine Transferase | AJ30: 1433 | AK30: 9.8863364 | AL30: =AL29 -> 24.05 | AM30: 5.06 | AN30: =AK30+AL30+AM30 -> 38.996336 | AO30: =AN30-AN8 -> -15.138169 | AQ30: Biochemistry | AR30: Alanine Transferase | AS30: 330 | AT30: =AN30 -> 38.996336 | AU30: =AS30-AT30 -> 291.00366 | AV30: =AU30/AS30 -> 0.88182928 | AW30: =AV30-AV8 -> 0.04587324 | AZ30: 5 | BA30: Alanine Transferase | BC30: 39 | BG30: Glucose PAP | BH30: 910 | BI30: 0.82353549 | BJ30: =BH30/$BH$37 -> 0.058419465 | BK30: =BJ30*BI30 -> 0.048110502
AH31: Biochemistry | AI31: HDL Direct | AJ31: 244 | AK31: 69.672131 | AL31: =AL30 -> 24.05 | AM31: 5.06 | AN31: =AK31+AL31+AM31 -> 98.782131 | AO31: =AN31-AN9 -> -128.33237 | AQ31: Biochemistry | AR31: HDL Direct | AS31: 350 | AT31: =AN31 -> 98.782131 | AU31: =AS31-AT31 -> 251.21787 | AV31: =AU31/AS31 -> 0.71776534 | AW31: =AV31-AV9 -> 0.36666393 | AZ31: 6 | BA31: Total | BB31: 990 | BC31: =SUM(BC26:BC30) -> 193.23 | BD31: =BB31-BC31 -> 796.77 | BE31: =BD31/BB31 -> 0.80481818 | BG31: Creatinine | BH31: 429 | BI31: 0.85428883 | BJ31: =BH31/$BH$37 -> 0.027540605 | BK31: =BJ31*BI31 -> 0.023527631
AH32: Biochemistry | AI32: Triglycerides | AJ32: 260 | AK32: 17.23077 | AL32: =AL31 -> 24.05 | AM32: 5.06 | AN32: =AK32+AL32+AM32 -> 46.34077 | AO32: =AN32-AN10 -> -34.003736 | AQ32: Biochemistry | AR32: Triglycerides | AS32: 290 | AT32: =AN32 -> 46.34077 | AU32: =AS32-AT32 -> 243.65923 | AV32: =AU32/AS32 -> 0.84020424 | AW32: =AV32-AV10 -> 0.11725426 | BG32: Hemoglobin (A1c) | BH32: 815 | BI32: 0.71632154 | BJ32: =BH32/$BH$37 -> 0.052320729 | BK32: =BJ32*BI32 -> 0.037478466
AH33: Biochemistry | AI33: Total Cholesterol | AJ33: 340 | AK33: 8.5882359 | AL33: =AL32 -> 24.05 | AM33: 5.06 | AN33: =AK33+AL33+AM33 -> 37.698236 | AO33: =AN33-AN11 -> -80.96627 | AQ33: Biochemistry | AR33: Total Cholesterol | AS33: 190 | AT33: =AN33 -> 37.698236 | AU33: =AS33-AT33 -> 152.30176 | AV33: =AU33/AS33 -> 0.80158823 | AW33: =AV33-AV11 -> 0.42613826 | BG33: HBV PCR Qualitative | BH33: 11 | BI33: -0.19458128 | BJ33: =BH33/$BH$37 -> 0.00070616935 | BK33: =BJ33*BI33 -> -0.00013740734
AH34: Biochemistry | AI34: LDL Direct | AJ34: 244 | AK34: 116.5082 | AL34: =AL33 -> 24.05 | AM34: 5.06 | AN34: =AK34+AL34+AM34 -> 145.6182 | AO34: =AN34-AN12 -> -272.96631 | AQ34: Biochemistry | AR34: LDL Direct | AS34: 350 | AT34: =AN34 -> 145.6182 | AU34: =AS34-AT34 -> 204.3818 | AV34: =AU34/AS34 -> 0.58394801 | AW34: =AV34-AV12 -> 0.77990374 | BG34: HBV PCR Quantitative | BH34: 9 | BI34: 0.11172161 | BJ34: =BH34/$BH$37 -> 0.00057777492 | BK34: =BJ34*BI34 -> 6.4549946e-05
AH35: Biochemistry | AI35: Uric Acid | AJ35: 205 | AK35: 11.160976 | AL35: =AL34 -> 24.05 | AM35: 5.06 | AN35: =AK35+AL35+AM35 -> 40.270976 | AO35: =AN35-AN13 -> -39.89353 | AQ35: Biochemistry | AR35: Uric Acid | AS35: 290 | AT35: =AN35 -> 40.270976 | AU35: =AS35-AT35 -> 249.72902 | AV35: =AU35/AS35 -> 0.86113457 | AW35: =AV35-AV13 -> 0.1375639 | BG35: HCV RNA PCR Qualitative | BH35: 52 | BI35: 0.13546798 | BJ35: =BH35/$BH$37 -> 0.0033382551 | BK35: =BJ35*BI35 -> 0.00045222668
AH36: Biochemistry | AI36: Urea UV | AJ36: 409 | AK36: 5.8190709 | AL36: =AL35 -> 24.05 | AM36: 5.06 | AN36: =AK36+AL36+AM36 -> 34.929071 | AO36: =AN36-AN14 -> -11.685435 | AQ36: Biochemistry | AR36: Urea UV | AS36: 290 | AT36: =AN36 -> 34.929071 | AU36: =AS36-AT36 -> 255.07093 | AV36: =AU36/AS36 -> 0.87955493 | AW36: =AV36-AV14 -> 0.040294602 | BG36: HCV RNA Quantitative | BH36: 45 | BI36: 0.15567766 | BJ36: =BH36/$BH$37 -> 0.0028888746 | BK36: =BJ36*BI36 -> 0.00044973323
AH37: Biochemistry | AI37: Glucose PAP | AJ37: 910 | AK37: 0.88896703 | AL37: =AL36 -> 24.05 | AM37: 5.06 | AN37: =AK37+AL37+AM37 -> 29.998967 | AO37: =AN37-AN15 -> -1.1555385 | AQ37: Biochemistry | AR37: Glucose PAP | AS37: 170 | AT37: =AN37 -> 29.998967 | AU37: =AS37-AT37 -> 140.00103 | AV37: =AU37/AS37 -> 0.82353549 | AW37: =AV37-AV15 -> 0.0067972855 | BH37: =SUM(BH25:BH36) -> 15577 | BK37: =SUM(BK25:BK36) -> 0.76999517
AH38: Biochemistry | AI38: Creatinine | AJ38: 429 | AK38: 7.3177925 | AL38: =AL37 -> 24.05 | AM38: 5.06 | AN38: =AK38+AL38+AM38 -> 36.427792 | AO38: =AN38-AN16 -> -17.576713 | AQ38: Biochemistry | AR38: Creatinine | AS38: 250 | AT38: =AN38 -> 36.427792 | AU38: =AS38-AT38 -> 213.57221 | AV38: =AU38/AS38 -> 0.85428883 | AW38: =AV38-AV16 -> 0.070306852
AH39: HbA1c | AI39: Hemoglobin (A1c) | AJ39: 815 | AK39: 212.57669 | AL39: =AL38 -> 24.05 | AM39: 4.5 | AN39: =AK39+AL39+AM39 -> 241.12669 | AO39: =AN39-AN17 -> -62.933738 | AQ39: HbA1c | AR39: Hemoglobin (A1c) | AS39: 850 | AT39: =AN39 -> 241.12669 | AU39: =AS39-AT39 -> 608.87331 | AV39: =AU39/AS39 -> 0.71632154 | AW39: =AV39-AV17 -> 0.074039692 | BG39: Reagents Cost % | BK39: =1-BK37 -> 0.23000483

Sheet Overhead Costs
A1: Main Centers
A2: Line-Item | B2: Cost-Head | C2: Average Cost Per Center PKR) | D2: Annual Cost Per Center PKR) | E2: Weightage
A3: Rent | B3: SG&A | C3: 125806 | D3: 1509672 | E3: =D3/$D$15 -> 0.53988701
A4: Electricity Bill | B4: Utilities | C4: 20198 | D4: 242379 | E4: =D4/$D$15 -> 0.086679274
A5: Generator Fuel | B5: Utilities | C5: 8885 | D5: 106620 | E5: =D5/$D$15 -> 0.038129311
A6: Internet | B6: SG&A | C6: 10120 | D6: 121435 | E6: =D6/$D$15 -> 0.043427432
A7: Water-Tanker | B7: Utilities | C7: 287 | D7: 3440 | E7: =D7/$D$15 -> 0.0012302085
A8: Grocery | B8: SG&A | C8: 5168 | D8: 62010 | E8: =D8/$D$15 -> 0.022175938
A9: Drinking Water | B9: SG&A | C9: 1694 | D9: 20330 | E9: =D9/$D$15 -> 0.0072703891
A10: PTCL Bill | B10: SG&A | C10: 2888 | D10: 34661 | E10: =D10/$D$15 -> 0.012395423
A11: Security services | B11: SG&A | C11: 15751 | D11: 189007 | E11: =D11/$D$15 -> 0.067592446
A12: Repairs & Maintenance | B12: SG&A | C12: 10568 | D12: 126811 | E12: =D12/$D$15 -> 0.045349991
A13: Stationery | B13: Supplies | C13: 13225 | D13: 158694 | E13: =D13/$D$15 -> 0.056751949
A14: Office Supplies | B14: Supplies | C14: 18435 | D14: 221215 | E14: =D14/$D$15 -> 0.079110631
A15: Total | C15: =SUM(C3:C14) -> 233025 | D15: =SUM(D3:D14) -> 2796274 | E15: =D15/$D$15 -> 1
A17: Satellite Centers
A18: Line-Item | B18: Cost-Head | C18: Average Cost Per Center PKR) | D18: Annual Cost Per Center PKR)
A19: Rent | B19: SG&A | C19: 63651 | D19: 763815 | E19: =D19/$D$32 -> 0.50680201
A20: Electricity Bill | B20: Utilities | C20: 4805 | D20: 57661 | E20: =D20/$D$32 -> 0.038258886
A21: Generator Fuel | B21: Utilities | C21: 5329 | D21: 63952 | E21: =D21/$D$32 -> 0.042433053
A22: Internet | B22: SG&A | C22: 9276 | D22: 111315 | E22: =D22/$D$32 -> 0.073859071
A23: Water-Tanker | B23: Utilities | C23: 3692 | D23: 44305 | E23: =D23/$D$32 -> 0.029396992
A24: Grocery | B24: SG&A | C24: 2290 | D24: 27483 | E24: =D24/$D$32 -> 0.018235358
A25: Drinking Water | B25: SG&A | C25: 826 | D25: 9918 | E25: =D25/$D$32 -> 0.0065807327
A26: PTCL Bill | B26: SG&A | C26: 2400 | D26: 28806 | E26: =D26/$D$32 -> 0.019113187
A27: Security services | B27: SG&A | C27: 15074 | D27: 180894 | E27: =D27/$D$32 -> 0.12002572
A28: Bike Fuel | B28: SG&A | C28: 9675 | D28: 116097 | E28: =D28/$D$32 -> 0.077031995
A29: Repairs & Maintenance | B29: SG&A | C29: 7265 | D29: 87182 | E29: =D29/$D$32 -> 0.057846485
A30: Stationery | B30: Supplies | C30: 1014 | D30: 12169 | E30: =D30/$D$32 -> 0.008074303
A31: Office Supplies | B31: Supplies | C31: 294 | D31: 3530 | E31: =D31/$D$32 -> 0.0023422047
A32: Total | C32: =SUM(C19:C31) -> 125591 | D32: =SUM(D19:D31) -> 1507127 | E32: =D32/$D$32 -> 1
C34: =C15-C32 -> 107434 | D34: =D15-D32 -> 1289147

Sheet Average_charge_3_Main_centers
A1: Sr. # | B1: Net Sales | C1: Commerical Tests
A2: SZC-KORANGI | B2: 2706395 | C2: 6913
A3: SZC-MALIR | B3: 2243231 | C3: 5469
A4: SZC-NAZIMABAD MAIN CENTER | B4: 3366587 | C4: 7722
A7: Total | B7: =SUM(B2:B6) -> 8316213 | C7: =SUM(C2:C6) -> 20104
A9: Average Charge | B9: =B7/C7 -> 413.65962
A11: Average Sales | C11: =AVERAGE(C2:C4) -> 6701.3333

Sheet Central _support
A1: Staff Member | B1: Monthly Salary | C1: Fringe | D1: Monthly Total Salary | E1: Annual Salary | G1: Line-Item | H1: Avearge Monthly Costs (PKR) | I1: Annual
A2: Lab Manager | B2: 90000 | C2: =B2*0.15 -> 13500 | D2: =B2+C2 -> 103500 | E2: =D2*12 -> 1242000 | G2: Rent | H2: 20000 | I2: =H2*12 -> 240000
A3: Technicians | B3: 20330 | C3: =B3*0.15 -> 3049.5 | D3: =B3+C3 -> 23379.5 | E3: =D3*12 -> 280554 | G3: Electricity Bill | H3: 37230 | I3: =H3*12 -> 446760
A4: Technicians | B4: 20330 | C4: =B4*0.15 -> 3049.5 | D4: =B4+C4 -> 23379.5 | E4: =D4*12 -> 280554 | G4: Internet | H4: 18000 | I4: =H4*12 -> 216000
A5: Technicians | B5: 20330 | C5: =B5*0.15 -> 3049.5 | D5: =B5+C5 -> 23379.5 | E5: =D5*12 -> 280554 | G5: PTCL Bill | H5: 3670 | I5: =H5*12 -> 44040
A6: Technicians | B6: 20330 | C6: =B6*0.15 -> 3049.5 | D6: =B6+C6 -> 23379.5 | E6: =D6*12 -> 280554 | G6: Stationery | H6: 5000 | I6: =H6*12 -> 60000
A7: Total | B7: =SUM(B2:B6) -> 171320 | C7: =SUM(C2:C6) -> 25698 | D7: =SUM(D2:D6) -> 197018 | E7: =SUM(E2:E6) -> 2364216 | G7: Office Supplies | H7: 70000 | I7: =H7*12 -> 840000
G8: Total | H8: =SUM(H2:H7) -> 153900 | I8: =H8*12 -> 1846800
C9: Monthly | D9: Annual
A10: Total Cost | C10: =H8+D7 -> 350918 | D10: =I8+E7 -> 4211016
D11: =D10/135 -> 31192.711

Sheet Summary_Tables
A1: Revenue Per Lab Collection Unit
B2: Tests | C2: Spending | D2: Daily TR | E2: Monthly TR | F2: Annual TR
A3: Lower | B3: 40 | C3: 1500 | D3: =B3*C3 -> 60000 | E3: =D3*24 -> 1440000 | F3: =E3*12 -> 17280000
A4: Median | B4: 45 | C4: 1750 | D4: =B4*C4 -> 78750 | E4: =D4*24 -> 1890000 | F4: =E4*12 -> 22680000
A5: Upper | B5: 50 | C5: 2000 | D5: =B5*C5 -> 100000 | E5: =D5*24 -> 2400000 | F5: =E5*12 -> 28800000 | M5: Projected Revenues From Labs
A7: Revenue Per HealthCare Provider | N7: Labs | O7: Providers | P7: Patients | Q7: Average Monthly | R7: Average Annual
B8: OPD | C8: % Tests | D8: Spending | E8: Daily TR | F8: Monthly TR | G8: Annual TR | H8: Providers | I8: Monthly TR | J8: Annual TR | M8: Lower | N8: =E3 -> 1440000 | O8: =I9 -> 360000 | P8: =F17 -> 60000 | Q8: =AVERAGE(N8:P8) -> 620000 | R8: =Q8*12 -> 7440000
A9: Lower | B9: 30 | C9: 0.1 | D9: 1000 | E9: =B9*C9*D9 -> 3000 | F9: =E9*24 -> 72000 | G9: =F9*12 -> 864000 | H9: 5 | I9: =H9*F9 -> 360000 | J9: =H9*G9 -> 4320000 | M9: Median | N9: =E4 -> 1890000 | O9: =I10 -> 1575000 | P9: =F18 -> 360000 | Q9: =AVERAGE(N9:P9) -> 1275000 | R9: =Q9*12 -> 15300000
A10: Median | B10: 35 | C10: 0.15 | D10: 1250 | E10: =B10*C10*D10 -> 6562.5 | F10: =E10*24 -> 157500 | G10: =F10*12 -> 1890000 | H10: 10 | I10: =H10*F10 -> 1575000 | J10: =H10*G10 -> 18900000 | M10: Upper | N10: =E5 -> 2400000 | O10: =I11 -> 4320000 | P10: =F19 -> 1080000 | Q10: =AVERAGE(N10:P10) -> 2600000 | R10: =Q10*12 -> 31200000
A11: Upper | B11: 40 | C11: 0.2 | D11: 1500 | E11: =B11*C11*D11 -> 12000 | F11: =E11*24 -> 288000 | G11: =F11*12 -> 3456000 | H11: 15 | I11: =H11*F11 -> 4320000 | J11: =H11*G11 -> 51840000
A14: Revenue Patients
B16: OPD | C16: Tests | D16: Spending | E16: Daily TR | F16: Monthly TR | G16: Annual TR
A17: Lower | B17: 10 | C17: 0.5 | D17: 500 | E17: =B17*C17*D17 -> 2500 | F17: =E17*24 -> 60000 | G17: =F17*12 -> 720000
A18: Median | B18: 15 | C18: 1 | D18: 1000 | E18: =B18*C18*D18 -> 15000 | F18: =E18*24 -> 360000 | G18: =F18*12 -> 4320000
A19: Upper | B19: 20 | C19: 1.5 | D19: 1500 | E19: =B19*C19*D19 -> 45000 | F19: =E19*24 -> 1080000 | G19: =F19*12 -> 12960000
B22: *Green cells are assumptions not based on survey

Sheet Charts_Labs
A1: Row Labels | B1: Count of How many daily clients come for lab tests in your branch? | D1: Row Labels | E1: Count of On average how much does each patient spend during one visit
A2: 10-20 | B2: 9 | D2: 1000-1500 | E2: 25 | K2: Revenue Per Lab Collection Unit
A3: 20-30 | B3: 9 | D3: 1500-2000 | E3: 13 | F3: Median
A4: 30-40 | B4: 11 | D4: 2000-2500 | E4: 3 | J4: Tests | K4: Spending | L4: Daily TR | M4: Monthly TR | N4: Annual TR
A5: 40-50 | B5: 8 | C5: Median | D5: 2500-3000 | E5: 5 | I5: Lower | J5: 40 | K5: 1500 | L5: =J5*K5 -> 60000 | M5: =L5*24 -> 1440000 | N5: =M5*12 -> 17280000
A6: 50-60 | B6: 8 | D6: 500-1000 | E6: 11 | I6: Median | J6: 45 | K6: 1750 | L6: =J6*K6 -> 78750 | M6: =L6*24 -> 1890000 | N6: =M6*12 -> 22680000
A7: Less than 10 | B7: 3 | D7: Less than 500 | E7: 3 | I7: Upper | J7: 50 | K7: 2000 | L7: =J7*K7 -> 100000 | M7: =L7*24 -> 2400000 | N7: =M7*12 -> 28800000
A8: More than 60 | B8: 14 | D8: More than 3,000 | E8: 2
A9: (blank) | D9: (blank)
A10: Grand Total | B10: 62 | D10: Grand Total | E10: 62

Sheet Charts_Providers
A1: Row Labels | B1: Count of Daily Average OPD | E1: Row Labels | F1: Count of What percentage of patients are prescribed lab tests? | I1: Row Labels | J1: Count of On average how much does each patient spend on lab tests in your clinic?
A2: 10-20 | B2: 7 | E2: 0-10% | F2: 20 | I2: < 500 | J2: 20 | N2: Revenue Per HealthCare Provider
A3: 20-30 | B3: 16 | E3: 10-20% | F3: 18 | G3: Median | I3: 1000-1500 | J3: 13 | K3: Median
A4: 30 - 40 | B4: 13 | C4: Median | E4: 20-30% | F4: 9 | I4: 1500-2000 | J4: 7 | M4: OPD | N4: % Tests | O4: Spending | P4: Daily TR | Q4: Monthly TR | R4: Annual TR | S4: Providers | T4: Monthly TR | U4: Annual TR
A5: 40 - 50 | B5: 13 | E5: 30-40% | F5: 7 | I5: 2000-2500 | J5: 3 | L5: Lower | M5: 30 | N5: 0.1 | O5: 1000 | P5: =M5*N5*O5 -> 3000 | Q5: =P5*24 -> 72000 | R5: =Q5*12 -> 864000 | S5: 5 | T5: =S5*Q5 -> 360000 | U5: =S5*R5 -> 4320000
A6: 50-60 | B6: 4 | E6: 40-50% | F6: 4 | I6: 500-1000 | J6: 18 | L6: Median | M6: 35 | N6: 0.15 | O6: 1250 | P6: =M6*N6*O6 -> 6562.5 | Q6: =P6*24 -> 157500 | R6: =Q6*12 -> 1890000 | S6: 10 | T6: =S6*Q6 -> 1575000 | U6: =S6*R6 -> 18900000
A7: Less than 10 | B7: 5 | E7: More than 50% | F7: 3 | I7: (blank) | L7: Upper | M7: 40 | N7: 0.2 | O7: 1500 | P7: =M7*N7*O7 -> 12000 | Q7: =P7*24 -> 288000 | R7: =Q7*12 -> 3456000 | S7: 15 | T7: =S7*Q7 -> 4320000 | U7: =S7*R7 -> 51840000
A8: More than 60 | B8: 3 | E8: (blank) | I8: Grand Total | J8: 61
A9: (blank) | E9: Grand Total | F9: 61
A10: Grand Total | B10: 61

Sheet Charts_Patients
A1: Row Labels | B1: Count of Total family members have had a lab test in past one month (incl self) | E1: Row Labels | F1: Count of Total spending on lab tests in past one month | I1: Row Labels | J1: Count of How many tests were done last month.?
A2: Four or More | B2: 4 | E2: 1000-2000 | F2: 17 | I2: Four or More | J2: 13
A3: None | B3: 32 | E3: 2000-3000 | F3: 11 | I3: None | J3: 35
A4: One | B4: 56 | C4: Median | E4: 3000-5000 | F4: 6 | I4: One | J4: 32 | K4: Median | O4: OPD | P4: Tests | Q4: Spending | R4: Daily TR | S4: Monthly TR | T4: Annual TR
A5: Three | B5: 2 | E5: 5000-8000 | F5: 2 | I5: Three | J5: 15 | N5: Lower | O5: 20 | P5: 0.5 | Q5: 500 | R5: =O5*P5*Q5 -> 5000 | S5: =R5*24 -> 120000 | T5: =S5*12 -> 1440000
A6: Two | B6: 17 | E6: 8000-10000 | F6: 1 | I6: Two | J6: 16 | N6: Median | O6: 25 | P6: 1 | Q6: 1000 | R6: =O6*P6*Q6 -> 25000 | S6: =R6*24 -> 600000 | T6: =S6*12 -> 7200000
A7: Grand Total | B7: 111 | E7: Less than 1000 | F7: 72 | G7: Median | I7: (blank) | N7: Upper | O7: 30 | P7: 1.5 | Q7: 1500 | R7: =O7*P7*Q7 -> 67500 | S7: =R7*24 -> 1620000 | T7: =S7*12 -> 19440000
E8: More than 10,000 | F8: 2 | I8: Grand Total | J8: 111
E9: (blank)
E10: Grand Total | F10: 111

Sheet Labs
A1: Timestamp | B1: Name of Interviewer | C1: Responder name | D1: Designation | E1: Years of employment at current employer | F1: Qualifications | G1: Total Years of Experience | H1: How many daily clients come for lab tests in your branch? | I1: How many of the following tests are conducted on daily basis | J1: On average how much does each patient spend during one visit | K1: How many of the following tests are conducted on daily basis [0-5] | L1: What are the three most important reasons that patients choose your service? | M1: What is the staffing at your collection centers? | N1: What is the average area of each collection center? | O1: On average what is the daily clientele of your centers? | P1: On average what is the revenue of your collection centers? | Q1: What is the revenue of the highest performing centers? | R1: What is the revenue of the lowest performing centers? | S1: Monthly cost of running your center | T1: How many full-time staff at your center? | U1: How many part-time staff at your center? | V1: What is the percentage of revenues for other management, marketing, development and overhead costs? | W1: Most important factor in deciding lab for testing | X1: What are the three best marketing strategies and initiatives? | Y1: How long does it take for a center to be sustainable—covering operating costs? | Z1: How long does it take for sales to become stable once centers are open? | AA1: What is the average annual growth for a center once sales are stable? | AB1: What are the top performing cities by average sales per center? | AC1: Is there difference between rural vs urban in average sales per center? | AD1: Is there difference between provinces? | AE1: [Row 1] | AF1: % Spent on Tests: [What % is spent on CBC or CBC/ESR] | AG1: % Spent on Tests: [What % is spent on Biochemistry (LFTs, Lipid Profile, Creatinine, Diabetes tests)] | AH1: % Spent on Tests: [What % is spent on urine tests] | AI1: % Spent on Tests: [What % is spent on special chemistry] | AJ1: LAB Name | AK1: Branch | AL1: How many of the following tests are conducted on daily basis [6-10] | AM1: How many of the following tests are conducted on daily basis [15-20] | AN1: How many of the following tests are conducted on daily basis [20-25] | AO1: How many of the following tests are conducted on daily basis [11-15] | AP1: How many of the following tests are conducted on daily basis [25+] | AQ1: How many of the following tests are conducted on daily basis [2. LFT] | AR1: How many of the following tests are conducted on daily basis [3. Lipid Profile] | AS1: How many of the following tests are conducted on daily basis [4. Dengue] | AT1: How many of the following tests are conducted on daily basis [5. Malaria] | AU1: How many of the following tests are conducted on daily basis [6. Typhoid] | AV1: How many of the following tests are conducted on daily basis [7. Sugar test] | AW1: How many of the following tests are conducted on daily basis [8. HbA1c] | AX1: How many of the following tests are conducted on daily basis [9. Creatinine] | AY1: How many of the following tests are conducted on daily basis [10. Hormones] | AZ1: How many of the following tests are conducted on daily basis [11. Urine] | BA1: How many of the following tests are conducted on daily basis [12. PCRs]
A2: 43231.655 | C2: Usama | D2: Reception | E2: 1.5 | H2: Less than 10 | J2: Less than 500 | K2: Lipid Profile, Dengue, Malaria, PCRs | S2: 100000-150000 | T2: 25 | U2: 0 | W2: Lab Reputation | AJ2: Radiology | AK2: Bahadurabad | AL2: CBC / ESR, LFT, Typhoid, Sugar test, HbA1c, Creatinine, Hormones, Urine
A3: 43231.669 | C3: Hafiza Shabana Ashraf | D3: Shift Incharge | E3: 3 | H3: More than 60 | J3: 500-1000 | S3: no Idea | T3: 25 | U3: 0 | W3: Lab Reputation, Lab Quality, Lab Staff, Referral by Doctor, Pathologist | AJ3: Chugtai Lab | AK3: Bahadurabad | AL3: Dengue, Malaria, PCRs | AP3: CBC / ESR, LFT, Lipid Profile, Typhoid, Sugar test, HbA1c, Creatinine, Hormones, Urine
A4: 43231.715 | C4: Agha Khan-Collection Centre | D4: Reception | E4: No | H4: 40-50 | J4: 500-1000 | K4: Dengue, Malaria, Typhoid, PCRs | S4: No idea | T4: 2 | U4: 0 | W4: Lab Reputation, Lab Quality, Referral by Doctor | AJ4: Agha Khan Mehmodabad | AK4: Mehmodabad | AL4: HbA1c | AM4: Creatinine | AO4: LFT, Lipid Profile, Sugar test, Urine | AP4: CBC / ESR
A5: 43231.717 | C5: Agha Khan-Collection Point | D5: Reception | E5: Not disclosing | H5: More than 60 | J5: More than 3,000 | K5: Lipid Profile, Dengue, Malaria, Typhoid | S5: Don't know | T5: 4 | U5: 0 | W5: Lab Reputation, Lab Quality, Referral by Doctor | AJ5: Agha Khan | AK5: DHA Phase 2 | AL5: HbA1c, Hormones, PCRs | AM5: Urine | AN5: Creatinine | AO5: LFT, Sugar test | AP5: CBC / ESR
A6: 43279.865 | C6: Bushra | D6: MR | E6: 4 | H6: More than 60 | J6: 1000-1500 | K6: Dengue, Malaria, Typhoid, Sugar test | S6: 150000 - 200000 | T6: 5 | U6: 0 | W6: Lab Reputation, Lab Quality, Referral by Doctor, Location | AJ6: DOW | AK6: Korangi 5.00 | AM6: PCRs | AN6: HbA1c, Hormones | AP6: CBC / ESR, LFT, Lipid Profile, Creatinine, Urine
A7: 43279.867 | C7: Junaid Ahmed | D7: Owner | E7: 2 | H7: 30-40 | J7: 1000-1500 | K7: Dengue, Malaria, Typhoid, Sugar test | S7: 100000 - 150000 | T7: 5 | U7: 0 | W7: Price, Lab Reputation, Referral by Doctor, Location | AJ7: The Medicare Lab | AK7: Main Branch | AM7: Lipid Profile, PCRs | AN7: LFT | AO7: CBC / ESR, Hormones | AP7: Creatinine, Urine
A8: 43279.869 | C8: MR | D8: MR | E8: 6 | H8: 40-50 | J8: Less than 500 | K8: Dengue, Malaria, Hormones, PCRs | S8: 150000 - 200000 | T8: 12 | U8: 0 | W8: Price, Lab Reputation, Referral by Doctor, Location | AJ8: Hussaini Lab | AK8: Korangi | AL8: Sugar test, HbA1c | AM8: LFT, Creatinine, Urine | AO8: Lipid Profile, Typhoid | AP8: CBC / ESR
A9: 43279.87 | C9: Owais Khan | D9: MR | E9: 1.5 | H9: 30-40 | J9: 2500-3000 | K9: Dengue, Malaria, Typhoid | S9: 100000 - 150000 | T9: 4 | U9: 0 | W9: Lab Reputation, Lab Quality, Referral by Doctor, Location | AJ9: Agha Khan | AK9: Korangi | AL9: LFT, Lipid Profile, Sugar test, PCRs | AM9: CBC / ESR, HbA1c, Creatinine | AO9: Hormones | AP9: Urine
A10: 43279.873 | C10: Receptionis | D10: Reception | E10: 5 | H10: 30-40 | J10: Less than 500 | K10: LFT, Lipid Profile, Dengue, Malaria, Typhoid, HbA1c, Creatinine, Hormones, PCRs | S10: 100000 - 150000 | T10: 5 | U10: 0 | W10: Price, Lab Reputation, Lab Quality, Location | AJ10: Al Khidmat | AK10: Korangi | AM10: CBC / ESR | AO10: Sugar test, Urine
A11: 43279.875 | C11: Noman | D11: Owner and X-Ray Tech | E11: 5 | H11: 10-20 | J11: 1000-1500 | K11: LFT, Lipid Profile, Dengue, Malaria, HbA1c, Creatinine, Hormones, Urine, PCRs | S11: 150000 - 200000 | T11: 11 | U11: 0 | W11: Referral by Doctor | AJ11: Smart Lab | AK11: Main Branch-Korangi | AL11: CBC / ESR, Typhoid, Sugar test
A12: 43279.883 | C12: Reception | D12: Reception | E12: 5 | H12: More than 60 | J12: 1000-1500 | K12: Dengue, Malaria, Typhoid | S12: 150000 - 200000 | T12: 5 | U12: 0 | W12: Price, Lab Reputation, Referral by Doctor, Location | AJ12: Mehdi Manji | AK12: Korangi-Main | AM12: Lipid Profile | AO12: Sugar test, HbA1c, PCRs | AP12: CBC / ESR, LFT, Creatinine, Hormones, Urine
A13: 43279.887 | C13: Reception | D13: Reception | E13: 2 | H13: More than 60 | J13: 1000-1500 | K13: Dengue, Malaria, Typhoid, PCRs | S13: 100000 - 150000 | T13: 5 | U13: 0 | W13: Price, Lab Reputation, Referral by Doctor, Location | AJ13: Shaukat Khanum | AK13: Korangi | AL13: Sugar test | AM13: HbA1c, Creatinine, Hormones | AN13: Lipid Profile | AP13: CBC / ESR, LFT, Urine
A14: 43336.794 | C14: Reception | D14: Recption | E14: 5 | H14: More than 60 | J14: 2500-3000 | K14: Dengue, Malaria, Typhoid, HbA1c, PCRs | S14: 200000 | T14: 5 | U14: 2 | W14: Lab Reputation, Lab Quality, Pathologist | AJ14: Agha Khan Lab | AK14: Clifton Teen Talwar | AL14: Hormones | AM14: Sugar test | AN14: Creatinine, Urine | AO14: Lipid Profile | AP14: CBC / ESR, LFT
A15: 43386.011 | C15: Azhar | D15: Reception | E15: 10 | H15: 20-30 | J15: 500-1000 | K15: CBC / ESR, Malaria, Sugar test, HbA1c | S15: 100000 | T15: 0 | U15: 2 | W15: Price, Lab Quality | AJ15: AKU | AK15: Korangi | AL15: LFT, Creatinine, Urine
A16: 43386.013 | C16: Aamir | D16: Reception | E16: 2 | H16: 20-30 | J16: 1000-1500 | K16: CBC / ESR, LFT, Malaria | S16: 150000 | T16: 0 | U16: 2 | W16: Price, Lab Quality | AJ16: AKU | AK16: Mehmodabad | AL16: Sugar test, HbA1c, Creatinine | AO16: Urine
A17: 43386.014 | C17: Reception | D17: Reception | E17: 7 | H17: 50-60 | J17: 1000-1500 | K17: LFT, Malaria | S17: 225000 | T17: 0 | U17: 5 | W17: Price, Lab Quality, Referral by Doctor | AJ17: Essa Lab | AK17: Zamzama | AL17: Urine | AM17: CBC / ESR, Sugar test, HbA1c | AO17: Creatinine
A18: 43386.016 | C18: Reception | D18: Reception | E18: 9 | H18: 30-40 | J18: 500-1000 | S18: 250000 | T18: 0 | U18: 4 | W18: Lab Quality, Referral by Doctor | AJ18: Essa Lab | AK18: Medilink | AL18: Malaria, Creatinine, Urine | AM18: Sugar test | AO18: LFT, HbA1c | AP18: CBC / ESR
A19: 43386.018 | C19: Reception | D19: Reception | E19: 5 | H19: 40-50 | J19: 1000-1500 | K19: Malaria | S19: 250000 | T19: 0 | U19: 4 | W19: Lab Quality, Referral by Doctor | AJ19: Essa Lab | AK19: Badar Phase V (Ext) | AL19: LFT | AM19: Creatinine | AN19: CBC / ESR, Sugar test | AO19: Urine
A20: 43386.02 | C20: Reception | D20: Reception | E20: 7 | H20: 20-30 | J20: 1500-2000 | K20: Malaria | S20: 150000 | T20: 0 | U20: 2 | W20: Lab Quality, Referral by Doctor | AJ20: AKU | AK20: Defence Delton Market | AL20: LFT, Creatinine, Urine | AM20: CBC / ESR | AN20: Sugar test | AO20: HbA1c
A21: 43386.022 | C21: Reception | D21: Reception | E21: 2 | H21: 30-40 | J21: 2000-2500 | S21: 210000 | T21: 0 | U21: 2 | W21: Price, Lab Quality, Referral by Doctor | AJ21: AKU | AK21: Khayaban-e-Badar | AL21: LFT, Malaria, Creatinine | AM21: CBC / ESR, HbA1c | AN21: Sugar test | AO21: Urine
A22: 43386.025 | C22: Reception | D22: Reception | E22: 7 | H22: 20-30 | J22: 2500-3000 | S22: 200000 | T22: 0 | U22: 4 | W22: Lab Quality, Referral by Doctor | AJ22: AKU | AK22: Korangi Medical centre | AL22: CBC / ESR, LFT, Malaria, Creatinine | AM22: Sugar test | AN22: HbA1c | AO22: Urine
A23: 43386.027 | C23: Reception | D23: Reception | E23: 10 | H23: 30-40 | J23: 1000-1500 | K23: CBC / ESR, LFT, Malaria | S23: 150000 | T23: 0 | U23: 2 | W23: Lab Quality, Referral by Doctor | AJ23: Chugtai Lab | AK23: Block-8, Clifton | AM23: Sugar test, Creatinine, Urine | AN23: HbA1c
A24: 43386.028 | C24: Reception | D24: Reception | E24: 5 | H24: 40-50 | J24: 1500-2000 | S24: 210000 | T24: 0 | U24: 6 | W24: Lab Quality, Referral by Doctor | AJ24: Chugtai lab | AK24: Sehar Commercial DHA | AL24: Malaria, Urine | AM24: LFT | AN24: Creatinine | AP24: CBC / ESR, Sugar test, HbA1c
A25: 43386.03 | C25: Reception | D25: Reception | E25: 8 | H25: 30-40 | J25: 1000-1500 | K25: Malaria, Creatinine | S25: 120000 | T25: 0 | U25: 4 | W25: Price, Lab Quality, Referral by Doctor | AJ25: Chugtai Lab | AK25: Malir Township colony | AL25: LFT, Urine | AM25: CBC / ESR | AP25: Sugar test, HbA1c
A26: 43386.032 | C26: Reception | D26: Reception | E26: 3 | H26: 40-50 | J26: 1500-2000 | S26: 200000 | T26: 2 | U26: 4 | W26: Price, Lab Quality, Referral by Doctor | AJ26: Sindh Lab | AK26: Hilal-e-Ahmr | AL26: Malaria | AN26: LFT, Sugar test, HbA1c, Creatinine | AO26: Urine | AP26: CBC / ESR
A27: 43386.033 | C27: Anwar | D27: Owner | E27: 10 | H27: 20-30 | J27: 1000-1500 | K27: LFT, Malaria | S27: 175000 | T27: 1 | U27: 2 | W27: Price, Lab Quality, Referral by Doctor | AJ27: The Grace Laboratory | AK27: Korangi 5 | AL27: CBC / ESR, Sugar test, Creatinine, Urine | AO27: HbA1c
A28: 43386.035 | C28: Reception | D28: Reception | E28: 7 | H28: 10-20 | J28: 1000-1500 | K28: CBC / ESR, LFT, Malaria | S28: 150000 | T28: 0 | U28: 3 | W28: Price, Lab Quality, Referral by Doctor | AJ28: Global Lab Diagnostic Centre | AK28: Korangi | AL28: Sugar test, Creatinine, Urine | AO28: HbA1c
A29: 43386.038 | C29: Reception | D29: Reception | E29: 7 | H29: More than 60 | J29: 1000-1500 | S29: 200000 | T29: 0 | U29: 4 | W29: Price, Lab Quality, Referral by Doctor | AJ29: Hussaini | AK29: Mehmodabad | AL29: Malaria | AM29: LFT, Creatinine | AN29: CBC / ESR | AP29: Sugar test, HbA1c, Urine
A30: 43386.039 | C30: Reception | D30: Reception | E30: 5 | H30: 50-60 | J30: 1000-1500 | K30: Malaria | S30: 200000 | T30: 2 | U30: 4 | W30: Price, Lab Quality, Referral by Doctor | AJ30: Mehdi A Manji | AK30: PECHS Block 2 | AM30: LFT | AN30: Creatinine, Urine | AP30: CBC / ESR, Sugar test, HbA1c
A31: 43386.041 | C31: Reception | D31: Reception | E31: 10 | H31: More than 60 | J31: 1000-1500 | S31: 200000 | T31: 2 | U31: 6 | W31: Price, Lab Quality, Referral by Doctor | AJ31: Mehdi A Manji | AK31: DHS Malir | AM31: LFT | AN31: Malaria | AO31: Creatinine, Urine | AP31: CBC / ESR, Sugar test, HbA1c
A32: 43386.042 | C32: Farhan | D32: Reception | E32: 7 | H32: 30-40 | J32: 1500-2000 | K32: LFT | S32: 175000 | T32: 1 | U32: 3 | W32: Price, Lab Quality, Referral by Doctor | AJ32: Dow Lab | AK32: Jami Commercial | AL32: CBC / ESR, Malaria | AM32: Sugar test, Creatinine, Urine | AP32: HbA1c
A33: 43386.044 | C33: Reception | D33: Reception | E33: 9 | H33: 10-20 | J33: 500-1000 | K33: CBC / ESR, LFT, Malaria, HbA1c | S33: 100000 | T33: 0 | U33: 3 | W33: Price, Lab Quality, Referral by Doctor | AJ33: Drs. Shamsi and Ansari Diagnostic | AK33: Jami Commercial, DHA | AL33: Sugar test, Creatinine | AO33: Urine
A34: 43388.703 | C34: Syed Mumtaz Ali | D34: Receptionist (Inchage) | E34: From 20 Years | H34: 10-20 | J34: 500-1000 | K34: LFT, Malaria | S34: 50,000/= | T34: 3 | U34: 5 | W34: Lab Quality | AJ34: Karachi XRay & Lab | AK34: Nazimabad -7 | AL34: CBC / ESR, Sugar test, HbA1c, Creatinine | AO34: Urine
A35: 43388.705 | C35: Kashan Akrm | D35: Admin | E35: 5 years | H35: 10-20 | J35: 500-1000 | K35: Malaria, HbA1c | S35: no | T35: 8 | U35: 10 | W35: Lab Quality | AJ35: Karachi XRay | AK35: Nazimabad | AL35: CBC / ESR, LFT, Creatinine | AM35: Urine | AO35: Sugar test
A36: 43388.707 | C36: Bassam | D36: Manager Lab | E36: 1 year | H36: 10-20 | J36: 500-1000 | K36: CBC / ESR, LFT, Malaria, Sugar test, HbA1c, Creatinine, Urine | S36: 1 Lac | T36: 2 | U36: 0 | W36: Lab Quality | AJ36: Metro Lab | AK36: Nazimabad
A37: 43388.708 | C37: Sunaina | D37: Receptionist | E37: From 5 Years | H37: 20-30 | J37: 1000-1500 | K37: CBC / ESR, LFT, Malaria, Sugar test, HbA1c, Creatinine, Urine | S37: 80,000/= | T37: 7 | U37: 5 | W37: Price | AJ37: Ehsan Ullah Lab | AK37: Nazimabad Head Office
A38: 43388.711 | C38: Luba Qasim | D38: Receptiousit | E38: 5 Years | H38: 20-30 | J38: 500-1000 | K38: LFT, Malaria, Sugar test | S38: 50.000/= | T38: 1 | U38: 5 | W38: Lab Quality | AJ38: Qasim | AK38: Karachi XRay & Diaguostic Center | AL38: HbA1c | AM38: CBC / ESR, Urine | AO38: Creatinine
A39: 43388.712 | C39: Ahmed Bilal | D39: Inchage | E39: 3 Years | H39: 30-40 | J39: 1500-2000 | K39: CBC / ESR, LFT | S39: 6 to 7 Lac | T39: 3 | U39: 0 | W39: Price | AJ39: Dow Lab | AK39: Memon Goth | AL39: Malaria, Sugar test | AO39: HbA1c, Creatinine, Urine
A40: 43388.714 | C40: Seema | D40: Receptionist | E40: 4 Month | H40: 10-20 | J40: 1000-1500 | K40: CBC / ESR, LFT, Malaria, Sugar test, HbA1c, Creatinine, Urine | S40: 1 Lac | T40: 2 | U40: 1 | W40: Price | AJ40: Raheel Lab | AK40: Gulshan-e-Hadid
A41: 43388.715 | C41: Jameel Ahmed | D41: Incharge | E41: 7 years | H41: Less than 10 | J41: 1000-1500 | K41: CBC / ESR, LFT, Malaria, Sugar test, HbA1c, Creatinine, Urine | S41: 40 to 50,000/= | T41: 3 | U41: 1 | W41: Price | AJ41: Fatha Lab | AK41: Memon Goth
A42: 43388.717 | C42: Ali Raza Zadi | D42: Receptionist | E42: 4 Years | H42: 50-60 | J42: 2000-2500 | S42: 2 Lac | T42: 3 | U42: 6 | W42: Price | AJ42: Dow Lab | AK42: Shah Faisal Collection Point | AL42: Malaria | AM42: LFT, HbA1c, Creatinine | AN42: CBC / ESR, Sugar test, Urine
A43: 43388.723 | C43: fiza | D43: Phelobtius | E43: 1 years | H43: 50-60 | J43: 1500-2000 | K43: Malaria, Urine | S43: 50,000/= | T43: 2 | U43: 6 | W43: Lab Quality | AJ43: Dr Essa | AK43: Shah Faisal | AL43: CBC / ESR, LFT, Creatinine | AO43: HbA1c | AP43: Sugar test
A44: 43388.727 | C44: Kiran Zehra | D44: Blood Bank Tech | E44: Since 2014 | H44: Less than 10 | J44: 1500-2000 | K44: CBC / ESR, LFT, Sugar test, Creatinine, Urine | S44: 1 Lac | T44: 2 | U44: 0 | W44: Price | AJ44: Hussani Lab | AK44: Shah Faisal (BB18)
A45: 43397.54 | C45: Faisal | D45: Regional Manager | E45: 20 Years | H45: 40-50 | J45: 500-1000 | K45: LFT, Malaria, HbA1c | S45: 2-3 Lac+ | T45: 12 | U45: 6 | W45: Referral by Doctor | AJ45: Hussaini Lab | AK45: Malir | AL45: CBC / ESR, Sugar test, Creatinine | AO45: Urine
A46: 43397.542 | C46: Kamran (112040) | D46: Phelbotmist | E46: 3 Years | H46: More than 60 | J46: 1000-1500 | K46: Malaria | S46: 1 Lac+ | T46: 3 | U46: 1 | W46: Price | AJ46: Dow Lab | AK46: Garden Branch (Soldier Bazaar) | AO46: HbA1c, Creatinine | AP46: CBC / ESR, LFT, Sugar test, Urine
A47: 43397.545 | C47: S.Firdus Sultana | D47: MR | E47: 12 YEARS | H47: More than 60 | J47: More than 3,000 | K47: Malaria | S47: 3-4 Lac | T47: 14 | U47: 0 | W47: Lab Quality | AJ47: Agha Khan Lab | AK47: Malir | AN47: LFT, HbA1c, Creatinine | AP47: CBC / ESR, Sugar test, Urine
A48: 43397.546 | C48: Ali Hussan | D48: MO | E48: 3 YEARS | H48: 10-20 | J48: 1000-1500 | K48: CBC / ESR, LFT, Malaria, HbA1c, Creatinine, Urine | S48: 1 LAC | T48: 2 | U48: 0 | W48: Lab Quality | AJ48: Chugtitai Lab | AK48: Malir
A49: 43425.994 | C49: Lab guy | D49: Lab assistant | E49: 5 | H49: More than 60 | J49: 1000-1500 | K49: CBC / ESR, Malaria | S49: 150000 | T49: 5 | U49: 3 | W49: Price, Lab Quality | AJ49: Chugtai lab | AK49: Nazimabad Branch | AL49: LFT | AM49: Sugar test, Creatinine, Urine | AP49: HbA1c
A50: 43425.995 | C50: Lab | D50: Lab assistant | E50: 2 | H50: 40-50 | J50: 1000-1500 | S50: 150000 | T50: 7 | U50: 2 | W50: Price, Lab Quality | AJ50: DOW Lab | AK50: Nazimabad | AL50: CBC / ESR, Malaria | AM50: Sugar test, HbA1c | AN50: Creatinine, Urine | AO50: LFT
A51: 43425.997 | C51: Reception | D51: Assistant | E51: 4 | H51: More than 60 | J51: 500-1000 | K51: CBC / ESR, Malaria | S51: 100000 | T51: 5 | U51: 3 | W51: Price, Lab Quality | AJ51: ESSA Lab | AK51: Nazimabad | AL51: LFT | AM51: Sugar test | AO51: Creatinine, Urine | AP51: HbA1c
A52: 43426 | C52: Reception | D52: Reception | E52: 5 | H52: 40-50 | J52: 2500-3000 | K52: CBC / ESR, Malaria | S52: 100000 | T52: 2 | U52: 1 | W52: Price, Referral by Doctor, Location | AJ52: Mothers Lab | AK52: Nazimabad | AL52: LFT | AN52: Sugar test, HbA1c, Urine | AP52: Creatinine
A53: 43426.001 | C53: Reception | D53: Reception | E53: 3 | H53: 10-20 | J53: 1500-2000 | K53: CBC / ESR, LFT, Malaria | S53: 150000 | T53: 3 | U53: 1 | W53: Lab Quality, Referral by Doctor | AJ53: Agha Khan | AK53: Nazimabad 2 | AM53: Sugar test, HbA1c, Creatinine, Urine
A54: 43426.003 | C54: Reception | D54: Assistant | E54: 2 | H54: 50-60 | J54: 1500-2000 | S54: 75000 | T54: 3 | U54: 1 | W54: Price, Lab Quality | AJ54: Mehdi A Manjhi | AK54: Shahra-e-Quaideen | AL54: LFT, Malaria | AM54: CBC / ESR, Sugar test, Urine | AN54: HbA1c, Creatinine
A55: 43426.004 | C55: Reception | D55: Assistant | E55: 4 | H55: 20-30 | J55: 1500-2000 | K55: CBC / ESR, LFT, Malaria | S55: 90000 | T55: 2 | U55: 1 | W55: Referral by Doctor | AJ55: Dr. Ehsanullah Lab | AK55: Nazimabad | AM55: Sugar test, HbA1c | AN55: Creatinine, Urine
A56: 43426.005 | C56: Reception | D56: Assistant | E56: 1 | H56: 20-30 | J56: 1000-1500 | K56: CBC / ESR, Malaria | S56: 150000 | T56: 3 | U56: 0 | W56: Lab Quality, Referral by Doctor | AJ56: Agha Khan | AK56: Liaquatabad | AL56: LFT | AM56: Sugar test | AO56: HbA1c, Creatinine, Urine
A57: 43426.006 | C57: Assistant | D57: Assistant | E57: 5 | H57: 50-60 | J57: 1000-1500 | K57: Malaria | S57: 120000 | T57: 3 | U57: 1 | W57: Lab Quality, Referral by Doctor | AJ57: Sindlab | AK57: Liaquatabad | AL57: CBC / ESR, LFT | AM57: Sugar test, Creatinine, Urine | AN57: HbA1c
A58: 43426.007 | C58: Lab Assistant | D58: Assistant | E58: 1 | H58: More than 60 | J58: 1000-1500 | K58: CBC / ESR, Malaria | S58: 150000 | T58: 4 | U58: 2 | W58: Price, Lab Quality | AJ58: Hussaini Lab | AK58: Liaquatabad | AM58: HbA1c | AN58: Sugar test | AO58: LFT | AP58: Creatinine, Urine
A59: 43426.009 | C59: Reception | D59: Assistant | E59: 3 | H59: 30-40 | J59: 2000-2500 | K59: CBC / ESR, Sugar test | S59: 200000 | T59: 3 | U59: 1 | W59: Price, Lab Quality, Referral by Doctor | AJ59: DOW Lab | AK59: Jami Commercial | AN59: HbA1c, Creatinine | AO59: LFT, Malaria | AP59: Urine
A60: 43426.01 | C60: Reception | D60: Assistant | E60: 5 | H60: More than 60 | J60: 1500-2000 | K60: LFT, Malaria | S60: 120000 | T60: 4 | U60: 1 | W60: Price, Lab Quality | AJ60: Dr. Essa Lab | AK60: Gulshan Branch | AL60: CBC / ESR | AM60: Sugar test | AN60: HbA1c | AP60: Creatinine, Urine
A61: 43426.011 | C61: Assistant | D61: Assistant | E61: 3 | H61: 50-60 | J61: 2500-3000 | K61: CBC / ESR, LFT, Malaria | S61: 150000 | T61: 3 | U61: 1 | W61: Price, Lab Quality | AJ61: Agha Khan | AK61: Gulshan Branch | AM61: HbA1c, Creatinine | AN61: Sugar test | AP61: Urine
A62: 43426.012 | C62: Assistant | D62: Assistant | E62: 5 | H62: 50-60 | J62: 1500-2000 | K62: CBC / ESR, LFT | S62: 100000 | T62: 4 | U62: 0 | W62: Price, Lab Quality, Referral by Doctor | AJ62: Dr. Essa Lab | AK62: Abul Asfani Road | AL62: Malaria | AN62: Sugar test, Urine | AP62: HbA1c, Creatinine
A63: 43426.013 | C63: Lab Assistant | D63: Assistant | E63: 2 | H63: 30-40 | J63: 1500-2000 | K63: CBC / ESR, LFT | S63: 120000 | T63: 4 | U63: 0 | W63: Price, Lab Quality, Referral by Doctor | AJ63: Sindlab Collection point | AK63: Gulshan | AL63: Malaria | AN63: Sugar test, HbA1c, Urine | AP63: Creatinine

Sheet Providers
A1: Timestamp | B1: Name | C1: Age | D1: Sex | E1: Qualification | F1: Specialization | G1: Area | H1: Daily Average OPD | I1: How many hours on average do you practice your OPD/consultancy? | J1: How many patients on average do you see on a daily basis? | K1: What percentage of patients are prescribed lab tests? | L1: On average how many total tests do you prescribe per day? | M1: What are the most commonly prescribed tests in your clinical practice? | N1: Which 5 tests are most common? | O1: What percentage of patients need special chemistry tests? | P1: On average how much does each patient spend on lab tests in your clinic? | Q1: How many labs do you refer patients to? | R1: What are the three most important reasons for which lab you refer? | S1: Do you refer patients to certain labs based on the type of test? | T1: Do you receive incentives from labs for carrying out tests? | U1: Do visits by Medical Reps or PRO’s influence your decision to send tests to a certain lab? | V1: What do you think are the right prices for the following tests: [CBC-COMPLETE BLOOD COUNT] | W1: What do you think are the right prices for the following tests: [CBC/ESR Combined] | X1: What do you think are the right prices for the following tests: [MALARIAL PARASITE] | Y1: What do you think are the right prices for the following tests: [RANDOM BLOOD SUGAR] | Z1: What do you think are the right prices for the following tests: [FASTING BLOOD SUGAR] | AA1: What do you think are the right prices for the following tests: [CREATININE] | AB1: What do you think are the right prices for the following tests: [LIPID PROFILE] | AC1: What do you think are the right prices for the following tests: [LIVER FUNCTION TESTS] | AD1: What do you think are the right prices for the following tests: [HBA1C/GLYCOSYLATED HAEMOGLOBIN] | AE1: What do you think are the right prices for the following tests: [Dengue] | AF1: What do you think are the right prices for the following tests: [Typhoid] | AG1: What do you think are the right prices for the following tests: [Hepatitis Serology] | AH1: What do you think are the right prices for the following tests: [PCRs] | AI1: How many hours on average do you practice your OPD/consultancy? | AJ1: Which labs do you refer patients to? | AK1: Most important factor in deciding lab for testing? | AL1: Do you refer patients to certain labs based on the type of test? | AM1: Do you receive incentives from labs for carrying out tests? | AN1: Do visits by Medical Reps or PRO’s influence your decision to send tests to a certain lab? | AO1: What are the criteria for you to refer the lab to your patients? | AP1: What would you like labs to offer to doctors that will help doctors in improving their own practice/clinic?
A2: 43360.532 | B2: Dr Komal | C2: 31 | D2: Female | E2: Other Medical Qualification | F2: Gynae | G2: Gadap Town | H2: 10-20 | K2: 10-20% | L2: Less than 5 | M2: CBC / ESR | O2: 0-10% | P2: 2000-2500 | V2: 200 | W2: 300 | X2: 300 | Y2: 100 | Z2: 100 | AA2: 200 | AB2: 400 | AC2: 400 | AD2: 500 | AE2: 800 | AF2: 1000 | AG2: Other | AH2: Other | AI2: More than 6 | AJ2: other | AL2: Yes | AM2: Yes | AN2: Yes | AO2: 1. Price | AP2: other
A3: 43360.54 | B3: Dr Matloob Zaman | C3: 29 | D3: Male | E3: MBBS | F3: General Practice | G3: Gadap Town | H3: 10-20 | K3: 0-10% | L3: Less than 5 | M3: CBC / ESR | O3: 0-10% | P3: < 500 | V3: 200 | W3: 300 | X3: 300 | Y3: 100 | Z3: 100 | AA3: 200 | AB3: 400 | AC3: 400 | AD3: 500 | AE3: 800 | AF3: 400 | AG3: 800 | AH3: Other | AI3: 6 | AJ3: other | AL3: Yes | AM3: Yes | AN3: Yes | AO3: 1. Price | AP3: Seminars on new technologies
A4: 43360.551 | B4: Sarwar Kumar | C4: 38 | D4: Male | E4: Other Medical Qualification | F4: General Practice | G4: Gadap Town | H4: 30 - 40 | K4: 0-10% | L4: Less than 5 | M4: CBC / ESR | O4: 0-10% | P4: < 500 | V4: 200 | W4: 200 | X4: 200 | Y4: 100 | Z4: 100 | AA4: 200 | AB4: 400 | AC4: 400 | AD4: 600 | AE4: 600 | AF4: 500 | AG4: 200 | AH4: Other | AI4: 6 | AJ4: other | AL4: Yes | AM4: Yes | AN4: Yes | AO4: 3. Lab Quality | AP4: other
A5: 43360.555 | B5: Dr SANAULLAH | C5: 42 | D5: Male | E5: MBBS | F5: General Practice | G5: SITE Town | H5: 40 - 50 | K5: 20-30% | L5: 11-15 | M5: CBC / ESR | O5: 0-10% | P5: 1000-1500 | V5: 200 | W5: 400 | X5: 200 | Y5: 100 | Z5: 100 | AA5: 200 | AB5: 500 | AC5: 500 | AD5: 400 | AE5: 400 | AF5: 400 | AG5: Other | AH5: Other | AI5: More than 6 | AJ5: OTHER | AL5: Yes | AM5: Yes | AN5: Yes | AO5: 3. Lab Quality | AP5: OTHER
A6: 43360.603 | B6: Sher Muhammad Khan | C6: 38 | D6: Male | E6: Other Medical Qualification | F6: General Practice | G6: SITE Town | H6: 40 - 50 | K6: 30-40% | L6: 11-15 | M6: CBC / ESR | O6: 0-10% | P6: 500-1000 | V6: 200 | W6: 300 | X6: 100 | Y6: 100 | Z6: 100 | AA6: 100 | AB6: 300 | AC6: 200 | AD6: 400 | AE6: Other | AF6: 300 | AG6: 200 | AH6: Other | AI6: 5 | AJ6: AKU | AL6: Yes | AM6: Yes | AN6: Yes | AO6: 1. Price | AP6: Online reporting
A7: 43360.607 | B7: Dr Irfan ACI | C7: 38 | D7: Male | E7: Other Medical Qualification | F7: General Practice | G7: SITE Town | H7: 40 - 50 | K7: 10-20% | L7: Less than 5 | M7: CBC / ESR | O7: 0-10% | P7: 1500-2000 | V7: 100 | W7: 200 | X7: 200 | Y7: 100 | Z7: 100 | AA7: 200 | AB7: 500 | AC7: 300 | AD7: 500 | AE7: Other | AF7: 300 | AG7: Other | AH7: Other | AI7: More than 6 | AJ7: AKU | AL7: Yes | AM7: Yes | AN7: Yes | AO7: 3. Lab Quality | AP7: OTHER
A8: 43360.612 | B8: Dr Khadil | C8: 56 | D8: Male | E8: MBBS | F8: General Practice | G8: Liaquatabad Town | H8: 50-60 | K8: 40-50% | L8: Less than 5 | M8: CBC / ESR | O8: 30-40% | P8: < 500 | V8: 200 | W8: 300 | X8: 300 | Y8: 100 | Z8: 100 | AA8: 300 | AB8: 500 | AC8: 500 | AD8: 600 | AE8: Other | AF8: Other | AG8: Other | AH8: Other | AI8: 4 | AJ8: OTHER | AL8: Yes | AM8: No | AN8: Yes | AO8: 3. Lab Quality | AP8: Seminars on new technologies
A9: 43360.619 | B9: Dr Akhter Hussain | C9: 52 | D9: Male | E9: MBBS | F9: General Practice | G9: Liaquatabad Town | H9: 30 - 40 | K9: 0-10% | L9: Less than 5 | M9: LFT | O9: 40-50% | P9: 500-1000 | V9: 300 | W9: 400 | X9: 400 | Y9: 100 | Z9: 100 | AA9: 200 | AB9: 500 | AC9: 500 | AD9: 600 | AE9: 600 | AF9: Other | AG9: Other | AH9: Other | AI9: 4 | AJ9: other | AL9: Yes | AM9: Yes | AN9: Yes | AO9: 1. Price | AP9: Seminars on new technologies
A10: 43360.621 | B10: Dr Rubina Saleem | C10: 49 | D10: Female | E10: MBBS | F10: Gynae | G10: Liaquatabad Town | H10: 40 - 50 | K10: 40-50% | L10: 6-10 | M10: CBC / ESR | O10: 30-40% | P10: 500-1000 | V10: 400 | W10: 300 | X10: 300 | Y10: 100 | Z10: 100 | AA10: Other | AB10: 600 | AC10: Other | AD10: Other | AE10: Other | AF10: Other | AG10: Other | AH10: Other | AI10: 6 | AJ10: Essa | AL10: Yes | AM10: Yes | AN10: Yes | AO10: 3. Lab Quality | AP10: Online reporting
A11: 43360.626 | B11: Dr Jamal | C11: 42 | D11: Male | E11: MBBS | F11: Chest Disease | G11: Liaquatabad Town | H11: 50-60 | K11: 0-10% | L11: Less than 5 | M11: CBC / ESR | O11: 30-40% | P11: < 500 | V11: 300 | W11: Other | X11: Other | Y11: 100 | Z11: Other | AA11: 600 | AB11: 500 | AC11: Other | AD11: Other | AE11: Other | AF11: 500, Other | AG11: Other | AH11: Other | AI11: 6 | AJ11: OTHER | AL11: No | AM11: No | AN11: Yes | AO11: 3. Lab Quality | AP11: Seminars on new technologies
A12: 43360.63 | B12: Dr Ratan | C12: 40 | D12: Male | E12: MBBS | F12: General Practice | G12: Liaquatabad Town | H12: 20-30 | K12: 40-50% | L12: 6-10 | M12: CBC / ESR | O12: 30-40% | P12: 1000-1500 | V12: 300 | W12: 400 | X12: 500 | Y12: 100 | Z12: 100 | AA12: Other | AB12: Other | AC12: 500 | AD12: Other | AE12: Other | AF12: Other | AG12: Other | AH12: Other | AI12: 4 | AJ12: Essa | AL12: No | AM12: No | AN12: No | AO12: 1. Price | AP12: Online reporting
A13: 43360.634 | B13: Dr Noor | C13: 35 | D13: Male | E13: MBBS | F13: General Practice | G13: Orangi Town | H13: 40 - 50 | K13: 0-10% | L13: Less than 5 | M13: CBC / ESR | O13: 0-10% | P13: 500-1000 | V13: 300 | W13: 400 | X13: 200 | Y13: 100 | Z13: 100 | AA13: 200 | AB13: 600 | AC13: 600 | AD13: 600 | AE13: 500 | AF13: 700 | AG13: 700 | AH13: Other | AI13: More than 6 | AJ13: Own Lab | AL13: Yes | AM13: Yes | AN13: Yes | AO13: 1. Price | AP13: Online reporting
A14: 43360.637 | B14: Dr Zahid | C14: 30 | D14: Male | E14: MBBS | F14: General Practice | G14: Orangi Town | H14: More than 60 | K14: 0-10% | L14: Less than 5 | M14: CBC / ESR | O14: 0-10% | P14: < 500 | V14: 100 | W14: 100 | X14: 200 | Y14: 100 | Z14: 100 | AA14: 200 | AB14: 500 | AC14: 500 | AD14: 600 | AE14: 400 | AF14: 600 | AG14: 600 | AH14: Other | AI14: More than 6 | AJ14: Daw and IPL Lab | AL14: Yes | AM14: Yes | AN14: Yes | AO14: 1. Price | AP14: Online reporting
A15: 43360.642 | B15: Dr Shakeel A Warsi | C15: 58 | D15: Male | E15: MBBS | F15: General Practice | G15: Orangi Town | H15: 50-60 | K15: 10-20% | L15: 6-10 | M15: CBC / ESR | O15: 10-20% | P15: < 500 | V15: 200 | W15: 100 | X15: 200 | Y15: 100 | Z15: 100 | AA15: 200 | AB15: 500 | AC15: 500 | AD15: 600 | AE15: 600 | AF15: 700 | AG15: 600 | AH15: Other | AI15: More than 6 | AJ15: AKU | AL15: Yes | AM15: Yes | AN15: Yes | AO15: 1. Price | AP15: Online reporting
A16: 43360.642 | B16: Dr Shakeel A Warsi | C16: 58 | D16: Male | E16: MBBS | F16: General Practice | G16: Orangi Town | H16: 50-60 | K16: 10-20% | L16: 6-10 | M16: CBC / ESR | O16: 10-20% | P16: < 500 | V16: 200 | W16: 100 | X16: 200 | Y16: 100 | Z16: 100 | AA16: 200 | AB16: 500 | AC16: 500 | AD16: 600 | AE16: 600 | AF16: 700 | AG16: 600 | AH16: Other | AI16: More than 6 | AJ16: AKU | AL16: Yes | AM16: Yes | AN16: Yes | AO16: 1. Price | AP16: Online reporting
A17: 43360.646 | B17: Dr Taj Bareem | C17: 42 | D17: Male | E17: MBBS | F17: General Practice | G17: Orangi Town | H17: 40 - 50 | K17: 0-10% | L17: Less than 5 | M17: CBC / ESR | O17: 0-10% | P17: < 500 | V17: 100 | W17: 100 | X17: 200 | Y17: 100 | Z17: 100 | AA17: 200 | AB17: 500 | AC17: 500 | AD17: 500 | AE17: 500 | AF17: 600 | AG17: 600 | AH17: 1300 | AI17: 6 | AJ17: Local Labs | AL17: Yes | AM17: Yes | AN17: Yes | AO17: 1. Price | AP17: Online reporting
A18: 43360.655 | B18: Dr Ghulam Mustafa | C18: 31 | D18: Male | E18: MBBS | F18: General Practice | G18: Gadap Town | H18: 20-30 | K18: 30-40% | L18: 11-15 | M18: CBC / ESR | O18: 10-20% | P18: 500-1000 | V18: 200 | W18: 200 | X18: 100 | Y18: 100 | Z18: 100 | AA18: 200 | AB18: 700 | AC18: 800 | AD18: 700 | AE18: 1000 | AF18: 200 | AG18: 700 | AH18: Other | AI18: More than 6 | AJ18: AKU | AL18: Yes | AM18: Yes | AN18: Yes | AO18: 3. Lab Quality | AP18: Seminars on new technologies
A19: 43360.658 | B19: Naveed Khan | C19: 33 | D19: Male | E19: Other Medical Qualification | F19: General Practice | G19: SITE Town | H19: More than 60 | K19: 40-50% | L19: 6-10 | M19: CBC / ESR | O19: 10-20% | P19: 500-1000 | V19: 100 | W19: 200 | X19: 100 | Y19: 100 | Z19: 100 | AA19: 100 | AB19: 600 | AC19: 300 | AD19: 300 | AE19: 300 | AF19: 300 | AG19: 300 | AH19: Other | AI19: More than 6 | AJ19: Husaini | AL19: Yes | AM19: Yes | AN19: Yes | AO19: 1. Price | AP19: Seminars on new technologies
A20: 43360.66 | B20: Dr Muhammad Akram Quadri | C20: 50 | D20: Male | E20: MBBS | F20: General Practice | G20: Orangi Town | H20: 40 - 50 | K20: 0-10% | L20: Less than 5 | M20: CBC / ESR | O20: 0-10% | P20: < 500 | V20: 100 | W20: 100 | X20: 200 | Y20: 100 | Z20: 100 | AA20: 200 | AB20: 500 | AC20: 500 | AD20: 600 | AE20: 600 | AF20: 600 | AG20: 600 | AH20: Other | AI20: 5 | AJ20: Shamim | AL20: Yes | AM20: Yes | AN20: Yes | AO20: 1. Price | AP20: Online reporting
A21: 43361.708 | B21: Jamil-ur-Rehman | C21: 30 | D21: Male | E21: Other Medical Qualification | F21: General Practice | G21: Orangi Town | H21: 30 - 40 | K21: 10-20% | L21: Less than 5 | M21: CBC / ESR | O21: 10-20% | P21: 500-1000 | V21: 200 | W21: 300 | X21: 300 | Y21: 100 | Z21: 100 | AA21: 100 | AB21: 500 | AC21: 500 | AD21: 100 | AE21: 700 | AF21: 400 | AG21: Other | AH21: Other | AI21: 3 | AJ21: Noor Lan and Dow Lab | AL21: Yes | AM21: Yes | AN21: Yes | AO21: 1. Price | AP21: other
A22: 43361.71 | B22: Dr Ibrahim | C22: 35 | D22: Male | E22: MBBS | F22: General Practice | G22: Gadap Town | H22: 10-20 | K22: 0-10% | L22: Less than 5 | M22: CBC / ESR | O22: 0-10% | P22: 1000-1500 | V22: 200 | W22: 300 | X22: 300 | Y22: 100 | Z22: 200 | AA22: 400 | AB22: 400 | AC22: Other | AD22: 500 | AE22: 800 | AF22: 400 | AG22: 800 | AH22: Other | AI22: More than 6 | AJ22: other | AL22: Yes | AM22: Yes | AN22: Yes | AO22: 1. Price | AP22: Seminars on new technologies
A23: 43361.713 | B23: Nazir Ahmed Shaikh | C23: 62 | D23: Male | E23: FCPS | F23: General Practice | G23: New Karachi Town | H23: 30 - 40 | K23: 0-10% | L23: Less than 5 | M23: CBC / ESR | O23: 0-10% | P23: 1000-1500 | V23: Other | W23: 300 | X23: 200 | Y23: 100 | Z23: 100 | AA23: 100 | AB23: 500 | AC23: 600 | AD23: 600 | AE23: Other | AF23: 300 | AG23: Other | AH23: Other | AI23: 3 | AJ23: other | AL23: Yes | AM23: Yes | AN23: Yes | AO23: 3. Lab Quality | AP23: Infomration about diagnostc machines
A24: 43385.407 | B24: Dr Sagram Das | C24: 42 | D24: Male | E24: MBBS | F24: General Practice | G24: Jamshed Town | H24: More than 60 | K24: 30-40% | L24: Less than 5 | M24: CBC / ESR | O24: 20-30% | P24: 500-1000 | V24: 100 | W24: 200 | X24: 100 | Y24: 100 | Z24: 100 | AA24: 200 | AB24: 300 | AC24: 300 | AD24: 400 | AE24: 300 | AF24: 400 | AG24: Other | AH24: Other | AI24: 6 | AJ24: other | AL24: Yes | AM24: Yes | AN24: Yes | AO24: 1. Price | AP24: Online reporting
A25: 43385.43 | B25: Dr Yasmeen Asif Ahmed | C25: 50 | D25: Female | E25: MBBS | F25: General Practice | G25: Jamshed Town | H25: 10-20 | K25: 0-10% | L25: Less than 5 | M25: CBC / ESR | O25: 0-10% | P25: < 500 | V25: 200 | W25: 300 | X25: 300 | Y25: 100 | Z25: 100 | AA25: 200 | AB25: 300 | AC25: 400 | AD25: 500 | AE25: 200 | AF25: 400 | AG25: 100 | AH25: Column 15 | AI25: 4 | AJ25: Sehatmant Zindagi Center | AL25: Yes | AM25: No | AN25: Yes | AO25: 3. Lab Quality | AP25: Seminars on new technologies
A26: 43385.435 | B26: Dr Nayyar Ali | C26: 60 | D26: Male | E26: MBBS | F26: Diabetes | G26: Jamshed Town | H26: 30 - 40 | K26: More than 50% | L26: 6-10 | M26: CBC / ESR | O26: 20-30% | P26: 500-1000 | V26: 100 | W26: 200 | X26: 400 | Y26: 100 | Z26: 100 | AA26: 200 | AB26: 300 | AC26: 300 | AD26: 500 | AE26: 400 | AF26: 400 | AG26: 100 | AH26: 1300 | AI26: 5 | AJ26: Sehatmand zingadi center | AL26: Yes | AM26: Yes | AN26: Yes | AO26: 3. Lab Quality | AP26: Online reporting
A27: 43385.44 | B27: Dr Javed Hamed | C27: 58 | D27: Male | E27: MBBS | F27: General Practice | G27: Jamshed Town | H27: 30 - 40 | K27: 10-20% | L27: 11-15 | M27: CBC / ESR | O27: 0-10% | P27: < 500 | V27: 200 | W27: 300 | X27: 100 | Y27: 100 | Z27: 100 | AA27: Other | AB27: 500 | AC27: 400 | AD27: 500 | AE27: 500 | AF27: 400 | AG27: 500 | AH27: Other | AI27: More than 6 | AJ27: Dow Lab | AL27: Yes | AM27: Yes | AN27: Yes | AO27: 2. Lab Reputation | AP27: Online reporting
A28: 43385.465 | B28: Dr Adeel Ahmed | C28: 45 | D28: Male | E28: MBBS | F28: General Practice | G28: Gulshan Town | H28: 30 - 40 | K28: 30-40% | L28: 6-10 | M28: CBC / ESR | O28: 10-20% | P28: 1500-2000 | V28: 200 | W28: 300 | X28: Other | Y28: 100 | Z28: 100 | AA28: 300 | AB28: 400 | AC28: 700 | AD28: 300 | AE28: 700 | AF28: 500 | AG28: 500 | AH28: Other | AI28: More than 6 | AJ28: Sehatmand Zindagi Center | AL28: No | AM28: Yes | AN28: Yes | AO28: 1. Price | AP28: Seminars on new technologies
A29: 43385.467 | B29: Dr Wajid | C29: 55 | D29: Male | E29: MBBS | F29: General Practice | G29: Gulshan Town | H29: 20-30 | K29: 10-20% | L29: Less than 5 | M29: CBC / ESR | O29: 0-10% | P29: 1000-1500 | V29: 200 | W29: 300 | X29: 100 | Y29: 100 | Z29: 100 | AA29: 100 | AB29: 500 | AC29: 400 | AD29: 600 | AE29: 600 | AF29: 400 | AG29: 500 | AH29: Other | AI29: 3 | AJ29: Essa | AL29: Yes | AM29: Yes | AN29: Yes | AO29: 1. Price | AP29: Seminars on new technologies
A30: 43385.471 | B30: Dr Sarwar Iaqbal | C30: 60 | D30: Male | E30: MBBS | F30: General Practice | G30: Gulshan Town | H30: Less than 10 | K30: 0-10% | L30: Less than 5 | M30: CBC / ESR | O30: 0-10% | P30: 500-1000 | V30: 200 | W30: 300 | X30: 100 | Y30: 100 | Z30: 100 | AA30: 100 | AB30: 600 | AC30: 600 | AD30: 600 | AE30: 700 | AF30: 400 | AG30: 300 | AH30: Other | AI30: More than 6 | AJ30: other | AL30: Yes | AM30: No | AN30: Yes | AO30: 1. Price | AP30: other
A31: 43385.568 | B31: Dr Azeem Sultan | C31: 36 | D31: Male | E31: MBBS | F31: General Practice | G31: Gulshan Town | H31: 30 - 40 | K31: 10-20% | L31: Less than 5 | M31: CBC / ESR | O31: 0-10% | P31: 500-1000 | V31: 200 | W31: 300 | X31: Other | Y31: 100 | Z31: 100 | AA31: Other | AB31: 600 | AC31: 600 | AD31: 600 | AE31: 700 | AF31: 500 | AG31: Other | AH31: Other | AI31: 6 | AJ31: Essa | AL31: Yes | AM31: Yes | AN31: Yes | AO31: 1. Price | AP31: Online reporting
A32: 43385.609 | B32: Dr Abdul Rasheed | C32: 49 | D32: Male | E32: MBBS | F32: General Practice | G32: Gulshan Town | H32: 20-30 | K32: 0-10% | L32: Less than 5 | M32: CBC / ESR | O32: 0-10% | P32: 500-1000 | V32: 200 | W32: 400 | X32: 300 | Y32: 100 | Z32: 100 | AA32: 100, 600 | AB32: 600 | AC32: 600 | AD32: 700 | AE32: Other | AF32: Other | AG32: Other | AH32: Other | AI32: 3 | AJ32: Essa | AL32: Yes | AM32: Yes | AN32: Yes | AO32: 1. Price | AP32: Online reporting
A33: 43385.611 | B33: Dr Meraj Hussain | C33: 51 | D33: Male | E33: MBBS | F33: General Practice | G33: Gulshan Town | H33: 20-30 | K33: 10-20% | L33: Less than 5 | M33: CBC / ESR | O33: 0-10% | P33: 1000-1500 | V33: 300 | W33: 400 | X33: 200 | Y33: 100 | Z33: 100 | AA33: 200 | AB33: 500 | AC33: 500 | AD33: 500 | AE33: 800 | AF33: 400 | AG33: Other | AH33: Other | AI33: More than 6 | AJ33: other | AL33: Yes | AM33: Yes | AN33: Yes | AO33: 1. Price | AP33: Seminars on new technologies
A34: 43385.616 | B34: Dr Ishtiaq Ahmed Basar | C34: 30 | D34: Male | E34: MBBS | F34: General Practice | G34: Jamshed Town | H34: 40 - 50 | K34: 30-40% | L34: 11-15 | M34: CBC / ESR | O34: 30-40% | P34: 1000-1500 | V34: 200 | W34: 400 | X34: 100 | Y34: 100 | Z34: 100 | AA34: 300 | AB34: 500 | AC34: 300 | AD34: 300 | AE34: 500 | AF34: 300 | AG34: 500 | AH34: 1000 | AI34: 4 | AJ34: AKU | AL34: Yes | AM34: No | AN34: Yes | AO34: 1. Price | AP34: Online reporting
A35: 43385.621 | B35: Dr Haeeb Nawaz | C35: 36 | D35: Male | E35: MBBS | F35: General Practice | G35: Gulberg Town | H35: 40 - 50 | K35: 20-30% | L35: 11-15 | M35: CBC / ESR | O35: 10-20% | P35: 1500-2000 | V35: 100 | W35: 100 | X35: 300 | Y35: 100 | Z35: 100 | AA35: 200 | AB35: 200 | AC35: 500 | AD35: 100 | AE35: 300 | AF35: 300 | AG35: 400 | AH35: 1200 | AI35: More than 6 | AJ35: Essa | AL35: Yes | AM35: Yes | AN35: Yes | AO35: 1. Price | AP35: Infomration about diagnostc machines
A36: 43385.623 | B36: Dr Aqeel Mukhyar | C36: 41 | D36: Male | E36: MBBS | F36: General Practice | G36: Gulshan Town | H36: 30 - 40 | K36: 30-40% | L36: 11-15 | M36: CBC / ESR | O36: 10-20% | P36: 500-1000 | V36: 200 | W36: 100 | X36: 200 | Y36: 100 | Z36: 100 | AA36: 200 | AB36: 400 | AC36: 700 | AD36: 200 | AE36: 300 | AF36: 300 | AG36: 500 | AH36: Other | AI36: More than 6 | AJ36: other | AL36: Yes | AM36: Yes | AN36: Yes | AO36: 1. Price | AP36: Online reporting
A37: 43385.626 | B37: Dr Ashfaq | C37: 50 | D37: Male | E37: MBBS | F37: General Practice | G37: Gulshan Town | H37: 40 - 50 | K37: 10-20% | L37: 6-10 | M37: CBC / ESR | O37: 0-10% | P37: 500-1000 | V37: 300 | W37: 400 | X37: 500 | Y37: 100 | Z37: 100 | AA37: 200 | AB37: 300 | AC37: 600 | AD37: 100 | AE37: 300 | AF37: 300 | AG37: 100 | AH37: Other | AI37: 3 | AJ37: Sehatmand Zingadi Center | AL37: Yes | AM37: Yes | AN37: Yes | AO37: 1. Price | AP37: Online reporting
A38: 43385.632 | B38: Dr Amir Siddiuqe | C38: 32 | D38: Male | E38: MBBS | F38: General Practice | G38: Saddar Town | H38: 40 - 50 | K38: 0-10% | L38: Less than 5 | M38: CBC / ESR | O38: 0-10% | P38: < 500 | V38: 200 | W38: 300 | X38: Other | Y38: 100 | Z38: 100 | AA38: 300 | AB38: 400 | AC38: Other | AD38: 300 | AE38: Other | AF38: 400 | AG38: 400 | AH38: Other | AI38: 4 | AJ38: other | AL38: Yes | AM38: Yes | AN38: Yes | AO38: 1. Price | AP38: Infomration about diagnostc machines
A39: 43385.636 | B39: Dr Hhassan Ali | C39: 34 | D39: Male | E39: MBBS | F39: General Practice | G39: Saddar Town | H39: 20-30 | K39: More than 50% | L39: Less than 5 | M39: CBC / ESR | O39: More than 50% | P39: < 500 | V39: 400 | W39: Other | X39: 100, Other | Y39: 100 | Z39: 200 | AA39: 400 | AB39: 400 | AC39: 500 | AD39: 500 | AE39: 300 | AF39: 400 | AG39: Other | AH39: Other | AI39: 6 | AJ39: other | AL39: Yes | AM39: No | AN39: No | AO39: 8. Location | AP39: Infomration about diagnostc machines
A40: 43385.659 | B40: Dr Sadaf Sofia Siddique | C40: 45 | D40: Female | E40: MBBS | F40: Gynae | G40: Saddar Town | H40: 20-30 | K40: 10-20% | L40: Less than 5 | M40: CBC / ESR | O40: 0-10% | P40: 1000-1500 | V40: 400 | W40: 300 | X40: 200 | Y40: 200 | Z40: 200 | AA40: 300 | AB40: 500 | AC40: 500 | AD40: 500 | AE40: 500 | AF40: 500 | AG40: 600 | AH40: 600 | AI40: 4 | AJ40: other | AL40: Yes | AM40: Yes | AN40: Yes | AO40: 1. Price | AP40: Online reporting
A41: 43385.666 | B41: Dr Abdul Jabbar | C41: 42 | D41: Male | E41: MBBS | F41: General Practice | G41: Kiamari Town | H41: 20-30 | K41: 20-30% | L41: 6-10 | M41: CBC / ESR | O41: 10-20% | P41: 1500-2000 | V41: 300 | W41: 400 | X41: 100 | Y41: 100 | Z41: 100 | AA41: Other | AB41: 500 | AC41: 400 | AD41: 200 | AE41: 500 | AF41: 500 | AG41: 300 | AH41: Other | AI41: 6 | AJ41: AKU | AL41: Yes | AM41: Yes | AN41: Yes | AO41: 3. Lab Quality | AP41: Online reporting
A42: 43385.668 | B42: Dr Tariq Nadeem | C42: 55 | D42: Male | E42: MBBS | F42: General Practice | G42: Saddar Town | H42: 30 - 40 | K42: 10-20% | L42: 6-10 | M42: CBC / ESR | O42: 0-10% | P42: 1000-1500 | V42: 300 | W42: 400 | X42: 100 | Y42: 200 | Z42: 100 | AA42: 200 | AB42: 500 | AC42: 600 | AD42: 500 | AE42: 700 | AF42: 500 | AG42: 900 | AH42: Other | AI42: More than 6 | AJ42: AKU | AL42: Yes | AM42: Yes | AN42: No | AO42: 1. Price | AP42: Online reporting
A43: 43385.67 | B43: Dr Sarfarz Khan | C43: 50 | D43: Male | E43: MBBS | F43: General Practice | G43: Saddar Town | H43: 20-30 | K43: 20-30% | L43: 6-10 | M43: CBC / ESR | O43: 20-30% | P43: 1500-2000 | V43: 100 | W43: 300 | X43: 200 | Y43: 100 | Z43: 100 | AA43: 200 | AB43: 300 | AC43: 400 | AD43: 500 | AE43: 300 | AF43: 400 | AG43: 100 | AH43: Column 15 | AI43: 6 | AJ43: Sehatmand zindagi center | AL43: Yes | AM43: Yes | AN43: Yes | AO43: 3. Lab Quality | AP43: Online reporting
A44: 43385.673 | B44: Dr Shaista Ehsan | C44: 40 | D44: Female | E44: MBBS | F44: General Practice | G44: Kiamari Town | H44: 20-30 | K44: 10-20% | L44: Less than 5 | M44: CBC / ESR | O44: 10-20% | P44: 1000-1500 | V44: 100 | W44: 300 | X44: 400 | Y44: 100 | Z44: 100 | AA44: 200 | AB44: 300 | AC44: 400 | AD44: 500 | AE44: 100 | AF44: 300 | AG44: 100 | AH44: Column 15 | AI44: 6 | AJ44: Sehatmand zindagi center | AL44: Yes | AM44: Yes | AN44: Yes | AO44: 3. Lab Quality | AP44: Online reporting
A45: 43385.675 | B45: Dr Ayaz Ali Fawad | C45: 45 | D45: Male | E45: MBBS | F45: General Practice | G45: Kiamari Town | H45: 40 - 50 | K45: 10-20% | L45: 6-10 | M45: CBC / ESR | O45: 10-20% | P45: 1000-1500 | V45: 200 | W45: 200 | X45: 300 | Y45: 100 | Z45: 100 | AA45: 200 | AB45: 400 | AC45: 400 | AD45: 500 | AE45: 400 | AF45: 400 | AG45: 100 | AH45: Other | AI45: 6 | AJ45: Sehatmand zindagi center | AL45: Yes | AM45: Yes | AN45: Yes | AO45: 3. Lab Quality | AP45: Online reporting
A46: 43385.677 | B46: Dr Sohail Khan | C46: 45 | D46: Male | E46: MBBS | F46: General Practice | G46: Kiamari Town | H46: 20-30 | K46: 10-20% | L46: Less than 5 | M46: CBC / ESR | O46: 0-10% | P46: < 500 | V46: 100 | W46: 200 | X46: 300 | Y46: 100 | Z46: 100 | AA46: 200 | AB46: 400 | AC46: 400 | AD46: 500 | AE46: 200 | AF46: 400 | AG46: 100 | AH46: 1200 | AI46: 6 | AJ46: Sehatmand Zindagi Center | AL46: No | AM46: Yes | AN46: Yes | AO46: 3. Lab Quality | AP46: Seminars on new technologies
A47: 43388.685 | B47: Hazrat Noor | C47: 36 | D47: Male | E47: Other Medical Qualification | F47: General Practice | G47: Kiamari Town | H47: 20-30 | K47: 20-30% | L47: Less than 5 | M47: CBC / ESR | O47: 0-10% | P47: 500-1000 | V47: 200 | W47: 300 | X47: 200 | Y47: 100 | Z47: 100 | AA47: 200 | AB47: 400 | AC47: 400 | AD47: 400 | AE47: 500 | AF47: 300 | AG47: 400 | AH47: Other | AI47: 6 | AJ47: AKU | AL47: Yes | AM47: No | AN47: No | AO47: 6. Relationship | AP47: Infomration about diagnostc machines
A48: 43388.689 | B48: Dr Maro | C48: 45 | D48: Male | E48: MBBS | F48: General Practice | G48: Gulshan Town | H48: 40 - 50 | K48: 0-10% | L48: Less than 5 | M48: LFT | O48: 0-10% | P48: < 500 | V48: 200 | W48: 400 | X48: 200 | Y48: 100 | Z48: 100 | AA48: 200 | AB48: 500 | AC48: 500 | AD48: 600 | AE48: 900 | AF48: 400 | AG48: 800 | AH48: Other | AI48: 6 | AJ48: Essa | AL48: Yes | AM48: No | AN48: No | AO48: 3. Lab Quality | AP48: Infomration about diagnostc machines
A49: 43388.691 | B49: Dr Raja Dewan | C49: 32 | D49: Male | E49: Post Graduate Diploma | F49: General Practice | G49: Gulshan Town | H49: 30 - 40 | K49: 10-20% | L49: 6-10 | M49: CBC / ESR | O49: 0-10% | P49: < 500 | V49: 300 | W49: 400 | X49: 200 | Y49: 100 | Z49: 100 | AA49: 400 | AB49: 600 | AC49: 300 | AD49: 600 | AE49: Other | AF49: 300 | AG49: 700 | AH49: Other | AI49: More than 6 | AJ49: Mehnan Lab | AL49: Yes | AM49: Yes | AN49: Yes | AO49: 3. Lab Quality | AP49: Online reporting
A50: 43388.694 | B50: Dr Asghar Hussain Abbassi | C50: 52 | D50: Male | E50: MBBS | F50: General Practice | G50: Gulshan Town | H50: 20-30 | K50: 0-10% | L50: Less than 5 | M50: Typhoid | O50: 0-10% | P50: < 500 | V50: 200 | W50: 400 | X50: 200 | Y50: 100 | Z50: 100 | AA50: 500 | AB50: 500 | AC50: 700 | AD50: 700 | AE50: Other | AF50: 500 | AG50: 300, 600 | AH50: Other | AI50: 3 | AJ50: Essa | AL50: Yes | AM50: Yes | AN50: No | AO50: 3. Lab Quality | AP50: Seminars on new technologies
A51: 43388.697 | B51: Dr Ali Akbar Abbasi | C51: 63 | D51: Male | E51: MBBS | F51: General Practice | G51: Gulshan Town | H51: Less than 10 | K51: 0-10% | L51: Less than 5 | M51: CBC / ESR | O51: 0-10% | P51: < 500 | V51: 100 | W51: 200 | X51: 200 | Y51: 100 | Z51: 100 | AA51: 100 | AB51: 300 | AC51: 300 | AD51: 400 | AE51: 200 | AF51: 200 | AG51: Other | AH51: Other | AI51: 2 | AJ51: Dow Lab | AL51: Yes | AM51: Yes | AN51: No | AO51: 3. Lab Quality | AP51: Free Diagnosing camps for orneriness program
A52: 43388.699 | B52: Dr Sadaf | C52: 40 | D52: Female | E52: MBBS | F52: General Practice | G52: Gulshan Town | H52: 10-20 | K52: 0-10% | L52: Less than 5 | M52: Malaria | O52: 0-10% | P52: < 500 | V52: 200 | W52: 300 | X52: 100 | Y52: 100 | Z52: 100 | AA52: 300 | AB52: 400 | AC52: 500 | AD52: 400 | AE52: 300 | AF52: 200 | AG52: 500 | AH52: Other | AI52: 3 | AJ52: Essa | AL52: Yes | AM52: Yes | AN52: No | AO52: 3. Lab Quality | AP52: Online reporting
A53: 43424.447 | B53: Dr Zahid | C53: 35 | D53: Male | E53: MCPS | F53: Paeds | G53: Korangi Town | H53: 10-20 | K53: 10-20% | L53: Less than 5 | M53: CBC / ESR | O53: 10-20% | P53: 1500-2000 | V53: 500 | W53: 800 | X53: 600 | Y53: 500 | Z53: 500 | AA53: 600 | AB53: 800 | AC53: 900 | AD53: 1000 | AE53: 900 | AF53: 1000 | AG53: 1000 | AH53: 1300 | AI53: More than 6 | AJ53: other | AL53: Yes | AM53: No | AN53: No | AO53: 6. Relationship | AP53: Online reporting
A54: 43424.45 | B54: Dr Danish Raja | C54: 32 | D54: Male | E54: MCPS | F54: General Practice | G54: North Nazimabad Town | H54: 10-20 | K54: 20-30% | L54: 6-10 | M54: HbA1c | O54: 20-30% | P54: 500-1000 | V54: 500 | W54: 700 | X54: 800 | Y54: 500 | Z54: 500 | AA54: 1200 | AB54: 500 | AC54: 1000 | AD54: 1000 | AE54: 800 | AF54: 1000 | AG54: 1100 | AH54: 1200 | AI54: More than 6 | AJ54: AKU | AL54: No | AM54: No | AN54: No | AO54: 3. Lab Quality | AP54: Online reporting
A55: 43424.453 | B55: Dr Mehreen | C55: 36 | D55: Female | E55: MCPS | F55: General Practice | G55: Baldia Town | H55: Less than 10 | K55: 20-30% | L55: 6-10 | M55: CBC / ESR | O55: 10-20% | P55: 2000-2500 | V55: 600 | W55: 1200 | X55: 800 | Y55: 800 | Z55: 1000 | AA55: 1000 | AB55: 1200 | AC55: 1200 | AD55: 1200 | AE55: 600 | AF55: 600 | AG55: 1200 | AH55: 1000 | AI55: More than 6 | AJ55: AKU | AL55: Yes | AM55: No | AN55: No | AO55: 1. Price | AP55: Infomration about diagnostc machines
A56: 43424.456 | B56: Dr Nimrah Iftikhar | C56: 26 | D56: Female | E56: MBBS | F56: General Practice | G56: Korangi Town | H56: 30 - 40 | K56: 10-20% | L56: Less than 5 | M56: CBC / ESR | O56: 0-10% | P56: 500-1000 | V56: 400 | W56: 700 | X56: 800 | Y56: 500 | Z56: 800 | AA56: 500 | AB56: 600 | AC56: 800 | AD56: 800 | AE56: 600 | AF56: 600 | AG56: 700 | AH56: 900 | AI56: 6 | AJ56: Other | AL56: Yes | AM56: No | AN56: No | AO56: 2. Lab Reputation | AP56: Online reporting
A57: 43424.458 | B57: Dr Shaheen Ahmed | C57: 35 | D57: Female | E57: MCPS | F57: General Practice | G57: Korangi Town | H57: 30 - 40 | K57: 20-30% | L57: Less than 5 | M57: LFT | O57: 10-20% | P57: 1000-1500 | V57: 600 | W57: 600 | X57: 1000 | Y57: 800 | Z57: 800 | AA57: 500 | AB57: 800 | AC57: 1000 | AD57: 1200 | AE57: 1000 | AF57: 1000 | AG57: 1200 | AH57: 1300 | AI57: More than 6 | AJ57: Other | AL57: Yes | AM57: No | AN57: Yes | AO57: 3. Lab Quality | AP57: Seminars on new technologies
A58: 43424.462 | B58: Dr Talha Ahmed | C58: 34 | D58: Male | E58: MCPS | F58: General Practice | G58: Gulshan Town | H58: Less than 10 | K58: More than 50% | L58: Less than 5 | M58: CBC / ESR | O58: 30-40% | P58: 1000-1500 | V58: 400 | W58: 1000 | X58: 400, 1200 | Y58: 400 | Z58: 600 | AA58: 500 | AB58: Other | AC58: 1000 | AD58: 1000 | AE58: 1000 | AF58: 1200 | AG58: Column 15 | AH58: Column 15 | AI58: More than 6 | AJ58: Shifa | AL58: Yes | AM58: No | AN58: No | AO58: 5. Referral by Doctor | AP58: Seminars on new technologies
A59: 43424.465 | B59: Dr Yasir Paracha | C59: 35 | D59: Male | E59: FCPS | F59: General Practice | G59: North Nazimabad Town | H59: 20-30 | K59: 20-30% | L59: Less than 5 | M59: CBC / ESR | O59: 10-20% | P59: 1500-2000 | V59: 400 | W59: 800 | X59: 1200 | Y59: 400 | Z59: 400 | AA59: 600, 1200 | AB59: Other | AC59: 1100 | AD59: 1100 | AE59: 800 | AF59: 1000 | AG59: Other | AH59: Other | AI59: More than 6 | AJ59: Nicvd | AL59: Yes | AM59: No | AN59: No | AO59: 1. Price | AP59: Online reporting
A60: 43424.468 | B60: Dr Sanam | C60: 37 | D60: Female | E60: MBBS | F60: General Practice | G60: New Karachi Town | H60: 20-30 | K60: 0-10% | L60: Less than 5 | M60: LFT | O60: 10-20% | P60: < 500 | V60: 300 | W60: 400 | X60: 400 | Y60: 200 | Z60: 200 | AA60: 300 | AB60: 400 | AC60: 600 | AD60: 700 | AE60: 400 | AF60: 400 | AG60: 300 | AH60: 700 | AI60: 6 | AJ60: Other | AL60: Yes | AM60: No | AN60: No | AO60: 1. Price | AP60: Other
A61: 43424.471 | B61: Dr Mehreena | C61: 36 | D61: Female | E61: FCPS | F61: Chest Disease | G61: Saddar Town | H61: 20-30 | K61: 30-40% | L61: 6-10 | M61: Typhoid | O61: 30-40% | P61: 2000-2500 | V61: 500 | W61: 1000 | X61: 800 | Y61: 500 | Z61: 600 | AA61: 700 | AB61: 800 | AC61: 900 | AD61: 1000 | AE61: 1000 | AF61: 800 | AG61: 800 | AH61: 900 | AI61: More than 6 | AJ61: Essa | AL61: Yes | AM61: No | AN61: No | AO61: 3. Lab Quality | AP61: Other
A62: 43424.473 | B62: Dr Amjad | C62: 30 | D62: Male | E62: MBBS | F62: General Practice | G62: Liaquatabad Town | H62: Less than 10 | K62: 0-10% | L62: Less than 5 | M62: Malaria | O62: 0-10% | P62: 500-1000 | V62: 400 | W62: 400 | X62: 500 | Y62: 400 | Z62: 500 | AA62: 600 | AB62: 800 | AC62: 800 | AD62: 600 | AE62: 600 | AF62: 700 | AG62: 700 | AH62: 700 | AI62: 6 | AJ62: Other | AL62: No | AM62: No | AN62: No | AO62: 1. Price | AP62: Other

Sheet Patients
A1: Timestamp | B1: Age | C1: Sex | D1: Residence | E1: Monthly Household Income | F1: Employment | G1: Employment | H1: Mode of Transport to Center | I1: Total Family Members | J1: Total family members under treatment for any illness (incl self) currently? In last one month? | K1: Total family members have had a lab test in past one month (incl self) | L1: How many tests were done last month.? | M1: Total spending on lab tests in past one month | N1: Which tests do you remember were conducted? Do you have the prescription? | O1: How often does the doctor prescribe lab tests? | P1: Which laboratory have you used for tests? | Q1: How many different laboratories have you visited for tests in the last year? | R1: Most important factor in deciding lab for testing | S1: Which Hospital/Doctor you have used during your illness? i. Name of Hospital, ii. Location, iii. Name of Doctor | T1: Email address
A2: 43290.538 | B2: 35 | C2: Male | D2: New Karachi Town | E2: Below PKR 30,000 | F2: Unemployed | H2: Bus | J2: Two | K2: One | L2: None | M2: Less than 1000 | N2: LFT, ICT HBSAG & ICT HCV | O2: Every 3 visits | P2: M.M LABORATORY/ SINDH GOVERNMENT | Q2: Three | R2: Price | S2: SINDH GOVERNMENT HOSPITAL
A3: 43290.552 | B3: 41 | C3: Male | D3: New Karachi Town | E3: Below PKR 30,000 | F3: Employed | H3: Motorcycle | J3: One | K3: Two | L3: Four or More | M3: 2000-3000 | N3: CBC, Malaria, Typhoid, Urine, BLOOD TEST | O3: Every 2 visits | P3: DOW / ASIAN LAB | Q3: More than Three | R3: Price, Referral by Doctor | S3: DR.SOHAIL HAIDER BALOCH
A4: 43290.578 | B4: 58 | C4: Female | D4: Sukkur | E4: Below PKR 30,000 | F4: Self-Employed | H4: Motorcycle | J4: Two | K4: One | L4: One | M4: Less than 1000 | N4: ESR | O4: Every 3 visits | P4: AL KHAIR HOSPITAL | Q4: One | R4: Price, Lab Staff, Location | S4: DR MUHAMMAD UMAR
A5: 43290.593 | B5: 12 | C5: Female | D5: New Karachi Town | E5: Below PKR 30,000 | F5: Student | H5: Rickshaw | J5: None | K5: One | L5: None | M5: Less than 1000 | N5: x-ray / | O5: More than 4 | P5: ASIA LABORATORY | Q5: One | R5: Price | S5: Doctor shameem(Shameem clinic)
A6: 43290.688 | B6: 60 | C6: Male | D6: Gulshan Town | E6: PKR 30,000 - 60,000 | F6: Employed | H6: Walk-in | J6: One | K6: None | L6: None | M6: Less than 1000 | N6: NONE | O6: Every 4 visits | P6: AS PER DR INSTRUCTION | Q6: Two | R6: Referral by Doctor | S6: GULZAR E HAJRI
A7: 43292.406 | B7: 20 | C7: Male | D7: New Karachi Town | E7: Below PKR 30,000 | F7: Employed | H7: Motorcycle | J7: Three | K7: One | L7: None | M7: Less than 1000 | N7: CHEST X-RAY | O7: More than 4 | P7: DR WASEEM COLLECT BLOOD AND ISSUE REPORT | Q7: One | R7: Price | S7: DR. JUNAID/ DR WASEEM
A8: 43307.574 | B8: 45 | C8: Male | D8: Orangi Town | E8: Below PKR 30,000 | F8: Unemployed | H8: Walk-in | J8: Two | K8: One | L8: Two | M8: Less than 1000 | N8: CBC, HbA1c | O8: More than 4 | P8: SMZ | Q8: Two | R8: Referral by Doctor | S8: DR AHMED
A9: 43307.576 | B9: 6 | C9: Male | D9: SITE Town | E9: Below PKR 30,000 | F9: Employed | H9: Motorcycle | J9: One | K9: One | L9: None | M9: Less than 1000 | N9: CBC | O9: More than 4 | P9: SMZ | Q9: One | R9: Referral by Doctor | S9: DR MEHMOOD
A10: 43307.669 | B10: 54 | C10: Female | D10: North Nazimabad Town | E10: Below PKR 30,000 | F10: Employed | H10: Rickshaw | J10: None | K10: None | L10: One | M10: Less than 1000 | N10: X RAY CARVICAL | O10: More than 4 | P10: RASHID LAB HOP LAB | Q10: Two | R10: Price | S10: DR ADIL
A11: 43308.51 | B11: 18 | C11: Female | D11: Liaquatabad Town | E11: Below PKR 30,000 | F11: Unemployed | H11: Motorcycle | J11: Two | K11: Four or More | L11: Four or More | M11: 5000-8000 | N11: CBC, LFT, Malaria, Typhoid, Sugar test, Creatinine, Urine | O11: Every visit | P11: HOP LAB KKF LAB | Q11: One | R11: Price | S11: ABBASI HOSPITAL
A12: 43308.513 | B12: 42 | C12: Male | D12: North Nazimabad Town | E12: Below PKR 30,000 | F12: Employed | H12: Walk-in | J12: None | K12: None | L12: One | M12: Less than 1000 | N12: CBC | O12: More than 4 | P12: METRO LAB HI CARE LAB | Q12: Two | R12: Price, Referral by Doctor | S12: DR ADIL
A13: 43308.648 | B13: 35 | C13: Female | D13: SITE Town | E13: Below PKR 30,000 | F13: Employed | H13: Motorcycle | J13: One | K13: One | L13: One | M13: Less than 1000 | N13: CBC | O13: More than 4 | P13: dow ab | Q13: One | R13: Lab Reputation | S13: dr noor
... A112: 43399.601 | B112: 23 | C112: Male | D112: Bin Qasim Town | E112: PKR 30,000 - 60,000 | F112: Employed | H112: Bus | J112: One | K112: One | L112: Three | M112: 2000-3000 | N112: Malaria, Typhoid | O112: Every 2 visits | P112: Mehran lab | Q112: Two | R112: Price | S112: Dr adil,iftikhar ,gulshan e hadeed

Sheet Assumptions_charts
C2: CHS | D2: ='Main Center'!E64 -> 177342.77 | E2: ='Main Center'!F64 -> 231259.44 | F2: ='Main Center'!G64 -> 301674.88 | G2: ='Main Center'!H64 -> 394869.27 | H2: ='Main Center'!I64 -> 511162.13 | I2: ='Main Center'!J64 -> 634310.72 | J2: ='Main Center'!K64 -> 787356.85 | K2: ='Main Center'!L64 -> 977624.71 | ... W2: ='Main Center'!X64 -> 6858401.9
C3: Competitor Labs (Lower Limit) | D3: 1440000 | E3: 1584000 | F3: 1742400 | G3: 1916640 | H3: 2108304 | I3: 2319134 | J3: 2551048 | K3: 2806153 | L3: 3086768 | M3: 3395445 | N3: 3734989 | O3: 4108488 | P3: 4519337 | Q3: 4971271 | R3: 5468398 | S3: 6015237 | T3: 6616761 | U3: 7278437 | V3: 8006281 | W3: 8806909
C4: Competitor Labs (Average) | D4: 1890000 | E4: 2079000 | F4: 2286900 | G4: 2515590 | H4: 2767149 | I4: 3043864 | J4: 3348250 | K4: 3683075 | L4: 4051383 | M4: 4456521 | N4: 4902173 | O4: 5392391 | P4: 5931630 | Q4: 6524793 | R4: 7177272 | S4: 7894999 | T4: 8684499 | U4: 9552949 | V4: 10508244 | W4: 11559068
C5: Competitor Labs (Higher Limit) | D5: 2400000 | E5: 2640000 | F5: 2904000 | G5: 3194400 | H5: 3513840 | I5: 3865224 | J5: 4251746 | K5: 4676921 | L5: 5144613 | M5: 5659074 | N5: 6224982 | O5: 6847480 | P5: 7532228 | Q5: 8285451 | R5: 9113996 | S5: 10025396 | T5: 11027935 | U5: 12130729 | V5: 13343802 | W5: 14678182

Sheet Sheet1
B1: Sr. # | F1: Test Name | I1: # of Tests | N1: Gross Amount | R1: Discount | T1: Net Sales
B2: 1 | F2: ANKLE JOINT A/P &LATERAL RIGHT (DR/DIGITAL) | I2: 35 | P2: 17900 | R2: 4910 | T2: 12990
B3: 2 | F3: 24 HOURS URINE FOR CALCIUM | I3: 3 | P3: 1170 | R3: 630 | T3: 540
B4: 3 | F4: 24 HOURS URINE FOR CREATININECLEARANCE | I4: 5 | P4: 3450 | R4: 906 | T4: 2544
B5: 4 | F5: 24 HOURS URINE FOR MICROALBUMIN | I5: 3 | P5: 3090 | R5: 450 | T5: 2640
B6: 5 | F6: 24 HOURS URINE FOR URIC ACID | I6: 4 | P6: 1560 | R6: 480 | T6: 1080
B7: 6 | F7: ABDOMEN ERECT & SUPINE (DR/DIGITAL) | I7: 6 | P7: 4800 | R7: 1000 | T7: 3800
B8: 7 | F8: ABDOMEN ERECT (DR/DIGITAL) | I8: 30 | P8: 15000 | R8: 3513 | T8: 11487
B9: 8 | F9: ABDOMEN SUPINE (DR/DIGITAL) | I9: 14 | P9: 7000 | R9: 2080 | T9: 4920
B10: 9 | F10: ABSOLUTE INDICES | I10: 1 | P10: 290 | R10: 0 | T10: 290
B11: 10 | F11: ACID PHOSPHATASE | I11: 1 | P11: 920 | R11: 140 | T11: 780
B12: 11 | F12: ACTH/ ADRENOCORTICOTROPIC HORMONE | I12: 1 | P12: 100 | R12: 0 | T12: 100
B13: 12 | F13: ADENOIDS (DR/DIGITAL) | I13: 4 | P13: 2000 | R13: 600 | T13: 1400
... B351: 330 | F351: Z.N. STAIN / AFB STAIN -PRIVATE PATIENT | I351: 2273 | P351: 659170 | R351: 153064 | T351: 506106
C353: Over All Sales Summary | P353: 297315900 | R353: 258400282 | T353: 38916383
B356: Center Wise Tests Summary
A358: Sr. # | F358: Test Name | I358: # of Tests | O358: Gross Amount | R358: Discount | T358: Net Sales
A359: ALLAMA IQBAL ROAD LAHORE (GHARI SHAW) | K359: 1463 | P359: 1322790 | R359: 1082715 | T359: 240075
B360: 1 | F360: AFB SMEAR MICROSCOPY - FREE FOR TB | J360: 27 | P360: 7830 | R360: 7830 | T360: 0
B361: 2 | F361: BLOOD GROUP & RH FACTOR | J361: 1 | P361: 430 | R361: 130 | T361: 300
B362: 3 | F362: CALCIUM | J362: 16 | P362: 4640 | R362: 1280 | T362: 3360
B363: 4 | F363: CBC/ESR COMBINED | J363: 211 | P363: 116050 | R363: 46193 | T363: 69857
B364: 5 | F364: CBC-COMPLETE BLOOD COUNT | J364: 37 | P364: 18130 | R364: 7955 | T364: 10175
B365: 6 | F365: CERVICAL SPINE AP/LAT/OBLIQUE (DR/DIGITAL) | J365: 1 | P365: 700 | R365: 180 | T365: 520
B366: 7 | F366: CHEST X-RAY FREE FOR TB / INFECTION | J366: 279 | P366: 114300 | R366: 114300 | T366: 0
B367: 8 | F367: CHOLESTEROL | J367: 7 | P367: 1330 | R367: 430 | T367: 900
B368: 9 | F368: CLAVICLE AP (DR/DIGITAL) | J368: 1 | P368: 500 | R368: 150 | T368: 350
B369: 10 | F369: CORTISOL | J369: 1 | P369: 1790 | R369: 270 | T369: 1520
B370: 11 | F370: CREATININE | J370: 96 | P370: 24000 | R370: 12051 | T370: 11949
B371: 12 | F371: ESR / ERYTHROCYTE SEDIMENTATION RATE | J371: 3 | P371: 690 | R371: 230 | T371: 460
... B406: 47 | F406: XRAY PNS | J406: 1 | P406: 500 | R406: 150 | T406: 350
A407: KASHMIR CHOWK,MAIN HOSPITAL ROAD, MITHI, THARPAKAR | K407: 716 | P407: 244470 | R407: 237605 | T407: 6865
B408: 1 | F408: AFB SMEAR MICROSCOPY - FREE FOR TB | J408: 466 | P408: 135140 | R408: 135140 | T408: 0
B409: 2 | F409: CALCIUM | J409: 1 | P409: 290 | R409: 0 | T409: 290
B410: 3 | F410: CBC/ESR COMBINED | J410: 5 | P410: 2750 | R410: 680 | T410: 2070
B411: 4 | F411: CBC-COMPLETE BLOOD COUNT | J411: 5 | P411: 2450 | R411: 215 | T411: 2235
B412: 5 | F412: CHEST X-RAY FREE FOR TB / INFECTION | J412: 236 | P412: 100900 | R412: 100900 | T412: 0
B413: 6 | F413: HELICOBACTER PYLORI ANTIBODY IGG (ELISA) | J413: 1 | P413: 1570 | R413: 240 | T413: 1330
B414: 7 | F414: MALARIAL PARASITE | J414: 1 | P414: 290 | R414: 110 | T414: 180
B415: 8 | F415: TYPHIDOT | J415: 1 | P415: 1080 | R415: 320 | T415: 760
A416: SZC - GM ABAD FAISALABAD | K416: 2877 | P416: 3139620 | R416: 2893652 | T416: 245968
B417: 1 | F417: ABDOMEN ERECT (DR/DIGITAL) | J417: 1 | P417: 500 | R417: 150 | T417: 350
B418: 2 | F418: AFB SMEAR MICROSCOPY - FREE FOR TB | J418: 135 | P418: 39150 | R418: 39150 | T418: 0
B419: 3 | F419: ALBUMIN | J419: 1 | P419: 250 | R419: 70 | T419: 180
B420: 4 | F420: ANA | J420: 1 | P420: 1300 | R420: 200 | T420: 1100
B421: 5 | F421: ANKLE JOINT A/P & LATERAL LEFT (DR/DIGITAL) | J421: 1 | P421: 500 | R421: 150 | T421: 350
B422: 6 | F422: APTT/ACTIVATED PARTIAL THROMBOPLASTIN TIME | J422: 1 | P422: 590 | R422: 180 | T422: 410
B423: 7 | F423: BICARBONATE | J423: 1 | P423: 240 | R423: 70 | T423: 170
B424: 8 | F424: BLOOD GROUP & RH FACTOR | J424: 1 | P424: 430 | R424: 187 | T424: 243
B425: 9 | F425: BLOOD UREA NITROGEN / BUN | J425: 1 | P425: 290 | R425: 80 | T425: 210
B426: 10 | F426: CALCIUM | J426: 26 | P426: 7540 | R426: 2080 | T426: 5460
B427: 11 | F427: CBC/ESR COMBINED | J427: 84 | P427: 46200 | R427: 17705 | T427: 28495
B428: 12 | F428: CBC-COMPLETE BLOOD COUNT | J428: 254 | P428: 124460 | R428: 55713 | T428: 68747
... B470: 53 | F470: X-RAY WRIST A/P | J470: 1 | P470: 500 | R470: 130 | T470: 370
A471: SZC- DHOK SYEDAN | K471: 4432 | P471: 3126150 | R471: 2384086 | T471: 742064
B472: 1 | F472: ANKLE JOINT A/P &LATERAL RIGHT (DR/DIGITAL) | J472: 1 | P472: 500 | R472: 150 | T472: 350
B473: 2 | F473: ABDOMEN ERECT (DR/DIGITAL) | J473: 1 | P473: 500 | R473: 150 | T473: 350
B474: 3 | F474: AFB SMEAR MICROSCOPY - FREE FOR TB | J474: 537 | P474: 155730 | R474: 155730 | T474: 0
B475: 4 | F475: ANA | J475: 1 | P475: 1300 | R475: 200 | T475: 1100
B476: 5 | F476: ANKLE JOINT A/P & LATERAL LEFT (DR/DIGITAL) | J476: 1 | P476: 500 | R476: 150 | T476: 350
B477: 6 | F477: ANTI T-T IGG/ ANTI TISSUE TRANSGLUTAMINASE IGG | J477: 1 | P477: 1200 | R477: 180 | T477: 1020
B478: 7 | F478: ANTI T-TG IGA/ ANTI TISSUE TRANSGLUTAMINASE IGA | J478: 1 | P478: 1200 | R478: 180 | T478: 1020
B479: 8 | F479: APTT/ACTIVATED PARTIAL THROMBOPLASTIN TIME | J479: 1 | P479: 590 | R479: 0 | T479: 590
B480: 9 | F480: BLOOD GROUP & RH FACTOR | J480: 41 | P480: 17630 | R480: 7676 | T480: 9954
B481: 10 | F481: CALCIUM | J481: 1 | P481: 290 | R481: 80 | T481: 210
B482: 11 | F482: CBC/ESR COMBINED | J482: 625 | P482: 343750 | R482: 158869 | T482: 184881
B483: 12 | F483: CBC-COMPLETE BLOOD COUNT | J483: 47 | P483: 23030 | R483: 8524 | T483: 14506
... B533: 62 | F533: WIDAL | J533: 7 | P533: 4130 | R533: 900 | T533: 3230
A534: SZC- SATTLITE TOWN | K534: 5060 | P534: 3921380 | R534: 3120684 | T534: 800696
B535: 1 | F535: AFB SMEAR MICROSCOPY - FREE FOR TB | J535: 615 | P535: 178350 | R535: 178350 | T535: 0
B536: 2 | F536: AMYLASE | J536: 1 | P536: 570 | R536: 170 | T536: 400
B537: 3 | F537: ANKLE JOINT A/P & LATERAL LEFT (DR/DIGITAL) | J537: 1 | P537: 500 | R537: 130 | T537: 370
B538: 4 | F538: ANTI T-T IGG/ ANTI TISSUE TRANSGLUTAMINASE IGG | J538: 1 | P538: 1200 | R538: 180 | T538: 1020
B539: 5 | F539: ANTI T-TG IGA/ ANTI TISSUE TRANSGLUTAMINASE IGA | J539: 1 | P539: 1200 | R539: 180 | T539: 1020
B540: 6 | F540: ASOT /ANTI STREPTOLYSIN O TITRE | J540: 1 | P540: 590 | R540: 180 | T540: 410
B541: 7 | F541: BLOOD C/S (CULTURE & SENSITIVITY) | J541: 1 | P541: 1190 | R541: 180 | T541: 1010
B542: 8 | F542: BLOOD GROUP & RH FACTOR | J542: 25 | P542: 10750 | R542: 4654 | T542: 6096
B543: 9 | F543: CALCIUM | J543: 12 | P543: 3480 | R543: 960 | T543: 2520
B544: 10 | F544: CARDIAC ENZYMES | J544: 1 | P544: 1350 | R544: 400 | T544: 950
B545: 11 | F545: CBC/ESR COMBINED | J545: 820 | P545: 451000 | R545: 162630 | T545: 288370
B546: 12 | F546: CBC-COMPLETE BLOOD COUNT | J546: 41 | P546: 20090 | R546: 8714 | T546: 11376
... B623: 89 | F623: X-RAY L.S SPINE A/P | J623: 1 | P623: 500 | R623: 130 | T623: 370
A624: SZC-AFANDI ROAD - HYDERABAD CITY | K624: 4223 | P624: 4976750 | R624: 4576281 | T624: 400469
B625: 1 | F625: 24 HOURS URINE FOR URIC ACID | J625: 1 | P625: 390 | R625: 120 | T625: 270
B626: 2 | F626: AFB SMEAR MICROSCOPY - FREE FOR TB | J626: 456 | P626: 132240 | R626: 132240 | T626: 0
B627: 3 | F627: BLOOD GROUP & RH FACTOR | J627: 4 | P627: 1720 | R627: 570 | T627: 1150
B628: 4 | F628: CALCIUM | J628: 22 | P628: 6380 | R628: 960 | T628: 5420
B629: 5 | F629: CBC/ESR COMBINED | J629: 416 | P629: 228800 | R629: 65206 | T629: 163594
B630: 6 | F630: CBC-COMPLETE BLOOD COUNT | J630: 261 | P630: 127890 | R630: 52735 | T630: 75155
B631: 7 | F631: CHEST AP VIEW (DR/DIGITAL) | J631: 11 | P631: 5500 | R631: 1650 | T631: 3850
B632: 8 | F632: CHEST X-RAY 8 X 10 | J632: 2 | P632: 600 | R632: 160 | T632: 440
B633: 9 | F633: CHEST X-RAY FREE FOR TB / INFECTION | J633: 837 | P633: 339700 | R633: 339700 | T633: 0
B634: 10 | F634: CHEST-XR, GENEXP & SPIROMETRY | J634: 8 | P634: 4800 | R634: 4800 | T634: 0
B635: 11 | F635: CHOLESTEROL | J635: 5 | P635: 950 | R635: 220 | T635: 730
B636: 12 | F636: CREATININE | J636: 8 | P636: 2000 | R636: 340 | T636: 1660
... B673: 49 | F673: X-RAY MANDIBLE | J673: 1 | P673: 500 | R673: 150 | T673: 350
A674: SZC-AKHUNZADA TOWER DALAZAK ROAD , PESHAWAR | K674: 1084 | P674: 1874000 | R674: 1872950 | T674: 1050
B675: 1 | F675: AFB SMEAR MICROSCOPY - FREE FOR TB | J675: 40 | P675: 11600 | R675: 11600 | T675: 0
B676: 2 | F676: CHEST P/A LAT (DR/DIGITAL) | J676: 1 | P676: 700 | R676: 700 | T676: 0
B677: 3 | F677: CHEST X-RAY FREE FOR TB / INFECTION | J677: 350 | P677: 142800 | R677: 142800 | T677: 0
...

Sheet Sheet3
A1: Sr. # | F1: Test Name | J1: # of Tests | O1: Gross Amount | R1: Discount | T1: Net Sales | Y1: Commerical Tests
A2: ALLAMA IQBAL ROAD LAHORE (GHARI SHAW) | K2: 1463 | P2: 1322790 | R2: 1082715 | T2: 240075
B3: 1 | F3: AFB SMEAR MICROSCOPY - FREE FOR TB | J3: 27 | P3: 7830 | R3: 7830 | T3: 0
B4: 2 | F4: BLOOD GROUP & RH FACTOR | J4: 1 | P4: 430 | R4: 130 | T4: 300
B5: 3 | F5: CALCIUM | J5: 16 | P5: 4640 | R5: 1280 | T5: 3360
B6: 4 | F6: CBC/ESR COMBINED | J6: 211 | P6: 116050 | R6: 46193 | T6: 69857
B7: 5 | F7: CBC-COMPLETE BLOOD COUNT | J7: 37 | P7: 18130 | R7: 7955 | T7: 10175
B8: 6 | F8: CERVICAL SPINE AP/LAT/OBLIQUE (DR/DIGITAL) | J8: 1 | P8: 700 | R8: 180 | T8: 520
B9: 7 | F9: CHEST X-RAY FREE FOR TB / INFECTION | J9: 279 | P9: 114300 | R9: 114300 | T9: 0
B10: 8 | F10: CHOLESTEROL | J10: 7 | P10: 1330 | R10: 430 | T10: 900
B11: 9 | F11: CLAVICLE AP (DR/DIGITAL) | J11: 1 | P11: 500 | R11: 150 | T11: 350
B12: 10 | F12: CORTISOL | J12: 1 | P12: 1790 | R12: 270 | T12: 1520
B13: 11 | F13: CREATININE | J13: 96 | P13: 24000 | R13: 12051 | T13: 11949
B14: 12 | F14: ESR / ERYTHROCYTE SEDIMENTATION RATE | J14: 3 | P14: 690 | R14: 230 | T14: 460
... B49: 47 | F49: XRAY PNS | J49: 1 | P49: 500 | R49: 150 | T49: 350
A50: KASHMIR CHOWK,MAIN HOSPITAL ROAD, MITHI, THARPAKAR | K50: 716 | P50: 244470 | R50: 237605 | T50: 6865
B51: 1 | F51: AFB SMEAR MICROSCOPY - FREE FOR TB | J51: 466 | P51: 135140 | R51: 135140 | T51: 0
B52: 2 | F52: CALCIUM | J52: 1 | P52: 290 | R52: 0 | T52: 290
B53: 3 | F53: CBC/ESR COMBINED | J53: 5 | P53: 2750 | R53: 680 | T53: 2070
B54: 4 | F54: CBC-COMPLETE BLOOD COUNT | J54: 5 | P54: 2450 | R54: 215 | T54: 2235
B55: 5 | F55: CHEST X-RAY FREE FOR TB / INFECTION | J55: 236 | P55: 100900 | R55: 100900 | T55: 0
B56: 6 | F56: HELICOBACTER PYLORI ANTIBODY IGG (ELISA) | J56: 1 | P56: 1570 | R56: 240 | T56: 1330
B57: 7 | F57: MALARIAL PARASITE | J57: 1 | P57: 290 | R57: 110 | T57: 180
B58: 8 | F58: TYPHIDOT | J58: 1 | P58: 1080 | R58: 320 | T58: 760
A59: SZC - GM ABAD FAISALABAD | K59: 2877 | P59: 3139620 | R59: 2893652 | T59: 245968
B60: 1 | F60: ABDOMEN ERECT (DR/DIGITAL) | J60: 1 | P60: 500 | R60: 150 | T60: 350
B61: 2 | F61: AFB SMEAR MICROSCOPY - FREE FOR TB | J61: 135 | P61: 39150 | R61: 39150 | T61: 0
B62: 3 | F62: ALBUMIN | J62: 1 | P62: 250 | R62: 70 | T62: 180
B63: 4 | F63: ANA | J63: 1 | P63: 1300 | R63: 200 | T63: 1100
B64: 5 | F64: ANKLE JOINT A/P & LATERAL LEFT (DR/DIGITAL) | J64: 1 | P64: 500 | R64: 150 | T64: 350
B65: 6 | F65: APTT/ACTIVATED PARTIAL THROMBOPLASTIN TIME | J65: 1 | P65: 590 | R65: 180 | T65: 410
B66: 7 | F66: BICARBONATE | J66: 1 | P66: 240 | R66: 70 | T66: 170
B67: 8 | F67: BLOOD GROUP & RH FACTOR | J67: 1 | P67: 430 | R67: 187 | T67: 243
B68: 9 | F68: BLOOD UREA NITROGEN / BUN | J68: 1 | P68: 290 | R68: 80 | T68: 210
B69: 10 | F69: CALCIUM | J69: 26 | P69: 7540 | R69: 2080 | T69: 5460
B70: 11 | F70: CBC/ESR COMBINED | J70: 84 | P70: 46200 | R70: 17705 | T70: 28495
B71: 12 | F71: CBC-COMPLETE BLOOD COUNT | J71: 254 | P71: 124460 | R71: 55713 | T71: 68747
... B113: 53 | F113: X-RAY WRIST A/P | J113: 1 | P113: 500 | R113: 130 | T113: 370
A114: SZC- DHOK SYEDAN | K114: 4432 | P114: 3126150 | R114: 2384086 | T114: 742064
B115: 1 | F115: ANKLE JOINT A/P &LATERAL RIGHT (DR/DIGITAL) | J115: 1 | P115: 500 | R115: 150 | T115: 350
B116: 2 | F116: ABDOMEN ERECT (DR/DIGITAL) | J116: 1 | P116: 500 | R116: 150 | T116: 350
B117: 3 | F117: AFB SMEAR MICROSCOPY - FREE FOR TB | J117: 537 | P117: 155730 | R117: 155730 | T117: 0
B118: 4 | F118: ANA | J118: 1 | P118: 1300 | R118: 200 | T118: 1100
B119: 5 | F119: ANKLE JOINT A/P & LATERAL LEFT (DR/DIGITAL) | J119: 1 | P119: 500 | R119: 150 | T119: 350
B120: 6 | F120: ANTI T-T IGG/ ANTI TISSUE TRANSGLUTAMINASE IGG | J120: 1 | P120: 1200 | R120: 180 | T120: 1020
B121: 7 | F121: ANTI T-TG IGA/ ANTI TISSUE TRANSGLUTAMINASE IGA | J121: 1 | P121: 1200 | R121: 180 | T121: 1020
B122: 8 | F122: APTT/ACTIVATED PARTIAL THROMBOPLASTIN TIME | J122: 1 | P122: 590 | R122: 0 | T122: 590
B123: 9 | F123: BLOOD GROUP & RH FACTOR | J123: 41 | P123: 17630 | R123: 7676 | T123: 9954
B124: 10 | F124: CALCIUM | J124: 1 | P124: 290 | R124: 80 | T124: 210
B125: 11 | F125: CBC/ESR COMBINED | J125: 625 | P125: 343750 | R125: 158869 | T125: 184881
B126: 12 | F126: CBC-COMPLETE BLOOD COUNT | J126: 47 | P126: 23030 | R126: 8524 | T126: 14506
... B176: 62 | F176: WIDAL | J176: 7 | P176: 4130 | R176: 900 | T176: 3230
A177: SZC- SATTLITE TOWN | K177: 5060 | P177: 3921380 | R177: 3120684 | T177: 800696
B178: 1 | F178: AFB SMEAR MICROSCOPY - FREE FOR TB | J178: 615 | P178: 178350 | R178: 178350 | T178: 0
B179: 2 | F179: AMYLASE | J179: 1 | P179: 570 | R179: 170 | T179: 400
B180: 3 | F180: ANKLE JOINT A/P & LATERAL LEFT (DR/DIGITAL) | J180: 1 | P180: 500 | R180: 130 | T180: 370
B181: 4 | F181: ANTI T-T IGG/ ANTI TISSUE TRANSGLUTAMINASE IGG | J181: 1 | P181: 1200 | R181: 180 | T181: 1020
B182: 5 | F182: ANTI T-TG IGA/ ANTI TISSUE TRANSGLUTAMINASE IGA | J182: 1 | P182: 1200 | R182: 180 | T182: 1020
B183: 6 | F183: ASOT /ANTI STREPTOLYSIN O TITRE | J183: 1 | P183: 590 | R183: 180 | T183: 410
B184: 7 | F184: BLOOD C/S (CULTURE & SENSITIVITY) | J184: 1 | P184: 1190 | R184: 180 | T184: 1010
B185: 8 | F185: BLOOD GROUP & RH FACTOR | J185: 25 | P185: 10750 | R185: 4654 | T185: 6096
B186: 9 | F186: CALCIUM | J186: 12 | P186: 3480 | R186: 960 | T186: 2520
B187: 10 | F187: CARDIAC ENZYMES | J187: 1 | P187: 1350 | R187: 400 | T187: 950
B188: 11 | F188: CBC/ESR COMBINED | J188: 820 | P188: 451000 | R188: 162630 | T188: 288370
B189: 12 | F189: CBC-COMPLETE BLOOD COUNT | J189: 41 | P189: 20090 | R189: 8714 | T189: 11376
... B266: 89 | F266: X-RAY L.S SPINE A/P | J266: 1 | P266: 500 | R266: 130 | T266: 370
A267: SZC-AFANDI ROAD - HYDERABAD CITY | K267: 4223 | P267: 4976750 | R267: 4576281 | T267: 400469
B268: 1 | F268: 24 HOURS URINE FOR URIC ACID | J268: 1 | P268: 390 | R268: 120 | T268: 270
B269: 2 | F269: AFB SMEAR MICROSCOPY - FREE FOR TB | J269: 456 | P269: 132240 | R269: 132240 | T269: 0
B270: 3 | F270: BLOOD GROUP & RH FACTOR | J270: 4 | P270: 1720 | R270: 570 | T270: 1150
B271: 4 | F271: CALCIUM | J271: 22 | P271: 6380 | R271: 960 | T271: 5420
B272: 5 | F272: CBC/ESR COMBINED | J272: 416 | P272: 228800 | R272: 65206 | T272: 163594
B273: 6 | F273: CBC-COMPLETE BLOOD COUNT | J273: 261 | P273: 127890 | R273: 52735 | T273: 75155
B274: 7 | F274: CHEST AP VIEW (DR/DIGITAL) | J274: 11 | P274: 5500 | R274: 1650 | T274: 3850
B275: 8 | F275: CHEST X-RAY 8 X 10 | J275: 2 | P275: 600 | R275: 160 | T275: 440
B276: 9 | F276: CHEST X-RAY FREE FOR TB / INFECTION | J276: 837 | P276: 339700 | R276: 339700 | T276: 0
B277: 10 | F277: CHEST-XR, GENEXP & SPIROMETRY | J277: 8 | P277: 4800 | R277: 4800 | T277: 0
B278: 11 | F278: CHOLESTEROL | J278: 5 | P278: 950 | R278: 220 | T278: 730
B279: 12 | F279: CREATININE | J279: 8 | P279: 2000 | R279: 340 | T279: 1660
... B316: 49 | F316: X-RAY MANDIBLE | J316: 1 | P316: 500 | R316: 150 | T316: 350
A317: SZC-AKHUNZADA TOWER DALAZAK ROAD , PESHAWAR | K317: 1084 | P317: 1874000 | R317: 1872950 | T317: 1050
B318: 1 | F318: AFB SMEAR MICROSCOPY - FREE FOR TB | J318: 40 | P318: 11600 | R318: 11600 | T318: 0
B319: 2 | F319: CHEST P/A LAT (DR/DIGITAL) | J319: 1 | P319: 700 | R319: 700 | T319: 0
B320: 3 | F320: CHEST X-RAY FREE FOR TB / INFECTION | J320: 350 | P320: 142800 | R320: 142800 | T320: 0
B321: 4 | F321: CHEST-XR, GENEXP & SPIROMETRY | J321: 4 | P321: 2400 | R321: 2400 | T321: 0
B322: 5 | F322: GENEXPERT TB ASSAY | J322: 686 | P322: 1715000 | R322: 1715000 | T322: 0
B323: 6 | F323: PNS WATER'S VIEW (DR/DIGITAL) | J323: 1 | P323: 500 | R323: 150 | T323: 350
B324: 7 | F324: WRIST JOINT AP FOR BONE AGE (DR/DIGITAL) | J324: 2 | P324: 1000 | R324: 300 | T324: 700
A325: SZC-AL ASIF SATELLITE CENTER | K325: 4416 | P325: 3885715 | R325: 3186083 | T325: 699632
B326: 1 | F326: ANKLE JOINT A/P &LATERAL RIGHT (DR/DIGITAL) | J326: 1 | P326: 500 | R326: 150 | T326: 350
B327: 2 | F327: ABDOMEN ERECT (DR/DIGITAL) | J327: 1 | P327: 500 | R327: 150 | T327: 350
B328: 3 | F328: AFB SMEAR MICROSCOPY - FREE FOR TB | J328: 174 | P328: 50460 | R328: 50460 | T328: 0
B329: 4 | F329: AMYLASE | J329: 2 | P329: 1140 | R329: 340 | T329: 800
B330: 5 | F330: ANTI T-T IGG/ ANTI TISSUE TRANSGLUTAMINASE IGG | J330: 1 | P330: 1200 | R330: 180 | T330: 1020
B331: 6 | F331: APTT/ACTIVATED PARTIAL THROMBOPLASTIN TIME | J331: 1 | P331: 590 | R331: 180 | T331: 410
B332: 7 | F332: ASOT /ANTI STREPTOLYSIN O TITRE | J332: 1 | P332: 590 | R332: 180 | T332: 410
B333: 8 | F333: BLOOD C/S (CULTURE & SENSITIVITY) | J333: 6 | P333: 7140 | R333: 1080 | T333: 6060
B334: 9 | F334: BLOOD GROUP & RH FACTOR | J334: 16 | P334: 6880 | R334: 2824 | T334: 4056
B335: 10 | F335: BLOOD UREA NITROGEN / BUN | J335: 1 | P335: 290 | R335: 80 | T335: 210
B336: 11 | F336: BP / BLOOD PRESSURE TEST | J336: 9 | P336: 225 | R336: 45 | T336: 180
...
