Workbook

Sheet Input Parameters
B3: Plant Parameters
B4: Parameter | C4: Unit | D4: Value | E4: Source
B5: Clinker Production | C5: tClk/day | D5: 2896 | E5: CEMCAP
B6: Plant Capacity | C6: % | D6: 0.913 | E6: CEMCAP
B7: Operation | C7: days | D7: =365*D6 -> 333.245 | E7: Calculated
B8: Annual clinker production | C8: tons/year | D8: =D7*D5 -> 965077.52 | E8: Calculated
B9: Specific CO2 emissions | C9: tCO2/tClk | D9: 0.85 | E9: CEMCAP
B10: Plant Emissions | C10: tCO2 | D10: =D9*D8 -> 820315.89 | E10: Calculated
B12: Energy System Inputs
B13: Parameter | C13: Unit | D13: Value | E13: Source
B14: Denmark Natural Gas Price | C14: Euro/kWh | D14: 0.058 | E14: https://ec.europa.eu/eurostat/databrowser/view/nrg_pc_203__custom_20285923/default/table
B15: Germany Natural Gas Price | C15: Euro/kWh | D15: 0.05 | E15: https://ec.europa.eu/eurostat/databrowser/view/nrg_pc_203__custom_20285923/default/table
B16: Denmark Electricity Price | C16: Euro/kWh | D16: 0.126 | E16: https://ec.europa.eu/eurostat/statistics-explained/index.php?title=Electricity_price_statistics#Electricity_prices_for_non-household_consumers
B17: Germany Electricity Price | C17: Euro/kWh | D17: 0.1932 | E17: https://ec.europa.eu/eurostat/statistics-explained/index.php?title=Electricity_price_statistics#Electricity_prices_for_non-household_consumers
B18: Denmark Grid Emission Factor | C18: kgCO2/kWh | D18: 0.076 | E18: https://www.eea.europa.eu/en/analysis/indicators/greenhouse-gas-emission-intensity-of-1
B19: Germany Grid Emission Factor | C19: kgCO2/kWh | D19: 0.298 | E19: https://www.eea.europa.eu/en/analysis/indicators/greenhouse-gas-emission-intensity-of-1
B20: Natural Gas Emission Factor | C20: kgCO2/kWh | D20: 0.2 | E20: https://en.energinet.dk/media/nkmdwnwb/co2-emission-factor.pdf
B23: Cost Inputs
B24: Parameter | C24: Unit | D24: Value | E24: Source
B25: Capex without liquefication | C25: mEur/tCO2/h | D25: 2.8 | E25: DEA
B26: Fixed Opex | C26: % | D26: 0.03 | E26: DEA, 3% of Capex
B27: Variable Opex | C27: Eur/tCO2 | D27: 2.9 | E27: DEA, Includes Amine and other smaller consumables as well as waste disposal.
B29: Transport and Storage Inputs
B30: Parameter | C30: Unit | D30: Value | E30: Source
B31: Transport and Storage emission factor | C31: tCO2e/tCO2 | D31: 0.026 | E31: https://norlights.com/wp-content/uploads/2023/11/Report-Carbon-footprint-of-the-Northern-Lights-JV-co2-transport-and-storage-value-chain.pdf
B33: Financial Parameters
B34: Parameter | C34: Unit | D34: Value | E34: Source
B35: Lifetime | C35: years | D35: 25 | E35: CEMCAP
B36: WACC | C36: % | D36: ='Inflation and WACC'!C64 -> 0.0962 | E36: CEMCAP
B37: Inflation Rate | C37: % | D37: 0.015 | E37: CATF
B38: Construction Time | C38: years | D38: 3 | E38: CEMCAP
B39: CAPEX Split | C39: % | D39: 40-30-30 | E39: CEMCAP, Split over 3 years
B40: CRF | D40: =(D36*(1+D36)^D35)/(((1+D36)^D35)-1) -> 0.10696452 | E40: Calculated
B41: DKK - EUR Exchange rate 2025 average | D41: 7.4634 | E41: https://www.ecb.europa.eu/stats/policy_and_exchange_rates/euro_reference_exchange_rates/html/eurofxref-graph-dkk.en.html
B42: Germany Tax Rate | C42: % | D42: 0.3013 | E42: https://kpmg.com/dk/en/services/tax/corporate-tax/corporate-tax-rates-table.html
B43: Denmark Tax Rate | C43: % | D43: 0.22 | E43: https://kpmg.com/dk/en/services/tax/corporate-tax/corporate-tax-rates-table.html
B44: Danish CO2 Tax 2025 | C44: Euro/ton | D44: =114.9/D41 -> 15.395128 | E44: Danish CO2 tax, inflated to 2025, using the danish inflation calculator (https://www.dst.dk/en/Statistik/laer-om-statistik/prisberegner)
B45: Danish CO2 Tax 2026 | C45: Euro/ton | D45: =120.59/D41 -> 16.157515 | E45: Danish CO2 tax, inflated to 2025
B46: Danish CO2 Tax 2027 | C46: Euro/ton | D46: =126.4/D41 -> 16.935981 | E46: Danish CO2 tax, inflated to 2025
B47: Danish CO2 Tax 2028 | C47: Euro/ton | D47: =132.09/D41 -> 17.698368 | E47: Danish CO2 tax, inflated to 2025
B48: Danish CO2 Tax 2029 | C48: Euro/ton | D48: =137.9/D41 -> 18.476834 | E48: Danish CO2 tax, inflated to 2025
B49: Danish CO2 Tax 2030 onwards | C49: Euro/ton | D49: =143.59/D41 -> 19.239221 | E49: Danish CO2 tax, inflated to 2025

Sheet Transport and Storage
B3: Transport and Storage Costs | K3: Cost Separation
B4: Pipeline? | C4: Country | D4: Location | E4: Mode of Transport | F4: Transport Hub | G4: Storage Type | H4: Sector Germany | I4: Cost per t/CO2 in 2024 | J4: Cost per t/CO2 in 2025 | K4: Conditioning Cost | L4: Storage Cost | M4: Transport Cost | R4: Country | S4: Pipeline | T4: T&S percentile | U4: Value | W4: Inflation Factor
B5: Pipeline Allowed | C5: Denmark | D5: Aalborg | E5: Located at storage hub | F5: Aalborg | G5: =IF(OR(F5="Ruby",F5="Aalborg"),"Onshore","Offshore") -> Onshore | H5: Denmark | I5: 33.3 | J5: =I5*$W$5 -> 34.1325 | K5: 15 | L5: =IF(G5="Onshore",15,30) -> 15 | M5: =J5-SUM(K5:L5) -> 4.1325 | R5: Denmark | S5: Pipeline allowed | T5: P25 | U5: =J5 -> 34.1325 | W5: 1.025
B6: Pipeline Disallowed | C6: Denmark | D6: Aalborg | E6: Located at storage hub | F6: Aalborg | G6: =IF(OR(F6="Ruby",F6="Aalborg"),"Onshore","Offshore") -> Onshore | H6: Denmark | I6: 33.86 | J6: =I6*$W$5 -> 34.7065 | K6: 15 | L6: =IF(G6="Onshore",15,30) -> 15 | M6: =J6-SUM(K6:L6) -> 4.7065 | R6: Denmark | S6: Pipeline disallowed | T6: P25 | U6: =J6 -> 34.7065
B7: Pipeline Disallowed | C7: Germany | D7: Kalkwerke Rüdersdorf | E7: Rail | F7: Esbjerg | G7: =IF(OR(F7="Ruby",F7="Aalborg"),"Onshore","Offshore") -> Offshore | H7: North | I7: 121.04 | J7: =I7*$W$5 -> 124.066 | K7: =IF(E7="Pipeline",15,17.5) -> 17.5 | L7: =IF(G7="Onshore",15,30) -> 30 | M7: =J7-SUM(K7:L7) -> 76.566 | R7: Denmark | S7: Pipeline allowed | T7: P50 | U7: =J5 -> 34.1325
B8: Pipeline Disallowed | C8: Germany | D8: Zementwerk Karsdorf | E8: Rail | F8: Esbjerg | G8: =IF(OR(F8="Ruby",F8="Aalborg"),"Onshore","Offshore") -> Offshore | H8: North | I8: 120.59 | J8: =I8*$W$5 -> 123.60475 | K8: =IF(E8="Pipeline",15,17.5) -> 17.5 | L8: =IF(G8="Onshore",15,30) -> 30 | M8: =J8-SUM(K8:L8) -> 76.10475 | R8: Denmark | S8: Pipeline disallowed | T8: P50 | U8: =J6 -> 34.7065
B9: Pipeline Disallowed | C9: Germany | D9: Zementwerk Rüdersdorf | E9: Rail | F9: Esbjerg | G9: =IF(OR(F9="Ruby",F9="Aalborg"),"Onshore","Offshore") -> Offshore | H9: North | I9: 120.38 | J9: =I9*$W$5 -> 123.3895 | K9: =IF(E9="Pipeline",15,17.5) -> 17.5 | L9: =IF(G9="Onshore",15,30) -> 30 | M9: =J9-SUM(K9:L9) -> 75.8895 | R9: Denmark | S9: Pipeline allowed | T9: P75 | U9: =J5 -> 34.1325
B10: Pipeline Disallowed | C10: Germany | D10: Zementwerk Bernburg | E10: Rail | F10: Esbjerg | G10: =IF(OR(F10="Ruby",F10="Aalborg"),"Onshore","Offshore") -> Offshore | H10: North | I10: 117.54 | J10: =I10*$W$5 -> 120.4785 | K10: =IF(E10="Pipeline",15,17.5) -> 17.5 | L10: =IF(G10="Onshore",15,30) -> 30 | M10: =J10-SUM(K10:L10) -> 72.9785 | R10: Denmark | S10: Pipeline disallowed | T10: P75 | U10: =J6 -> 34.7065
B11: Pipeline Disallowed | C11: Germany | D11: Fels KH NSO 1-5 Oberharz am Brocken | E11: Rail | F11: Esbjerg | G11: =IF(OR(F11="Ruby",F11="Aalborg"),"Onshore","Offshore") -> Offshore | H11: North | I11: 115.23 | J11: =I11*$W$5 -> 118.11075 | K11: =IF(E11="Pipeline",15,17.5) -> 17.5 | L11: =IF(G11="Onshore",15,30) -> 30 | M11: =J11-SUM(K11:L11) -> 70.61075 | R11: Germany | S11: Pipeline allowed | T11: P25 | U11: {=_xlfn.PERCENTILE.INC(_xlfn._xlws.FILTER($J$5:$J$98,($C$5:$C$98="Germany")*($B$5:B98="Pipeline Allowed")),0.25)} -> 52.784937
B12: Pipeline Disallowed | C12: Germany | D12: Fels KR NSO 1-8 Oberharz am Brocken | E12: Rail | F12: Esbjerg | G12: =IF(OR(F12="Ruby",F12="Aalborg"),"Onshore","Offshore") -> Offshore | H12: North | I12: 114.96 | J12: =I12*$W$5 -> 117.834 | K12: =IF(E12="Pipeline",15,17.5) -> 17.5 | L12: =IF(G12="Onshore",15,30) -> 30 | M12: =J12-SUM(K12:L12) -> 70.334 | R12: Germany | S12: Pipeline disallowed | T12: P25 | U12: {=_xlfn.PERCENTILE.INC(_xlfn._xlws.FILTER($J$5:$J$98,($C$5:$C$98="Germany")*($B$5:B98="Pipeline Disallowed")),0.25)} -> 97.308375
B13: Pipeline Disallowed | C13: Germany | D13: Fels KK GGR 6 Oberharz am Brocken | E13: Rail | F13: Esbjerg | G13: =IF(OR(F13="Ruby",F13="Aalborg"),"Onshore","Offshore") -> Offshore | H13: North | I13: 114.89 | J13: =I13*$W$5 -> 117.76225 | K13: =IF(E13="Pipeline",15,17.5) -> 17.5 | L13: =IF(G13="Onshore",15,30) -> 30 | M13: =J13-SUM(K13:L13) -> 70.26225 | R13: Germany | S13: Pipeline allowed | T13: P50 | U13: {=MEDIAN(_xlfn._xlws.FILTER(J5:J98,(C5:C98="Germany")*(B5:B98="Pipeline Allowed")))} -> 71.939625
B14: Pipeline Disallowed | C14: Germany | D14: Zementwerk Dotternhausen | E14: Rail | F14: Rotterdam | G14: =IF(OR(F14="Ruby",F14="Aalborg"),"Onshore","Offshore") -> Offshore | H14: South | I14: 114.01 | J14: =I14*$W$5 -> 116.86025 | K14: =IF(E14="Pipeline",15,17.5) -> 17.5 | L14: =IF(G14="Onshore",15,30) -> 30 | M14: =J14-SUM(K14:L14) -> 69.36025 | R14: Germany | S14: Pipeline disallowed | T14: P50 | U14: {=MEDIAN(_xlfn._xlws.FILTER(J5:J98,(C5:C98="Germany")*(B5:B98="Pipeline Disallowed")))} -> 105.575
B15: Pipeline Disallowed | C15: Germany | D15: Kalkwerk Seesen | E15: Rail | F15: Esbjerg | G15: =IF(OR(F15="Ruby",F15="Aalborg"),"Onshore","Offshore") -> Offshore | H15: North | I15: 113.63 | J15: =I15*$W$5 -> 116.47075 | K15: =IF(E15="Pipeline",15,17.5) -> 17.5 | L15: =IF(G15="Onshore",15,30) -> 30 | M15: =J15-SUM(K15:L15) -> 68.97075 | R15: Germany | S15: Pipeline allowed | T15: P75 | U15: {=_xlfn.PERCENTILE.INC(_xlfn._xlws.FILTER(J5:J98,(C5:C98="Germany")*(B5:B98="Pipeline Allowed")),0.75)} -> 78.960875
B16: Pipeline Disallowed | C16: Germany | D16: Zementwerk Burglengenfeld | E16: Rail | F16: Ravenna | G16: =IF(OR(F16="Ruby",F16="Aalborg"),"Onshore","Offshore") -> Offshore | H16: South | I16: 112.33 | J16: =I16*$W$5 -> 115.13825 | K16: =IF(E16="Pipeline",15,17.5) -> 17.5 | L16: =IF(G16="Onshore",15,30) -> 30 | M16: =J16-SUM(K16:L16) -> 67.63825 | R16: Germany | S16: Pipeline disallowed | T16: P75 | U16: {=_xlfn.PERCENTILE.INC(_xlfn._xlws.FILTER(J5:J98,(C5:C98="Germany")*(B5:B98="Pipeline Disallowed")),0.75)} -> 112.48862
B17: Pipeline Disallowed | C17: Germany | D17: Zementwerk Solnhofen | E17: Rail | F17: Ravenna | G17: =IF(OR(F17="Ruby",F17="Aalborg"),"Onshore","Offshore") -> Offshore | H17: South | I17: 109.89 | J17: =I17*$W$5 -> 112.63725 | K17: =IF(E17="Pipeline",15,17.5) -> 17.5 | L17: =IF(G17="Onshore",15,30) -> 30 | M17: =J17-SUM(K17:L17) -> 65.13725 | R17: Germany | S17: Pipeline allowed | T17: P0 | U17: {=MIN(_xlfn._xlws.FILTER(J5:J98,(C5:C98="Germany")*(B5:B98="Pipeline Allowed")))} -> 38.376
B18: Pipeline Disallowed | C18: Germany | D18: Zementwerk Sehnde | E18: Rail | F18: Esbjerg | G18: =IF(OR(F18="Ruby",F18="Aalborg"),"Onshore","Offshore") -> Offshore | H18: North | I18: 109.86 | J18: =I18*$W$5 -> 112.6065 | K18: =IF(E18="Pipeline",15,17.5) -> 17.5 | L18: =IF(G18="Onshore",15,30) -> 30 | M18: =J18-SUM(K18:L18) -> 65.1065 | R18: Germany | S18: Pipeline disallowed | T18: P0 | U18: {=MIN(_xlfn._xlws.FILTER(J5:J98,(C5:C98="Germany")*(B5:B98="Pipeline Disallowed")))} -> 79.868
B19: Pipeline Disallowed | C19: Germany | D19: Zementwerk Hannover | E19: Rail | F19: Esbjerg | G19: =IF(OR(F19="Ruby",F19="Aalborg"),"Onshore","Offshore") -> Offshore | H19: North | I19: 109.4 | J19: =I19*$W$5 -> 112.135 | K19: =IF(E19="Pipeline",15,17.5) -> 17.5 | L19: =IF(G19="Onshore",15,30) -> 30 | M19: =J19-SUM(K19:L19) -> 64.635 | R19: Germany | S19: Pipeline allowed | T19: P100 | U19: {=MAX(_xlfn._xlws.FILTER(J5:J98,(C5:C98="Germany")*(B5:B98="Pipeline Allowed")))} -> 116.86025
B20: Pipeline Disallowed | C20: Germany | D20: Kalkwerke Blaustein | E20: Rail | F20: Ravenna | G20: =IF(OR(F20="Ruby",F20="Aalborg"),"Onshore","Offshore") -> Offshore | H20: South | I20: 108.8 | J20: =I20*$W$5 -> 111.52 | K20: =IF(E20="Pipeline",15,17.5) -> 17.5 | L20: =IF(G20="Onshore",15,30) -> 30 | M20: =J20-SUM(K20:L20) -> 64.02 | R20: Germany | S20: Pipeline disallowed | T20: P100 | U20: {=MAX(_xlfn._xlws.FILTER(J5:J98,(C5:C98="Germany")*(B5:B98="Pipeline Disallowed")))} -> 124.066
B21: Pipeline Disallowed | C21: Germany | D21: Kalkwerke Harburg | E21: Rail | F21: Ravenna | G21: =IF(OR(F21="Ruby",F21="Aalborg"),"Onshore","Offshore") -> Offshore | H21: South | I21: 108.77 | J21: =I21*$W$5 -> 111.48925 | K21: =IF(E21="Pipeline",15,17.5) -> 17.5 | L21: =IF(G21="Onshore",15,30) -> 30 | M21: =J21-SUM(K21:L21) -> 63.98925
B22: Pipeline Disallowed | C22: Germany | D22: Zementwerk Schelklingen | E22: Rail | F22: Ravenna | G22: =IF(OR(F22="Ruby",F22="Aalborg"),"Onshore","Offshore") -> Offshore | H22: South | I22: 108.48 | J22: =I22*$W$5 -> 111.192 | K22: =IF(E22="Pipeline",15,17.5) -> 17.5 | L22: =IF(G22="Onshore",15,30) -> 30 | M22: =J22-SUM(K22:L22) -> 63.692 | R22: Pipeline? | S22: Pipeline Allowed | U22: Pipeline? | V22: Pipeline Disallowed | X22: Country | Y22: Germany | AA22: Country | AB22: Germany
B23: Pipeline Disallowed | C23: Germany | D23: Zementwerk Allmendingen | E23: Rail | F23: Ravenna | G23: =IF(OR(F23="Ruby",F23="Aalborg"),"Onshore","Offshore") -> Offshore | H23: South | I23: 108.45 | J23: =I23*$W$5 -> 111.16125 | K23: =IF(E23="Pipeline",15,17.5) -> 17.5 | L23: =IF(G23="Onshore",15,30) -> 30 | M23: =J23-SUM(K23:L23) -> 63.66125 | R23: Country | S23: Germany | U23: Country | V23: Germany
B24: Pipeline Disallowed | C24: Germany | D24: Zementwerk Heidenheim an der Brenz | E24: Rail | F24: Ravenna | G24: =IF(OR(F24="Ruby",F24="Aalborg"),"Onshore","Offshore") -> Offshore | H24: South | I24: 108.44 | J24: =I24*$W$5 -> 111.151 | K24: =IF(E24="Pipeline",15,17.5) -> 17.5 | L24: =IF(G24="Onshore",15,30) -> 30 | M24: =J24-SUM(K24:L24) -> 63.651 | X24: Row Labels | Y24: Average of Transport Cost | AA24: Row Labels | AB24: Average of Cost per t/CO2 in 2025 | AC24: Average of Conditioning Cost | AD24: Average of Storage Cost | AE24: Average of Transport Cost
B25: Pipeline Disallowed | C25: Germany | D25: Zementwerk Harburg | E25: Rail | F25: Ravenna | G25: =IF(OR(F25="Ruby",F25="Aalborg"),"Onshore","Offshore") -> Offshore | H25: South | I25: 108.24 | J25: =I25*$W$5 -> 110.946 | K25: =IF(E25="Pipeline",15,17.5) -> 17.5 | L25: =IF(G25="Onshore",15,30) -> 30 | M25: =J25-SUM(K25:L25) -> 63.446 | R25: Row Labels | S25: Sum of Cost per t/CO2 in 2025 | U25: Row Labels | V25: Sum of Cost per t/CO2 in 2025 | X25: Barge | Y25: 38.865036 | AA25: Pipeline Allowed | AB25: 68.947293 | AC25: 15.054348 | AD25: 25.76087 | AE25: 28.132076
B26: Pipeline Disallowed | C26: Germany | D26: Zementwerk Walzbachtal | E26: Rail | F26: Rotterdam | G26: =IF(OR(F26="Ruby",F26="Aalborg"),"Onshore","Offshore") -> Offshore | H26: South | I26: 108.1 | J26: =I26*$W$5 -> 110.8025 | K26: =IF(E26="Pipeline",15,17.5) -> 17.5 | L26: =IF(G26="Onshore",15,30) -> 30 | M26: =J26-SUM(K26:L26) -> 63.3025 | R26: Zementwerk Dotternhausen | S26: 116.394 | U26: Kalkwerke Rüdersdorf | V26: 123.541 | X26: South | Y26: 38.865036 | AA26: North | AB26: 57.419163 | AC26: 15 | AD26: 22.173913 | AE26: 20.24525
B27: Pipeline Disallowed | C27: Germany | D27: Zementwerk Niederorschel | E27: Rail | F27: Rotterdam | G27: =IF(OR(F27="Ruby",F27="Aalborg"),"Onshore","Offshore") -> Offshore | H27: North | I27: 106.94 | J27: =I27*$W$5 -> 109.6135 | K27: =IF(E27="Pipeline",15,17.5) -> 17.5 | L27: =IF(G27="Onshore",15,30) -> 30 | M27: =J27-SUM(K27:L27) -> 62.1135 | R27: Lhoist Istein | S27: 87.2955 | U27: Zementwerk Karsdorf | V27: 123.1326 | X27: Pipeline | Y27: 27.215894 | AA27: Pipeline | AB27: 57.419163 | AC27: 15 | AD27: 22.173913 | AE27: 20.24525
B28: Pipeline Disallowed | C28: Germany | D28: Zementwerk Großenlüder | E28: Rail | F28: Rotterdam | G28: =IF(OR(F28="Ruby",F28="Aalborg"),"Onshore","Offshore") -> Offshore | H28: South | I28: 104.75 | J28: =I28*$W$5 -> 107.36875 | K28: =IF(E28="Pipeline",15,17.5) -> 17.5 | L28: =IF(G28="Onshore",15,30) -> 30 | M28: =J28-SUM(K28:L28) -> 59.86875 | R28: Kalkwerke Harburg | S28: 85.6619 | U28: Zementwerk Rüdersdorf | V28: 122.9284 | X28: North | Y28: 20.24525 | AA28: Rotterdam | AB28: 70.008432 | AC28: 15 | AD28: 30 | AE28: 25.008432
B29: Pipeline Disallowed | C29: Germany | D29: Zementwerk Göllheim | E29: Rail | F29: Rotterdam | G29: =IF(OR(F29="Ruby",F29="Aalborg"),"Onshore","Offshore") -> Offshore | H29: South | I29: 103.33 | J29: =I29*$W$5 -> 105.91325 | K29: =IF(E29="Pipeline",15,17.5) -> 17.5 | L29: =IF(G29="Onshore",15,30) -> 30 | M29: =J29-SUM(K29:L29) -> 58.41325 | R29: Zementwerk Harburg | S29: 85.6619 | U29: Zementwerk Bernburg | V29: 119.9675 | X29: South | Y29: 34.503386 | AA29: Ruby | AB29: 45.879 | AC29: 15 | AD29: 15 | AE29: 15.879
B30: Pipeline Disallowed | C30: Germany | D30: Zementwerk Rohrdorf | E30: Rail | F30: Ravenna | G30: =IF(OR(F30="Ruby",F30="Aalborg"),"Onshore","Offshore") -> Offshore | H30: South | I30: 102.67 | J30: =I30*$W$5 -> 105.23675 | K30: =IF(E30="Pipeline",15,17.5) -> 17.5 | L30: =IF(G30="Onshore",15,30) -> 30 | M30: =J30-SUM(K30:L30) -> 57.73675 | R30: Zementwerk Solnhofen | S30: 85.4577 | U30: Fels KH NSO 1-5 Oberharz am Brocken | V30: 117.64983 | X30: Rail | Y30: 61.005731 | AA30: South | AB30: 80.475424 | AC30: 15.108696 | AD30: 29.347826 | AE30: 36.018902
B31: Pipeline Disallowed | C31: Germany | D31: Brennanlage Runkel | E31: Rail | F31: Rotterdam | G31: =IF(OR(F31="Ruby",F31="Aalborg"),"Onshore","Offshore") -> Offshore | H31: South | I31: 99.67 | J31: =I31*$W$5 -> 102.16175 | K31: =IF(E31="Pipeline",15,17.5) -> 17.5 | L31: =IF(G31="Onshore",15,30) -> 30 | M31: =J31-SUM(K31:L31) -> 54.66175 | R31: Zementwerk Heidenheim an der Brenz | S31: 84.5388 | U31: Fels KR NSO 1-8 Oberharz am Brocken | V31: 117.37416 | X31: North | Y31: 60.2685 | AA31: Pipeline | AB31: 78.821568 | AC31: 15 | AD31: 29.318182 | AE31: 34.503386
B32: Pipeline Disallowed | C32: Germany | D32: Kalkwerk Hahnstätten | E32: Rail | F32: Rotterdam | G32: =IF(OR(F32="Ruby",F32="Aalborg"),"Onshore","Offshore") -> Offshore | H32: South | I32: 99.67 | J32: =I32*$W$5 -> 102.16175 | K32: =IF(E32="Pipeline",15,17.5) -> 17.5 | L32: =IF(G32="Onshore",15,30) -> 30 | M32: =J32-SUM(K32:L32) -> 54.66175 | R32: Kalkwerke Blaustein | S32: 84.4367 | U32: Fels KK GGR 6 Oberharz am Brocken | V32: 117.30269 | X32: South | Y32: 62.003162 | AA32: Ravenna | AB32: 76.068667 | AC32: 15 | AD32: 30 | AE32: 31.068667
B33: Pipeline Disallowed | C33: Germany | D33: Zementwerk Paderborn | E33: Rail | F33: Rotterdam | G33: =IF(OR(F33="Ruby",F33="Aalborg"),"Onshore","Offshore") -> Offshore | H33: North | I33: 99.57 | J33: =I33*$W$5 -> 102.05925 | K33: =IF(E33="Pipeline",15,17.5) -> 17.5 | L33: =IF(G33="Onshore",15,30) -> 30 | M33: =J33-SUM(K33:L33) -> 54.55925 | R33: Zementwerk Schelklingen | S33: 84.4367 | U33: Zementwerk Dotternhausen | V33: 116.394 | X33: Grand Total | Y33: 42.793476 | AA33: Rotterdam | AB33: 80.283125 | AC33: 15 | AD33: 30 | AE33: 35.283125
B34: Pipeline Disallowed | C34: Germany | D34: Drehofen 11 Lägerdorf | E34: Rail | F34: Esbjerg | G34: =IF(OR(F34="Ruby",F34="Aalborg"),"Onshore","Offshore") -> Offshore | H34: North | I34: 99.02 | J34: =I34*$W$5 -> 101.4955 | K34: =IF(E34="Pipeline",15,17.5) -> 17.5 | L34: =IF(G34="Onshore",15,30) -> 30 | M34: =J34-SUM(K34:L34) -> 53.9955 | R34: Zementwerk Allmendingen | S34: 84.4367 | U34: Kalkwerk Seesen | V34: 115.9856 | AA34: Ruby | AB34: 60.77225 | AC34: 15 | AD34: 15 | AE34: 30.77225
B35: Pipeline Disallowed | C35: Germany | D35: Zementwerk Geseke | E35: Rail | F35: Rotterdam | G35: =IF(OR(F35="Ruby",F35="Aalborg"),"Onshore","Offshore") -> Offshore | H35: North | I35: 98.56 | J35: =I35*$W$5 -> 101.024 | K35: =IF(E35="Pipeline",15,17.5) -> 17.5 | L35: =IF(G35="Onshore",15,30) -> 30 | M35: =J35-SUM(K35:L35) -> 53.524 | R35: Zementwerk Walzbachtal | S35: 80.0464 | U35: Zementwerk Burglengenfeld | V35: 114.6583 | AA35: Rail | AB35: 116.86025 | AC35: 17.5 | AD35: 30 | AE35: 69.36025
B36: Pipeline Disallowed | C36: Germany | D36: Kalkwerk Warstein | E36: Rail | F36: Rotterdam | G36: =IF(OR(F36="Ruby",F36="Aalborg"),"Onshore","Offshore") -> Offshore | H36: North | I36: 98.44 | J36: =I36*$W$5 -> 100.901 | K36: =IF(E36="Pipeline",15,17.5) -> 17.5 | L36: =IF(G36="Onshore",15,30) -> 30 | M36: =J36-SUM(K36:L36) -> 53.401 | R36: Zementwerk Karlstadt | S36: 79.0254 | U36: Zementwerk Sehnde | V36: 112.2079 | AA36: Rotterdam | AB36: 116.86025 | AC36: 17.5 | AD36: 30 | AE36: 69.36025
B37: Pipeline Disallowed | C37: Germany | D37: Zementwerk Erwitte | E37: Rail | F37: Rotterdam | G37: =IF(OR(F37="Ruby",F37="Aalborg"),"Onshore","Offshore") -> Offshore | H37: North | I37: 97.24 | J37: =I37*$W$5 -> 99.671 | K37: =IF(E37="Pipeline",15,17.5) -> 17.5 | L37: =IF(G37="Onshore",15,30) -> 30 | M37: =J37-SUM(K37:L37) -> 52.171 | R37: Zementwerk Triefenstein | S37: 78.8212 | U37: Zementwerk Solnhofen | V37: 112.2079 | AA37: Pipeline Disallowed | AB37: 104.95487 | AC37: 17.5 | AD37: 30 | AE37: 57.454875
B38: Pipeline Disallowed | C38: Germany | D38: Zementwerk Üxheim | E38: Rail | F38: Rotterdam | G38: =IF(OR(F38="Ruby",F38="Aalborg"),"Onshore","Offshore") -> Offshore | H38: South | I38: 96.54 | J38: =I38*$W$5 -> 98.9535 | K38: =IF(E38="Pipeline",15,17.5) -> 17.5 | L38: =IF(G38="Onshore",15,30) -> 30 | M38: =J38-SUM(K38:L38) -> 51.4535 | R38: Kalkwerke Regensburg | S38: 78.2086 | U38: Zementwerk Hannover | V38: 111.6974 | AA38: North | AB38: 107.7685 | AC38: 17.5 | AD38: 30 | AE38: 60.2685
B39: Pipeline Disallowed | C39: Germany | D39: Zementwerk Beckum | E39: Rail | F39: Rotterdam | G39: =IF(OR(F39="Ruby",F39="Aalborg"),"Onshore","Offshore") -> Offshore | H39: North | I39: 96.1 | J39: =I39*$W$5 -> 98.5025 | K39: =IF(E39="Pipeline",15,17.5) -> 17.5 | L39: =IF(G39="Onshore",15,30) -> 30 | M39: =J39-SUM(K39:L39) -> 51.0025 | R39: Zementwerk Leimen | S39: 78.1065 | U39: Kalkwerke Blaustein | V39: 111.0848 | AA39: Rail | AB39: 107.7685 | AC39: 17.5 | AD39: 30 | AE39: 60.2685
B40: Pipeline Disallowed | C40: Germany | D40: Zementwerk Enningerloh | E40: Rail | F40: Rotterdam | G40: =IF(OR(F40="Ruby",F40="Aalborg"),"Onshore","Offshore") -> Offshore | H40: North | I40: 95.22 | J40: =I40*$W$5 -> 97.6005 | K40: =IF(E40="Pipeline",15,17.5) -> 17.5 | L40: =IF(G40="Onshore",15,30) -> 30 | M40: =J40-SUM(K40:L40) -> 50.1005 | R40: Kalkwerke Saal a. d. Donau | S40: 77.4939 | U40: Kalkwerke Harburg | V40: 111.0848 | AA40: Esbjerg | AB40: 117.08668 | AC40: 17.5 | AD40: 30 | AE40: 69.586682
B41: Pipeline Disallowed | C41: Germany | D41: Kalkwerk Lienen | E41: Rail | F41: Rotterdam | G41: =IF(OR(F41="Ruby",F41="Aalborg"),"Onshore","Offshore") -> Offshore | H41: North | I41: 94.84 | J41: =I41*$W$5 -> 97.211 | K41: =IF(E41="Pipeline",15,17.5) -> 17.5 | L41: =IF(G41="Onshore",15,30) -> 30 | M41: =J41-SUM(K41:L41) -> 49.711 | R41: Zementwerk Großenlüder | S41: 77.0855 | U41: Zementwerk Schelklingen | V41: 110.7785 | AA41: Rotterdam | AB41: 99.226833 | AC41: 17.5 | AD41: 30 | AE41: 51.726833
B42: Pipeline Disallowed | C42: Germany | D42: Brennen von Kalkstein Menden | E42: Rail | F42: Rotterdam | G42: =IF(OR(F42="Ruby",F42="Aalborg"),"Onshore","Offshore") -> Offshore | H42: North | I42: 94.43 | J42: =I42*$W$5 -> 96.79075 | K42: =IF(E42="Pipeline",15,17.5) -> 17.5 | L42: =IF(G42="Onshore",15,30) -> 30 | M42: =J42-SUM(K42:L42) -> 49.29075 | R42: Zementwerk Göllheim | S42: 75.3498 | U42: Zementwerk Allmendingen | V42: 110.7785 | AA42: South | AB42: 102.14125 | AC42: 17.5 | AD42: 30 | AE42: 54.64125
B43: Pipeline Disallowed | C43: Germany | D43: Zementherstellung Lengerich | E43: Rail | F43: Rotterdam | G43: =IF(OR(F43="Ruby",F43="Aalborg"),"Onshore","Offshore") -> Offshore | H43: North | I43: 94.03 | J43: =I43*$W$5 -> 96.38075 | K43: =IF(E43="Pipeline",15,17.5) -> 17.5 | L43: =IF(G43="Onshore",15,30) -> 30 | M43: =J43-SUM(K43:L43) -> 48.88075 | R43: Zementwerk Wiesbaden | S43: 73.9204 | U43: Zementwerk Heidenheim an der Brenz | V43: 110.6764 | AA43: Barge | AB43: 86.365036 | AC43: 17.5 | AD43: 30 | AE43: 38.865036
B44: Pipeline Disallowed | C44: Germany | D44: Kalksteinbrennöfen Wuppertal | E44: Rail | F44: Rotterdam | G44: =IF(OR(F44="Ruby",F44="Aalborg"),"Onshore","Offshore") -> Offshore | H44: North | I44: 93.5 | J44: =I44*$W$5 -> 95.8375 | K44: =IF(E44="Pipeline",15,17.5) -> 17.5 | L44: =IF(G44="Onshore",15,30) -> 30 | M44: =J44-SUM(K44:L44) -> 48.3375 | R44: Zementwerk Paderborn | S44: 73.0015 | U44: Zementwerk Harburg | V44: 110.4722 | AA44: Rotterdam | AB44: 86.365036 | AC44: 17.5 | AD44: 30 | AE44: 38.865036
B45: Pipeline Disallowed | C45: Germany | D45: Kalkwerk Wülfrath | E45: Rail | F45: Rotterdam | G45: =IF(OR(F45="Ruby",F45="Aalborg"),"Onshore","Offshore") -> Offshore | H45: North | I45: 92.81 | J45: =I45*$W$5 -> 95.13025 | K45: =IF(E45="Pipeline",15,17.5) -> 17.5 | L45: =IF(G45="Onshore",15,30) -> 30 | M45: =J45-SUM(K45:L45) -> 47.63025 | R45: Kalkwerk Hahnstätten | S45: 72.7973 | U45: Zementwerk Walzbachtal | V45: 110.3701 | AA45: Rail | AB45: 109.04334 | AC45: 17.5 | AD45: 30 | AE45: 61.543344
... B48: Pipeline Disallowed | C48: Germany | D48: Lhoist Istein | E48: Barge | F48: Rotterdam | G48: =IF(OR(F48="Ruby",F48="Aalborg"),"Onshore","Offshore") -> Offshore | H48: South | I48: 87 | J48: =I48*$W$5 -> 89.175 | K48: =IF(E48="Pipeline",15,17.5) -> 17.5 | L48: =IF(G48="Onshore",15,30) -> 30 | M48: =J48-SUM(K48:L48) -> 41.675 | R48: Zementwerk Rohrdorf | S48: 71.6742 | U48: Zementwerk Göllheim | V48: 105.4693 | AA48: Grand Total | AB48: 86.951084 | AC48: 16.277174 | AD48: 27.880435 | AE48: 42.793476
B49: Pipeline Disallowed | C49: Germany | D49: Zementwerk Karlstadt | E49: Barge | F49: Rotterdam | G49: =IF(OR(F49="Ruby",F49="Aalborg"),"Onshore","Offshore") -> Offshore | H49: South | I49: 81.7 | J49: =I49*$W$5 -> 83.7425 | K49: =IF(E49="Pipeline",15,17.5) -> 17.5 | L49: =IF(G49="Onshore",15,30) -> 30 | M49: =J49-SUM(K49:L49) -> 36.2425 | R49: Kalkwerk Warstein | S49: 71.6742 | U49: Zementwerk Rohrdorf | V49: 104.8567
B50: Pipeline Disallowed | C50: Germany | D50: Zementwerk Triefenstein | E50: Barge | F50: Rotterdam | G50: =IF(OR(F50="Ruby",F50="Aalborg"),"Onshore","Offshore") -> Offshore | H50: South | I50: 81.11 | J50: =I50*$W$5 -> 83.13775 | K50: =IF(E50="Pipeline",15,17.5) -> 17.5 | L50: =IF(G50="Onshore",15,30) -> 30 | M50: =J50-SUM(K50:L50) -> 35.63775 | R50: Zementwerk Erwitte | S50: 71.2658 | U50: Kalkwerk Hahnstätten | V50: 101.7937
B51: Pipeline Disallowed | C51: Germany | D51: Zementwerk Leimen | E51: Barge | F51: Rotterdam | G51: =IF(OR(F51="Ruby",F51="Aalborg"),"Onshore","Offshore") -> Offshore | H51: South | I51: 80.53 | J51: =I51*$W$5 -> 82.54325 | K51: =IF(E51="Pipeline",15,17.5) -> 17.5 | L51: =IF(G51="Onshore",15,30) -> 30 | M51: =J51-SUM(K51:L51) -> 35.04325 | R51: Zementwerk Beckum | S51: 70.8574 | U51: Brennanlage Runkel | V51: 101.7937
B52: Pipeline Disallowed | C52: Germany | D52: Zementwerk Wiesbaden | E52: Barge | F52: Rotterdam | G52: =IF(OR(F52="Ruby",F52="Aalborg"),"Onshore","Offshore") -> Offshore | H52: South | I52: 77.92 | J52: =I52*$W$5 -> 79.868 | K52: =IF(E52="Pipeline",15,17.5) -> 17.5 | L52: =IF(G52="Onshore",15,30) -> 30 | M52: =J52-SUM(K52:L52) -> 32.368 | R52: Zementwerk Enningerloh | S52: 70.5511 | U52: Zementwerk Paderborn | V52: 101.6916
B53: Pipeline Allowed | C53: Germany | D53: Zementwerk Dotternhausen | E53: Rail | F53: Rotterdam | G53: =IF(OR(F53="Ruby",F53="Aalborg"),"Onshore","Offshore") -> Offshore | H53: South | I53: 114.01 | J53: =I53*$W$5 -> 116.86025 | K53: =IF(E53="Pipeline",15,17.5) -> 17.5 | L53: =IF(G53="Onshore",15,30) -> 30 | M53: =J53-SUM(K53:L53) -> 69.36025 | R53: Zementwerk Üxheim | S53: 69.8364 | U53: Drehofen 11 Lägerdorf | V53: 101.079
B54: Pipeline Allowed | C54: Germany | D54: Lhoist Istein | E54: Pipeline | F54: Rotterdam | G54: =IF(OR(F54="Ruby",F54="Aalborg"),"Onshore","Offshore") -> Offshore | H54: South | I54: 85.47 | J54: =I54*$W$5 -> 87.60675 | K54: =IF(E54="Pipeline",15,17.5) -> 15 | L54: =IF(G54="Onshore",15,30) -> 30 | M54: =J54-SUM(K54:L54) -> 42.60675 | R54: Brennen von Kalkstein Menden | S54: 69.6322 | U54: Zementwerk Geseke | V54: 100.6706
B55: Pipeline Allowed | C55: Germany | D55: Kalkwerke Harburg | E55: Pipeline | F55: Rotterdam | G55: =IF(OR(F55="Ruby",F55="Aalborg"),"Onshore","Offshore") -> Offshore | H55: South | I55: 83.9 | J55: =I55*$W$5 -> 85.9975 | K55: =IF(E55="Pipeline",15,17.5) -> 15 | L55: =IF(G55="Onshore",15,30) -> 30 | M55: =J55-SUM(K55:L55) -> 40.9975 | R55: Kalkwerk Lienen | S55: 69.5301 | U55: Kalkwerk Warstein | V55: 100.4664
B56: Pipeline Allowed | C56: Germany | D56: Zementwerk Harburg | E56: Pipeline | F56: Rotterdam | G56: =IF(OR(F56="Ruby",F56="Aalborg"),"Onshore","Offshore") -> Offshore | H56: South | I56: 83.9 | J56: =I56*$W$5 -> 85.9975 | K56: =IF(E56="Pipeline",15,17.5) -> 15 | L56: =IF(G56="Onshore",15,30) -> 30 | M56: =J56-SUM(K56:L56) -> 40.9975 | R56: Zementherstellung Lengerich | S56: 68.3049 | U56: Zementwerk Erwitte | V56: 99.2412
B57: Pipeline Allowed | C57: Germany | D57: Zementwerk Solnhofen | E57: Pipeline | F57: Rotterdam | G57: =IF(OR(F57="Ruby",F57="Aalborg"),"Onshore","Offshore") -> Offshore | H57: South | I57: 83.68 | J57: =I57*$W$5 -> 85.772 | K57: =IF(E57="Pipeline",15,17.5) -> 15 | L57: =IF(G57="Onshore",15,30) -> 30 | M57: =J57-SUM(K57:L57) -> 40.772 | R57: Kalksteinbrennöfen Wuppertal | S57: 67.4881 | U57: Zementwerk Üxheim | V57: 98.5265
B58: Pipeline Allowed | C58: Germany | D58: Zementwerk Heidenheim an der Brenz | E58: Pipeline | F58: Rotterdam | G58: =IF(OR(F58="Ruby",F58="Aalborg"),"Onshore","Offshore") -> Offshore | H58: South | I58: 82.78 | J58: =I58*$W$5 -> 84.8495 | K58: =IF(E58="Pipeline",15,17.5) -> 15 | L58: =IF(G58="Onshore",15,30) -> 30 | M58: =J58-SUM(K58:L58) -> 39.8495 | R58: Kalkwerk Wülfrath | S58: 63.1999 | U58: Zementwerk Beckum | V58: 98.1181
B59: Pipeline Allowed | C59: Germany | D59: Kalkwerke Blaustein | E59: Pipeline | F59: Rotterdam | G59: =IF(OR(F59="Ruby",F59="Aalborg"),"Onshore","Offshore") -> Offshore | H59: South | I59: 82.7 | J59: =I59*$W$5 -> 84.7675 | K59: =IF(E59="Pipeline",15,17.5) -> 15 | L59: =IF(G59="Onshore",15,30) -> 30 | M59: =J59-SUM(K59:L59) -> 39.7675 | R59: Zementwerk Burglengenfeld | S59: 60.5453 | U59: Zementwerk Enningerloh | V59: 97.1992
B60: Pipeline Allowed | C60: Germany | D60: Zementwerk Schelklingen | E60: Pipeline | F60: Rotterdam | G60: =IF(OR(F60="Ruby",F60="Aalborg"),"Onshore","Offshore") -> Offshore | H60: South | I60: 82.7 | J60: =I60*$W$5 -> 84.7675 | K60: =IF(E60="Pipeline",15,17.5) -> 15 | L60: =IF(G60="Onshore",15,30) -> 30 | M60: =J60-SUM(K60:L60) -> 39.7675 | R60: Zementwerk Karsdorf | S60: 49.9269 | U60: Kalkwerk Lienen | V60: 96.7908
... B72: Pipeline Allowed | C72: Germany | D72: Kalkwerk Hahnstätten | E72: Pipeline | F72: Rotterdam | G72: =IF(OR(F72="Ruby",F72="Aalborg"),"Onshore","Offshore") -> Offshore | H72: South | I72: 71.28 | J72: =I72*$W$5 -> 73.062 | K72: =IF(E72="Pipeline",15,17.5) -> 15 | L72: =IF(G72="Onshore",15,30) -> 30 | M72: =J72-SUM(K72:L72) -> 28.062 | R72: Grand Total | S72: 3159.1782 | U72: Grand Total | V72: 4808.8896
B73: Pipeline Allowed | C73: Germany | D73: Brennanlage Runkel | E73: Pipeline | F73: Rotterdam | G73: =IF(OR(F73="Ruby",F73="Aalborg"),"Onshore","Offshore") -> Offshore | H73: South | I73: 71.1 | J73: =I73*$W$5 -> 72.8775 | K73: =IF(E73="Pipeline",15,17.5) -> 15 | L73: =IF(G73="Onshore",15,30) -> 30 | M73: =J73-SUM(K73:L73) -> 27.8775
B74: Pipeline Allowed | C74: Germany | D74: Zementwerk Rohrdorf | E74: Pipeline | F74: Ravenna | G74: =IF(OR(F74="Ruby",F74="Aalborg"),"Onshore","Offshore") -> Offshore | H74: South | I74: 70.17 | J74: =I74*$W$5 -> 71.92425 | K74: =IF(E74="Pipeline",15,17.5) -> 15 | L74: =IF(G74="Onshore",15,30) -> 30 | M74: =J74-SUM(K74:L74) -> 26.92425
B75: Pipeline Allowed | C75: Germany | D75: Zementwerk Geseke | E75: Pipeline | F75: Rotterdam | G75: =IF(OR(F75="Ruby",F75="Aalborg"),"Onshore","Offshore") -> Offshore | H75: North | I75: 70.25 | J75: =I75*$W$5 -> 72.00625 | K75: =IF(E75="Pipeline",15,17.5) -> 15 | L75: =IF(G75="Onshore",15,30) -> 30 | M75: =J75-SUM(K75:L75) -> 27.00625
B76: Pipeline Allowed | C76: Germany | D76: Kalkwerk Warstein | E76: Pipeline | F76: Rotterdam | G76: =IF(OR(F76="Ruby",F76="Aalborg"),"Onshore","Offshore") -> Offshore | H76: North | I76: 70.2 | J76: =I76*$W$5 -> 71.955 | K76: =IF(E76="Pipeline",15,17.5) -> 15 | L76: =IF(G76="Onshore",15,30) -> 30 | M76: =J76-SUM(K76:L76) -> 26.955
B77: Pipeline Allowed | C77: Germany | D77: Zementwerk Erwitte | E77: Pipeline | F77: Rotterdam | G77: =IF(OR(F77="Ruby",F77="Aalborg"),"Onshore","Offshore") -> Offshore | H77: North | I77: 69.75 | J77: =I77*$W$5 -> 71.49375 | K77: =IF(E77="Pipeline",15,17.5) -> 15 | L77: =IF(G77="Onshore",15,30) -> 30 | M77: =J77-SUM(K77:L77) -> 26.49375
B78: Pipeline Allowed | C78: Germany | D78: Zementwerk Beckum | E78: Pipeline | F78: Rotterdam | G78: =IF(OR(F78="Ruby",F78="Aalborg"),"Onshore","Offshore") -> Offshore | H78: North | I78: 69.35 | J78: =I78*$W$5 -> 71.08375 | K78: =IF(E78="Pipeline",15,17.5) -> 15 | L78: =IF(G78="Onshore",15,30) -> 30 | M78: =J78-SUM(K78:L78) -> 26.08375
B79: Pipeline Allowed | C79: Germany | D79: Zementwerk Enningerloh | E79: Pipeline | F79: Rotterdam | G79: =IF(OR(F79="Ruby",F79="Aalborg"),"Onshore","Offshore") -> Offshore | H79: North | I79: 69.08 | J79: =I79*$W$5 -> 70.807 | K79: =IF(E79="Pipeline",15,17.5) -> 15 | L79: =IF(G79="Onshore",15,30) -> 30 | M79: =J79-SUM(K79:L79) -> 25.807
B80: Pipeline Allowed | C80: Germany | D80: Zementwerk Üxheim | E80: Pipeline | F80: Rotterdam | G80: =IF(OR(F80="Ruby",F80="Aalborg"),"Onshore","Offshore") -> Offshore | H80: South | I80: 68.37 | J80: =I80*$W$5 -> 70.07925 | K80: =IF(E80="Pipeline",15,17.5) -> 15 | L80: =IF(G80="Onshore",15,30) -> 30 | M80: =J80-SUM(K80:L80) -> 25.07925
B81: Pipeline Allowed | C81: Germany | D81: Brennen von Kalkstein Menden | E81: Pipeline | F81: Rotterdam | G81: =IF(OR(F81="Ruby",F81="Aalborg"),"Onshore","Offshore") -> Offshore | H81: North | I81: 68.19 | J81: =I81*$W$5 -> 69.89475 | K81: =IF(E81="Pipeline",15,17.5) -> 15 | L81: =IF(G81="Onshore",15,30) -> 30 | M81: =J81-SUM(K81:L81) -> 24.89475
B82: Pipeline Allowed | C82: Germany | D82: Kalkwerk Lienen | E82: Pipeline | F82: Rotterdam | G82: =IF(OR(F82="Ruby",F82="Aalborg"),"Onshore","Offshore") -> Offshore | H82: North | I82: 68.05 | J82: =I82*$W$5 -> 69.75125 | K82: =IF(E82="Pipeline",15,17.5) -> 15 | L82: =IF(G82="Onshore",15,30) -> 30 | M82: =J82-SUM(K82:L82) -> 24.75125
B83: Pipeline Allowed | C83: Germany | D83: Zementherstellung Lengerich | E83: Pipeline | F83: Rotterdam | G83: =IF(OR(F83="Ruby",F83="Aalborg"),"Onshore","Offshore") -> Offshore | H83: North | I83: 66.89 | J83: =I83*$W$5 -> 68.56225 | K83: =IF(E83="Pipeline",15,17.5) -> 15 | L83: =IF(G83="Onshore",15,30) -> 30 | M83: =J83-SUM(K83:L83) -> 23.56225
B84: Pipeline Allowed | C84: Germany | D84: Kalksteinbrennöfen Wuppertal | E84: Pipeline | F84: Rotterdam | G84: =IF(OR(F84="Ruby",F84="Aalborg"),"Onshore","Offshore") -> Offshore | H84: North | I84: 66.13 | J84: =I84*$W$5 -> 67.78325 | K84: =IF(E84="Pipeline",15,17.5) -> 15 | L84: =IF(G84="Onshore",15,30) -> 30 | M84: =J84-SUM(K84:L84) -> 22.78325
... B98: Pipeline Allowed | C98: Germany | D98: Drehofen 11 Lägerdorf | E98: Pipeline | F98: Ruby | G98: =IF(OR(F98="Ruby",F98="Aalborg"),"Onshore","Offshore") -> Onshore | H98: North | I98: 37.44 | J98: =I98*$W$5 -> 38.376 | K98: =IF(E98="Pipeline",15,17.5) -> 15 | L98: =IF(G98="Onshore",15,30) -> 15 | M98: =J98-SUM(K98:L98) -> 8.376

Sheet Capture Model
B3: Capture Performance
B4: Parameter | C4: Unit | D4: Value | E4: Source
B5: Capture Rate | C5: % | D5: 0.9 | E5: CEMCAP, Davila-Gallego
B6: CO2 captured | C6: tCO2 | D6: =D5*'Input Parameters'!D10 -> 738284.3 | E6: Calculated
B7: Specific Capture Performance | C7: tCO2/h | D7: =D6/(8760*'Input Parameters'!D6) -> 92.31 | E7: Calculated
B9: Capture Technology Energy Demand
B10: Parameter | C10: Unit | D10: Value | E10: Source
B11: Reboiler duty | C11: MWh/tCO2 | D11: 0.833 | E11: DEA
B12: Boiler efficiency | C12: % | D12: 0.9 | E12: CEMCAP
B13: Power demand MEA | C13: MWh/tCO2 | D13: 0.025 | E13: DEA
B14: Amine Make-up | C14: kg/tCO2 | D14: 0.3 | E14: DEA
B16: Steam Demand
B17: Parameter | C17: Unit | D17: Value | E17: Source
B18: Steam Generation from Waste heat | C18: % | D18: 0.04 | E18: CEMCAP, 4.6
B19: Steam Generation from Natural Gas boiler | C19: % | D19: 0.96 | E19: CEMCAP, 4.6
B20: Total Steam from Waste Heat | C20: MWh | D20: =D11*D6*D18 -> 24599.633 | E20: Calculated
B21: Total Steam from Natural Gas | C21: MWh | D21: =D11*D6*D19 -> 590391.19 | E21: Calculated
B22: Natural Gas Fuel Energy | C22: MWh | D22: =D21/D12 -> 655990.21 | E22: Calculated
B24: Extra Electricity
B25: Parameter | C25: Unit | D25: Value | E25: Source
B26: Extra Electricity Demand | C26: MWh/year | D26: =D13*D6 -> 18457.108 | E26: Calculated
B29: Additional Emissions
B30: Parameter | C30: Unit | D30: Value | E30: Source
B31: Additional Emissions Steam | C31: tCO2 | D31: =D22*'Input Parameters'!D20 -> 131198.04 | E31: Calculated
B32: Additional Emissions Electricity | C32: tCO2 | D32: =IF('Cost of CO2 Avoided'!C37="Germany",D26*'Input Parameters'!D19,D26*'Input Parameters'!D18) -> 5500.2181 | E32: Calculated
B33: Additional Emissons Transport and Storage | C33: tCO2 | D33: =D6*'Input Parameters'!D31 -> 19195.392 | E33: Calculated

Sheet ETS
B2: ETS Overview
D3: Source
B4: EU ETS 2025 low | C4: =MIN(G14:G226) -> 59.76
B5: EU ETS 2025 | C5: =MEDIAN(G14:G226) -> 72.16 | D5: Emission Spot Primary Market Auction Report 2025, Median
B6: EU ETS 2025 high | C6: =MAX(G14:G226) -> 84.6
B7: EU ETS 2030 projection | C7: 124 | D7: IEA World Energy Outlook
B10: More information | D10: =HYPERLINK("https://www.eex.com/en/markets/environmental-markets/emissions-auctions","https://www.eex.com/en/markets/environmental-markets/emissions-auctions") -> https://www.eex.com/en/markets/environmental-markets/emissions-auctions
L11: EEX Emissions market / Primary Market Auction
B12: References | G12: Prices | L12: Volumes | W12: Participants | Y12: Revenue | AA12: Revenue
B13: Date | C13: Time | D13: Auction Name | E13: Contract | F13: Status | G13: Auction Price €/tCO2 | H13: Minimum Bid €/tCO2 | I13: Maximum Bid €/tCO2 | J13: Mean €/tCO2 | K13: Median €/tCO2 | L13: Auction Volume tCO2 | M13: Total Amount of Bids | N13: Number of bids submitted | O13: Number of successful bids | P13: Average number of bids per bidder | Q13: Average bid size | R13: Average volume bid per bidder | S13: Standard deviation of bid volume per bidder | T13: Average volume won per bidder | U13: Standard deviation of volume won per bidder | V13: Cover Ratio | W13: Total Number of Bidders | X13: Number of Successful Bidders | Y13: Total Revenue € | Z13: Country | AA13: Austria (AT) | AB13: Belgium (BE) | AC13: Bulgaria (BG) | AD13: Cyprus (CY) | AE13: Czech Republic (CZ) | AF13: Germany (DE) | AG13: Denmark (DK) | AH13: Estonia (EE) | AI13: Greece (EL) | AJ13: Spain (ES) | AK13: Finland (FI) | AL13: France (FR) | AM13: Croatia (HR) | AN13: Hungary (HU) | AO13: Ireland (IE) | AP13: Innovation Fund (IF) | AQ13: Iceland (IS) | AR13: Italy (IT) | AS13: InnoFund RRF (IX) | AT13: Liechtenstein (LI) | AU13: Lithuania (LT) | AV13: Luxembourg (LU) | AW13: Latvia (LV) | AX13: Modernisation Fund (MF) | AY13: Malta (MT) | AZ13: MS RRF (MX) | BA13: Netherlands (NL) | BB13: Norway (NO) | BC13: Poland (PL) | BD13: Portugal (PT) | BE13: Romania (RO) | BF13: Sweden (SE) | BG13: Social Climate Fund (SF) | BH13: Slovenia (SI) | BI13: Slovakia (SK) | BJ13: Northern Ireland (XI)
B14: 46006 | C14: 46006.459 | D14: Auction 4. Period CAP3 EU | E14: T3PA | F14: successful | G14: 84.6 | H14: 64 | I14: 90 | J14: 84.04 | K14: 84.32 | L14: 3273000 | M14: 5084000 | N14: 100 | O14: 31 | P14: 4 | Q14: 50840 | R14: 203360 | S14: 310008 | T14: 181833 | U14: 309586 | V14: 1.55 | W14: 25 | X14: 18 | Y14: 276895800 | Z14: EU | AA14: 3045600 | AB14: 3722400 | AC14: 5795100 | AD14: 1776600 | AE14: 2157300 | AG14: 1988100 | AH14: 2241900 | AI14: 9855900 | AJ14: 21742200 | AK14: 1903500 | AL14: 11294100 | AM14: 253800 | AN14: 2538000 | AO14: 84600 | AP14: 20134800 | AQ14: 1480500 | AR14: 20177100 | AS14: 34263000 | AT14: 42300 | AU14: 1015200 | AV14: 0 | AW14: 846000 | AX14: 53171100 | AY14: 1099800 | AZ14: 22842000 | BA14: 7191000 | BB14: 676800 | BD14: 4949100 | BE14: 4018500 | BF14: 2072700 | BG14: 31132800 | BH14: 761400 | BI14: 2622600
B15: 46003 | C15: 46003.459 | D15: Auction 4. Period DE | E15: T3PA | F15: successful | G15: 83.65 | H15: 64 | I15: 150 | J15: 84.73 | K15: 83.45 | L15: 1696000 | M15: 3492000 | N15: 75 | O15: 23 | P15: 3 | Q15: 46560 | R15: 139680 | S15: 156013 | T15: 113067 | U15: 140961 | V15: 2.06 | W15: 25 | X15: 15 | Y15: 141870400 | Z15: DE | AF15: 141870400
B16: 46002 | C16: 46002.459 | D16: Auction 4. Period CAP3 EU | E16: T3PA | F16: successful | G16: 83.77 | H16: 64 | I16: 150 | J16: 84.51 | K16: 83.48 | L16: 3268000 | M16: 5580000 | N16: 97 | O16: 23 | P16: 3.73 | Q16: 57526 | R16: 214615 | S16: 295689 | T16: 217867 | U16: 322382 | V16: 1.71 | W16: 26 | X16: 15 | Y16: 273760360 | Z16: EU | AA16: 2429330 | AB16: 4230385 | AC16: 6869140 | AD16: 879585 | AE16: 4523580 | AG16: 2387445 | AH16: 2094250 | AI16: 9298470 | AJ16: 21193810 | AK16: 3350800 | AL16: 12565500 | AM16: 963355 | AN16: 3602110 | AO16: 1005240 | AP16: 20900615 | AQ16: 41885 | AR16: 21110040 | AS16: 30659820 | AT16: 0 | AU16: 670160 | AV16: 0 | AW16: 544505 | AX16: 52104940 | AY16: 418850 | AZ16: 20439880 | BA16: 7497415 | BB16: 1633515 | BD16: 4439810 | BE16: 3685880 | BF16: 1465975 | BG16: 29487040 | BH16: 1089010 | BI16: 2178020
B17: 46001 | C17: 46001.459 | D17: Auction 4. Period CAP3 PL | E17: T3PA | F17: successful | G17: 82.18 | H17: 64 | I17: 85 | J17: 81.8 | K17: 82.12 | L17: 2166000 | M17: 3405500 | N17: 84 | O17: 37 | P17: 3.65 | Q17: 40542 | R17: 148065 | S17: 175481 | T17: 103143 | U17: 145787 | V17: 1.57 | W17: 23 | X17: 21 | Y17: 178001880 | Z17: PL | BC17: 178001880
B18: 46000 | C18: 46000.459 | D18: Auction 4. Period CAP3 EU | E18: T3PA | F18: successful | G18: 82.22 | H18: 0.01 | I18: 150 | J18: 81.41 | K18: 82 | L18: 3268000 | M18: 5374500 | N18: 91 | O18: 21 | P18: 3.5 | Q18: 59060 | R18: 206712 | S18: 249747 | T18: 192235 | U18: 234054 | V18: 1.64 | W18: 26 | X18: 17 | Y18: 268694960 | Z18: EU | AA18: 2384380 | AB18: 4152110 | AC18: 6742040 | AD18: 863310 | AE18: 4439880 | AG18: 2343270 | AH18: 2055500 | AI18: 9126420 | AJ18: 20801660 | AK18: 3288800 | AL18: 12333000 | AM18: 945530 | AN18: 3535460 | AO18: 986640 | AP18: 20513890 | AQ18: 41110 | AR18: 20719440 | AS18: 30092520 | AT18: 0 | AU18: 657760 | AV18: 0 | AW18: 534430 | AX18: 51140840 | AY18: 411100 | AZ18: 20061680 | BA18: 7358690 | BB18: 1603290 | BD18: 4357660 | BE18: 3617680 | BF18: 1438850 | BG18: 28941440 | BH18: 1068860 | BI18: 2137720
B19: 45999 | C19: 45999.459 | D19: Auction 4. Period CAP3 EU | E19: T3PA | F19: successful | G19: 82.17 | H19: 64 | I19: 150 | J19: 83.85 | K19: 81.84 | L19: 3268000 | M19: 5324000 | N19: 86 | O19: 17 | P19: 3.91 | Q19: 61907 | R19: 242000 | S19: 344482 | T19: 326800 | U19: 410689 | V19: 1.63 | W19: 22 | X19: 10 | Y19: 268531560 | Z19: EU | AA19: 2382930 | AB19: 4149585 | AC19: 6737940 | AD19: 862785 | AE19: 4437180 | AG19: 2341845 | AH19: 2054250 | AI19: 9120870 | AJ19: 20789010 | AK19: 3286800 | AL19: 12325500 | AM19: 944955 | AN19: 3533310 | AO19: 986040 | AP19: 20501415 | AQ19: 41085 | AR19: 20706840 | AS19: 30074220 | AT19: 0 | AU19: 657360 | AV19: 0 | AW19: 534105 | AX19: 51109740 | AY19: 410850 | AZ19: 20049480 | BA19: 7354215 | BB19: 1602315 | BD19: 4355010 | BE19: 3615480 | BF19: 1437975 | BG19: 28923840 | BH19: 1068210 | BI19: 2136420
B20: 45996 | C20: 45996.459 | D20: Auction 4. Period DE | E20: T3PA | F20: successful | G20: 82.25 | H20: 64 | I20: 85 | J20: 81.39 | K20: 81.87 | L20: 1691000 | M20: 3494500 | N20: 80 | O20: 11 | P20: 3.33 | Q20: 43681 | R20: 145604 | S20: 191690 | T20: 169100 | U20: 218515 | V20: 2.07 | W20: 24 | X20: 10 | Y20: 139084750 | Z20: DE | AF20: 139084750
B21: 45995 | C21: 45995.459 | D21: Auction 4. Period CAP3 EU | E21: T3PA | F21: successful | G21: 81.39 | H21: 64 | I21: 120 | J21: 81.39 | K21: 81.2 | L21: 3268000 | M21: 5274500 | N21: 97 | O21: 27 | P21: 3.46 | Q21: 54376 | R21: 188375 | S21: 261535 | T21: 163400 | U21: 240275 | V21: 1.61 | W21: 28 | X21: 20 | Y21: 265982520 | Z21: EU | AA21: 2360310 | AB21: 4110195 | AC21: 6673980 | AD21: 854595 | AE21: 4395060 | AG21: 2319615 | AH21: 2034750 | AI21: 9034290 | AJ21: 20591670 | AK21: 3255600 | AL21: 12208500 | AM21: 935985 | AN21: 3499770 | AO21: 976680 | AP21: 20306805 | AQ21: 40695 | AR21: 20510280 | AS21: 29788740 | AT21: 0 | AU21: 651120 | AV21: 0 | AW21: 529035 | AX21: 50624580 | AY21: 406950 | AZ21: 19859160 | BA21: 7284405 | BB21: 1587105 | BD21: 4313670 | BE21: 3581160 | BF21: 1424325 | BG21: 28649280 | BH21: 1058070 | BI21: 2116140
B22: 45993 | C22: 45993.459 | D22: Auction 4. Period CAP3 EU | E22: T3PA | F22: successful | G22: 82.19 | H22: 64 | I22: 150 | J22: 83.33 | K22: 82.04 | L22: 3268000 | M22: 4548000 | N22: 91 | O22: 32 | P22: 3.96 | Q22: 49978 | R22: 197739 | S22: 270181 | T22: 181556 | U22: 272442 | V22: 1.39 | W22: 23 | X22: 18 | Y22: 268596920 | Z22: EU | AA22: 2383510 | AB22: 4150595 | AC22: 6739580 | AD22: 862995 | AE22: 4438260 | AG22: 2342415 | AH22: 2054750 | AI22: 9123090 | AJ22: 20794070 | AK22: 3287600 | AL22: 12328500 | AM22: 945185 | AN22: 3534170 | AO22: 986280 | AP22: 20506405 | AQ22: 41095 | AR22: 20711880 | AS22: 30081540 | AT22: 0 | AU22: 657520 | AV22: 0 | AW22: 534235 | AX22: 51122180 | AY22: 410950 | AZ22: 20054360 | BA22: 7356005 | BB22: 1602705 | BD22: 4356070 | BE22: 3616360 | BF22: 1438325 | BG22: 28930880 | BH22: 1068470 | BI22: 2136940
B23: 45992 | C23: 45992.459 | D23: Auction 4. Period CAP3 EU | E23: T3PA | F23: successful | G23: 83.01 | H23: 80 | I23: 150 | J23: 83.74 | K23: 82.97 | L23: 3268000 | M23: 4606000 | N23: 88 | O23: 37 | P23: 4 | Q23: 52341 | R23: 209364 | S23: 292814 | T23: 181556 | U23: 276565 | V23: 1.41 | W23: 22 | X23: 18 | Y23: 271276680 | Z23: EU | AA23: 2407290 | AB23: 4192005 | AC23: 6806820 | AD23: 871605 | AE23: 4482540 | AG23: 2365785 | AH23: 2075250 | AI23: 9214110 | AJ23: 21001530 | AK23: 3320400 | AL23: 12451500 | AM23: 954615 | AN23: 3569430 | AO23: 996120 | AP23: 20710995 | AQ23: 41505 | AR23: 20918520 | AS23: 30381660 | AT23: 0 | AU23: 664080 | AV23: 0 | AW23: 539565 | AX23: 51632220 | AY23: 415050 | AZ23: 20254440 | BA23: 7429395 | BB23: 1618695 | BD23: 4399530 | BE23: 3652440 | BF23: 1452675 | BG23: 29219520 | BH23: 1079130 | BI23: 2158260
B24: 45989 | C24: 45989.459 | D24: Auction 4. Period DE | E24: T3PA | F24: successful | G24: 82.6 | H24: 64 | I24: 85 | J24: 81.92 | K24: 82.32 | L24: 1691000 | M24: 3176500 | N24: 82 | O24: 18 | P24: 3.57 | Q24: 38738 | R24: 138109 | S24: 205238 | T24: 112733 | U24: 212229 | V24: 1.88 | W24: 23 | X24: 15 | Y24: 139676600 | Z24: DE | AF24: 139676600
B25: 45988 | C25: 45988.459 | D25: Auction 4. Period CAP3 EU | E25: T3PA | F25: successful | G25: 81.07 | H25: 64 | I25: 120 | J25: 81.62 | K25: 80.81 | L25: 3268000 | M25: 5308500 | N25: 105 | O25: 28 | P25: 4.2 | Q25: 50557 | R25: 212340 | S25: 247083 | T25: 192235 | U25: 224885 | V25: 1.62 | W25: 25 | X25: 17 | Y25: 264936760 | Z25: EU | AA25: 2351030 | AB25: 4094035 | AC25: 6647740 | AD25: 851235 | AE25: 4377780 | AG25: 2310495 | AH25: 2026750 | AI25: 8998770 | AJ25: 20510710 | AK25: 3242800 | AL25: 12160500 | AM25: 932305 | AN25: 3486010 | AO25: 972840 | AP25: 20226965 | AQ25: 40535 | AR25: 20429640 | AS25: 29671620 | AT25: 0 | AU25: 648560 | AV25: 0 | AW25: 526955 | AX25: 50425540 | AY25: 405350 | AZ25: 19781080 | BA25: 7255765 | BB25: 1580865 | BD25: 4296710 | BE25: 3567080 | BF25: 1418725 | BG25: 28536640 | BH25: 1053910 | BI25: 2107820
B26: 45987 | C26: 45987.459 | D26: Auction 4. Period CAP3 PL | E26: T3PA | F26: successful | G26: 81.51 | H26: 64 | I26: 150 | J26: 83.3 | K26: 81.46 | L26: 2162500 | M26: 3608500 | N26: 97 | O26: 40 | P26: 3.73 | Q26: 37201 | R26: 138788 | S26: 184516 | T26: 94022 | U26: 166352 | V26: 1.67 | W26: 26 | X26: 23 | Y26: 176265375 | Z26: PL | BC26: 176265375
B27: 45986 | C27: 45986.459 | D27: Auction 4. Period CAP3 EU | E27: T3PA | F27: successful | G27: 81.19 | H27: 64 | I27: 150 | J27: 81.86 | K27: 80.99 | L27: 3268000 | M27: 4897000 | N27: 95 | O27: 29 | P27: 3.96 | Q27: 51547 | R27: 204042 | S27: 245490 | T27: 192235 | U27: 246799 | V27: 1.5 | W27: 24 | X27: 17 | Y27: 265328920 | Z27: EU | AA27: 2354510 | AB27: 4100095 | AC27: 6657580 | AD27: 852495 | AE27: 4384260 | AG27: 2313915 | AH27: 2029750 | AI27: 9012090 | AJ27: 20541070 | AK27: 3247600 | AL27: 12178500 | AM27: 933685 | AN27: 3491170 | AO27: 974280 | AP27: 20256905 | AQ27: 40595 | AR27: 20459880 | AS27: 29715540 | AT27: 0 | AU27: 649520 | AV27: 0 | AW27: 527735 | AX27: 50500180 | AY27: 405950 | AZ27: 19810360 | BA27: 7266505 | BB27: 1583205 | BD27: 4303070 | BE27: 3572360 | BF27: 1420825 | BG27: 28578880 | BH27: 1055470 | BI27: 2110940
B28: 45985 | C28: 45985.459 | D28: Auction 4. Period CAP3 EU | E28: T3PA | F28: successful | G28: 80 | H28: 64 | I28: 150 | J28: 80.87 | K28: 79.72 | L28: 3268000 | M28: 4831000 | N28: 86 | O28: 21 | P28: 4.3 | Q28: 56174 | R28: 241550 | S28: 303027 | T28: 297091 | U28: 303202 | V28: 1.48 | W28: 20 | X28: 11 | Y28: 261440000 | Z28: EU | AA28: 2320000 | AB28: 4040000 | AC28: 6560000 | AD28: 840000 | AE28: 4320000 | AG28: 2280000 | AH28: 2000000 | AI28: 8880000 | AJ28: 20240000 | AK28: 3200000 | AL28: 12000000 | AM28: 920000 | AN28: 3440000 | AO28: 960000 | AP28: 19960000 | AQ28: 40000 | AR28: 20160000 | AS28: 29280000 | AT28: 0 | AU28: 640000 | AV28: 0 | AW28: 520000 | AX28: 49760000 | AY28: 400000 | AZ28: 19520000 | BA28: 7160000 | BB28: 1560000 | BD28: 4240000 | BE28: 3520000 | BF28: 1400000 | BG28: 28160000 | BH28: 1040000 | BI28: 2080000
B29: 45982 | C29: 45982.459 | D29: Auction 4. Period DE | E29: T3PA | F29: successful | G29: 80.47 | H29: 64 | I29: 85 | J29: 80.24 | K29: 80.26 | L29: 1691000 | M29: 3215500 | N29: 85 | O29: 23 | P29: 3.7 | Q29: 37829 | R29: 139804 | S29: 231743 | T29: 130077 | U29: 263141 | V29: 1.9 | W29: 23 | X29: 13 | Y29: 136074770 | Z29: DE | AF29: 136074770
B30: 45981 | C30: 45981.459 | D30: Auction 4. Period CAP3 EU | E30: T3PA | F30: successful | G30: 81.16 | H30: 64 | I30: 93 | J30: 80.78 | K30: 80.77 | L30: 3268000 | M30: 5488000 | N30: 114 | O30: 24 | P30: 4.22 | Q30: 48140 | R30: 203259 | S30: 279429 | T30: 192235 | U30: 249320 | V30: 1.68 | W30: 27 | X30: 17 | Y30: 265230880 | Z30: EU | AA30: 2353640 | AB30: 4098580 | AC30: 6655120 | AD30: 852180 | AE30: 4382640 | AG30: 2313060 | AH30: 2029000 | AI30: 9008760 | AJ30: 20533480 | AK30: 3246400 | AL30: 12174000 | AM30: 933340 | AN30: 3489880 | AO30: 973920 | AP30: 20249420 | AQ30: 40580 | AR30: 20452320 | AS30: 29704560 | AT30: 0 | AU30: 649280 | AV30: 0 | AW30: 527540 | AX30: 50481520 | AY30: 405800 | AZ30: 19803040 | BA30: 7263820 | BB30: 1582620 | BD30: 4301480 | BE30: 3571040 | BF30: 1420300 | BG30: 28568320 | BH30: 1055080 | BI30: 2110160
B31: 45979 | C31: 45979.459 | D31: Auction 4. Period CAP3 EU | E31: T3PA | F31: successful | G31: 80.41 | H31: 64 | I31: 83 | J31: 80.03 | K31: 80.16 | L31: 3268000 | M31: 5781000 | N31: 114 | O31: 26 | P31: 4.07 | Q31: 50711 | R31: 206464 | S31: 307796 | T31: 192235 | U31: 326450 | V31: 1.77 | W31: 28 | X31: 17 | Y31: 262779880 | Z31: EU | AA31: 2331890 | AB31: 4060705 | AC31: 6593620 | AD31: 844305 | AE31: 4342140 | AG31: 2291685 | AH31: 2010250 | AI31: 8925510 | AJ31: 20343730 | AK31: 3216400 | AL31: 12061500 | AM31: 924715 | AN31: 3457630 | AO31: 964920 | AP31: 20062295 | AQ31: 40205 | AR31: 20263320 | AS31: 29430060 | AT31: 0 | AU31: 643280 | AV31: 0 | AW31: 522665 | AX31: 50015020 | AY31: 402050 | AZ31: 19620040 | BA31: 7196695 | BB31: 1567995 | BD31: 4261730 | BE31: 3538040 | BF31: 1407175 | BG31: 28304320 | BH31: 1045330 | BI31: 2090660
B32: 45978 | C32: 45978.459 | D32: Auction 4. Period CAP3 EU | E32: T3PA | F32: successful | G32: 80.25 | H32: 64 | I32: 85 | J32: 79.8 | K32: 80.03 | L32: 3268000 | M32: 5601000 | N32: 104 | O32: 23 | P32: 4.52 | Q32: 53856 | R32: 243522 | S32: 292389 | T32: 192235 | U32: 236355 | V32: 1.71 | W32: 23 | X32: 17 | Y32: 262257000 | Z32: EU | AA32: 2327250 | AB32: 4052625 | AC32: 6580500 | AD32: 842625 | AE32: 4333500 | AG32: 2287125 | AH32: 2006250 | AI32: 8907750 | AJ32: 20303250 | AK32: 3210000 | AL32: 12037500 | AM32: 922875 | AN32: 3450750 | AO32: 963000 | AP32: 20022375 | AQ32: 40125 | AR32: 20223000 | AS32: 29371500 | AT32: 0 | AU32: 642000 | AV32: 0 | AW32: 521625 | AX32: 49915500 | AY32: 401250 | AZ32: 19581000 | BA32: 7182375 | BB32: 1564875 | BD32: 4253250 | BE32: 3531000 | BF32: 1404375 | BG32: 28248000 | BH32: 1043250 | BI32: 2086500
B33: 45975 | C33: 45975.459 | D33: Auction 4. Period DE | E33: T3PA | F33: successful | G33: 80.85 | H33: 64 | I33: 82.33 | J33: 80.3 | K33: 80.67 | L33: 1691000 | M33: 3672000 | N33: 101 | O33: 31 | P33: 4.81 | Q33: 36356 | R33: 174857 | S33: 220569 | T33: 112733 | U33: 228377 | V33: 2.17 | W33: 21 | X33: 15 | Y33: 136717350 | Z33: DE | AF33: 136717350
B34: 45974 | C34: 45974.459 | D34: Auction 4. Period CAP3 EU | E34: T3PA | F34: successful | G34: 81.31 | H34: 64 | I34: 150 | J34: 82.83 | K34: 81.28 | L34: 3268000 | M34: 4987500 | N34: 106 | O34: 50 | P34: 4.08 | Q34: 47052 | R34: 191827 | S34: 244887 | T34: 142087 | U34: 226024 | V34: 1.53 | W34: 26 | X34: 23 | Y34: 265721080 | Z34: EU | AA34: 2357990 | AB34: 4106155 | AC34: 6667420 | AD34: 853755 | AE34: 4390740 | AG34: 2317335 | AH34: 2032750 | AI34: 9025410 | AJ34: 20571430 | AK34: 3252400 | AL34: 12196500 | AM34: 935065 | AN34: 3496330 | AO34: 975720 | AP34: 20286845 | AQ34: 40655 | AR34: 20490120 | AS34: 29759460 | AT34: 0 | AU34: 650480 | AV34: 0 | AW34: 528515 | AX34: 50574820 | AY34: 406550 | AZ34: 19839640 | BA34: 7277245 | BB34: 1585545 | BD34: 4309430 | BE34: 3577640 | BF34: 1422925 | BG34: 28621120 | BH34: 1057030 | BI34: 2114060
B35: 45973 | C35: 45973.459 | D35: Auction 4. Period CAP3 PL | E35: T3PA | F35: successful | G35: 81.51 | H35: 64 | I35: 150 | J35: 82.46 | K35: 81.43 | L35: 2162500 | M35: 3680000 | N35: 101 | O35: 39 | P35: 4.39 | Q35: 36436 | R35: 160000 | S35: 226599 | T35: 120139 | U35: 233479 | V35: 1.7 | W35: 23 | X35: 18 | Y35: 176265375 | Z35: PL | BC35: 176265375
B36: 45972 | C36: 45972.459 | D36: Auction 4. Period CAP3 EU | E36: T3PA | F36: successful | G36: 79.91 | H36: 64 | I36: 150 | J36: 80.2 | K36: 79.75 | L36: 3268000 | M36: 5425500 | N36: 112 | O36: 32 | P36: 4.15 | Q36: 48442 | R36: 200944 | S36: 267977 | T36: 148545 | U36: 265836 | V36: 1.66 | W36: 27 | X36: 22 | Y36: 261145880 | Z36: EU | AA36: 2317390 | AB36: 4035455 | AC36: 6552620 | AD36: 839055 | AE36: 4315140 | AG36: 2277435 | AH36: 1997750 | AI36: 8870010 | AJ36: 20217230 | AK36: 3196400 | AL36: 11986500 | AM36: 918965 | AN36: 3436130 | AO36: 958920 | AP36: 19937545 | AQ36: 39955 | AR36: 20137320 | AS36: 29247060 | AT36: 0 | AU36: 639280 | AV36: 0 | AW36: 519415 | AX36: 49704020 | AY36: 399550 | AZ36: 19498040 | BA36: 7151945 | BB36: 1558245 | BD36: 4235230 | BE36: 3516040 | BF36: 1398425 | BG36: 28128320 | BH36: 1038830 | BI36: 2077660
B37: 45971 | C37: 45971.459 | D37: Auction 4. Period CAP3 EU | E37: T3PA | F37: successful | G37: 79.97 | H37: 64 | I37: 91.74 | J37: 79.76 | K37: 79.65 | L37: 3268000 | M37: 5037500 | N37: 110 | O37: 26 | P37: 4.78 | Q37: 45795 | R37: 219022 | S37: 310378 | T37: 217867 | U37: 315534 | V37: 1.54 | W37: 23 | X37: 15 | Y37: 261341960 | Z37: EU | AA37: 2319130 | AB37: 4038485 | AC37: 6557540 | AD37: 839685 | AE37: 4318380 | AG37: 2279145 | AH37: 1999250 | AI37: 8876670 | AJ37: 20232410 | AK37: 3198800 | AL37: 11995500 | AM37: 919655 | AN37: 3438710 | AO37: 959640 | AP37: 19952515 | AQ37: 39985 | AR37: 20152440 | AS37: 29269020 | AT37: 0 | AU37: 639760 | AV37: 0 | AW37: 519805 | AX37: 49741340 | AY37: 399850 | AZ37: 19512680 | BA37: 7157315 | BB37: 1559415 | BD37: 4238410 | BE37: 3518680 | BF37: 1399475 | BG37: 28149440 | BH37: 1039610 | BI37: 2079220
B38: 45968 | C38: 45968.459 | D38: Auction 4. Period DE | E38: T3PA | F38: successful | G38: 79.76 | H38: 64 | I38: 100 | J38: 79.77 | K38: 79.6 | L38: 1691000 | M38: 3252000 | N38: 90 | O38: 30 | P38: 4.09 | Q38: 36133 | R38: 147818 | S38: 182050 | T38: 99471 | U38: 171680 | V38: 1.92 | W38: 22 | X38: 17 | Y38: 134874160 | Z38: DE | AF38: 134874160
B39: 45967 | C39: 45967.459 | D39: Auction 4. Period CAP3 EU | E39: T3PA | F39: successful | G39: 80.07 | H39: 64 | I39: 120 | J39: 80.75 | K39: 80 | L39: 3268000 | M39: 5005000 | N39: 106 | O39: 40 | P39: 3.66 | Q39: 47217 | R39: 172586 | S39: 219399 | T39: 136167 | U39: 186718 | V39: 1.53 | W39: 29 | X39: 24 | Y39: 261668760 | Z39: EU | AA39: 2322030 | AB39: 4043535 | AC39: 6565740 | AD39: 840735 | AE39: 4323780 | AG39: 2281995 | AH39: 2001750 | AI39: 8887770 | AJ39: 20257710 | AK39: 3202800 | AL39: 12010500 | AM39: 920805 | AN39: 3443010 | AO39: 960840 | AP39: 19977465 | AQ39: 40035 | AR39: 20177640 | AS39: 29305620 | AT39: 0 | AU39: 640560 | AV39: 0 | AW39: 520455 | AX39: 49803540 | AY39: 400350 | AZ39: 19537080 | BA39: 7166265 | BB39: 1561365 | BD39: 4243710 | BE39: 3523080 | BF39: 1401225 | BG39: 28184640 | BH39: 1040910 | BI39: 2081820
B40: 45965 | C40: 45965.459 | D40: Auction 4. Period CAP3 EU | E40: T3PA | F40: successful | G40: 81.26 | H40: 64 | I40: 150 | J40: 81.48 | K40: 81.03 | L40: 3268000 | M40: 5237500 | N40: 100 | O40: 28 | P40: 3.85 | Q40: 52375 | R40: 201442 | S40: 237779 | T40: 204250 | U40: 205955 | V40: 1.6 | W40: 26 | X40: 16 | Y40: 265557680 | Z40: EU | AA40: 2356540 | AB40: 4103630 | AC40: 6663320 | AD40: 853230 | AE40: 4388040 | AG40: 2315910 | AH40: 2031500 | AI40: 9019860 | AJ40: 20558780 | AK40: 3250400 | AL40: 12189000 | AM40: 934490 | AN40: 3494180 | AO40: 975120 | AP40: 20274370 | AQ40: 40630 | AR40: 20477520 | AS40: 29741160 | AT40: 0 | AU40: 650080 | AV40: 0 | AW40: 528190 | AX40: 50543720 | AY40: 406300 | AZ40: 19827440 | BA40: 7272770 | BB40: 1584570 | BD40: 4306780 | BE40: 3575440 | BF40: 1422050 | BG40: 28603520 | BH40: 1056380 | BI40: 2112760
B41: 45964 | C41: 45964.459 | D41: Auction 4. Period CAP3 EU | E41: T3PA | F41: successful | G41: 79.3 | H41: 64 | I41: 85 | J41: 78.87 | K41: 78.99 | L41: 3268000 | M41: 5272000 | N41: 95 | O41: 23 | P41: 3.96 | Q41: 55495 | R41: 219667 | S41: 309204 | T41: 217867 | U41: 298303 | V41: 1.61 | W41: 24 | X41: 15 | Y41: 259152400 | Z41: EU | AA41: 2299700 | AB41: 4004650 | AC41: 6502600 | AD41: 832650 | AE41: 4282200 | AG41: 2260050 | AH41: 1982500 | AI41: 8802300 | AJ41: 20062900 | AK41: 3172000 | AL41: 11895000 | AM41: 911950 | AN41: 3409900 | AO41: 951600 | AP41: 19785350 | AQ41: 39650 | AR41: 19983600 | AS41: 29023800 | AT41: 0 | AU41: 634400 | AV41: 0 | AW41: 515450 | AX41: 49324600 | AY41: 396500 | AZ41: 19349200 | BA41: 7097350 | BB41: 1546350 | BD41: 4202900 | BE41: 3489200 | BF41: 1387750 | BG41: 27913600 | BH41: 1030900 | BI41: 2061800
B42: 45961 | C42: 45961.459 | D42: Auction 4. Period DE | E42: T3PA | F42: successful | G42: 78.66 | H42: 0.01 | I42: 85 | J42: 77.4 | K42: 78.51 | L42: 1691000 | M42: 3390500 | N42: 78 | O42: 24 | P42: 3.71 | Q42: 43468 | R42: 161452 | S42: 228933 | T42: 105688 | U42: 236311 | V42: 2.01 | W42: 21 | X42: 16 | Y42: 133014060 | Z42: DE | AF42: 133014060
B43: 45960 | C43: 45960.459 | D43: Auction 4. Period CAP3 EU | E43: T3PA | F43: successful | G43: 78.71 | H43: 64 | I43: 150 | J43: 80.16 | K43: 78.51 | L43: 3268000 | M43: 5240000 | N43: 88 | O43: 28 | P43: 4 | Q43: 59545 | R43: 238182 | S43: 324151 | T43: 217867 | U43: 327356 | V43: 1.6 | W43: 22 | X43: 15 | Y43: 257224280 | Z43: EU | AA43: 2282590 | AB43: 3974855 | AC43: 6454220 | AD43: 826455 | AE43: 4250340 | AG43: 2243235 | AH43: 1967750 | AI43: 8736810 | AJ43: 19913630 | AK43: 3148400 | AL43: 11806500 | AM43: 905165 | AN43: 3384530 | AO43: 944520 | AP43: 19638145 | AQ43: 39355 | AR43: 19834920 | AS43: 28807860 | AT43: 0 | AU43: 629680 | AV43: 0 | AW43: 511615 | AX43: 48957620 | AY43: 393550 | AZ43: 19205240 | BA43: 7044545 | BB43: 1534845 | BD43: 4171630 | BE43: 3463240 | BF43: 1377425 | BG43: 27705920 | BH43: 1023230 | BI43: 2046460
B44: 45959 | C44: 45959.459 | D44: Auction 4. Period CAP3 PL | E44: T3PA | F44: successful | G44: 78.55 | H44: 64 | I44: 150 | J44: 79.54 | K44: 78.33 | L44: 2162500 | M44: 4135500 | N44: 100 | O44: 22 | P44: 4.17 | Q44: 41355 | R44: 172313 | S44: 232142 | T44: 154464 | U44: 278328 | V44: 1.91 | W44: 24 | X44: 14 | Y44: 169864375 | Z44: PL | BC44: 169864375
B45: 45958 | C45: 45958.459 | D45: Auction 4. Period CAP3 EU | E45: T3PA | F45: successful | G45: 77.85 | H45: 62 | I45: 100 | J45: 77.71 | K45: 77.65 | L45: 3268000 | M45: 5305500 | N45: 94 | O45: 26 | P45: 4.48 | Q45: 56441 | R45: 252643 | S45: 344324 | T45: 233429 | U45: 323718 | V45: 1.62 | W45: 21 | X45: 14 | Y45: 254413800 | Z45: EU | AA45: 2257650 | AB45: 3931425 | AC45: 6383700 | AD45: 817425 | AE45: 4203900 | AG45: 2218725 | AH45: 1946250 | AI45: 8641350 | AJ45: 19696050 | AK45: 3114000 | AL45: 11677500 | AM45: 895275 | AN45: 3347550 | AO45: 934200 | AP45: 19423575 | AQ45: 38925 | AR45: 19618200 | AS45: 28493100 | AT45: 0 | AU45: 622800 | AV45: 0 | AW45: 506025 | AX45: 48422700 | AY45: 389250 | AZ45: 18995400 | BA45: 6967575 | BB45: 1518075 | BD45: 4126050 | BE45: 3425400 | BF45: 1362375 | BG45: 27403200 | BH45: 1012050 | BI45: 2024100
B46: 45957 | C46: 45957.459 | D46: Auction 4. Period CAP3 EU | E46: T3PA | F46: successful | G46: 77.56 | H46: 62 | I46: 89.77 | J46: 77.35 | K46: 77.31 | L46: 3268000 | M46: 4684000 | N46: 81 | O46: 24 | P46: 3.68 | Q46: 57827 | R46: 212909 | S46: 359031 | T46: 204250 | U46: 350340 | V46: 1.43 | W46: 22 | X46: 16 | Y46: 253466080 | Z46: EU | AA46: 2249240 | AB46: 3916780 | AC46: 6359920 | AD46: 814380 | AE46: 4188240 | AG46: 2210460 | AH46: 1939000 | AI46: 8609160 | AJ46: 19622680 | AK46: 3102400 | AL46: 11634000 | AM46: 891940 | AN46: 3335080 | AO46: 930720 | AP46: 19351220 | AQ46: 38780 | AR46: 19545120 | AS46: 28386960 | AT46: 0 | AU46: 620480 | AV46: 0 | AW46: 504140 | AX46: 48242320 | AY46: 387800 | AZ46: 18924640 | BA46: 6941620 | BB46: 1512420 | BD46: 4110680 | BE46: 3412640 | BF46: 1357300 | BG46: 27301120 | BH46: 1008280 | BI46: 2016560
B47: 45954 | C47: 45954.459 | D47: Auction 4. Period DE | E47: T3PA | F47: successful | G47: 78.47 | H47: 62 | I47: 85 | J47: 77.95 | K47: 78.2 | L47: 1691000 | M47: 3429000 | N47: 82 | O47: 20 | P47: 3.42 | Q47: 41817 | R47: 142875 | S47: 250710 | T47: 169100 | U47: 345347 | V47: 2.03 | W47: 24 | X47: 10 | Y47: 132692770 | Z47: DE | AF47: 132692770
B48: 45953 | C48: 45953.459 | D48: Auction 4. Period CAP3 EU | E48: T3PA | F48: successful | G48: 78.54 | H48: 62 | I48: 85 | J48: 78.24 | K48: 78.3 | L48: 3268000 | M48: 5336500 | N48: 89 | O48: 26 | P48: 3.87 | Q48: 59961 | R48: 232022 | S48: 288904 | T48: 217867 | U48: 260109 | V48: 1.63 | W48: 23 | X48: 15 | Y48: 256668720 | Z48: EU | AA48: 2277660 | AB48: 3966270 | AC48: 6440280 | AD48: 824670 | AE48: 4241160 | AG48: 2238390 | AH48: 1963500 | AI48: 8717940 | AJ48: 19870620 | AK48: 3141600 | AL48: 11781000 | AM48: 903210 | AN48: 3377220 | AO48: 942480 | AP48: 19595730 | AQ48: 39270 | AR48: 19792080 | AS48: 28745640 | AT48: 0 | AU48: 628320 | AV48: 0 | AW48: 510510 | AX48: 48851880 | AY48: 392700 | AZ48: 19163760 | BA48: 7029330 | BB48: 1531530 | BD48: 4162620 | BE48: 3455760 | BF48: 1374450 | BG48: 27646080 | BH48: 1021020 | BI48: 2042040
B49: 45951 | C49: 45951.459 | D49: Auction 4. Period CAP3 EU | E49: T3PA | F49: successful | G49: 78.94 | H49: 62 | I49: 100 | J49: 78.88 | K49: 78.66 | L49: 3268000 | M49: 5626500 | N49: 115 | O49: 33 | P49: 4.11 | Q49: 48926 | R49: 200946 | S49: 250140 | T49: 192235 | U49: 239086 | V49: 1.72 | W49: 28 | X49: 17 | Y49: 257975920 | Z49: EU | AA49: 2289260 | AB49: 3986470 | AC49: 6473080 | AD49: 828870 | AE49: 4262760 | AG49: 2249790 | AH49: 1973500 | AI49: 8762340 | AJ49: 19971820 | AK49: 3157600 | AL49: 11841000 | AM49: 907810 | AN49: 3394420 | AO49: 947280 | AP49: 19695530 | AQ49: 39470 | AR49: 19892880 | AS49: 28892040 | AT49: 0 | AU49: 631520 | AV49: 0 | AW49: 513110 | AX49: 49100680 | AY49: 394700 | AZ49: 19261360 | BA49: 7065130 | BB49: 1539330 | BD49: 4183820 | BE49: 3473360 | BF49: 1381450 | BG49: 27786880 | BH49: 1026220 | BI49: 2052440
B50: 45950 | C50: 45950.459 | D50: Auction 4. Period CAP3 EU | E50: T3PA | F50: successful | G50: 78.75 | H50: 77.12 | I50: 85 | J50: 78.87 | K50: 78.66 | L50: 3268000 | M50: 5240000 | N50: 89 | O50: 32 | P50: 4.05 | Q50: 58876 | R50: 238182 | S50: 267824 | T50: 204250 | U50: 264196 | V50: 1.6 | W50: 22 | X50: 16 | Y50: 257355000 | Z50: EU | AA50: 2283750 | AB50: 3976875 | AC50: 6457500 | AD50: 826875 | AE50: 4252500 | AG50: 2244375 | AH50: 1968750 | AI50: 8741250 | AJ50: 19923750 | AK50: 3150000 | AL50: 11812500 | AM50: 905625 | AN50: 3386250 | AO50: 945000 | AP50: 19648125 | AQ50: 39375 | AR50: 19845000 | AS50: 28822500 | AT50: 0 | AU50: 630000 | AV50: 0 | AW50: 511875 | AX50: 48982500 | AY50: 393750 | AZ50: 19215000 | BA50: 7048125 | BB50: 1535625 | BD50: 4173750 | BE50: 3465000 | BF50: 1378125 | BG50: 27720000 | BH50: 1023750 | BI50: 2047500
B51: 45947 | C51: 45947.459 | D51: Auction 4. Period DE | E51: T3PA | F51: successful | G51: 77.99 | H51: 62 | I51: 85 | J51: 77.64 | K51: 77.89 | L51: 1691000 | M51: 3345000 | N51: 72 | O51: 24 | P51: 3.43 | Q51: 46458 | R51: 159286 | S51: 182779 | T51: 120786 | U51: 185614 | V51: 1.98 | W51: 21 | X51: 14 | Y51: 131881090 | Z51: DE | AF51: 131881090
B52: 45946 | C52: 45946.459 | D52: Auction 4. Period CAP3 EU | E52: T3PA | F52: successful | G52: 77.82 | H52: 60 | I52: 80 | J52: 77.36 | K52: 77.56 | L52: 3268000 | M52: 5237000 | N52: 95 | O52: 25 | P52: 4.32 | Q52: 55126 | R52: 238045 | S52: 277838 | T52: 204250 | U52: 230665 | V52: 1.6 | W52: 22 | X52: 16 | Y52: 254315760 | Z52: EU | AA52: 2256780 | AB52: 3929910 | AC52: 6381240 | AD52: 817110 | AE52: 4202280 | AG52: 2217870 | AH52: 1945500 | AI52: 8638020 | AJ52: 19688460 | AK52: 3112800 | AL52: 11673000 | AM52: 894930 | AN52: 3346260 | AO52: 933840 | AP52: 19416090 | AQ52: 38910 | AR52: 19610640 | AS52: 28482120 | AT52: 0 | AU52: 622560 | AV52: 0 | AW52: 505830 | AX52: 48404040 | AY52: 389100 | AZ52: 18988080 | BA52: 6964890 | BB52: 1517490 | BD52: 4124460 | BE52: 3424080 | BF52: 1361850 | BG52: 27392640 | BH52: 1011660 | BI52: 2023320
B53: 45945 | C53: 45945.459 | D53: Auction 4. Period CAP3 PL | E53: T3PA | F53: successful | G53: 76.58 | H53: 62 | I53: 80 | J53: 76.43 | K53: 76.45 | L53: 2162500 | M53: 4012500 | N53: 103 | O53: 35 | P53: 3.55 | Q53: 38956 | R53: 138362 | S53: 166254 | T53: 108125 | U53: 149146 | V53: 1.86 | W53: 29 | X53: 20 | Y53: 165604250 | Z53: PL | BC53: 165604250
B54: 45944 | C54: 45944.459 | D54: Auction 4. Period CAP3 EU | E54: T3PA | F54: successful | G54: 76.91 | H54: 62 | I54: 80 | J54: 76.61 | K54: 76.81 | L54: 3268000 | M54: 5096000 | N54: 89 | O54: 33 | P54: 3.87 | Q54: 57258 | R54: 221565 | S54: 240167 | T54: 163400 | U54: 197008 | V54: 1.56 | W54: 23 | X54: 20 | Y54: 251341880 | Z54: EU | AA54: 2230390 | AB54: 3883955 | AC54: 6306620 | AD54: 807555 | AE54: 4153140 | AG54: 2191935 | AH54: 1922750 | AI54: 8537010 | AJ54: 19458230 | AK54: 3076400 | AL54: 11536500 | AM54: 884465 | AN54: 3307130 | AO54: 922920 | AP54: 19189045 | AQ54: 38455 | AR54: 19381320 | AS54: 28149060 | AT54: 0 | AU54: 615280 | AV54: 0 | AW54: 499915 | AX54: 47838020 | AY54: 384550 | AZ54: 18766040 | BA54: 6883445 | BB54: 1499745 | BD54: 4076230 | BE54: 3384040 | BF54: 1345925 | BG54: 27072320 | BH54: 999830 | BI54: 1999660
B55: 45943 | C55: 45943.459 | D55: Auction 4. Period CAP3 EU | E55: T3PA | F55: successful | G55: 78.66 | H55: 62 | I55: 80.88 | J55: 78.17 | K55: 78.5 | L55: 3268000 | M55: 4783000 | N55: 77 | O55: 27 | P55: 3.67 | Q55: 62117 | R55: 227762 | S55: 367388 | T55: 217867 | U55: 383099 | V55: 1.46 | W55: 21 | X55: 15 | Y55: 257060880 | Z55: EU | AA55: 2281140 | AB55: 3972330 | AC55: 6450120 | AD55: 825930 | AE55: 4247640 | AG55: 2241810 | AH55: 1966500 | AI55: 8731260 | AJ55: 19900980 | AK55: 3146400 | AL55: 11799000 | AM55: 904590 | AN55: 3382380 | AO55: 943920 | AP55: 19625670 | AQ55: 39330 | AR55: 19822320 | AS55: 28789560 | AT55: 0 | AU55: 629280 | AV55: 0 | AW55: 511290 | AX55: 48926520 | AY55: 393300 | AZ55: 19193040 | BA55: 7040070 | BB55: 1533870 | BD55: 4168980 | BE55: 3461040 | BF55: 1376550 | BG55: 27688320 | BH55: 1022580 | BI55: 2045160
B56: 45940 | C56: 45940.459 | D56: Auction 4. Period DE | E56: T3PA | F56: successful | G56: 79.22 | H56: 62 | I56: 90 | J56: 78.82 | K56: 79.12 | L56: 1691000 | M56: 3102000 | N56: 61 | O56: 24 | P56: 2.77 | Q56: 50852 | R56: 141000 | S56: 198540 | T56: 130077 | U56: 216066 | V56: 1.83 | W56: 22 | X56: 13 | Y56: 133961020 | Z56: DE | AF56: 133961020
B57: 45939 | C57: 45939.459 | D57: Auction 4. Period CAP3 EU | E57: T3PA | F57: successful | G57: 77.95 | H57: 62 | I57: 120 | J57: 78.52 | K57: 77.78 | L57: 3268000 | M57: 5237500 | N57: 83 | O57: 27 | P57: 3.95 | Q57: 63102 | R57: 249405 | S57: 272818 | T57: 192235 | U57: 250142 | V57: 1.6 | W57: 21 | X57: 17 | Y57: 254740600 | Z57: EU | AA57: 2260550 | AB57: 3936475 | AC57: 6391900 | AD57: 818475 | AE57: 4209300 | AG57: 2221575 | AH57: 1948750 | AI57: 8652450 | AJ57: 19721350 | AK57: 3118000 | AL57: 11692500 | AM57: 896425 | AN57: 3351850 | AO57: 935400 | AP57: 19448525 | AQ57: 38975 | AR57: 19643400 | AS57: 28529700 | AT57: 0 | AU57: 623600 | AV57: 0 | AW57: 506675 | AX57: 48484900 | AY57: 389750 | AZ57: 19019800 | BA57: 6976525 | BB57: 1520025 | BD57: 4131350 | BE57: 3429800 | BF57: 1364125 | BG57: 27438400 | BH57: 1013350 | BI57: 2026700
B58: 45938 | C58: 45938.459 | D58: Auction 4. Period CAP3 NIR | E58: T3PA | F58: successful | G58: 77.39 | H58: 60 | I58: 79.3 | J58: 76.99 | K58: 77.5 | L58: 796500 | M58: 1312000 | N58: 49 | O58: 29 | P58: 3.77 | Q58: 26776 | R58: 100923 | S58: 70230 | T58: 66375 | U58: 42778 | V58: 1.65 | W58: 13 | X58: 12 | Y58: 61641135 | Z58: XI | BJ58: 61641135
B59: 45937 | C59: 45937.459 | D59: Auction 4. Period CAP3 EU | E59: T3PA | F59: successful | G59: 78.3 | H59: 64 | I59: 120 | J59: 79.23 | K59: 78.11 | L59: 3268000 | M59: 4618000 | N59: 71 | O59: 22 | P59: 3.38 | Q59: 65042 | R59: 219905 | S59: 246676 | T59: 192235 | U59: 231555 | V59: 1.41 | W59: 21 | X59: 17 | Y59: 255884400 | Z59: EU | AA59: 2270700 | AB59: 3954150 | AC59: 6420600 | AD59: 822150 | AE59: 4228200 | AG59: 2231550 | AH59: 1957500 | AI59: 8691300 | AJ59: 19809900 | AK59: 3132000 | AL59: 11745000 | AM59: 900450 | AN59: 3366900 | AO59: 939600 | AP59: 19535850 | AQ59: 39150 | AR59: 19731600 | AS59: 28657800 | AT59: 0 | AU59: 626400 | AV59: 0 | AW59: 508950 | AX59: 48702600 | AY59: 391500 | AZ59: 19105200 | BA59: 7007850 | BB59: 1526850 | BD59: 4149900 | BE59: 3445200 | BF59: 1370250 | BG59: 27561600 | BH59: 1017900 | BI59: 2035800
B60: 45936 | C60: 45936.459 | D60: Auction 4. Period CAP3 EU | E60: T3PA | F60: successful | G60: 79.19 | H60: 64 | I60: 120 | J60: 79.3 | K60: 78.91 | L60: 3268000 | M60: 5329500 | N60: 86 | O60: 22 | P60: 3.74 | Q60: 61971 | R60: 231717 | S60: 306791 | T60: 217867 | U60: 327208 | V60: 1.63 | W60: 23 | X60: 15 | Y60: 258792920 | Z60: EU | AA60: 2296510 | AB60: 3999095 | AC60: 6493580 | AD60: 831495 | AE60: 4276260 | AG60: 2256915 | AH60: 1979750 | AI60: 8790090 | AJ60: 20035070 | AK60: 3167600 | AL60: 11878500 | AM60: 910685 | AN60: 3405170 | AO60: 950280 | AP60: 19757905 | AQ60: 39595 | AR60: 19955880 | AS60: 28983540 | AT60: 0 | AU60: 633520 | AV60: 0 | AW60: 514735 | AX60: 49256180 | AY60: 395950 | AZ60: 19322360 | BA60: 7087505 | BB60: 1544205 | BD60: 4197070 | BE60: 3484360 | BF60: 1385825 | BG60: 27874880 | BH60: 1029470 | BI60: 2058940
B61: 45932 | C61: 45932.459 | D61: Auction 4. Period CAP3 EU | E61: T3PA | F61: successful | G61: 76.05 | H61: 68 | I61: 90 | J61: 75.99 | K61: 75.87 | L61: 3268000 | M61: 5071000 | N61: 89 | O61: 26 | P61: 3.87 | Q61: 56978 | R61: 220478 | S61: 300349 | T61: 217867 | U61: 307273 | V61: 1.55 | W61: 23 | X61: 15 | Y61: 248531400 | Z61: EU | AA61: 2205450 | AB61: 3840525 | AC61: 6236100 | AD61: 798525 | AE61: 4106700 | AG61: 2167425 | AH61: 1901250 | AI61: 8441550 | AJ61: 19240650 | AK61: 3042000 | AL61: 11407500 | AM61: 874575 | AN61: 3270150 | AO61: 912600 | AP61: 18974475 | AQ61: 38025 | AR61: 19164600 | AS61: 27834300 | AT61: 0 | AU61: 608400 | AV61: 0 | AW61: 494325 | AX61: 47303100 | AY61: 380250 | AZ61: 18556200 | BA61: 6806475 | BB61: 1482975 | BD61: 4030650 | BE61: 3346200 | BF61: 1330875 | BG61: 26769600 | BH61: 988650 | BI61: 1977300
B62: 45931 | C62: 45931.459 | D62: Auction 4. Period CAP3 PL | E62: T3PA | F62: successful | G62: 74.3 | H62: 65 | I62: 90 | J62: 74.61 | K62: 74.18 | L62: 2162500 | M62: 3092000 | N62: 75 | O62: 25 | P62: 3.75 | Q62: 41227 | R62: 154600 | S62: 215476 | T62: 154464 | U62: 255064 | V62: 1.43 | W62: 20 | X62: 14 | Y62: 160673750 | Z62: PL | BC62: 160673750
B63: 45930 | C63: 45930.459 | D63: Auction 4. Period CAP3 EU | E63: T3PA | F63: successful | G63: 75.95 | H63: 65 | I63: 120 | J63: 76.75 | K63: 75.81 | L63: 3268500 | M63: 4711000 | N63: 91 | O63: 29 | P63: 4.14 | Q63: 51769 | R63: 214136 | S63: 277026 | T63: 192265 | U63: 242573 | V63: 1.44 | W63: 22 | X63: 17 | Y63: 248242575 | Z63: EU | AA63: 2202550 | AB63: 3835475 | AC63: 6227900 | AD63: 797475 | AE63: 4101300 | AG63: 2164575 | AH63: 1898750 | AI63: 8430450 | AJ63: 19215350 | AK63: 3038000 | AL63: 11392500 | AM63: 873425 | AN63: 3265850 | AO63: 911400 | AP63: 18949525 | AQ63: 37975 | AR63: 19139400 | AS63: 27797700 | AT63: 37975 | AU63: 607600 | AV63: 0 | AW63: 493675 | AX63: 47240900 | AY63: 379750 | AZ63: 18531800 | BA63: 6797525 | BB63: 1481025 | BD63: 4025350 | BE63: 3341800 | BF63: 1329125 | BG63: 26734400 | BH63: 987350 | BI63: 1974700
B64: 45929 | C64: 45929.459 | D64: Auction 4. Period CAP3 EU | E64: T3PA | F64: successful | G64: 75.2 | H64: 65 | I64: 90 | J64: 75.19 | K64: 74.91 | L64: 3268000 | M64: 4941000 | N64: 85 | O64: 24 | P64: 3.4 | Q64: 58129 | R64: 197640 | S64: 229561 | T64: 204250 | U64: 213068 | V64: 1.51 | W64: 25 | X64: 16 | Y64: 245753600 | Z64: EU | AA64: 2180800 | AB64: 3797600 | AC64: 6166400 | AD64: 789600 | AE64: 4060800 | AG64: 2143200 | AH64: 1880000 | AI64: 8347200 | AJ64: 19025600 | AK64: 3008000 | AL64: 11280000 | AM64: 864800 | AN64: 3233600 | AO64: 902400 | AP64: 18762400 | AQ64: 37600 | AR64: 18950400 | AS64: 27523200 | AT64: 0 | AU64: 601600 | AV64: 0 | AW64: 488800 | AX64: 46774400 | AY64: 376000 | AZ64: 18348800 | BA64: 6730400 | BB64: 1466400 | BD64: 3985600 | BE64: 3308800 | BF64: 1316000 | BG64: 26470400 | BH64: 977600 | BI64: 1955200
B65: 45926 | C65: 45926.459 | D65: Auction 4. Period DE | E65: T3PA | F65: successful | G65: 75.17 | H65: 69 | I65: 78 | J65: 74.77 | K65: 74.74 | L65: 1691000 | M65: 3513000 | N65: 87 | O65: 18 | P65: 3.78 | Q65: 40379 | R65: 152739 | S65: 179220 | T65: 130077 | U65: 161770 | V65: 2.08 | W65: 23 | X65: 13 | Y65: 127112470 | Z65: DE | AF65: 127112470
B66: 45925 | C66: 45925.459 | D66: Auction 4. Period CAP3 EU | E66: T3PA | F66: successful | G66: 75.56 | H66: 74.5 | I66: 120 | J66: 77.67 | K66: 75.71 | L66: 3268000 | M66: 3521000 | N66: 75 | O66: 54 | P66: 3.41 | Q66: 46947 | R66: 160045 | S66: 203601 | T66: 155619 | U66: 206055 | V66: 1.08 | W66: 22 | X66: 21 | Y66: 246930080 | Z66: EU | AA66: 2191240 | AB66: 3815780 | AC66: 6195920 | AD66: 793380 | AE66: 4080240 | AG66: 2153460 | AH66: 1889000 | AI66: 8387160 | AJ66: 19116680 | AK66: 3022400 | AL66: 11334000 | AM66: 868940 | AN66: 3249080 | AO66: 906720 | AP66: 18852220 | AQ66: 37780 | AR66: 19041120 | AS66: 27654960 | AT66: 0 | AU66: 604480 | AV66: 0 | AW66: 491140 | AX66: 46998320 | AY66: 377800 | AZ66: 18436640 | BA66: 6762620 | BB66: 1473420 | BD66: 4004680 | BE66: 3324640 | BF66: 1322300 | BG66: 26597120 | BH66: 982280 | BI66: 1964560
B67: 45923 | C67: 45923.459 | D67: Auction 4. Period CAP3 EU | E67: T3PA | F67: successful | G67: 75.6 | H67: 70 | I67: 85 | J67: 75.71 | K67: 75.6 | L67: 3268000 | M67: 3985500 | N67: 87 | O67: 43 | P67: 3.48 | Q67: 45810 | R67: 159420 | S67: 241924 | T67: 155619 | U67: 254423 | V67: 1.22 | W67: 25 | X67: 21 | Y67: 247060800 | Z67: EU | AA67: 2192400 | AB67: 3817800 | AC67: 6199200 | AD67: 793800 | AE67: 4082400 | AG67: 2154600 | AH67: 1890000 | AI67: 8391600 | AJ67: 19126800 | AK67: 3024000 | AL67: 11340000 | AM67: 869400 | AN67: 3250800 | AO67: 907200 | AP67: 18862200 | AQ67: 37800 | AR67: 19051200 | AS67: 27669600 | AT67: 0 | AU67: 604800 | AV67: 0 | AW67: 491400 | AX67: 47023200 | AY67: 378000 | AZ67: 18446400 | BA67: 6766200 | BB67: 1474200 | BD67: 4006800 | BE67: 3326400 | BF67: 1323000 | BG67: 26611200 | BH67: 982800 | BI67: 1965600
B68: 45922 | C68: 45922.459 | D68: Auction 4. Period CAP3 EU | E68: T3PA | F68: successful | G68: 76.8 | H68: 70 | I68: 120 | J68: 77.55 | K68: 76.73 | L68: 3268000 | M68: 4859500 | N68: 114 | O68: 49 | P68: 4.22 | Q68: 42627 | R68: 179981 | S68: 230487 | T68: 130720 | U68: 192615 | V68: 1.49 | W68: 27 | X68: 25 | Y68: 250982400 | Z68: EU | AA68: 2227200 | AB68: 3878400 | AC68: 6297600 | AD68: 806400 | AE68: 4147200 | AG68: 2188800 | AH68: 1920000 | AI68: 8524800 | AJ68: 19430400 | AK68: 3072000 | AL68: 11520000 | AM68: 883200 | AN68: 3302400 | AO68: 921600 | AP68: 19161600 | AQ68: 38400 | AR68: 19353600 | AS68: 28108800 | AT68: 0 | AU68: 614400 | AV68: 0 | AW68: 499200 | AX68: 47769600 | AY68: 384000 | AZ68: 18739200 | BA68: 6873600 | BB68: 1497600 | BD68: 4070400 | BE68: 3379200 | BF68: 1344000 | BG68: 27033600 | BH68: 998400 | BI68: 1996800
B69: 45919 | C69: 45919.459 | D69: Auction 4. Period DE | E69: T3PA | F69: successful | G69: 76.57 | H69: 68 | I69: 120 | J69: 77.3 | K69: 76.43 | L69: 1691000 | M69: 2832000 | N69: 82 | O69: 27 | P69: 3.9 | Q69: 34537 | R69: 134857 | S69: 165506 | T69: 93944 | U69: 155202 | V69: 1.67 | W69: 21 | X69: 18 | Y69: 129479870 | Z69: DE | AF69: 129479870
B70: 45918 | C70: 45918.459 | D70: Auction 4. Period CAP3 EU | E70: T3PA | F70: successful | G70: 77.22 | H70: 68.31 | I70: 120 | J70: 77.49 | K70: 77.11 | L70: 3268000 | M70: 5201500 | N70: 97 | O70: 33 | P70: 4.04 | Q70: 53624 | R70: 216729 | S70: 273277 | T70: 155619 | U70: 256540 | V70: 1.59 | W70: 24 | X70: 21 | Y70: 252354960 | Z70: EU | AA70: 2239380 | AB70: 3899610 | AC70: 6332040 | AD70: 810810 | AE70: 4169880 | AG70: 2200770 | AH70: 1930500 | AI70: 8571420 | AJ70: 19536660 | AK70: 3088800 | AL70: 11583000 | AM70: 888030 | AN70: 3320460 | AO70: 926640 | AP70: 19266390 | AQ70: 38610 | AR70: 19459440 | AS70: 28262520 | AT70: 0 | AU70: 617760 | AV70: 0 | AW70: 501930 | AX70: 48030840 | AY70: 386100 | AZ70: 18841680 | BA70: 6911190 | BB70: 1505790 | BD70: 4092660 | BE70: 3397680 | BF70: 1351350 | BG70: 27181440 | BH70: 1003860 | BI70: 2007720
B71: 45917 | C71: 45917.459 | D71: Auction 4. Period CAP3 PL | E71: T3PA | F71: successful | G71: 77.53 | H71: 64 | I71: 85 | J71: 77.22 | K71: 77.41 | L71: 2162500 | M71: 3324000 | N71: 85 | O71: 26 | P71: 3.54 | Q71: 39106 | R71: 138500 | S71: 198973 | T71: 135156 | U71: 230244 | V71: 1.54 | W71: 24 | X71: 16 | Y71: 167658625 | Z71: PL | BC71: 167658625
B72: 45916 | C72: 45916.459 | D72: Auction 4. Period CAP3 EU | E72: T3PA | F72: successful | G72: 76.17 | H72: 64 | I72: 120 | J72: 77.17 | K72: 75.99 | L72: 3268000 | M72: 5478000 | N72: 108 | O72: 29 | P72: 3.72 | Q72: 50722 | R72: 188897 | S72: 231698 | T72: 172000 | U72: 220045 | V72: 1.68 | W72: 29 | X72: 19 | Y72: 248923560 | Z72: EU | AA72: 2208930 | AB72: 3846585 | AC72: 6245940 | AD72: 799785 | AE72: 4113180 | AG72: 2170845 | AH72: 1904250 | AI72: 8454870 | AJ72: 19271010 | AK72: 3046800 | AL72: 11425500 | AM72: 875955 | AN72: 3275310 | AO72: 914040 | AP72: 19004415 | AQ72: 38085 | AR72: 19194840 | AS72: 27878220 | AT72: 0 | AU72: 609360 | AV72: 0 | AW72: 495105 | AX72: 47377740 | AY72: 380850 | AZ72: 18585480 | BA72: 6817215 | BB72: 1485315 | BD72: 4037010 | BE72: 3351480 | BF72: 1332975 | BG72: 26811840 | BH72: 990210 | BI72: 1980420
B73: 45915 | C73: 45915.459 | D73: Auction 4. Period CAP3 EU | E73: T3PA | F73: successful | G73: 75.02 | H73: 64 | I73: 80 | J73: 74.83 | K73: 74.84 | L73: 3268000 | M73: 5812000 | N73: 111 | O73: 30 | P73: 4.44 | Q73: 52360 | R73: 232480 | S73: 290578 | T73: 204250 | U73: 288239 | V73: 1.78 | W73: 25 | X73: 16 | Y73: 245165360 | Z73: EU | AA73: 2175580 | AB73: 3788510 | AC73: 6151640 | AD73: 787710 | AE73: 4051080 | AG73: 2138070 | AH73: 1875500 | AI73: 8327220 | AJ73: 18980060 | AK73: 3000800 | AL73: 11253000 | AM73: 862730 | AN73: 3225860 | AO73: 900240 | AP73: 18717490 | AQ73: 37510 | AR73: 18905040 | AS73: 27457320 | AT73: 0 | AU73: 600160 | AV73: 0 | AW73: 487630 | AX73: 46662440 | AY73: 375100 | AZ73: 18304880 | BA73: 6714290 | BB73: 1462890 | BD73: 3976060 | BE73: 3300880 | BF73: 1312850 | BG73: 26407040 | BH73: 975260 | BI73: 1950520
B74: 45912 | C74: 45912.459 | D74: Auction 4. Period DE | E74: T3PA | F74: successful | G74: 75.02 | H74: 73.01 | I74: 80 | J74: 74.88 | K74: 74.8 | L74: 1691000 | M74: 3524000 | N74: 77 | O74: 20 | P74: 3.21 | Q74: 45766 | R74: 146833 | S74: 163898 | T74: 112733 | U74: 148524 | V74: 2.08 | W74: 24 | X74: 15 | Y74: 126858820 | Z74: DE | AF74: 126858820
B75: 45911 | C75: 45911.459 | D75: Auction 4. Period CAP3 EU | E75: T3PA | F75: successful | G75: 76.07 | H75: 74.01 | I75: 87.6 | J75: 76.19 | K75: 76 | L75: 3268000 | M75: 4567000 | N75: 87 | O75: 32 | P75: 3.35 | Q75: 52494 | R75: 175654 | S75: 232692 | T75: 148545 | U75: 228606 | V75: 1.4 | W75: 26 | X75: 22 | Y75: 248596760 | Z75: EU | AA75: 2206030 | AB75: 3841535 | AC75: 6237740 | AD75: 798735 | AE75: 4107780 | AG75: 2167995 | AH75: 1901750 | AI75: 8443770 | AJ75: 19245710 | AK75: 3042800 | AL75: 11410500 | AM75: 874805 | AN75: 3271010 | AO75: 912840 | AP75: 18979465 | AQ75: 38035 | AR75: 19169640 | AS75: 27841620 | AT75: 0 | AU75: 608560 | AV75: 0 | AW75: 494455 | AX75: 47315540 | AY75: 380350 | AZ75: 18561080 | BA75: 6808265 | BB75: 1483365 | BD75: 4031710 | BE75: 3347080 | BF75: 1331225 | BG75: 26776640 | BH75: 988910 | BI75: 1977820
B76: 45909 | C76: 45909.459 | D76: Auction 4. Period CAP3 EU | E76: T3PA | F76: successful | G76: 76.4 | H76: 68 | I76: 120 | J76: 76.75 | K76: 76.21 | L76: 3268000 | M76: 5111000 | N76: 94 | O76: 35 | P76: 3.48 | Q76: 54372 | R76: 189296 | S76: 213733 | T76: 172000 | U76: 172270 | V76: 1.56 | W76: 27 | X76: 19 | Y76: 249675200 | Z76: EU | AA76: 2215600 | AB76: 3858200 | AC76: 6264800 | AD76: 802200 | AE76: 4125600 | AG76: 2177400 | AH76: 1910000 | AI76: 8480400 | AJ76: 19329200 | AK76: 3056000 | AL76: 11460000 | AM76: 878600 | AN76: 3285200 | AO76: 916800 | AP76: 19061800 | AQ76: 38200 | AR76: 19252800 | AS76: 27962400 | AT76: 0 | AU76: 611200 | AV76: 0 | AW76: 496600 | AX76: 47520800 | AY76: 382000 | AZ76: 18641600 | BA76: 6837800 | BB76: 1489800 | BD76: 4049200 | BE76: 3361600 | BF76: 1337000 | BG76: 26892800 | BH76: 993200 | BI76: 1986400
B77: 45908 | C77: 45908.459 | D77: Auction 4. Period CAP3 EU | E77: T3PA | F77: successful | G77: 75.21 | H77: 68 | I77: 80 | J77: 75 | K77: 74.96 | L77: 3268000 | M77: 5514500 | N77: 90 | O77: 27 | P77: 3.91 | Q77: 61272 | R77: 239761 | S77: 241789 | T77: 233429 | U77: 222874 | V77: 1.69 | W77: 23 | X77: 14 | Y77: 245786280 | Z77: EU | AA77: 2181090 | AB77: 3798105 | AC77: 6167220 | AD77: 789705 | AE77: 4061340 | AG77: 2143485 | AH77: 1880250 | AI77: 8348310 | AJ77: 19028130 | AK77: 3008400 | AL77: 11281500 | AM77: 864915 | AN77: 3234030 | AO77: 902520 | AP77: 18764895 | AQ77: 37605 | AR77: 18952920 | AS77: 27526860 | AT77: 0 | AU77: 601680 | AV77: 0 | AW77: 488865 | AX77: 46780620 | AY77: 376050 | AZ77: 18351240 | BA77: 6731295 | BB77: 1466595 | BD77: 3986130 | BE77: 3309240 | BF77: 1316175 | BG77: 26473920 | BH77: 977730 | BI77: 1955460
B78: 45905 | C78: 45905.459 | D78: Auction 4. Period DE | E78: T3PA | F78: successful | G78: 75.44 | H78: 73.2 | I78: 120 | J78: 75.97 | K78: 75.31 | L78: 1691000 | M78: 2964000 | N78: 74 | O78: 29 | P78: 3.22 | Q78: 40054 | R78: 128870 | S78: 133099 | T78: 93944 | U78: 117569 | V78: 1.75 | W78: 23 | X78: 18 | Y78: 127569040 | Z78: DE | AF78: 127569040
B79: 45904 | C79: 45904.459 | D79: Auction 4. Period CAP3 EU | E79: T3PA | F79: successful | G79: 74.38 | H79: 63 | I79: 80 | J79: 74.34 | K79: 74.33 | L79: 3268000 | M79: 4341500 | N79: 83 | O79: 38 | P79: 3.95 | Q79: 52307 | R79: 206738 | S79: 236219 | T79: 204250 | U79: 240592 | V79: 1.33 | W79: 21 | X79: 16 | Y79: 243073840 | Z79: EU | AA79: 2157020 | AB79: 3756190 | AC79: 6099160 | AD79: 780990 | AE79: 4016520 | AG79: 2119830 | AH79: 1859500 | AI79: 8256180 | AJ79: 18818140 | AK79: 2975200 | AL79: 11157000 | AM79: 855370 | AN79: 3198340 | AO79: 892560 | AP79: 18557810 | AQ79: 37190 | AR79: 18743760 | AS79: 27223080 | AT79: 0 | AU79: 595040 | AV79: 0 | AW79: 483470 | AX79: 46264360 | AY79: 371900 | AZ79: 18148720 | BA79: 6657010 | BB79: 1450410 | BD79: 3942140 | BE79: 3272720 | BF79: 1301650 | BG79: 26181760 | BH79: 966940 | BI79: 1933880
B80: 45903 | C80: 45903.459 | D80: Auction 4. Period CAP3 PL | E80: T3PA | F80: successful | G80: 73.27 | H80: 64 | I80: 80 | J80: 73.24 | K80: 73.17 | L80: 2162500 | M80: 3118500 | N80: 76 | O80: 32 | P80: 3.62 | Q80: 41033 | R80: 148500 | S80: 205941 | T80: 127206 | U80: 228161 | V80: 1.44 | W80: 21 | X80: 17 | Y80: 158446375 | Z80: PL | BC80: 158446375
B81: 45902 | C81: 45902.459 | D81: Auction 4. Period CAP3 EU | E81: T3PA | F81: successful | G81: 73.5 | H81: 64 | I81: 80 | J81: 73.58 | K81: 73.45 | L81: 3268000 | M81: 4191500 | N81: 84 | O81: 37 | P81: 4.2 | Q81: 49899 | R81: 209575 | S81: 278254 | T81: 181556 | U81: 286556 | V81: 1.28 | W81: 20 | X81: 18 | Y81: 240198000 | Z81: EU | AA81: 2131500 | AB81: 3711750 | AC81: 6027000 | AD81: 771750 | AE81: 3969000 | AG81: 2094750 | AH81: 1837500 | AI81: 8158500 | AJ81: 18595500 | AK81: 2940000 | AL81: 11025000 | AM81: 845250 | AN81: 3160500 | AO81: 882000 | AP81: 18338250 | AQ81: 36750 | AR81: 18522000 | AS81: 26901000 | AT81: 0 | AU81: 588000 | AV81: 0 | AW81: 477750 | AX81: 45717000 | AY81: 367500 | AZ81: 17934000 | BA81: 6578250 | BB81: 1433250 | BD81: 3895500 | BE81: 3234000 | BF81: 1286250 | BG81: 25872000 | BH81: 955500 | BI81: 1911000
B82: 45901 | C82: 45901.459 | D82: Auction 4. Period CAP3 EU | E82: T3PA | F82: successful | G82: 73.14 | H82: 64 | I82: 85 | J82: 73.24 | K82: 73.01 | L82: 3268000 | M82: 4365500 | N82: 79 | O82: 30 | P82: 3.43 | Q82: 55259 | R82: 189804 | S82: 231458 | T82: 204250 | U82: 231581 | V82: 1.34 | W82: 23 | X82: 16 | Y82: 239021520 | Z82: EU | AA82: 2121060 | AB82: 3693570 | AC82: 5997480 | AD82: 767970 | AE82: 3949560 | AG82: 2084490 | AH82: 1828500 | AI82: 8118540 | AJ82: 18504420 | AK82: 2925600 | AL82: 10971000 | AM82: 841110 | AN82: 3145020 | AO82: 877680 | AP82: 18248430 | AQ82: 36570 | AR82: 18431280 | AS82: 26769240 | AT82: 0 | AU82: 585120 | AV82: 0 | AW82: 475410 | AX82: 45493080 | AY82: 365700 | AZ82: 17846160 | BA82: 6546030 | BB82: 1426230 | BD82: 3876420 | BE82: 3218160 | BF82: 1279950 | BG82: 25745280 | BH82: 950820 | BI82: 1901640
B83: 45898 | C83: 45898.459 | D83: Auction 4. Period DE | E83: T3PA | F83: successful | G83: 71.3 | H83: 65 | I83: 80 | J83: 71.73 | K83: 71.17 | L83: 1614500 | M83: 2932500 | N83: 79 | O83: 25 | P83: 3.59 | Q83: 37120 | R83: 133295 | S83: 130477 | T83: 124192 | U83: 163448 | V83: 1.82 | W83: 22 | X83: 13 | Y83: 115113850 | Z83: DE | AF83: 115113850
B84: 45897 | C84: 45897.459 | D84: Auction 4. Period CAP3 EU | E84: T3PA | F84: successful | G84: 71.18 | H84: 64 | I84: 82 | J84: 71.46 | K84: 71.1 | L84: 3244500 | M84: 4520000 | N84: 87 | O84: 37 | P84: 3.78 | Q84: 51954 | R84: 196522 | S84: 240404 | T84: 162225 | U84: 225485 | V84: 1.39 | W84: 23 | X84: 20 | Y84: 230943510 | Z84: EU | AA84: 1993040 | AB84: 3487820 | AC84: 5801170 | AD84: 391490 | AE84: 2491300 | AG84: 2953970 | AH84: 1103290 | AI84: 5836760 | AJ84: 16122270 | AK84: 4199620 | AL84: 10463460 | AM84: 1637140 | AN84: 1352420 | AO84: 640620 | AP84: 17759410 | AQ84: 2491300 | AR84: 16193450 | AS84: 26051880 | AT84: 0 | AU84: 284720 | AV84: 0 | AW84: 3025150 | AX84: 44273960 | AY84: 462670 | AZ84: 17367920 | BA84: 7509490 | BB84: 1565960 | BD84: 3986080 | BE84: 2562480 | BF84: 1423600 | BG84: 25055360 | BH84: 1957450 | BI84: 498260
B85: 45895 | C85: 45895.459 | D85: Auction 4. Period CAP3 EU | E85: T3PA | F85: successful | G85: 71.31 | H85: 69 | I85: 82.06 | J85: 71.58 | K85: 71.11 | L85: 3245500 | M85: 4798500 | N85: 90 | O85: 28 | P85: 3.91 | Q85: 53317 | R85: 208630 | S85: 263629 | T85: 202844 | U85: 284061 | V85: 1.48 | W85: 23 | X85: 16 | Y85: 231436605 | Z85: EU | AA85: 2067990 | AB85: 3565500 | AC85: 5669145 | AD85: 748755 | AE85: 3850740 | AG85: 1996680 | AH85: 1747095 | AI85: 7772790 | AJ85: 17720535 | AK85: 2781090 | AL85: 10518225 | AM85: 784410 | AN85: 2995020 | AO85: 855720 | AP85: 17791845 | AQ85: 35655 | AR85: 17720535 | AS85: 26099460 | AT85: 0 | AU85: 570480 | AV85: 0 | AW85: 427860 | AX85: 44354820 | AY85: 356550 | AZ85: 17399640 | BA85: 6275280 | BB85: 1354890 | BD85: 3708120 | BE85: 3173295 | BF85: 1247925 | BG85: 25101120 | BH85: 891375 | BI85: 1854060
B86: 45894 | C86: 45894.459 | D86: Auction 4. Period CAP3 EU | E86: T3PA | F86: successful | G86: 71.36 | H86: 64 | I86: 80 | J86: 71.51 | K86: 71.21 | L86: 3245500 | M86: 5042500 | N86: 91 | O86: 30 | P86: 4.14 | Q86: 55412 | R86: 229205 | S86: 286331 | T86: 202844 | U86: 297013 | V86: 1.55 | W86: 22 | X86: 16 | Y86: 231598880 | Z86: EU | AA86: 2069440 | AB86: 3568000 | AC86: 5673120 | AD86: 749280 | AE86: 3853440 | AG86: 1998080 | AH86: 1748320 | AI86: 7778240 | AJ86: 17732960 | AK86: 2783040 | AL86: 10525600 | AM86: 784960 | AN86: 2997120 | AO86: 856320 | AP86: 17804320 | AQ86: 35680 | AR86: 17732960 | AS86: 26117760 | AT86: 0 | AU86: 570880 | AV86: 0 | AW86: 428160 | AX86: 44385920 | AY86: 356800 | AZ86: 17411840 | BA86: 6279680 | BB86: 1355840 | BD86: 3710720 | BE86: 3175520 | BF86: 1248800 | BG86: 25118720 | BH86: 892000 | BI86: 1855360
B87: 45891 | C87: 45891.459 | D87: Auction 4. Period DE | E87: T3PA | F87: successful | G87: 72.05 | H87: 69.5 | I87: 80 | J87: 72.14 | K87: 71.85 | L87: 1607000 | M87: 2596000 | N87: 63 | O87: 19 | P87: 3 | Q87: 41206 | R87: 123619 | S87: 133129 | T87: 160700 | U87: 175114 | V87: 1.62 | W87: 21 | X87: 10 | Y87: 115784350 | Z87: DE | AF87: 115784350
B88: 45890 | C88: 45890.459 | D88: Auction 4. Period CAP3 EU | E88: T3PA | F88: successful | G88: 71.19 | H88: 60 | I88: 85 | J88: 71.43 | K88: 71.05 | L88: 3245500 | M88: 4433000 | N88: 84 | O88: 34 | P88: 3.23 | Q88: 52774 | R88: 170500 | S88: 223594 | T88: 162275 | U88: 207676 | V88: 1.37 | W88: 26 | X88: 20 | Y88: 231047145 | Z88: EU | AA88: 2064510 | AB88: 3559500 | AC88: 5659605 | AD88: 747495 | AE88: 3844260 | AG88: 1993320 | AH88: 1744155 | AI88: 7759710 | AJ88: 17690715 | AK88: 2776410 | AL88: 10500525 | AM88: 783090 | AN88: 2989980 | AO88: 854280 | AP88: 17761905 | AQ88: 35595 | AR88: 17690715 | AS88: 26055540 | AT88: 0 | AU88: 569520 | AV88: 0 | AW88: 427140 | AX88: 44280180 | AY88: 355950 | AZ88: 17370360 | BA88: 6264720 | BB88: 1352610 | BD88: 3701880 | BE88: 3167955 | BF88: 1245825 | BG88: 25058880 | BH88: 889875 | BI88: 1850940
B89: 45889 | C89: 45889.459 | D89: Auction 4. Period CAP3 PL | E89: T3PA | F89: successful | G89: 70.47 | H89: 68.05 | I89: 80 | J89: 70.54 | K89: 70.15 | L89: 2069000 | M89: 3428000 | N89: 80 | O89: 26 | P89: 3.48 | Q89: 42850 | R89: 149043 | S89: 139049 | T89: 137933 | U89: 159499 | V89: 1.66 | W89: 23 | X89: 15 | Y89: 145802430 | Z89: PL | BC89: 145802430
B90: 45888 | C90: 45888.459 | D90: Auction 4. Period CAP3 EU | E90: T3PA | F90: successful | G90: 71.37 | H90: 68 | I90: 85 | J90: 71.32 | K90: 71.11 | L90: 3245500 | M90: 5172000 | N90: 93 | O90: 27 | P90: 3.88 | Q90: 55613 | R90: 215500 | S90: 228329 | T90: 216367 | U90: 216361 | V90: 1.59 | W90: 24 | X90: 15 | Y90: 231631335 | Z90: EU | AA90: 2069730 | AB90: 3568500 | AC90: 5673915 | AD90: 749385 | AE90: 3853980 | AG90: 1998360 | AH90: 1748565 | AI90: 7779330 | AJ90: 17735445 | AK90: 2783430 | AL90: 10527075 | AM90: 785070 | AN90: 2997540 | AO90: 856440 | AP90: 17806815 | AQ90: 35685 | AR90: 17735445 | AS90: 26121420 | AT90: 0 | AU90: 570960 | AV90: 0 | AW90: 428220 | AX90: 44392140 | AY90: 356850 | AZ90: 17414280 | BA90: 6280560 | BB90: 1356030 | BD90: 3711240 | BE90: 3175965 | BF90: 1248975 | BG90: 25122240 | BH90: 892125 | BI90: 1855620
B91: 45887 | C91: 45887.459 | D91: Auction 4. Period CAP3 EU | E91: T3PA | F91: successful | G91: 70.21 | H91: 68.05 | I91: 120 | J91: 70.84 | K91: 69.95 | L91: 3245500 | M91: 5175000 | N91: 94 | O91: 29 | P91: 3.62 | Q91: 55053 | R91: 199038 | S91: 228243 | T91: 170816 | U91: 197793 | V91: 1.59 | W91: 26 | X91: 19 | Y91: 227866555 | Z91: EU | AA91: 2036090 | AB91: 3510500 | AC91: 5581695 | AD91: 737205 | AE91: 3791340 | AG91: 1965880 | AH91: 1720145 | AI91: 7652890 | AJ91: 17447185 | AK91: 2738190 | AL91: 10355975 | AM91: 772310 | AN91: 2948820 | AO91: 842520 | AP91: 17517395 | AQ91: 35105 | AR91: 17447185 | AS91: 25696860 | AT91: 0 | AU91: 561680 | AV91: 0 | AW91: 421260 | AX91: 43670620 | AY91: 351050 | AZ91: 17131240 | BA91: 6178480 | BB91: 1333990 | BD91: 3650920 | BE91: 3124345 | BF91: 1228675 | BG91: 24713920 | BH91: 877625 | BI91: 1825460
B92: 45884 | C92: 45884.459 | D92: Auction 4. Period DE | E92: T3PA | F92: successful | G92: 70.13 | H92: 65 | I92: 80 | J92: 70.03 | K92: 69.92 | L92: 1607000 | M92: 3512500 | N92: 76 | O92: 18 | P92: 3.8 | Q92: 46217 | R92: 175625 | S92: 170176 | T92: 123615 | U92: 137252 | V92: 2.19 | W92: 20 | X92: 13 | Y92: 112698910 | Z92: DE | AF92: 112698910
B93: 45883 | C93: 45883.459 | D93: Auction 4. Period CAP3 EU | E93: T3PA | F93: successful | G93: 70.54 | H93: 69.2 | I93: 80 | J93: 71.03 | K93: 70.49 | L93: 3245500 | M93: 4824500 | N93: 83 | O93: 34 | P93: 3.46 | Q93: 58127 | R93: 201021 | S93: 255152 | T93: 180306 | U93: 226187 | V93: 1.49 | W93: 24 | X93: 18 | Y93: 228937570 | Z93: EU | AA93: 2045660 | AB93: 3527000 | AC93: 5607930 | AD93: 740670 | AE93: 3809160 | AG93: 1975120 | AH93: 1728230 | AI93: 7688860 | AJ93: 17529190 | AK93: 2751060 | AL93: 10404650 | AM93: 775940 | AN93: 2962680 | AO93: 846480 | AP93: 17599730 | AQ93: 35270 | AR93: 17529190 | AS93: 25817640 | AT93: 0 | AU93: 564320 | AV93: 0 | AW93: 423240 | AX93: 43875880 | AY93: 352700 | AZ93: 17211760 | BA93: 6207520 | BB93: 1340260 | BD93: 3668080 | BE93: 3139030 | BF93: 1234450 | BG93: 24830080 | BH93: 881750 | BI93: 1834040
B94: 45881 | C94: 45881.459 | D94: Auction 4. Period CAP3 EU | E94: T3PA | F94: successful | G94: 71.3 | H94: 60 | I94: 80 | J94: 71.22 | K94: 71.06 | L94: 3245500 | M94: 5125000 | N94: 86 | O94: 28 | P94: 3.74 | Q94: 59593 | R94: 222826 | S94: 271979 | T94: 202844 | U94: 273250 | V94: 1.58 | W94: 23 | X94: 16 | Y94: 231404150 | Z94: EU | AA94: 2067700 | AB94: 3565000 | AC94: 5668350 | AD94: 748650 | AE94: 3850200 | AG94: 1996400 | AH94: 1746850 | AI94: 7771700 | AJ94: 17718050 | AK94: 2780700 | AL94: 10516750 | AM94: 784300 | AN94: 2994600 | AO94: 855600 | AP94: 17789350 | AQ94: 35650 | AR94: 17718050 | AS94: 26095800 | AT94: 0 | AU94: 570400 | AV94: 0 | AW94: 427800 | AX94: 44348600 | AY94: 356500 | AZ94: 17397200 | BA94: 6274400 | BB94: 1354700 | BD94: 3707600 | BE94: 3172850 | BF94: 1247750 | BG94: 25097600 | BH94: 891250 | BI94: 1853800
B95: 45880 | C95: 45880.459 | D95: Auction 4. Period CAP3 EU | E95: T3PA | F95: successful | G95: 72.18 | H95: 70.63 | I95: 80 | J95: 72.26 | K95: 71.91 | L95: 3245500 | M95: 4734000 | N95: 81 | O95: 25 | P95: 4.26 | Q95: 58444 | R95: 249158 | S95: 309278 | T95: 249654 | U95: 333843 | V95: 1.46 | W95: 19 | X95: 13 | Y95: 234260190 | Z95: EU | AA95: 2093220 | AB95: 3609000 | AC95: 5738310 | AD95: 757890 | AE95: 3897720 | AG95: 2021040 | AH95: 1768410 | AI95: 7867620 | AJ95: 17936730 | AK95: 2815020 | AL95: 10646550 | AM95: 793980 | AN95: 3031560 | AO95: 866160 | AP95: 18008910 | AQ95: 36090 | AR95: 17936730 | AS95: 26417880 | AT95: 0 | AU95: 577440 | AV95: 0 | AW95: 433080 | AX95: 44895960 | AY95: 360900 | AZ95: 17611920 | BA95: 6351840 | BB95: 1371420 | BD95: 3753360 | BE95: 3212010 | BF95: 1263150 | BG95: 25407360 | BH95: 902250 | BI95: 1876680
B96: 45877 | C96: 45877.459 | D96: Auction 4. Period DE | E96: T3PA | F96: successful | G96: 72.14 | H96: 50 | I96: 80 | J96: 71.72 | K96: 71.87 | L96: 1607000 | M96: 2685500 | N96: 81 | O96: 21 | P96: 3.86 | Q96: 33154 | R96: 127881 | S96: 161492 | T96: 133917 | U96: 204643 | V96: 1.67 | W96: 21 | X96: 12 | Y96: 115928980 | Z96: DE | AF96: 115928980
B97: 45876 | C97: 45876.459 | D97: Auction 4. Period CAP3 EU | E97: T3PA | F97: successful | G97: 70.1 | H97: 68 | I97: 120 | J97: 70.76 | K97: 69.88 | L97: 3245500 | M97: 5493500 | N97: 93 | O97: 28 | P97: 4.04 | Q97: 59070 | R97: 238848 | S97: 352314 | T97: 180306 | U97: 328712 | V97: 1.69 | W97: 23 | X97: 18 | Y97: 227509550 | Z97: EU | AA97: 2032900 | AB97: 3505000 | AC97: 5572950 | AD97: 736050 | AE97: 3785400 | AG97: 1962800 | AH97: 1717450 | AI97: 7640900 | AJ97: 17419850 | AK97: 2733900 | AL97: 10339750 | AM97: 771100 | AN97: 2944200 | AO97: 841200 | AP97: 17489950 | AQ97: 35050 | AR97: 17419850 | AS97: 25656600 | AT97: 0 | AU97: 560800 | AV97: 0 | AW97: 420600 | AX97: 43602200 | AY97: 350500 | AZ97: 17104400 | BA97: 6168800 | BB97: 1331900 | BD97: 3645200 | BE97: 3119450 | BF97: 1226750 | BG97: 24675200 | BH97: 876250 | BI97: 1822600
B98: 45875 | C98: 45875.459 | D98: Auction 4. Period CAP3 PL | E98: T3PA | F98: successful | G98: 70.74 | H98: 68 | I98: 72.88 | J98: 70.56 | K98: 70.52 | L98: 2072500 | M98: 3621000 | N98: 83 | O98: 18 | P98: 3.77 | Q98: 43627 | R98: 164591 | S98: 219581 | T98: 172708 | U98: 230181 | V98: 1.75 | W98: 22 | X98: 12 | Y98: 146608650 | Z98: PL | BC98: 146608650
B99: 45874 | C99: 45874.459 | D99: Auction 4. Period CAP3 EU | E99: T3PA | F99: successful | G99: 70.07 | H99: 68.9 | I99: 80 | J99: 70.26 | K99: 69.83 | L99: 3245500 | M99: 5202000 | N99: 88 | O99: 23 | P99: 4.63 | Q99: 59114 | R99: 273789 | S99: 325525 | T99: 231821 | U99: 271413 | V99: 1.6 | W99: 19 | X99: 14 | Y99: 227412185 | Z99: EU | AA99: 2032030 | AB99: 3503500 | AC99: 5570565 | AD99: 735735 | AE99: 3783780 | AG99: 1961960 | AH99: 1716715 | AI99: 7637630 | AJ99: 17412395 | AK99: 2732730 | AL99: 10335325 | AM99: 770770 | AN99: 2942940 | AO99: 840840 | AP99: 17482465 | AQ99: 35035 | AR99: 17412395 | AS99: 25645620 | AT99: 0 | AU99: 560560 | AV99: 0 | AW99: 420420 | AX99: 43583540 | AY99: 350350 | AZ99: 17097080 | BA99: 6166160 | BB99: 1331330 | BD99: 3643640 | BE99: 3118115 | BF99: 1226225 | BG99: 24664640 | BH99: 875875 | BI99: 1821820
B100: 45873 | C100: 45873.459 | D100: Auction 4. Period CAP3 EU | E100: T3PA | F100: successful | G100: 69.52 | H100: 68 | I100: 80 | J100: 70.04 | K100: 69.44 | L100: 3245500 | M100: 4761500 | N100: 105 | O100: 48 | P100: 4.57 | Q100: 45348 | R100: 207022 | S100: 316887 | T100: 154548 | U100: 298322 | V100: 1.47 | W100: 23 | X100: 21 | Y100: 225627160 | Z100: EU | AA100: 2016080 | AB100: 3476000 | AC100: 5526840 | AD100: 729960 | AE100: 3754080 | AG100: 1946560 | AH100: 1703240 | AI100: 7577680 | AJ100: 17275720 | AK100: 2711280 | AL100: 10254200 | AM100: 764720 | AN100: 2919840 | AO100: 834240 | AP100: 17345240 | AQ100: 34760 | AR100: 17275720 | AS100: 25444320 | AT100: 0 | AU100: 556160 | AV100: 0 | AW100: 417120 | AX100: 43241440 | AY100: 347600 | AZ100: 16962880 | BA100: 6117760 | BB100: 1320880 | BD100: 3615040 | BE100: 3093640 | BF100: 1216600 | BG100: 24471040 | BH100: 869000 | BI100: 1807520
B101: 45870 | C101: 45870.459 | D101: Auction 4. Period DE | E101: T3PA | F101: successful | G101: 71.14 | H101: 69.5 | I101: 80 | J101: 71.47 | K101: 71.14 | L101: 1607000 | M101: 2813000 | N101: 71 | O101: 36 | P101: 3.94 | Q101: 39620 | R101: 156278 | S101: 204433 | T101: 100438 | U101: 157979 | V101: 1.75 | W101: 18 | X101: 16 | Y101: 114321980 | Z101: DE | AF101: 114321980
B102: 45869 | C102: 45869.459 | D102: Auction 4. Period CAP3 EU | E102: T3PA | F102: successful | G102: 72 | H102: 63.99 | I102: 80 | J102: 72.01 | K102: 72 | L102: 3245500 | M102: 4861500 | N102: 95 | O102: 47 | P102: 3.8 | Q102: 51174 | R102: 194460 | S102: 297088 | T102: 147523 | U102: 278261 | V102: 1.5 | W102: 25 | X102: 22 | Y102: 233676000 | Z102: EU | AA102: 2088000 | AB102: 3600000 | AC102: 5724000 | AD102: 756000 | AE102: 3888000 | AG102: 2016000 | AH102: 1764000 | AI102: 7848000 | AJ102: 17892000 | AK102: 2808000 | AL102: 10620000 | AM102: 792000 | AN102: 3024000 | AO102: 864000 | AP102: 17964000 | AQ102: 36000 | AR102: 17892000 | AS102: 26352000 | AT102: 0 | AU102: 576000 | AV102: 0 | AW102: 432000 | AX102: 44784000 | AY102: 360000 | AZ102: 17568000 | BA102: 6336000 | BB102: 1368000 | BD102: 3744000 | BE102: 3204000 | BF102: 1260000 | BG102: 25344000 | BH102: 900000 | BI102: 1872000
B103: 45867 | C103: 45867.459 | D103: Auction 4. Period CAP3 EU | E103: T3PA | F103: successful | G103: 70.53 | H103: 64 | I103: 80 | J103: 70.51 | K103: 70.31 | L103: 3245500 | M103: 5473000 | N103: 87 | O103: 29 | P103: 3.78 | Q103: 62908 | R103: 237957 | S103: 326818 | T103: 190912 | U103: 334781 | V103: 1.69 | W103: 23 | X103: 17 | Y103: 228905115 | Z103: EU | AA103: 2045370 | AB103: 3526500 | AC103: 5607135 | AD103: 740565 | AE103: 3808620 | AG103: 1974840 | AH103: 1727985 | AI103: 7687770 | AJ103: 17526705 | AK103: 2750670 | AL103: 10403175 | AM103: 775830 | AN103: 2962260 | AO103: 846360 | AP103: 17597235 | AQ103: 35265 | AR103: 17526705 | AS103: 25813980 | AT103: 0 | AU103: 564240 | AV103: 0 | AW103: 423180 | AX103: 43869660 | AY103: 352650 | AZ103: 17209320 | BA103: 6206640 | BB103: 1340070 | BD103: 3667560 | BE103: 3138585 | BF103: 1234275 | BG103: 24826560 | BH103: 881625 | BI103: 1833780
...

Sheet Inflation and WACC
B2: Denmark
D3: 2006M04 | E3: 2006M05 | F3: 2006M06 | G3: 2006M07 | H3: 2006M08 | I3: 2006M09 | J3: 2006M10 | K3: 2006M11 | L3: 2006M12 | M3: 2007M01 | N3: 2007M02 | O3: 2007M03 | P3: 2007M04 | Q3: 2007M05 | R3: 2007M06 | S3: 2007M07 | T3: 2007M08 | U3: 2007M09 | V3: 2007M10 | W3: 2007M11 | X3: 2007M12 | Y3: 2008M01 | Z3: 2008M02 | AA3: 2008M03 | AB3: 2008M04 | AC3: 2008M05 | AD3: 2008M06 | AE3: 2008M07 | AF3: 2008M08 | AG3: 2008M09 | AH3: 2008M10 | AI3: 2008M11 | AJ3: 2008M12 | AK3: 2009M01 | AL3: 2009M02 | AM3: 2009M03 | AN3: 2009M04 | AO3: 2009M05 | AP3: 2009M06 | AQ3: 2009M07 | AR3: 2009M08 | AS3: 2009M09 | AT3: 2009M10 | AU3: 2009M11 | AV3: 2009M12 | AW3: 2010M01 | AX3: 2010M02 | AY3: 2010M03 | AZ3: 2010M04 | BA3: 2010M05 | BB3: 2010M06 | BC3: 2010M07 | BD3: 2010M08 | BE3: 2010M09 | BF3: 2010M10 | BG3: 2010M11 | BH3: 2010M12 | BI3: 2011M01 | BJ3: 2011M02 | BK3: 2011M03 | BL3: 2011M04 | BM3: 2011M05 | BN3: 2011M06 | BO3: 2011M07 | BP3: 2011M08 | BQ3: 2011M09 | BR3: 2011M10 | BS3: 2011M11 | BT3: 2011M12 | BU3: 2012M01 | BV3: 2012M02 | BW3: 2012M03 | BX3: 2012M04 | BY3: 2012M05 | BZ3: 2012M06 | CA3: 2012M07 | CB3: 2012M08 | CC3: 2012M09 | CD3: 2012M10 | CE3: 2012M11 | CF3: 2012M12 | CG3: 2013M01 | CH3: 2013M02 | CI3: 2013M03 | CJ3: 2013M04 | CK3: 2013M05 | CL3: 2013M06 | CM3: 2013M07 | CN3: 2013M08 | CO3: 2013M09 | CP3: 2013M10 | CQ3: 2013M11 | CR3: 2013M12 | CS3: 2014M01 | CT3: 2014M02 | CU3: 2014M03 | CV3: 2014M04 | CW3: 2014M05 | CX3: 2014M06 | CY3: 2014M07 | CZ3: 2014M08 | DA3: 2014M09 | DB3: 2014M10 | DC3: 2014M11 | DD3: 2014M12 | DE3: 2015M01 | DF3: 2015M02 | DG3: 2015M03 | DH3: 2015M04 | DI3: 2015M05 | DJ3: 2015M06 | DK3: 2015M07 | DL3: 2015M08 | DM3: 2015M09 | DN3: 2015M10 | DO3: 2015M11 | DP3: 2015M12 | DQ3: 2016M01 | DR3: 2016M02 | DS3: 2016M03 | DT3: 2016M04 | DU3: 2016M05 | DV3: 2016M06 | DW3: 2016M07 | DX3: 2016M08 | DY3: 2016M09 | DZ3: 2016M10 | EA3: 2016M11 | EB3: 2016M12 | EC3: 2017M01 | ED3: 2017M02 | EE3: 2017M03 | EF3: 2017M04 | EG3: 2017M05 | EH3: 2017M06 | EI3: 2017M07 | EJ3: 2017M08 | EK3: 2017M09 | EL3: 2017M10 | EM3: 2017M11 | EN3: 2017M12 | EO3: 2018M01 | EP3: 2018M02 | EQ3: 2018M03 | ER3: 2018M04 | ES3: 2018M05 | ET3: 2018M06 | EU3: 2018M07 | EV3: 2018M08 | EW3: 2018M09 | EX3: 2018M10 | EY3: 2018M11 | EZ3: 2018M12 | FA3: 2019M01 | FB3: 2019M02 | FC3: 2019M03 | FD3: 2019M04 | FE3: 2019M05 | FF3: 2019M06 | FG3: 2019M07 | FH3: 2019M08 | FI3: 2019M09 | FJ3: 2019M10 | FK3: 2019M11 | FL3: 2019M12 | FM3: 2020M01 | FN3: 2020M02 | FO3: 2020M03 | FP3: 2020M04 | FQ3: 2020M05 | FR3: 2020M06 | FS3: 2020M07 | FT3: 2020M08 | FU3: 2020M09 | FV3: 2020M10 | FW3: 2020M11 | FX3: 2020M12 | FY3: 2021M01 | FZ3: 2021M02 | GA3: 2021M03 | GB3: 2021M04 | GC3: 2021M05 | GD3: 2021M06 | GE3: 2021M07 | GF3: 2021M08 | GG3: 2021M09 | GH3: 2021M10 | GI3: 2021M11 | GJ3: 2021M12 | GK3: 2022M01 | GL3: 2022M02 | GM3: 2022M03 | GN3: 2022M04 | GO3: 2022M05 | GP3: 2022M06 | GQ3: 2022M07 | GR3: 2022M08 | GS3: 2022M09 | GT3: 2022M10 | GU3: 2022M11 | GV3: 2022M12 | GW3: 2023M01 | GX3: 2023M02 | GY3: 2023M03 | GZ3: 2023M04 | HA3: 2023M05 | HB3: 2023M06 | HC3: 2023M07 | HD3: 2023M08 | HE3: 2023M09 | HF3: 2023M10 | HG3: 2023M11 | HH3: 2023M12 | HI3: 2024M01 | HJ3: 2024M02 | HK3: 2024M03 | HL3: 2024M04 | HM3: 2024M05 | HN3: 2024M06 | HO3: 2024M07 | HP3: 2024M08 | HQ3: 2024M09 | HR3: 2024M10 | HS3: 2024M11 | HT3: 2024M12 | HU3: 2025M01 | HV3: 2025M02 | HW3: 2025M03 | HX3: 2025M04 | HY3: 2025M05 | HZ3: 2025M06 | IA3: 2025M07 | IB3: 2025M08 | IC3: 2025M09 | ID3: 2025M10 | IE3: 2025M11 | IF3: 2025M12 | IG3: 2026M01 | IH3: 2026M02 | II3: 2026M03 | IJ3: 2026M04
B4: Percentage change compared to same month the year before (per cent) | C4: 00 Consumer price index, total | D4: 1.9 | E4: 2 | F4: 2.1 | G4: 2 | H4: 2 | I4: 1.6 | J4: 1.5 | K4: 1.8 | L4: 1.7 | M4: 1.8 | N4: 1.9 | O4: 2 | P4: 1.7 | Q4: 1.8 | R4: 1.4 | S4: 1.2 | T4: 1 | U4: 1.3 | V4: 1.7 | W4: 2.4 | X4: 2.4 | Y4: 2.9 | Z4: 3.1 | AA4: 3.1 | AB4: 3.2 | AC4: 3.4 | AD4: 3.8 | AE4: 4 | AF4: 4.4 | AG4: 4.2 | AH4: 3.7 | AI4: 2.7 | AJ4: 2.4 | AK4: 1.8 | AL4: 1.9 | AM4: 1.7 | AN4: 1.3 | AO4: 1.3 | AP4: 1.2 | AQ4: 1 | AR4: 1.1 | AS4: 0.8 | AT4: 1 | AU4: 1.3 | AV4: 1.4 | AW4: 2 | AX4: 2 | AY4: 2.3 | AZ4: 2.5 | BA4: 2.1 | BB4: 1.8 | BC4: 2.3 | BD4: 2.4 | BE4: 2.6 | BF4: 2.4 | BG4: 2.5 | BH4: 2.8 | BI4: 2.7 | BJ4: 2.7 | BK4: 2.7 | BL4: 2.9 | BM4: 3.1 | BN4: 3 | BO4: 3 | BP4: 2.6 | BQ4: 2.5 | BR4: 2.8 | BS4: 2.6 | BT4: 2.5 | BU4: 2.8 | BV4: 2.8 | BW4: 2.7 | BX4: 2.3 | BY4: 2.2 | BZ4: 2.2 | CA4: 2.3 | CB4: 2.7 | CC4: 2.6 | CD4: 2.3 | CE4: 2.3 | CF4: 2 | CG4: 1.2 | CH4: 1.2 | CI4: 0.9 | CJ4: 0.8 | CK4: 0.9 | CL4: 0.9 | CM4: 0.7 | CN4: 0.4 | CO4: 0.5 | CP4: 0.6 | CQ4: 0.6 | CR4: 0.8 | CS4: 1 | CT4: 0.5 | CU4: 0.4 | CV4: 0.7 | CW4: 0.5 | CX4: 0.6 | CY4: 0.7 | CZ4: 0.5 | DA4: 0.5 | DB4: 0.5 | DC4: 0.5 | DD4: 0.3 | DE4: -0.1 | DF4: 0.3 | DG4: 0.6 | DH4: 0.6 | DI4: 0.6 | DJ4: 0.6 | DK4: 0.7 | DL4: 0.6 | DM4: 0.5 | DN4: 0.4 | DO4: 0.3 | DP4: 0.5 | DQ4: 0.6 | DR4: 0.3 | DS4: -0.1 | DT4: 0 | DU4: 0.2 | DV4: 0.3 | DW4: 0.3 | DX4: 0.3 | DY4: 0 | DZ4: 0.3 | EA4: 0.4 | EB4: 0.5 | EC4: 0.9 | ED4: 1 | EE4: 1 | EF4: 1.1 | EG4: 0.8 | EH4: 0.6 | EI4: 1.5 | EJ4: 1.5 | EK4: 1.6 | EL4: 1.5 | EM4: 1.3 | EN4: 0.9 | EO4: 0.7 | EP4: 0.6 | EQ4: 0.6 | ER4: 0.8 | ES4: 1.1 | ET4: 1.1 | EU4: 1.1 | EV4: 1 | EW4: 0.6 | EX4: 0.8 | EY4: 0.8 | EZ4: 0.8 | FA4: 1.3 | FB4: 1 | FC4: 1.2 | FD4: 0.9 | FE4: 0.7 | FF4: 0.5 | FG4: 0.3 | FH4: 0.4 | FI4: 0.5 | FJ4: 0.5 | FK4: 0.7 | FL4: 0.8 | FM4: 0.7 | FN4: 0.8 | FO4: 0.4 | FP4: 0 | FQ4: -0.1 | FR4: 0.3 | FS4: 0.5 | FT4: 0.5 | FU4: 0.5 | FV4: 0.4 | FW4: 0.5 | FX4: 0.5 | FY4: 0.5 | FZ4: 0.6 | GA4: 0.9 | GB4: 1.4 | GC4: 1.8 | GD4: 1.8 | GE4: 1.6 | GF4: 1.8 | GG4: 2.2 | GH4: 2.9 | GI4: 3.4 | GJ4: 3.1 | GK4: 4.4 | GL4: 4.8 | GM4: 5.4 | GN4: 6.7 | GO4: 7.4 | GP4: 8.2 | GQ4: 8.7 | GR4: 8.9 | GS4: 10 | GT4: 10.2 | GU4: 8.9 | GV4: 8.7 | GW4: 7.7 | GX4: 7.6 | GY4: 6.8 | GZ4: 5.3 | HA4: 2.9 | HB4: 2.4 | HC4: 3.2 | HD4: 2.4 | HE4: 0.9 | HF4: 0 | HG4: 0.6 | HH4: 0.7 | HI4: 1.2 | HJ4: 0.8 | HK4: 0.9 | HL4: 0.7 | HM4: 2.1 | HN4: 1.8 | HO4: 1.1 | HP4: 1.4 | HQ4: 1.3 | HR4: 1.6 | HS4: 1.7 | HT4: 1.9 | HU4: 1.5 | HV4: 2 | HW4: 1.5 | HX4: 1.6 | HY4: 1.6 | HZ4: 1.8 | IA4: 2.2 | IB4: 2 | IC4: 2.2 | ID4: 2.1 | IE4: 2.1 | IF4: 1.9 | IG4: 0.8 | IH4: 0.7 | II4: 1.2 | IJ4: 1.4
B6: Average Inflation Denmark 2016-2025 | C6: =AVERAGE(DQ4:IF4) -> 1.9533333 | D6: %
B8: Net price index by unit, commodity group and time
B9: Unit: -
D10: 2006M05 | E10: 2006M06 | F10: 2006M07 | G10: 2006M08 | H10: 2006M09 | I10: 2006M10 | J10: 2006M11 | K10: 2006M12 | L10: 2007M01 | M10: 2007M02 | N10: 2007M03 | O10: 2007M04 | P10: 2007M05 | Q10: 2007M06 | R10: 2007M07 | S10: 2007M08 | T10: 2007M09 | U10: 2007M10 | V10: 2007M11 | W10: 2007M12 | X10: 2008M01 | Y10: 2008M02 | Z10: 2008M03 | AA10: 2008M04 | AB10: 2008M05 | AC10: 2008M06 | AD10: 2008M07 | AE10: 2008M08 | AF10: 2008M09 | AG10: 2008M10 | AH10: 2008M11 | AI10: 2008M12 | AJ10: 2009M01 | AK10: 2009M02 | AL10: 2009M03 | AM10: 2009M04 | AN10: 2009M05 | AO10: 2009M06 | AP10: 2009M07 | AQ10: 2009M08 | AR10: 2009M09 | AS10: 2009M10 | AT10: 2009M11 | AU10: 2009M12 | AV10: 2010M01 | AW10: 2010M02 | AX10: 2010M03 | AY10: 2010M04 | AZ10: 2010M05 | BA10: 2010M06 | BB10: 2010M07 | BC10: 2010M08 | BD10: 2010M09 | BE10: 2010M10 | BF10: 2010M11 | BG10: 2010M12 | BH10: 2011M01 | BI10: 2011M02 | BJ10: 2011M03 | BK10: 2011M04 | BL10: 2011M05 | BM10: 2011M06 | BN10: 2011M07 | BO10: 2011M08 | BP10: 2011M09 | BQ10: 2011M10 | BR10: 2011M11 | BS10: 2011M12 | BT10: 2012M01 | BU10: 2012M02 | BV10: 2012M03 | BW10: 2012M04 | BX10: 2012M05 | BY10: 2012M06 | BZ10: 2012M07 | CA10: 2012M08 | CB10: 2012M09 | CC10: 2012M10 | CD10: 2012M11 | CE10: 2012M12 | CF10: 2013M01 | CG10: 2013M02 | CH10: 2013M03 | CI10: 2013M04 | CJ10: 2013M05 | CK10: 2013M06 | CL10: 2013M07 | CM10: 2013M08 | CN10: 2013M09 | CO10: 2013M10 | CP10: 2013M11 | CQ10: 2013M12 | CR10: 2014M01 | CS10: 2014M02 | CT10: 2014M03 | CU10: 2014M04 | CV10: 2014M05 | CW10: 2014M06 | CX10: 2014M07 | CY10: 2014M08 | CZ10: 2014M09 | DA10: 2014M10 | DB10: 2014M11 | DC10: 2014M12 | DD10: 2015M01 | DE10: 2015M02 | DF10: 2015M03 | DG10: 2015M04 | DH10: 2015M05 | DI10: 2015M06 | DJ10: 2015M07 | DK10: 2015M08 | DL10: 2015M09 | DM10: 2015M10 | DN10: 2015M11 | DO10: 2015M12 | DP10: 2016M01 | DQ10: 2016M02 | DR10: 2016M03 | DS10: 2016M04 | DT10: 2016M05 | DU10: 2016M06 | DV10: 2016M07 | DW10: 2016M08 | DX10: 2016M09 | DY10: 2016M10 | DZ10: 2016M11 | EA10: 2016M12 | EB10: 2017M01 | EC10: 2017M02 | ED10: 2017M03 | EE10: 2017M04 | EF10: 2017M05 | EG10: 2017M06 | EH10: 2017M07 | EI10: 2017M08 | EJ10: 2017M09 | EK10: 2017M10 | EL10: 2017M11 | EM10: 2017M12 | EN10: 2018M01 | EO10: 2018M02 | EP10: 2018M03 | EQ10: 2018M04 | ER10: 2018M05 | ES10: 2018M06 | ET10: 2018M07 | EU10: 2018M08 | EV10: 2018M09 | EW10: 2018M10 | EX10: 2018M11 | EY10: 2018M12 | EZ10: 2019M01 | FA10: 2019M02 | FB10: 2019M03 | FC10: 2019M04 | FD10: 2019M05 | FE10: 2019M06 | FF10: 2019M07 | FG10: 2019M08 | FH10: 2019M09 | FI10: 2019M10 | FJ10: 2019M11 | FK10: 2019M12 | FL10: 2020M01 | FM10: 2020M02 | FN10: 2020M03 | FO10: 2020M04 | FP10: 2020M05 | FQ10: 2020M06 | FR10: 2020M07 | FS10: 2020M08 | FT10: 2020M09 | FU10: 2020M10 | FV10: 2020M11 | FW10: 2020M12 | FX10: 2021M01 | FY10: 2021M02 | FZ10: 2021M03 | GA10: 2021M04 | GB10: 2021M05 | GC10: 2021M06 | GD10: 2021M07 | GE10: 2021M08 | GF10: 2021M09 | GG10: 2021M10 | GH10: 2021M11 | GI10: 2021M12 | GJ10: 2022M01 | GK10: 2022M02 | GL10: 2022M03 | GM10: 2022M04 | GN10: 2022M05 | GO10: 2022M06 | GP10: 2022M07 | GQ10: 2022M08 | GR10: 2022M09 | GS10: 2022M10 | GT10: 2022M11 | GU10: 2022M12 | GV10: 2023M01 | GW10: 2023M02 | GX10: 2023M03 | GY10: 2023M04 | GZ10: 2023M05 | HA10: 2023M06 | HB10: 2023M07 | HC10: 2023M08 | HD10: 2023M09 | HE10: 2023M10 | HF10: 2023M11 | HG10: 2023M12 | HH10: 2024M01 | HI10: 2024M02 | HJ10: 2024M03 | HK10: 2024M04 | HL10: 2024M05 | HM10: 2024M06 | HN10: 2024M07 | HO10: 2024M08 | HP10: 2024M09 | HQ10: 2024M10 | HR10: 2024M11 | HS10: 2024M12 | HT10: 2025M01 | HU10: 2025M02 | HV10: 2025M03 | HW10: 2025M04 | HX10: 2025M05 | HY10: 2025M06 | HZ10: 2025M07 | IA10: 2025M08 | IB10: 2025M09 | IC10: 2025M10 | ID10: 2025M11 | IE10: 2025M12 | IF10: 2026M01 | IG10: 2026M02 | IH10: 2026M03 | II10: 2026M04 | IJ10: 2026M05
B11: Percentage change compared to same month the year before (per cent) | C11: 00 Index of net prices, total | D11: 2.1 | E11: 2.3 | F11: 2.2 | G11: 2.2 | H11: 1.7 | I11: 1.6 | J11: 1.9 | K11: 1.8 | L11: 1.9 | M11: 2 | N11: 2.1 | O11: 1.8 | P11: 1.9 | Q11: 1.5 | R11: 1.4 | S11: 1.3 | T11: 1.6 | U11: 2.1 | V11: 2.8 | W11: 2.8 | X11: 3.3 | Y11: 3.4 | Z11: 3.4 | AA11: 3.6 | AB11: 3.9 | AC11: 4.3 | AD11: 4.4 | AE11: 4.7 | AF11: 4.4 | AG11: 3.9 | AH11: 2.9 | AI11: 2.6 | AJ11: 2 | AK11: 2.7 | AL11: 2.5 | AM11: 2.1 | AN11: 2 | AO11: 2 | AP11: 1.7 | AQ11: 1.9 | AR11: 1.6 | AS11: 1.8 | AT11: 2 | AU11: 2.2 | AV11: 2.3 | AW11: 1.7 | AX11: 2 | AY11: 2.1 | AZ11: 1.8 | BA11: 1.4 | BB11: 1.8 | BC11: 1.8 | BD11: 2.2 | BE11: 2 | BF11: 2.1 | BG11: 2.4 | BH11: 2.4 | BI11: 2.5 | BJ11: 2.5 | BK11: 2.9 | BL11: 2.9 | BM11: 2.8 | BN11: 2.9 | BO11: 2.5 | BP11: 2.5 | BQ11: 2.5 | BR11: 2.2 | BS11: 2.2 | BT11: 2.3 | BU11: 2.3 | BV11: 2.2 | BW11: 1.6 | BX11: 1.5 | BY11: 1.6 | BZ11: 1.6 | CA11: 2 | CB11: 1.9 | CC11: 1.9 | CD11: 1.9 | CE11: 1.6 | CF11: 1.2 | CG11: 1.2 | CH11: 1 | CI11: 0.8 | CJ11: 1 | CK11: 1 | CL11: 0.8 | CM11: 0.5 | CN11: 0.6 | CO11: 0.8 | CP11: 0.7 | CQ11: 0.9 | CR11: 0.9 | CS11: 0.7 | CT11: 0.5 | CU11: 0.9 | CV11: 0.7 | CW11: 0.8 | CX11: 0.9 | CY11: 0.7 | CZ11: 0.7 | DA11: 0.7 | DB11: 0.7 | DC11: 0.5 | DD11: 0.3 | DE11: 0.5 | DF11: 0.8 | DG11: 0.8 | DH11: 0.8 | DI11: 0.8 | DJ11: 0.9 | DK11: 0.7 | DL11: 0.7 | DM11: 0.6 | DN11: 0.5 | DO11: 0.7 | DP11: 0.8 | DQ11: 0.5 | DR11: 0.2 | DS11: 0.2 | DT11: 0.4 | DU11: 0.6 | DV11: 0.5 | DW11: 0.5 | DX11: 0.2 | DY11: 0.5 | DZ11: 0.6 | EA11: 0.7 | EB11: 1.1 | EC11: 1 | ED11: 1 | EE11: 1.2 | EF11: 0.9 | EG11: 0.7 | EH11: 1.7 | EI11: 1.7 | EJ11: 1.7 | EK11: 1.6 | EL11: 1.5 | EM11: 1.1 | EN11: 0.8 | EO11: 0.7 | EP11: 0.6 | EQ11: 0.8 | ER11: 1.1 | ES11: 1.1 | ET11: 1 | EU11: 0.9 | EV11: 0.7 | EW11: 0.8 | EX11: 0.8 | EY11: 0.8 | EZ11: 1.3 | FA11: 1.2 | FB11: 1.3 | FC11: 1.1 | FD11: 0.9 | FE11: 0.7 | FF11: 0.5 | FG11: 0.6 | FH11: 0.6 | FI11: 0.7 | FJ11: 0.8 | FK11: 1 | FL11: 0.9 | FM11: 0.9 | FN11: 0.5 | FO11: 0.2 | FP11: 0.1 | FQ11: 0.4 | FR11: 0.5 | FS11: 0.2 | FT11: 0.3 | FU11: 0.1 | FV11: 0 | FW11: 0 | FX11: 0.2 | FY11: 0.1 | FZ11: 0.5 | GA11: 0.9 | GB11: 1.3 | GC11: 1.2 | GD11: 1.2 | GE11: 1.5 | GF11: 2 | GG11: 2.6 | GH11: 3.3 | GI11: 3 | GJ11: 4 | GK11: 4.9 | GL11: 5.5 | GM11: 6.5 | GN11: 7.3 | GO11: 8.1 | GP11: 8.8 | GQ11: 9 | GR11: 10.1 | GS11: 10.3 | GT11: 9.1 | GU11: 9 | GV11: 8.8 | GW11: 8.2 | GX11: 7.4 | GY11: 6.3 | GZ11: 4.1 | HA11: 3.6 | HB11: 3.6 | HC11: 2.8 | HD11: 1.3 | HE11: 0.5 | HF11: 0.9 | HG11: 1 | HH11: 0.6 | HI11: 0.3 | HJ11: 0.4 | HK11: 0.1 | HL11: 1.4 | HM11: 1 | HN11: 1 | HO11: 1.2 | HP11: 1 | HQ11: 1.4 | HR11: 1.4 | HS11: 1.6 | HT11: 1.3 | HU11: 2 | HV11: 1.5 | HW11: 1.6 | HX11: 1.6 | HY11: 1.9 | HZ11: 2.2 | IA11: 2.1 | IB11: 2.3 | IC11: 2.2 | ID11: 2.2 | IE11: 2 | IF11: 1.7 | IG11: 1.6 | IH11: 2 | II11: 2.1 | IJ11: 2.7
B13: Average Net Price Index Denmark 2016-2025 | C13: =AVERAGE(DP11:IE11) -> 1.9916667 | D13: %
B15: Consumer price index: Germany, years
B16: Consumer price index for Germany
B17: Germany
B18: Year | C18: Consumer price index | E18: Annual change
C19: 2020=100 | E19: in (%)
B20: 1991 | C20: 61.9 | D20: e | E20: .
B21: 1992 | C21: 65 | D21: e | E21: 5 | F21: e
B22: 1993 | C22: 67.9 | D22: e | E22: 4.5 | F22: e
B23: 1994 | C23: 69.7 | D23: e | E23: 2.7 | F23: e
B24: 1995 | C24: 71 | D24: e | E24: 1.9 | F24: e
B25: 1996 | C25: 72 | D25: e | E25: 1.4 | F25: e
B26: 1997 | C26: 73.4 | D26: e | E26: 1.9 | F26: e
B27: 1998 | C27: 74 | D27: e | E27: 0.8 | F27: e
B28: 1999 | C28: 74.5 | D28: e | E28: 0.7 | F28: e
B29: 2000 | C29: 75.5 | D29: e | E29: 1.3 | F29: e
B30: 2001 | C30: 77 | D30: e | E30: 2 | F30: e
B31: 2002 | C31: 78.1 | D31: e | E31: 1.4 | F31: e
B32: 2003 | C32: 78.9 | D32: e | E32: 1 | F32: e
... B54: 2025 | C54: 121.9 | D54: e | E54: 2.2 | F54: e
B55: ______________
B57: © Statistisches Bundesamt (Destatis), 2026 | created: 2026-05-11 / 14:40:40
B59: Average Inflation Germany 2016-2025 | C59: =AVERAGE(E45:E54) -> 2.6 | D59: %
B60: Combined Inflation Denmark and Gerrmany 2016-2025 | C60: =AVERAGE(C59,C6) -> 2.2766667 | D60: %
B62: Real WACC | C62: 0.08 | D62: Cemcap
B63: Thesis Inflation Rate | C63: =1.5% -> 0.015 | D63: CATF
B64: Nominal WACC | C64: =(1+C62)*(1+C63)-1 -> 0.0962

Sheet Cost of CO2 Avoided
H4: Year | I4: 2025 | J4: 2026 | K4: 2027 | L4: 2028 | M4: 2029 | N4: 2030 | O4: 2031 | P4: 2032 | Q4: 2033 | R4: 2034 | S4: 2035 | T4: 2036 | U4: 2037 | V4: 2038 | W4: 2039 | X4: 2040 | Y4: 2041 | Z4: 2042 | AA4: 2043 | AB4: 2044 | AC4: 2045 | AD4: 2046 | AE4: 2047 | AF4: 2048 | AG4: 2049 | AH4: 2050 | AI4: 2051 | AJ4: 2052
H5: Year Number | I5: 0 | J5: 1 | K5: 2 | L5: 3 | M5: 4 | N5: 5 | O5: 6 | P5: 7 | Q5: 8 | R5: 9 | S5: 10 | T5: 11 | U5: 12 | V5: 13 | W5: 14 | X5: 15 | Y5: 16 | Z5: 17 | AA5: 18 | AB5: 19 | AC5: 20 | AD5: 21 | AE5: 22 | AF5: 23 | AG5: 24 | AH5: 25 | AI5: 26 | AJ5: 27
H6: Inflation Factor | I6: =1 -> 1 | J6: =(1+'Input Parameters'!$D$37)^J5 -> 1.015 | K6: =(1+'Input Parameters'!$D$37)^K5 -> 1.030225 | L6: =(1+'Input Parameters'!$D$37)^L5 -> 1.0456784 | M6: =(1+'Input Parameters'!$D$37)^M5 -> 1.0613636 | N6: =(1+'Input Parameters'!$D$37)^N5 -> 1.077284 | O6: =(1+'Input Parameters'!$D$37)^O5 -> 1.0934433 | P6: =(1+'Input Parameters'!$D$37)^P5 -> 1.1098449 | Q6: =(1+'Input Parameters'!$D$37)^Q5 -> 1.1264926 | ... AJ6: =(1+'Input Parameters'!$D$37)^AJ5 -> 1.4948002
H7: Inflation Factor Danish CO2 Tax | I7: =1 -> 1 | J7: 1 | K7: 1 | L7: 1 | M7: 1 | N7: 1 | O7: =N7*(1+'Inflation and WACC'!$C$63) -> 1.015 | P7: =O7*(1+'Inflation and WACC'!$C$63) -> 1.030225 | Q7: =P7*(1+'Inflation and WACC'!$C$63) -> 1.0456784 | R7: =Q7*(1+'Inflation and WACC'!$C$63) -> 1.0613636 | S7: =R7*(1+'Inflation and WACC'!$C$63) -> 1.077284 | T7: =S7*(1+'Inflation and WACC'!$C$63) -> 1.0934433 | U7: =T7*(1+'Inflation and WACC'!$C$63) -> 1.1098449 | V7: =U7*(1+'Inflation and WACC'!$C$63) -> 1.1264926 | ... AJ7: =AI7*(1+'Inflation and WACC'!$C$63) -> 1.3875637
B8: CCS Cost Parameters | H8: Capital Expenditures | I8: =SUM(I9:I10) -> 103387200 | J8: =SUM(J9:J10) -> 78703506 | K8: =SUM(K9:K10) -> 79884059 | L8: =SUM(L9:L10) -> 0 | M8: =SUM(M9:M10) -> 0 | N8: =SUM(N9:N10) -> 0 | O8: =SUM(O9:O10) -> 0 | P8: =SUM(P9:P10) -> 0 | ... AJ8: =SUM(AJ9:AJ10) -> 0
B9: Parameter | C9: Unit | D9: Value | E9: Source | H9: Capex | I9: =0.4*$D$10*1000000*I6 -> 103387200 | J9: =0.3*$D$10*1000000*J6 -> 78703506 | K9: =0.3*$D$10*1000000*K6 -> 79884059
B10: Capex | C10: mEuros | D10: ='Input Parameters'!D25*'Capture Model'!D7 -> 258.468 | E10: Calculated | H10: Investment Grant | I10: =IF($C$41="Yes",-Policies!$C$15*0.4,0) -> 0 | J10: =IF($C$41="Yes",-Policies!$C$15*0.3,0) -> 0 | K10: =IF($C$41="Yes",-Policies!$C$15*0.3,0) -> 0
B11: Annualized Capex | C11: mEuros/year | D11: =D10*'Input Parameters'!D40 -> 27.646907 | E11: Calculated | H11: Operational Expenditures | I11: =SUM(I12:I16) -> 0 | J11: =SUM(J12:J16) -> 0 | K11: =SUM(K12:K16) -> 0 | L11: =SUM(L12:L16) -> 1.0148549e+08 | M11: =SUM(M12:M16) -> 1.0221109e+08 | N11: =SUM(N12:N16) -> 1.0294758e+08 | O11: =SUM(O12:O16) -> 1.0369512e+08 | P11: =SUM(P12:P16) -> 1.0445386e+08 | ... AJ11: =SUM(AJ12:AJ16) -> 1.2226208e+08
B12: Fixed Opex | C12: mEuros/year | D12: ='Input Parameters'!D26*D10 -> 7.75404 | E12: Calculated | H12: Fixed Opex | I12: 0 | J12: 0 | K12: 0 | L12: =$D$12*1000000*L6 -> 8108231.9 | M12: =$D$12*1000000*M6 -> 8229855.4 | N12: =$D$12*1000000*N6 -> 8353303.3 | O12: =$D$12*1000000*O6 -> 8478602.8 | P12: =$D$12*1000000*P6 -> 8605781.8 | Q12: =$D$12*1000000*Q6 -> 8734868.6 | R12: =$D$12*1000000*R6 -> 8865891.6 | S12: =$D$12*1000000*S6 -> 8998880 | ... AJ12: =$D$12*1000000*AJ6 -> 11590740
B13: Variable Opex | C13: mEuros/year | D13: ='Input Parameters'!D27*'Capture Model'!D6/1000000 -> 2.1410245 | E13: Calculated | H13: Variable Opex - General and Amine Makeup | I13: 0 | J13: 0 | K13: 0 | L13: =($D$13)*1000000*L6 -> 2238823 | M13: =($D$13)*1000000*M6 -> 2272405.3 | N13: =($D$13)*1000000*N6 -> 2306491.4 | O13: =($D$13)*1000000*O6 -> 2341088.8 | P13: =($D$13)*1000000*P6 -> 2376205.1 | Q13: =($D$13)*1000000*Q6 -> 2411848.2 | R13: =($D$13)*1000000*R6 -> 2448025.9 | S13: =($D$13)*1000000*S6 -> 2484746.3 | ... AJ13: =($D$13)*1000000*AJ6 -> 3200403.8
B14: Gas | C14: mEuros/year | D14: =IF(C37="Germany",'Capture Model'!D22*'Input Parameters'!D15,'Capture Model'!D22*'Input Parameters'!D14)/1000 -> 32.799511 | E14: Calculated | H14: Variable Opex - Steam | I14: 0 | J14: 0 | K14: 0 | L14: =$D$14*1000000*L6 -> 34297739 | M14: =$D$14*1000000*M6 -> 34812205 | N14: =$D$14*1000000*N6 -> 35334388 | O14: =$D$14*1000000*O6 -> 35864404 | P14: =$D$14*1000000*P6 -> 36402370 | Q14: =$D$14*1000000*Q6 -> 36948406 | R14: =$D$14*1000000*R6 -> 37502632 | S14: =$D$14*1000000*S6 -> 38065171 | ... AJ14: =$D$14*1000000*AJ6 -> 49028714
B15: Electricity | C15: mEuros/year | D15: =IF(C37="Germany",'Capture Model'!D26*'Input Parameters'!D17,'Capture Model'!D26*'Input Parameters'!D16)/1000 -> 3.5659132 | E15: Calculated | H15: Variable Opex - Electricity | I15: 0 | J15: 0 | K15: 0 | L15: =$D$15*1000000*L6 -> 3728798.3 | M15: =$D$15*1000000*M6 -> 3784730.3 | N15: =$D$15*1000000*N6 -> 3841501.2 | O15: =$D$15*1000000*O6 -> 3899123.7 | P15: =$D$15*1000000*P6 -> 3957610.6 | Q15: =$D$15*1000000*Q6 -> 4016974.8 | R15: =$D$15*1000000*R6 -> 4077229.4 | S15: =$D$15*1000000*S6 -> 4138387.8 | ... AJ15: =$D$15*1000000*AJ6 -> 5330327.7
B16: Transport and Storage | C16: mEuros/year | D16: =I39*'Capture Model'!D6/1000000 -> 53.111896 | E16: Calculated | H16: Transport and Storage | I16: 0 | J16: 0 | K16: 0 | L16: =IF($C$39="Yes",$D$16*1000000,0) -> 53111896 | M16: =IF($C$39="Yes",$D$16*1000000,0) -> 53111896 | N16: =IF($C$39="Yes",$D$16*1000000,0) -> 53111896 | O16: =IF($C$39="Yes",$D$16*1000000,0) -> 53111896 | P16: =IF($C$39="Yes",$D$16*1000000,0) -> 53111896 | Q16: =IF($C$39="Yes",$D$16*1000000,0) -> 53111896 | R16: =IF($C$39="Yes",$D$16*1000000,0) -> 53111896 | S16: =IF($C$39="Yes",$D$16*1000000,0) -> 53111896 | ... AJ16: =IF($C$39="Yes",$D$16*1000000,0) -> 53111896
B17: T&S costs | C17: Euros/tCO2 | D17: {=_xlfn.XLOOKUP(1,('Transport and Storage'!R5:R16=C37)*('Transport and Storage'!S5:S16=C38)*('Transport and Storage'!T5:T16=C40),'Transport and Storage'!U5:U16)} -> 71.939625 | E17: Calculated | H17: Revenue | I17: =SUM(I18:I21) -> 0 | J17: =SUM(J18:J21) -> 0 | K17: =SUM(K18:K21) -> 0 | L17: =SUM(L18:L22) -> -43807345 | M17: =SUM(M18:M22) -> -43807345 | N17: =SUM(N18:N22) -> -43807345 | O17: =SUM(O18:O22) -> -43807345 | P17: =SUM(P18:P22) -> -43807345 | Q17: =SUM(Q18:Q22) -> -43807345 | R17: =SUM(R18:R22) -> -43807345 | S17: =SUM(S18:S22) -> -43807345 | ... AJ17: =SUM(AJ18:AJ22) -> -43807345
B18: Depreciation | C18: mEuros/year | D18: =SUM(I9:K9)/'Input Parameters'!D35/1000000 -> 10.478991 | E18: Straight Line | H18: Cashflow ETS Revenue | I18: 0 | J18: 0 | K18: 0 | L18: =-$D$19*L36 -> -43807345 | M18: =-$D$19*M36 -> -43807345 | N18: =-$D$19*N36 -> -43807345 | O18: =-$D$19*O36 -> -43807345 | P18: =-$D$19*P36 -> -43807345 | Q18: =-$D$19*Q36 -> -43807345 | R18: =-$D$19*R36 -> -43807345 | S18: =-$D$19*S36 -> -43807345 | ... AJ18: =-$D$19*AJ36 -> -43807345
B19: ETS Price | C19: Euros/tCO2 | D19: =ETS!C5 -> 72.16 | E19: Calculated | H19: CO2 Tax Savings | I19: 0 | J19: 0 | K19: 0 | L19: =IF($C$44="Yes",-IF(C37="Denmark",'Input Parameters'!D47*L36,0),0) -> 0 | M19: =IF($C$44="Yes",-IF(C37="Denmark",'Input Parameters'!D48*M36,0),0) -> 0 | N19: =IF($C$44="Yes",-IF($C$37="Denmark",'Input Parameters'!$D$49*N36*N7,0),0) -> 0 | O19: =IF($C$44="Yes",-IF($C$37="Denmark",'Input Parameters'!$D$49*O36*O7,0),0) -> 0 | P19: =IF($C$44="Yes",-IF($C$37="Denmark",'Input Parameters'!$D$49*P36*P7,0),0) -> 0 | Q19: =IF($C$44="Yes",-IF($C$37="Denmark",'Input Parameters'!$D$49*Q36*Q7,0),0) -> 0 | R19: =IF($C$44="Yes",-IF($C$37="Denmark",'Input Parameters'!$D$49*R36*R7,0),0) -> 0 | S19: =IF($C$44="Yes",-IF($C$37="Denmark",'Input Parameters'!$D$49*S36*S7,0),0) -> 0 | T19: =IF($C$44="Yes",-IF($C$37="Denmark",'Input Parameters'!$D$49*T36*T7,0),0) -> 0 | U19: =IF($C$44="Yes",-IF($C$37="Denmark",'Input Parameters'!$D$49*U36*U7,0),0) -> 0 | ... AJ19: =IF($C$44="Yes",-IF($C$37="Denmark",'Input Parameters'!$D$49*AJ36*AJ7,0),0) -> 0
H20: Cashflow CCfD Germany | I20: 0 | J20: 0 | K20: 0 | L20: =-IF($C$42="Yes",IF($C$37="Germany",IF(L4<2043,(Policies!$C$21-$D$19)*L36,0),0),0) -> 0 | M20: =-IF($C$42="Yes",IF($C$37="Germany",IF(M4<2043,(Policies!$C$21-$D$19)*M36,0),0),0) -> 0 | N20: =-IF($C$42="Yes",IF($C$37="Germany",IF(N4<2043,(Policies!$C$21-$D$19)*N36,0),0),0) -> 0 | O20: =-IF($C$42="Yes",IF($C$37="Germany",IF(O4<2043,(Policies!$C$21-$D$19)*O36,0),0),0) -> 0 | P20: =-IF($C$42="Yes",IF($C$37="Germany",IF(P4<2043,(Policies!$C$21-$D$19)*P36,0),0),0) -> 0 | Q20: =-IF($C$42="Yes",IF($C$37="Germany",IF(Q4<2043,(Policies!$C$21-$D$19)*Q36,0),0),0) -> 0 | R20: =-IF($C$42="Yes",IF($C$37="Germany",IF(R4<2043,(Policies!$C$21-$D$19)*R36,0),0),0) -> 0 | S20: =-IF($C$42="Yes",IF($C$37="Germany",IF(S4<2043,(Policies!$C$21-$D$19)*S36,0),0),0) -> 0 | ... AJ20: =-IF($C$42="Yes",IF($C$37="Germany",IF(AJ4<2043,(Policies!$C$21-$D$19)*AJ36,0),0),0) -> 0
H21: Cashflow CCfD Denmark | I21: 0 | J21: 0 | K21: 0 | L21: =-IF($C$42="Yes",IF($C$37="Denmark",IF(L4<(2028+Policies!$C$28),Policies!$C$27*L36*L6,0),0),0) -> 0 | M21: =-IF($C$42="Yes",IF($C$37="Denmark",IF(M4<(2028+Policies!$C$28),Policies!$C$27*M36*M6,0),0),0) -> 0 | N21: =-IF($C$42="Yes",IF($C$37="Denmark",IF(N4<(2028+Policies!$C$28),Policies!$C$27*N36*N6,0),0),0) -> 0 | O21: =-IF($C$42="Yes",IF($C$37="Denmark",IF(O4<(2028+Policies!$C$28),Policies!$C$27*O36*O6,0),0),0) -> 0 | P21: =-IF($C$42="Yes",IF($C$37="Denmark",IF(P4<(2028+Policies!$C$28),Policies!$C$27*P36*P6,0),0),0) -> 0 | Q21: =-IF($C$42="Yes",IF($C$37="Denmark",IF(Q4<(2028+Policies!$C$28),Policies!$C$27*Q36*Q6,0),0),0) -> 0 | R21: =-IF($C$42="Yes",IF($C$37="Denmark",IF(R4<(2028+Policies!$C$28),Policies!$C$27*R36*R6,0),0),0) -> 0 | S21: =-IF($C$42="Yes",IF($C$37="Denmark",IF(S4<(2028+Policies!$C$28),Policies!$C$27*S36*S6,0),0),0) -> 0 | ... AJ21: =-IF($C$42="Yes",IF($C$37="Denmark",IF(AJ4<(2028+Policies!$C$28),Policies!$C$27*AJ36*AJ6,0),0),0) -> 0
H22: T&S Support | I22: 0 | J22: 0 | K22: 0 | L22: =-IF($C$43="Yes",Policies!$C$33*'Capture Model'!$D$6,0) -> 0 | M22: =-IF($C$43="Yes",Policies!$C$33*'Capture Model'!$D$6,0) -> 0 | N22: =-IF($C$43="Yes",Policies!$C$33*'Capture Model'!$D$6,0) -> 0 | O22: =-IF($C$43="Yes",Policies!$C$33*'Capture Model'!$D$6,0) -> 0 | P22: =-IF($C$43="Yes",Policies!$C$33*'Capture Model'!$D$6,0) -> 0 | Q22: =-IF($C$43="Yes",Policies!$C$33*'Capture Model'!$D$6,0) -> 0 | R22: =-IF($C$43="Yes",Policies!$C$33*'Capture Model'!$D$6,0) -> 0 | S22: =-IF($C$43="Yes",Policies!$C$33*'Capture Model'!$D$6,0) -> 0 | ... Z22: =-IF($C$43="Yes",Policies!$C$33*'Capture Model'!$D$6,0) -> 0 | AA22: 0 | AB22: 0 | AC22: 0 | AD22: 0 | AE22: 0 | AF22: 0 | AG22: 0 | AH22: 0 | AI22: 0 | AJ22: 0
B23: CCS Cost Parameters | H23: EBITDA | I23: =I8 -> 103387200 | J23: =J8 -> 78703506 | K23: =K8 -> 79884059 | L23: =SUM(L24:L25) -> 57678144 | M23: =SUM(M24:M25) -> 58403747 | N23: =SUM(N24:N25) -> 59140235 | O23: =SUM(O24:O25) -> 59887771 | P23: =SUM(P24:P25) -> 60646519 | Q23: =SUM(Q24:Q25) -> 61416648 | R23: =SUM(R24:R25) -> 62198330 | S23: =SUM(S24:S25) -> 62991737 | ... AJ23: =SUM(AJ24:AJ25) -> 78454737
B24: Parameter | C24: Euro/tCO2 avoided | D24: Value | E24: Source | H24: Operational Expenditures | I24: =I11 -> 0 | J24: =J11 -> 0 | K24: =K11 -> 0 | L24: =L11 -> 1.0148549e+08 | M24: =M11 -> 1.0221109e+08 | N24: =N11 -> 1.0294758e+08 | O24: =O11 -> 1.0369512e+08 | P24: =P11 -> 1.0445386e+08 | ... AJ24: =AJ11 -> 1.2226208e+08
B25: Capex | C25: =(NPV('Input Parameters'!$D$36,J8:AJ8)+I8)/$C$52 -> 53.335184 | D25: =C25/$C$53 -> 0.22412552 | E25: Calculated | H25: Revenue | I25: =I17 -> 0 | J25: =J17 -> 0 | K25: =K17 -> 0 | L25: =L17 -> -43807345 | M25: =M17 -> -43807345 | N25: =N17 -> -43807345 | O25: =O17 -> -43807345 | P25: =P17 -> -43807345 | ... AJ25: =AJ17 -> -43807345
B26: Fixed Opex | C26: =(NPV('Input Parameters'!$D$36,J12:AJ12)+I12)/$C$52 -> 15.661894 | D26: =C26/$C$53 -> 0.06581453 | E26: Calculated | H26: EBIT | I26: =SUM(I27:I28) -> 103387200 | J26: =SUM(J27:J28) -> 78703506 | K26: =SUM(K27:K28) -> 79884059 | L26: =SUM(L27:L28) -> 68157134 | M26: =SUM(M27:M28) -> 68882738 | N26: =SUM(N27:N28) -> 69619226 | O26: =SUM(O27:O28) -> 70366761 | P26: =SUM(P27:P28) -> 71125510 | ... AJ26: =SUM(AJ27:AJ28) -> 88933728
B27: Variable Opex | C27: =(NPV('Input Parameters'!$D$36,J13:AJ13)+I13)/$C$52 -> 4.3245195 | D27: =C27/$C$53 -> 0.018172529 | E27: Calculated | H27: EBITDA | I27: =I23 -> 103387200 | J27: =J23 -> 78703506 | K27: =K23 -> 79884059 | L27: =L23 -> 57678144 | M27: =M23 -> 58403747 | N27: =N23 -> 59140235 | O27: =O23 -> 59887771 | P27: =P23 -> 60646519 | ... AJ27: =AJ23 -> 78454737
B28: Gas | C28: =(NPV('Input Parameters'!$D$36,J14:AJ14)+I14)/$C$52 -> 66.249651 | D28: =C28/$C$53 -> 0.27839479 | E28: Calculated | H28: Depreciation | I28: 0 | J28: 0 | K28: 0 | L28: =$D$18*1000000 -> 10478991 | M28: =$D$18*1000000 -> 10478991 | N28: =$D$18*1000000 -> 10478991 | O28: =$D$18*1000000 -> 10478991 | P28: =$D$18*1000000 -> 10478991 | Q28: =$D$18*1000000 -> 10478991 | R28: =$D$18*1000000 -> 10478991 | S28: =$D$18*1000000 -> 10478991 | ... AJ28: =$D$18*1000000 -> 10478991
B29: Electricity | C29: =(NPV('Input Parameters'!$D$36,J15:AJ15)+I15)/$C$52 -> 7.2025618 | D29: =C29/$C$53 -> 0.030266661 | E29: Calculated | H29: Taxes paid | I29: =-I31 -> 0 | J29: =-J31 -> 0 | K29: =-K31 -> 0 | L29: =-L31 -> 0 | M29: =-M31 -> 0 | N29: =-N31 -> 0 | O29: =-O31 -> 0 | P29: =-P31 -> 0 | ... AJ29: =-AJ31 -> 0
B30: Transport and Storage | C30: =(NPV('Input Parameters'!$D$36,J16:AJ16)+I16)/$C$52 -> 91.19634 | D30: =C30/$C$53 -> 0.38322596 | E30: Calculated | H30: Taxable Income | I30: =I26 -> 103387200 | J30: =J26 -> 78703506 | K30: =K26 -> 79884059 | L30: =L26 -> 68157134 | M30: =M26 -> 68882738 | N30: =N26 -> 69619226 | O30: =O26 -> 70366761 | P30: =P26 -> 71125510 | ... AJ30: =AJ26 -> 88933728
B31: Total | C31: =SUM(C25:C30) -> 237.97015 | D31: =SUM(D25:D30) -> 1 | E31: Calculated | H31: Taxes | I31: =IF(I30>=0,0,IF($C$37="Germany",I30*'Input Parameters'!$D$42,I30*'Input Parameters'!$D$43)) -> 0 | J31: =IF(J30>=0,0,IF($C$37="Germany",J30*'Input Parameters'!$D$42,J30*'Input Parameters'!$D$43)) -> 0 | K31: =IF(K30>=0,0,IF($C$37="Germany",K30*'Input Parameters'!$D$42,K30*'Input Parameters'!$D$43)) -> 0 | L31: =IF(L30>=0,0,IF($C$37="Germany",L30*'Input Parameters'!$D$42,L30*'Input Parameters'!$D$43)) -> 0 | M31: =IF(M30>=0,0,IF($C$37="Germany",M30*'Input Parameters'!$D$42,M30*'Input Parameters'!$D$43)) -> 0 | N31: =IF(N30>=0,0,IF($C$37="Germany",N30*'Input Parameters'!$D$42,N30*'Input Parameters'!$D$43)) -> 0 | O31: =IF(O30>=0,0,IF($C$37="Germany",O30*'Input Parameters'!$D$42,O30*'Input Parameters'!$D$43)) -> 0 | P31: =IF(P30>=0,0,IF($C$37="Germany",P30*'Input Parameters'!$D$42,P30*'Input Parameters'!$D$43)) -> 0 | ... AJ31: =IF(AJ30>=0,0,IF($C$37="Germany",AJ30*'Input Parameters'!$D$42,AJ30*'Input Parameters'!$D$43)) -> 0
H32: FCFF | I32: =SUM(I8,I29) -> 103387200 | J32: =SUM(J8,J29) -> 78703506 | K32: =SUM(K8,K29) -> 79884059 | L32: =SUM(L8,L23,L29) -> 57678144 | M32: =SUM(M8,M23,M29) -> 58403747 | N32: =SUM(N8,N23,N29) -> 59140235 | O32: =SUM(O8,O23,O29) -> 59887771 | P32: =SUM(P8,P23,P29) -> 60646519 | Q32: =SUM(Q8,Q23,Q29) -> 61416648 | R32: =SUM(R8,R23,R29) -> 62198330 | S32: =SUM(S8,S23,S29) -> 62991737 | ... AJ32: =SUM(AJ8,AJ23,AJ29) -> 78454737
H33: CCS Value Chain Cashflow | I33: =I9+I11 -> 103387200 | J33: =J9+J11 -> 78703506 | K33: =K9+K11 -> 79884059 | L33: =L8+L11 -> 1.0148549e+08 | M33: =M8+M11 -> 1.0221109e+08 | N33: =N8+N11 -> 1.0294758e+08 | O33: =O8+O11 -> 1.0369512e+08 | P33: =P8+P11 -> 1.0445386e+08 | Q33: =Q8+Q11 -> 1.0522399e+08 | R33: =R8+R11 -> 1.0600567e+08 | S33: =S8+S11 -> 1.0679908e+08 | ... AJ33: =AJ8+AJ11 -> 1.2226208e+08
B35: Scenario Control | H35: Captured Emissions | I35: 0 | J35: 0 | K35: 0 | L35: ='Capture Model'!$D$6 -> 738284.3 | M35: ='Capture Model'!$D$6 -> 738284.3 | N35: ='Capture Model'!$D$6 -> 738284.3 | O35: ='Capture Model'!$D$6 -> 738284.3 | P35: ='Capture Model'!$D$6 -> 738284.3 | Q35: ='Capture Model'!$D$6 -> 738284.3 | R35: ='Capture Model'!$D$6 -> 738284.3 | S35: ='Capture Model'!$D$6 -> 738284.3 | ... AJ35: ='Capture Model'!$D$6 -> 738284.3
B36: Paramater | C36: Selection | D36: Unit | H36: Plant-level Avoided Emissions | I36: 0 | J36: 0 | K36: 0 | L36: =L35-'Capture Model'!$D$31 -> 607086.26 | M36: =M35-'Capture Model'!$D$31 -> 607086.26 | N36: =N35-'Capture Model'!$D$31 -> 607086.26 | O36: =O35-'Capture Model'!$D$31 -> 607086.26 | P36: =P35-'Capture Model'!$D$31 -> 607086.26 | Q36: =Q35-'Capture Model'!$D$31 -> 607086.26 | R36: =R35-'Capture Model'!$D$31 -> 607086.26 | S36: =S35-'Capture Model'!$D$31 -> 607086.26 | ... AJ36: =AJ35-'Capture Model'!$D$31 -> 607086.26
B37: Country | C37: Germany | H37: Full Chain Avoided Emissions | I37: 0 | J37: 0 | K37: 0 | L37: =IF($C$39="Yes",'Capture Model'!$D$6-('Capture Model'!$D$31+'Capture Model'!$D$32+'Capture Model'!$D$33),'Capture Model'!$D$6-('Capture Model'!$D$31+'Capture Model'!$D$32)) -> 582390.65 | M37: =IF($C$39="Yes",'Capture Model'!$D$6-('Capture Model'!$D$31+'Capture Model'!$D$32+'Capture Model'!$D$33),'Capture Model'!$D$6-('Capture Model'!$D$31+'Capture Model'!$D$32)) -> 582390.65 | N37: =IF($C$39="Yes",'Capture Model'!$D$6-('Capture Model'!$D$31+'Capture Model'!$D$32+'Capture Model'!$D$33),'Capture Model'!$D$6-('Capture Model'!$D$31+'Capture Model'!$D$32)) -> 582390.65 | O37: =IF($C$39="Yes",'Capture Model'!$D$6-('Capture Model'!$D$31+'Capture Model'!$D$32+'Capture Model'!$D$33),'Capture Model'!$D$6-('Capture Model'!$D$31+'Capture Model'!$D$32)) -> 582390.65 | P37: =IF($C$39="Yes",'Capture Model'!$D$6-('Capture Model'!$D$31+'Capture Model'!$D$32+'Capture Model'!$D$33),'Capture Model'!$D$6-('Capture Model'!$D$31+'Capture Model'!$D$32)) -> 582390.65 | Q37: =IF($C$39="Yes",'Capture Model'!$D$6-('Capture Model'!$D$31+'Capture Model'!$D$32+'Capture Model'!$D$33),'Capture Model'!$D$6-('Capture Model'!$D$31+'Capture Model'!$D$32)) -> 582390.65 | R37: =IF($C$39="Yes",'Capture Model'!$D$6-('Capture Model'!$D$31+'Capture Model'!$D$32+'Capture Model'!$D$33),'Capture Model'!$D$6-('Capture Model'!$D$31+'Capture Model'!$D$32)) -> 582390.65 | S37: =IF($C$39="Yes",'Capture Model'!$D$6-('Capture Model'!$D$31+'Capture Model'!$D$32+'Capture Model'!$D$33),'Capture Model'!$D$6-('Capture Model'!$D$31+'Capture Model'!$D$32)) -> 582390.65 | ... AJ37: =IF($C$39="Yes",'Capture Model'!$D$6-('Capture Model'!$D$31+'Capture Model'!$D$32+'Capture Model'!$D$33),'Capture Model'!$D$6-('Capture Model'!$D$31+'Capture Model'!$D$32)) -> 582390.65
B38: Pipeline | C38: Pipeline allowed
B39: Transport and Storage | C39: Yes | H39: T&S cost | I39: =D17 -> 71.939625
B40: T&S percentile | C40: P50
B41: Investment grant | C41: No
B42: CCfD | C42: No
B43: T&S | C43: No
B44: Danish CO2 Tax | C44: Yes
B46: Results
B47: Paramater | C47: Value | D47: Unit
B48: NPV Full CCS Value Chain | C48: =NPV('Input Parameters'!D36,J33:AJ33)+I33 -> 1.0782452e+09 | D48: Euros
B49: NPV FCFF | C49: =NPV('Input Parameters'!D36,J32:AJ32)+I32 -> 7.3742321e+08 | D49: Euros
B50: NPV Captured CO2 | C50: =NPV('Input Parameters'!D36,J35:AJ35)+I35 -> 5743865.7 | D50: tCO2
B52: NPV CO2 avoided | C52: =NPV('Input Parameters'!D36,J37:AJ37)+I37 -> 4531010.2 | D52: tCO2
B53: Cost of CO2 avoided | C53: =C48/C52 -> 237.97015 | D53: Euros/tCO2
B54: Residual Cost Gap CO2 avoided | C54: =C49/C52 -> 162.75029 | D54: Euros/tCO2
B55: Cost of Policies Total | C55: =IF(C41="Yes",Policies!C16,0) + IF(C42="Yes",IF(C37="Germany",Policies!C23,Policies!C29),0) + IF(C43="Yes",Policies!C35,0) -> 0
B56: Public cost of grant | C56: =IF(C41="Yes",Policies!C16,0) -> 0
B57: Public cost of CCfD | C57: =IF(C42="Yes",IF(C37="Germany",Policies!C23,Policies!C29),0) -> 0
B58: Public cost of T&S support | C58: =IF(C43="Yes",Policies!C35,0) -> 0

Sheet Policies
B4: Investment Grant
B5: Paramater | C5: Value | D5: Unit
B6: Yearly Operational Benefits | C6: ='Cost of CO2 Avoided'!L18 -> -43807345 | D6: Euros
B7: Number of Periods | C7: 10 | D7: years
B9: CAPEX | C9: =SUM('Cost of CO2 Avoided'!I9:K9) -> 2.6197476e+08 | D9: Euros
B10: PV OPEX | C10: =NPV('Input Parameters'!D36,'Cost of CO2 Avoided'!M11:U11)+'Cost of CO2 Avoided'!L11 -> 7.1421777e+08 | D10: Euros
B11: PV ETS | C11: =-PV('Input Parameters'!D36,C7,C6) -> -2.7362803e+08 | D11: Euros
B13: Relevant Costs | C13: =SUM(C9:C11) -> 7.025645e+08 | D13: Euros
B14: Coverage | C14: 0.5 | D14: %
B15: Project Coverage | C15: =C14*C13 -> 3.5128225e+08 | D15: Euros
B16: NPV Investment Grant | C16: =-(NPV('Input Parameters'!D36,'Cost of CO2 Avoided'!J10:K10)+'Cost of CO2 Avoided'!I10) -> 0
B19: CCfD Subsidy Germany
B20: Paramater | C20: Value | D20: Unit
B21: CCfD Strike price | C21: 124 | D21: Euros/tonCO2
B22: Duration | C22: 15 | D22: years
B23: NPV CCfD | C23: =-(NPV('Input Parameters'!$D$36,'Cost of CO2 Avoided'!J20:Z20)+'Cost of CO2 Avoided'!I20) -> 0 | D23: Euros.
B25: CCfD Subsidy Denmark
B26: Paramater | C26: Value | D26: Unit
B27: Support per ton | C27: 51.84 | D27: Euros/tonCO2
B28: Duration | C28: 20 | D28: years
B29: NPV CCfD | C29: =-(NPV('Input Parameters'!D36,'Cost of CO2 Avoided'!J21:AE21)+'Cost of CO2 Avoided'!I21) -> 0 | D29: Euros
B31: T&S Subsidy
B32: Paramater | C32: Value | D32: Unit
B33: T&S Subsidy | C33: 30 | D33: Euros/tonCO2
B34: Duration | C34: 15 | D34: years
B35: NPV T&S Subsidy | C35: =-(NPV('Input Parameters'!D36,'Cost of CO2 Avoided'!J22:Z22)+'Cost of CO2 Avoided'!I22) -> 0 | D35: Euros

Sheet Scenario Design
C2: ETS | D2: T&S Cost | E2: Danish CO2 Tax (only applies to Denmark) | F2: Investment Grant | G2: CCfD | H2: T&S support
B3: S1 - Baseline | C3: Yes | D3: No | E3: Yes | F3: No | G3: No | H3: No
B4: S2 - Transport | C4: Yes | D4: Yes | E4: Yes | F4: No | G4: No | H4: No
B5: S3 - Investment Grant | C5: Yes | D5: Yes | E5: Yes | F5: Yes | G5: No | H5: No
B6: S4 - CCfD | C6: Yes | D6: Yes | E6: Yes | F6: No | G6: Yes | H6: No
B7: S5 - T&S Support | C7: Yes | D7: Yes | E7: Yes | F7: No | G7: No | H7: Yes
B8: S6 - Grant + CCfD | C8: Yes | D8: Yes | E8: Yes | F8: Yes | G8: Yes | H8: No
B9: S7 - CCfD + T&S Support | C9: Yes | D9: Yes | E9: Yes | F9: No | G9: Yes | H9: Yes
B12: Germany Scenario - Pipeline Allowed | J12: Germany Scenario - Pipeline Disallowed
C14: Cost of CO2 avoided | D14: Residual Gap | E14: Gap Closed (€/t) | F14: Policy Cost | G14: Gap reduction in % | H14: Needed ETS price | K14: Cost of CO2 avoided | L14: Residual Gap | M14: Gap Closed (€/t) | N14: Policy Cost | O14: Gap reduction in % | P14: Needed ETS price
B15: S1 - Baseline | C15: 142.091 | D15: 69.27081 | H15: 155.4238 | J15: S1 - Baseline | K15: 142.091 | L15: 69.27081 | P15: 155.4238
B16: S2 - Transport | C16: 237.97 | D16: 162.75029 | H16: 242.91038 | J16: S2 - Transport | K16: 280.609 | L16: 205.38914 | P16: 283.81473
B17: S3 - Investment Grant | C17: 237.97 | D17: 96.66449 | E17: =$D$16-D17 -> 66.0858 | F17: 3.2434891e+08 | G17: =E17/D16 -> 0.40605642 | J17: S3 - Investment Grant | K17: 280.609 | L17: 127.19889 | M17: =L16-L17 -> 78.19025 | N17: 4.0284528e+08 | O17: =M17/L16 -> 0.38069321
B18: S4 - CCfD | C18: 237.97 | D18: 117.81555 | E18: =$D$16-D18 -> 44.93474 | F18: 2.0359974e+08 | G18: =E18/D16 -> 0.27609622 | J18: S4 - CCfD | K18: 280.609 | L18: 160.45441 | M18: =L16-L18 -> 44.93473 | N18: 2.0359974e+08 | O18: =M18/L16 -> 0.21877851
B19: S5 - T&S Support | C19: 237.97 | D19: 131.12666 | E19: =$D$16-D19 -> 31.62363 | F19: 1.4328698e+08 | G19: =E19/D16 -> 0.19430767 | J19: S5 - T&S Support | K19: 280.609 | L19: 173.76551 | M19: =L16-L19 -> 31.62363 | N19: 1.4328698e+08 | O19: =M19/L16 -> 0.15396934
B20: S6 - Grant + CCfD | C20: 237.97 | D20: 51.72975 | E20: =$D$16-D20 -> 111.02054 | F20: 5.2794865e+08 | G20: =E20/D16 -> 0.68215264 | J20: S6 - Grant + CCfD | K20: 280.609 | L20: 82.26415 | M20: =L16-L20 -> 123.12499 | N20: 6.0644503e+08 | O20: =M20/L16 -> 0.59947176
B21: S7 - CCfD + T&S Support | C21: 237.97 | D21: 86.19192 | E21: =$D$16-D21 -> 76.55837 | F21: 3.4688672e+08 | G21: =E21/D16 -> 0.47040389 | J21: S7 - CCfD + T&S Support | K21: 280.609 | L21: 128.83078 | M21: =L16-L21 -> 76.55836 | N21: 3.4688672e+08 | O21: =M21/L16 -> 0.37274785
B23: Denmark Scenario - Pipeline Allowed | J23: Denmark Scenario - Pipeline Disallowed
C25: Cost of CO2 avoided | D25: Residual Gap | E25: Gap Closed (€/t) | F25: Policy Cost | G25: Gap reduction in % | H25: Needed ETS Price | K25: Cost of CO2 avoided | L25: Residual Gap | M25: Gap Closed (€/t) | N25: Policy Cost | O25: Gap reduction in % | P25: Needed ETS price
B26: S1 - Baseline | C26: 148.913 | D26: 55.66693 | H26: 137.2611 | J26: S1 - Baseline | K26: 148.913 | L26: 55.66693 | P26: 137.2611
B27: S2 - Transport | C27: 196.753 | D27: 100.45563 | H27: 178.77001 | J27: S2 - Transport | K27: 197.476 | L27: 101.17819 | P27: 179.46698
B28: S3 - Investment Grant | C28: 196.753 | D28: 46.04433 | E28: =$D27-$D28 -> 54.4113 | F28: 2.5013715e+08 | G28: =E28/D27 -> 0.5416451 | J28: S3 - Investment Grant | K28: 197.476 | L28: 46.53791 | M28: =L27-L28 -> 54.64028 | N28: 2.5147672e+08 | O28: =M28/L27 -> 0.5400401
B29: S4 - CCfD | C29: 196.753 | D29: 42.39823 | E29: =D27-D29 -> 58.0574 | F29: 2.6490944e+08 | G29: =E29/D27 -> 0.57794073 | J29: S4 - CCfD | K29: 197.476 | L29: 43.12079 | M29: =L27-L29 -> 58.0574 | N29: 2.6490944e+08 | O29: =M29/L27 -> 0.57381339
B30: S5 - T&S Support | C30: 196.753 | D30: 69.05294 | E30: =D27-D30 -> 31.40269 | F30: 1.4328698e+08 | G30: =E30/D27 -> 0.31260259 | J30: S5 - T&S Support | K30: 197.476 | L30: 69.7755 | M30: =L27-L30 -> 31.40269 | N30: 1.4328698e+08 | O30: =M30/L27 -> 0.31037015
B31: S6 - Grant + CCfD | C31: 196.753 | D31: -12.01306 | E31: =D27-D31 -> 112.46869 | F31: 5.1504659e+08 | G31: =E31/D27 -> 1.1195857 | J31: S6 - Grant + CCfD | K31: 197.476 | L31: -11.51949 | M31: =L27-L31 -> 112.69768 | N31: 5.1638616e+08 | O31: =M31/L27 -> 1.1138535
B32: S7 - CCfD + T&S Support | C32: 196.753 | D32: 17.59374 | E32: =D27-D32 -> 82.86189 | F32: 4.0819642e+08 | G32: =E32/D27 -> 0.82486059 | J32: S7 - CCfD + T&S Support | K32: 197.476 | L32: 18.18412 | M32: =L27-L32 -> 82.99407 | N32: 4.0819642e+08 | O32: =M32/L27 -> 0.82027629
B34: Required Support Levels for NPV = 0 - single instruments
C36: DE pipeline | D36: DE no pipeline | E36: DK pipeline | F36: DK no pipeline
B37: Actual T&S Cost | C37: ='Transport and Storage'!U13 -> 71.939625 | D37: ='Transport and Storage'!U14 -> 105.575 | E37: ='Transport and Storage'!U7 -> 34.1325 | F37: ='Transport and Storage'!U8 -> 34.7065
B38: ETS price | C38: =ETS!$C$5 -> 72.16 | D38: =ETS!$C$5 -> 72.16 | E38: =ETS!$C$5 -> 72.16 | F38: =ETS!$C$5 -> 72.16
B39: S3 - Required Grant Coverage (%) | C39: 1.4663375 | D39: 1.5238099 | E39: 1.0384102 | F39: 1.0412829
B40: S3 - Policy Cost (€) - Grant Coverage | C40: 9.5120992e+08 | D40: 1.2277193e+09 | E40: 5.1948992e+08 | F40: 5.2371682e+08
B41: S4 - Required CCFD strike/subsidy (€/t) | C41: 289.56177 | D41: 342.32665 | E41: 99.906883 | F41: 100.56394
B42: S4 - Required CCFD subsidy (€/t) - For Germany implied payment per ton | C42: =C41-C38 -> 217.40177 | D42: =D41-D38 -> 270.16665 | E42: =E41 -> 99.906883 | F42: =F41 -> 100.56394
B43: S4 - Policy Cost (€) - CCfD subsidy | C43: 8.5383768e+08 | D43: 1.0610698e+09 | E43: 5.1053774e+08 | F43: 5.1389537e+08
B44: S5 - Required T&S subsidy (€/t) | C44: 178.76803 | D44: 222.15623 | E44: 109.01815 | F44: 109.74124
B45: S5 - Policy Cost (€) - T&S subsidy | C45: 8.5383768e+08 | D45: 1.0610698e+09 | E45: 5.2069603e+08 | F45: 5.2414966e+08
B47: Required Support Levels for NPV = 0 - combined instruments
C49: DE pipeline | D49: DE no pipeline | E49: DK pipeline | F49: DK no pipeline
B50: Actual T&S Cost | C50: =C37 -> 71.939625 | D50: =D37 -> 105.575 | E50: =E37 -> 34.1325 | F50: =F37 -> 34.7065
B51: ETS price | C51: =ETS!$C$5 -> 72.16 | D51: =ETS!$C$5 -> 72.16 | E51: =ETS!$C$5 -> 72.16 | F51: =ETS!$C$5 -> 72.16
B52: S6 - Required Grant Coverage (%) - CCfD held at baseline | C52: 1.017133 | D52: 1.1621351 | E52: 0.38670466 | F52: 0.39119999
B53: S6 - Policy Cost (€) - Grant Coverage | C53: 8.6341172e+08 | D53: 1.1399211e+09 | E53: 4.5836784e+08 | F53: 4.6166482e+08
B54: S6 - Required CCFD strike/subsidy (€/t) - Grant held at 50% coverage | C54: 183.67923 | D54: 218.90594 | E54: 41.113422 | F54: 41.554137
B55: S6 - Required CCFD subsidy (€/t) - Grant held at 50% coverage and for Germany implied payment per ton | C55: =C54-C51 -> 111.51923 | D55: =D54-D51 -> 146.74594 | E55: =E54 -> 41.113422 | F55: =F54 -> 41.554137
B56: S6 - Policy Cost (€) - CCfD strike | C56: 7.623367e+08 | D56: 9.7918473e+08 | E56: 4.6023231e+08 | F56: 4.63824e+08
B57: S7 - Required CCFD strike/subsidy (€/t) - T&S subsidy held at baseline | C57: 253.07844 | D57: 305.84332 | E57: 71.867124 | F57: 72.524177
B58: S7 - Required CCFD strike/subsidy (€/t) - T&S subsidy held at baseline and for Germany implied payment per ton | C58: =C57-C51 -> 180.91844 | D58: =D57-D51 -> 233.68332 | E58: =E57 -> 71.867124 | F58: =F57 -> 72.524177
B59: S7 - Policy Cost (€) - CCfD strike | C59: 8.5383768e+08 | D59: 1.0610698e+09 | E59: 5.1053774e+08 | F59: 5.1389537e+08
B60: S7 - Required T&S subsidy (€/t) - CCfD held at baseline | C60: 136.14034 | D60: 179.52855 | E60: 51.548551 | F60: 52.271639
B61: S7 - Policy Cost (€) - T&S subsidy | C61: 8.5383768e+08 | D61: 1.0610698e+09 | E61: 5.1111731e+08 | F61: 5.1457095e+08

Sheet Sensitivities
B3: Parameters | G3: Cost of CO2 avoided | L3: Chnages in Percentages | R3: Heatmaps
B5: Germany Pipeline | G5: Germany Pipeline | L5: Germany Pipeline | R5: Germany - T&S Cost (rows) vs Gas Price (columns) | AB5: Denmark - Gas Price (rows) vs WACC (columns)
C6: Low | D6: Baseline | E6: High | H6: Low | I6: Baseline | J6: High | M6: Low | N6: Baseline | O6: High
B7: T&S Sensitivity | C7: ='Transport and Storage'!U17 -> 38.376 | D7: ='Transport and Storage'!U13 -> 71.939625 | E7: ='Transport and Storage'!U19 -> 116.86025 | G7: T&S Sensitivity | H7: 195.427 | I7: ='Scenario Design'!$C$16 -> 237.97 | J7: 294.915 | L7: T&S Sensitivity | M7: =(H7-I7)/I7 -> -0.17877464 | N7: 129.47 | O7: =(J7-I7)/I7 -> 0.23929487 | R7: Germany – Pipeline Allowed (DE) | AB7: Denmark – Pipeline Allowed (DK)
B8: Gas Price in €/kwh | C8: =D8*0.8 -> 0.04 | D8: 0.05 | E8: =D8*1.2 -> 0.06 | G8: Gas Price in €/kwh | H8: 224.72 | I8: ='Scenario Design'!$C$16 -> 237.97 | J8: 251.22 | L8: Gas Price in €/kwh | M8: =(H8-I8)/I8 -> -0.055679287 | N8: 129.47 | O8: =(J8-I8)/I8 -> 0.055679287 | R8: 237.97063 | S8: 0.035 | T8: 0.04 | U8: 0.045 | V8: 0.05 | W8: 0.055 | X8: 0.06 | Y8: 0.065 | AB8: 196.75328 | AC8: 0.04 | AD8: 0.05 | AE8: 0.06 | AF8: 0.07 | AG8: 0.08 | AH8: 0.09 | AI8: 0.1 | AJ8: 0.11 | AK8: 0.12
B9: Electricity Price in €/kwh | C9: =D9*0.8 -> 0.15456 | D9: 0.1932 | E9: =D9*1.2 -> 0.23184 | G9: Electricity Price in €/kwh | H9: 236.531 | I9: ='Scenario Design'!$C$16 -> 237.97 | J9: 239.409 | L9: Electricity Price in €/kwh | M9: =(H9-I9)/I9 -> -0.0060469807 | N9: 129.47 | O9: =(J9-I9)/I9 -> 0.0060469807 | R9: 38 | S9: 175.07071 | T9: 181.69568 | U9: 188.32064 | V9: 194.94561 | W9: 201.57057 | X9: 208.19554 | Y9: 214.8205 | AB9: 0.04 | AC9: 157.67422 | AD9: 161.14928 | AE9: 164.87814 | AF9: 168.85421 | AG9: 173.07003 | AH9: 177.51765 | AI9: 182.18889 | AJ9: 187.07558 | AK9: 192.16978
B10: WACC | C10: 0.06 | D10: 0.08 | E10: 0.1 | G10: WACC | H10: 229.914 | I10: ='Scenario Design'!$C$16 -> 237.97 | J10: 246.981 | L10: WACC | M10: =(H10-I10)/I10 -> -0.033853007 | N10: 129.47 | O10: =(J10-I10)/I10 -> 0.037866118 | R10: 45 | S10: 183.94446 | T10: 190.56943 | U10: 197.19439 | V10: 203.81936 | W10: 210.44432 | X10: 217.06929 | Y10: 223.69425 | AB10: 0.046 | AC10: 165.77344 | AD10: 169.19337 | AE10: 172.86969 | AF10: 176.79586 | AG10: 180.96445 | AH10: 185.36751 | AI10: 189.99681 | AJ10: 194.84413 | AK10: 199.90141
R11: 52 | S11: 192.81821 | T11: 199.44318 | U11: 206.06814 | V11: 212.69311 | W11: 219.31807 | X11: 225.94304 | Y11: 232.568 | AB11: 0.052 | AC11: 173.87266 | AD11: 177.23747 | AE11: 180.86124 | AF11: 184.7375 | AG11: 188.85887 | AH11: 193.21736 | AI11: 197.80473 | AJ11: 202.61267 | AK11: 207.63305
B12: Germany No Pipeline | G12: Germany No Pipeline | L12: Germany No Pipeline | R12: 60 | S12: 202.95964 | T12: 209.58461 | U12: 216.20958 | V12: 222.83454 | W12: 229.45951 | X12: 236.08447 | Y12: 242.70944 | AB12: 0.058 | AC12: 181.97188 | AD12: 185.28157 | AE12: 188.85279 | AF12: 192.67915 | AG12: 196.75328 | AH12: 201.06722 | AI12: 205.61265 | AJ12: 210.38121 | AK12: 215.36468
C13: Low | D13: Baseline | E13: High | H13: Low | I13: Baseline | J13: High | M13: Low | N13: Baseline | O13: High | R13: 68 | S13: 213.10108 | T13: 219.72604 | U13: 226.35101 | V13: 232.97597 | W13: 239.60094 | X13: 246.2259 | Y13: 252.85087 | AB13: 0.064 | AC13: 190.0711 | AD13: 193.32566 | AE13: 196.84434 | AF13: 200.62079 | AG13: 204.6477 | AH13: 208.91707 | AI13: 213.42057 | AJ13: 218.14975 | AK13: 223.09631
B14: T&S Sensitivity | C14: ='Transport and Storage'!U18 -> 79.868 | D14: ='Transport and Storage'!U14 -> 105.575 | E14: ='Transport and Storage'!U20 -> 124.066 | G14: T&S Sensitivity | H14: 248.023 | I14: ='Scenario Design'!$K$16 -> 280.609 | J14: 304.055 | L14: T&S Sensitivity | M14: =(H14-I14)/I14 -> -0.116126 | N14: 171.43 | O14: =(J14-I14)/I14 -> 0.083553984 | R14: 72 | S14: 218.17179 | T14: 224.79676 | U14: 231.42172 | V14: 238.04669 | W14: 244.67165 | X14: 251.29662 | Y14: 257.92158 | AB14: 0.07 | AC14: 198.17032 | AD14: 201.36976 | AE14: 204.83588 | AF14: 208.56243 | AG14: 212.54211 | AH14: 216.76693 | AI14: 221.22849 | AJ14: 225.91829 | AK14: 230.82795
B15: Gas Price in €/kwh | C15: =D15*0.8 -> 0.04 | D15: ='Input Parameters'!D15 -> 0.05 | E15: =D15*1.2 -> 0.06 | G15: Gas Price in €/kwh | H15: 267.359 | I15: ='Scenario Design'!$K$16 -> 280.609 | J15: 293.859 | L15: Gas Price in €/kwh | M15: =(H15-I15)/I15 -> -0.047218728 | N15: 171.43 | O15: =(J15-I15)/I15 -> 0.047218728 | R15: 78 | S15: 225.77786 | T15: 232.40283 | U15: 239.02779 | V15: 245.65276 | W15: 252.27772 | X15: 258.90269 | Y15: 265.52765 | AB15: 0.076 | AC15: 206.26953 | AD15: 209.41386 | AE15: 212.82743 | AF15: 216.50408 | AG15: 220.43653 | AH15: 224.61678 | AI15: 229.03641 | AJ15: 233.68683 | AK15: 238.55958
B16: Electricity Price in €/kwh | C16: =D16*0.8 -> 0.15456 | D16: 0.1932 | E16: =D16*1.2 -> 0.23184 | G16: Electricity Price in €/kwh | H16: 279.17 | I16: ='Scenario Design'!$K$16 -> 280.609 | J16: 282.048 | L16: Electricity Price in €/kwh | M16: =(H16-I16)/I16 -> -0.005128132 | N16: 171.43 | O16: =(J16-I16)/I16 -> 0.005128132 | R16: 85 | S16: 234.65162 | T16: 241.27658 | U16: 247.90155 | V16: 254.52651 | W16: 261.15148 | X16: 267.77644 | Y16: 274.40141
B17: WACC | C17: 0.06 | D17: 0.08 | E17: 0.1 | G17: WACC | H17: 272.553 | I17: ='Scenario Design'!$K$16 -> 280.609 | J17: 289.619 | L17: WACC | M17: =(H17-I17)/I17 -> -0.028708987 | N17: 171.43 | O17: =(J17-I17)/I17 -> 0.032108735 | R17: 95 | S17: 247.3284 | T17: 253.95337 | U17: 260.57833 | V17: 267.2033 | W17: 273.82826 | X17: 280.45323 | Y17: 287.07819
R18: 105 | S18: 260.00519 | T18: 266.63016 | U18: 273.25512 | V18: 279.88009 | W18: 286.50505 | X18: 293.13002 | Y18: 299.75498 | AB18: Denmark – Pipeline Allowed (DK)
B19: Denmark Pipeline | G19: Denmark Pipeline | L19: Denmark Pipeline | R19: 116 | S19: 273.94966 | T19: 280.57462 | U19: 287.19959 | V19: 293.82456 | W19: 300.44952 | X19: 307.07449 | Y19: 313.69945 | AB19: 197.47585 | AC19: 0.04 | AD19: 0.05 | AE19: 0.06 | AF19: 0.07 | AG19: 0.08 | AH19: 0.09 | AI19: 0.1 | AJ19: 0.11 | AK19: 0.12
C20: Low | D20: Baseline | E20: High | H20: Low | I20: Baseline | J20: High | M20: Low | N20: Baseline | O20: High | R20: 124 | S20: 284.09109 | T20: 290.71606 | U20: 297.34102 | V20: 303.96599 | W20: 310.59095 | X20: 317.21592 | Y20: 323.84088 | AB20: 0.04 | AC20: 158.39679 | AD20: 161.87184 | AE20: 165.60071 | AF20: 169.57678 | AG20: 173.7926 | AH20: 178.24022 | AI20: 182.91145 | AJ20: 187.79815 | AK20: 192.89234
B21: Gas Price in €/kwh | C21: =D21*0.8 -> 0.0464 | D21: 0.058 | E21: =D21*1.2 -> 0.0696 | G21: Gas Price in €/kwh | H21: 181.491 | I21: ='Scenario Design'!$C$27 -> 196.753 | J21: 212.016 | L21: Gas Price in €/kwh | M21: =(H21-I21)/I21 -> -0.077569338 | N21: 68.453 | O21: =(J21-I21)/I21 -> 0.077574421 | AB21: 0.046 | AC21: 166.49601 | AD21: 169.91594 | AE21: 173.59226 | AF21: 177.51842 | AG21: 181.68701 | AH21: 186.09007 | AI21: 190.71937 | AJ21: 195.56669 | AK21: 200.62398
B22: Electricity Price in €/kwh | C22: =D22*0.8 -> 0.1008 | D22: 0.126 | E22: =D22*1.2 -> 0.1512 | G22: Electricity Price in €/kwh | H22: 195.82 | I22: ='Scenario Design'!$C$27 -> 196.753 | J22: 197.686 | L22: Electricity Price in €/kwh | M22: =(H22-I22)/I22 -> -0.0047419861 | N22: 68.453 | O22: =(J22-I22)/I22 -> 0.0047419861 | AB22: 0.052 | AC22: 174.59523 | AD22: 177.96003 | AE22: 181.5838 | AF22: 185.46007 | AG22: 189.58143 | AH22: 193.93993 | AI22: 198.52729 | AJ22: 203.33523 | AK22: 208.35561
B23: WACC | C23: 0.06 | D23: 0.08 | E23: 0.1 | G23: WACC | H23: 188.853 | I23: ='Scenario Design'!$C$27 -> 196.753 | J23: 205.613 | L23: WACC | M23: =(H23-I23)/I23 -> -0.040151866 | N23: 68.453 | O23: =(J23-I23)/I23 -> 0.04503108 | R23: Germany – No Pipeline Allowed (DE) | AB23: 0.058 | AC23: 182.69444 | AD23: 186.00413 | AE23: 189.57535 | AF23: 193.40171 | AG23: 197.47585 | AH23: 201.78978 | AI23: 206.33521 | AJ23: 211.10377 | AK23: 216.08724
R24: 280.61534 | S24: 0.035 | T24: 0.04 | U24: 0.045 | V24: 0.05 | W24: 0.055 | X24: 0.06 | Y24: 0.065 | AB24: 0.064 | AC24: 190.79366 | AD24: 194.04823 | AE24: 197.5669 | AF24: 201.34335 | AG24: 205.37026 | AH24: 209.63964 | AI24: 214.14313 | AJ24: 218.87231 | AK24: 223.81888
B25: Denmark No Pipeline | G25: Denmark No Pipeline | L25: Denmark No Pipeline | R25: 38 | S25: 175.07071 | T25: 181.69568 | U25: 188.32064 | V25: 194.94561 | W25: 201.57057 | X25: 208.19554 | Y25: 214.8205 | AB25: 0.07 | AC25: 198.89288 | AD25: 202.09233 | AE25: 205.55845 | AF25: 209.285 | AG25: 213.26468 | AH25: 217.48949 | AI25: 221.95105 | AJ25: 226.64086 | AK25: 231.55051
C26: Low | D26: Baseline | E26: High | H26: Low | I26: Baseline | J26: High | M26: Low | N26: Baseline | O26: High | R26: 45 | S26: 183.94446 | T26: 190.56943 | U26: 197.19439 | V26: 203.81936 | W26: 210.44432 | X26: 217.06929 | Y26: 223.69425 | AB26: 0.076 | AC26: 206.9921 | AD26: 210.13642 | AE26: 213.54999 | AF26: 217.22664 | AG26: 221.15909 | AH26: 225.33935 | AI26: 229.75897 | AJ26: 234.4094 | AK26: 239.28214
B27: Gas Price in €/kwh | C27: =C21 -> 0.0464 | D27: =D21 -> 0.058 | E27: =E21 -> 0.0696 | G27: Gas Price in €/kwh | H27: 182.213 | I27: ='Scenario Design'!$K$27 -> 197.476 | J27: 212.738 | L27: Gas Price in €/kwh | M27: =(H27-I27)/I27 -> -0.077290405 | N27: =I27 -> 197.476 | O27: =(J27-I27)/I27 -> 0.077285341 | R27: 52 | S27: 192.81821 | T27: 199.44318 | U27: 206.06814 | V27: 212.69311 | W27: 219.31807 | X27: 225.94304 | Y27: 232.568
B28: Electricity Price in €/kwh | C28: =C22 -> 0.1008 | D28: 0.126 | E28: =E22 -> 0.1512 | G28: Electricity Price in €/kwh | H28: 196.543 | I28: ='Scenario Design'!$K$27 -> 197.476 | J28: 198.409 | L28: Electricity Price in €/kwh | M28: =(H28-I28)/I28 -> -0.0047246248 | N28: =I28 -> 197.476 | O28: =(J28-I28)/I28 -> 0.0047246248 | R28: 60 | S28: 202.95964 | T28: 209.58461 | U28: 216.20958 | V28: 222.83454 | W28: 229.45951 | X28: 236.08447 | Y28: 242.70944
B29: WACC | C29: 0.06 | D29: 0.08 | E29: 0.1 | G29: WACC | H29: 189.575 | I29: ='Scenario Design'!$K$27 -> 197.476 | J29: 206.335 | L29: WACC | M29: =(H29-I29)/I29 -> -0.040009925 | N29: =I29 -> 197.476 | O29: =(J29-I29)/I29 -> 0.044861148 | R29: 68 | S29: 213.10108 | T29: 219.72604 | U29: 226.35101 | V29: 232.97597 | W29: 239.60094 | X29: 246.2259 | Y29: 252.85087
R30: 72 | S30: 218.17179 | T30: 224.79676 | U30: 231.42172 | V30: 238.04669 | W30: 244.67165 | X30: 251.29662 | Y30: 257.92158
R31: 78 | S31: 225.77786 | T31: 232.40283 | U31: 239.02779 | V31: 245.65276 | W31: 252.27772 | X31: 258.90269 | Y31: 265.52765
B32: Denmark Scenario - Pipeline Allowed | I32: Denmark Scenario - No Pipeline Allowed | R32: 85 | S32: 234.65162 | T32: 241.27658 | U32: 247.90155 | V32: 254.52651 | W32: 261.15148 | X32: 267.77644 | Y32: 274.40141
R33: 95 | S33: 247.3284 | T33: 253.95337 | U33: 260.57833 | V33: 267.2033 | W33: 273.82826 | X33: 280.45323 | Y33: 287.07819
C34: Cost of CO2 avoided - without tax | D34: Cost of CO2 avoided - with tax | E34: Residual Gap - without tax | F34: Residual Gap - with tax | G34: Tax impact | J34: Cost of CO2 avoided - without tax | K34: Cost of CO2 avoided - with tax | L34: Residual Gap - without tax | M34: Residual Gap - with tax | N34: Tax impact | R34: 105 | S34: 260.00519 | T34: 266.63016 | U34: 273.25512 | V34: 279.88009 | W34: 286.50505 | X34: 293.13002 | Y34: 299.75498
B35: Baseline | C35: ='Scenario Design'!$C26 -> 148.913 | D35: ='Scenario Design'!$C26 -> 148.913 | E35: 76.58559 | F35: ='Scenario Design'!D26 -> 55.66693 | G35: =F35-E35 -> -20.91866 | I35: Baseline | J35: ='Scenario Design'!$K26 -> 148.913 | K35: ='Scenario Design'!$K26 -> 148.913 | L35: 76.58559 | M35: ='Scenario Design'!L26 -> 55.66693 | N35: =M35-L35 -> -20.91866 | R35: 116 | S35: 273.94966 | T35: 280.57462 | U35: 287.19959 | V35: 293.82456 | W35: 300.44952 | X35: 307.07449 | Y35: 313.69945
B36: Transport | C36: ='Scenario Design'!$C27 -> 196.753 | D36: ='Scenario Design'!$C27 -> 196.753 | E36: 122.05894 | F36: ='Scenario Design'!D27 -> 100.45563 | G36: =F36-E36 -> -21.60331 | I36: Transport | J36: ='Scenario Design'!$K27 -> 197.476 | K36: ='Scenario Design'!$K27 -> 197.476 | L36: 122.7815 | M36: ='Scenario Design'!L27 -> 101.17819 | N36: =M36-L36 -> -21.60331 | R36: 124 | S36: 284.09109 | T36: 290.71606 | U36: 297.34102 | V36: 303.96599 | W36: 310.59095 | X36: 317.21592 | Y36: 323.84088
B37: Investment Grant | C37: ='Scenario Design'!$C28 -> 196.753 | D37: ='Scenario Design'!$C28 -> 196.753 | E37: 67.64765 | F37: ='Scenario Design'!D28 -> 46.04433 | G37: =F37-E37 -> -21.60332 | I37: Investment Grant | J37: ='Scenario Design'!$K28 -> 197.476 | K37: ='Scenario Design'!$K28 -> 197.476 | L37: 68.14122 | M37: ='Scenario Design'!L28 -> 46.53791 | N37: =M37-L37 -> -21.60331
B38: CCfD | C38: ='Scenario Design'!$C29 -> 196.753 | D38: ='Scenario Design'!$C29 -> 196.753 | E38: 64.00154 | F38: ='Scenario Design'!D29 -> 42.39823 | G38: =F38-E38 -> -21.60331 | I38: CCfD | J38: ='Scenario Design'!$K29 -> 197.476 | K38: ='Scenario Design'!$K29 -> 197.476 | L38: 64.72411 | M38: ='Scenario Design'!L29 -> 43.12079 | N38: =M38-L38 -> -21.60332
B39: T&S Support | C39: ='Scenario Design'!$C30 -> 196.753 | D39: ='Scenario Design'!$C30 -> 196.753 | E39: 90.65625 | F39: ='Scenario Design'!D30 -> 69.05294 | G39: =F39-E39 -> -21.60331 | I39: T&S Support | J39: ='Scenario Design'!$K30 -> 197.476 | K39: ='Scenario Design'!$K30 -> 197.476 | L39: 91.37881 | M39: ='Scenario Design'!L30 -> 69.7755 | N39: =M39-L39 -> -21.60331
B40: Grant + CCfD | C40: ='Scenario Design'!$C31 -> 196.753 | D40: ='Scenario Design'!$C31 -> 196.753 | E40: 9.59025 | F40: ='Scenario Design'!D31 -> -12.01306 | G40: =F40-E40 -> -21.60331 | I40: Grant + CCfD | J40: ='Scenario Design'!$K31 -> 197.476 | K40: ='Scenario Design'!$K31 -> 197.476 | L40: 10.08382 | M40: ='Scenario Design'!L31 -> -11.51949 | N40: =M40-L40 -> -21.60331
B41: CCfD + T&S Support | C41: ='Scenario Design'!$C32 -> 196.753 | D41: ='Scenario Design'!$C32 -> 196.753 | E41: 35.39234 | F41: ='Scenario Design'!D32 -> 17.59374 | G41: =F41-E41 -> -17.7986 | I41: CCfD + T&S Support | J41: ='Scenario Design'!$K32 -> 197.476 | K41: ='Scenario Design'!$K32 -> 197.476 | L41: 35.98272 | M41: ='Scenario Design'!L32 -> 18.18412 | N41: =M41-L41 -> -17.7986
B44: HIGH ETS Sensitivity - residual cost gap - Germany pipeline | G44: HIGH ETS Sensitivity - residual cost gap - Denmark pipeline
C46: Baseline - 72.16€/t | D46: Strike - 124€/t | E46: Above Strike - 130€/t | H46: Baseline - 72.16€/t | I46: Strike - 124€/t | J46: Above Strike- 130€/t
B47: Baseline | C47: ='Scenario Design'!D15 -> 69.27081 | D47: 22.22691 | E47: 17.92984 | G47: Baseline | H47: ='Scenario Design'!D26 -> 55.66693 | I47: 10.36761 | J47: 5.67677
B48: Transport | C48: ='Scenario Design'!D16 -> 162.75029 | D48: 108.71207 | E48: 102.45765 | G48: Transport | H48: ='Scenario Design'!D27 -> 100.45563 | I48: 46.79495 | J48: 40.70039
B49: Investment Grant | C49: ='Scenario Design'!D17 -> 96.66449 | D49: 57.15688 | E49: 53.22063 | G49: Investment Grant | H49: ='Scenario Design'!D28 -> 46.04433 | I49: 11.86415 | J49: 8.07157
B50: CCfD | C50: ='Scenario Design'!D18 -> 117.81555 | D50: 108.71207 | E50: 107.65843 | G50: CCfD | H50: ='Scenario Design'!D29 -> 42.39823 | I50: -0.63654 | J50: -5.57003
B51: T&S Support | C51: ='Scenario Design'!D19 -> 131.12666 | D51: 77.08844 | E51: 70.83402 | G51: T&S Support | H51: ='Scenario Design'!D30 -> 69.05294 | I51: 20.67184 | J51: 15.59729
B52: Grant + CCfD | C52: ='Scenario Design'!D20 -> 51.72975 | D52: 57.15688 | E52: 58.42141 | G52: Grant + CCfD | H52: ='Scenario Design'!D31 -> -12.01306 | I52: -35.56734 | J52: -38.19885
B53: CCfD + T&S Support | C53: ='Scenario Design'!D21 -> 86.19192 | D53: 77.08844 | E53: 76.0348 | G53: CCfD + T&S Support | H53: ='Scenario Design'!D32 -> 17.59374 | I53: -25.13064 | J53: -30.06413
B56: CCfD Decomposition Pipeline scenario
C58: Required implied payment | D58: CCfD Gap Composition | E58: Policy Cost | F58: Segments
B59: Denmark CCfD | C59: ='Scenario Design'!E41 -> 99.906883 | D59: 0 | E59: ='Scenario Design'!E43 -> 5.1053774e+08
B60: Denmark CCfD, 15 years | C60: 116.87835 | D60: =(C60-C59)/(C62-C59) -> 0.14444426 | E60: 5.2069603e+08 | F60: =C60-C59 -> 16.971463
B61: Denmark CCfD, 15 years, No Indexation | C61: 132.57817 | D61: =(C61-C60)/(C62-C59) -> 0.13362136 | E61: 5.2069603e+08 | F61: =C61-C60 -> 15.699826
B62: Germany CCfD | C62: ='Scenario Design'!C42 -> 217.40177 | D62: =(C62-C61)/(C62-C59) -> 0.72193438 | E62: ='Scenario Design'!C43 -> 8.5383768e+08 | F62: =C62-C61 -> 84.823599

Sheet RQ1
B2: Parameter | C2: Germany - Pipeline | D2: Germany - No Pipeline | E2: Denmark - Pipeline | F2: Denmark - No Pipeline | I2: Transport and Storage
B3: Capex | C3: 51.633366 | D3: 51.633366 | E3: 51.284064 | F3: 51.284064
B4: Fixed Opex | C4: 15.162154 | D4: 15.162154 | E4: 15.059582 | F4: 15.059582
B5: Variable Opex | C5: 4.1865329 | D5: 4.1865329 | E5: 4.1582108 | F5: 4.1582108 | I5: Country | J5: Germany
B6: Gas | C6: 64.135759 | D6: 64.135759 | E6: 73.894178 | F6: 73.894178 | M6: Country | N6: (All)
B7: Electricity | C7: 6.9727427 | D7: 6.9727427 | E7: 4.5166772 | F7: 4.5166772 | I7: Row Labels | J7: Average of Transport Cost
B8: Transport and Storage | C8: 0 | D8: 0 | E8: 0 | F8: 0 | I8: Barge | J8: 38.865036 | M8: Row Labels | N8: Average of Cost per t/CO2 in 2025 | O8: Average of Conditioning Cost | P8: Average of Storage Cost | Q8: Average of Transport Cost
B9: Total | C9: 142.09055 | D9: 142.09055 | E9: 148.91271 | F9: 148.91271 | I9: South | J9: 38.865036 | M9: Pipeline Allowed | N9: 68.206553 | O9: 15.053191 | P9: 25.531915 | Q9: 27.621447
I10: Pipeline | J10: 27.215894 | M10: North | N10: 57.419163 | O10: 15 | P10: 22.173913 | Q10: 20.24525
B11: Parameter | C11: Germany - Pipeline | D11: Germany - No Pipeline | E11: Denmark - Pipeline | F11: Denmark - No Pipeline | I11: North | J11: 20.24525 | M11: Pipeline | N11: 57.419163 | O11: 15 | P11: 22.173913 | Q11: 20.24525
B12: Capex | C12: 53.335184 | D12: 53.335184 | E12: 52.96256 | F12: 52.96256 | I12: South | J12: 34.503386 | M12: Rotterdam | N12: 70.008432 | O12: 15 | P12: 30 | Q12: 25.008432
B13: Fixed Opex | C13: 15.661894 | D13: 15.661894 | E13: 15.552472 | F13: 15.552472 | I13: Rail | J13: 61.005731 | M13: Ruby | N13: 45.879 | O13: 15 | P13: 15 | Q13: 15.879
B14: Variable Opex | C14: 4.3245195 | D14: 4.3245195 | E14: 4.2943064 | F14: 4.2943064 | I14: North | J14: 60.2685 | M14: South | N14: 80.475424 | O14: 15.108696 | P14: 29.347826 | Q14: 36.018902
B15: Gas | C15: 66.249651 | D15: 66.249651 | E15: 76.312688 | F15: 76.312688 | I15: South | J15: 62.003162 | M15: Pipeline | N15: 78.821568 | O15: 15 | P15: 29.318182 | Q15: 34.503386
B16: Electricity | C16: 7.2025618 | D16: 7.2025618 | E16: 4.6645053 | F16: 4.6645053 | I16: Grand Total | J16: 42.793476 | M16: Ravenna | N16: 76.068667 | O16: 15 | P16: 30 | Q16: 31.068667
B17: Transport and Storage | C17: 91.19634 | D17: 133.83519 | E17: 42.96675 | F17: 43.689314 | M17: Rotterdam | N17: 80.283125 | O17: 15 | P17: 30 | Q17: 35.283125
B18: Total | C18: 237.97015 | D18: 280.609 | E18: 196.75328 | F18: 197.47585 | J18: North | K18: South | M18: Ruby | N18: 60.77225 | O18: 15 | P18: 15 | Q18: 30.77225
I19: Barge | K19: =GETPIVOTDATA("Transport Cost",$I$7,"Mode of Transport","Barge","Sector Germany","South") -> 38.865036 | M19: Rail | N19: 116.86025 | O19: 17.5 | P19: 30 | Q19: 69.36025
I20: Pipeline | J20: =GETPIVOTDATA("Transport Cost",$I$7,"Mode of Transport","Pipeline","Sector Germany","North") -> 20.24525 | K20: =GETPIVOTDATA("Transport Cost",$I$7,"Mode of Transport","Pipeline","Sector Germany","South") -> 34.503386 | M20: Rotterdam | N20: 116.86025 | O20: 17.5 | P20: 30 | Q20: 69.36025
I21: Rail | J21: =GETPIVOTDATA("Transport Cost",$I$7,"Mode of Transport","Rail","Sector Germany","North") -> 60.2685 | K21: =GETPIVOTDATA("Transport Cost",$I$7,"Mode of Transport","Rail","Sector Germany","South") -> 62.003162 | M21: Denmark | N21: 34.1325 | O21: 15 | P21: 15 | Q21: 4.1325
M22: Located at storage hub | N22: 34.1325 | O22: 15 | P22: 15 | Q22: 4.1325
M23: Aalborg | N23: 34.1325 | O23: 15 | P23: 15 | Q23: 4.1325
M24: Pipeline Disallowed | N24: 103.46023 | O24: 17.446809 | P24: 29.680851 | Q24: 56.332569
M25: North | N25: 107.7685 | O25: 17.5 | P25: 30 | Q25: 60.2685
M26: Rail | N26: 107.7685 | O26: 17.5 | P26: 30 | Q26: 60.2685
M27: Esbjerg | N27: 117.08668 | O27: 17.5 | P27: 30 | Q27: 69.586682
M28: Rotterdam | N28: 99.226833 | O28: 17.5 | P28: 30 | Q28: 51.726833
M29: South | N29: 102.14125 | O29: 17.5 | P29: 30 | Q29: 54.64125
M30: Barge | N30: 86.365036 | O30: 17.5 | P30: 30 | Q30: 38.865036
M31: Rotterdam | N31: 86.365036 | O31: 17.5 | P31: 30 | Q31: 38.865036
M32: Rail | N32: 109.04334 | O32: 17.5 | P32: 30 | Q32: 61.543344
M33: Ravenna | N33: 111.16353 | O33: 17.5 | P33: 30 | Q33: 63.663528
... M38: Grand Total | N38: 85.833391 | O38: 16.25 | P38: 27.606383 | Q38: 41.977008
I42: North - South Split
B43: Germany Pipeline
C44: Low | D44: High
B45: T&S Sensitivity | C45: =Sensitivities!M7 -> -0.17877464 | D45: =Sensitivities!O7 -> 0.23929487
B46: Gas Price in €/kwh | C46: =Sensitivities!M8 -> -0.055679287 | D46: =Sensitivities!O8 -> 0.055679287
B47: Electricity Price in €/kwh | C47: =Sensitivities!M9 -> -0.0060469807 | D47: =Sensitivities!O9 -> 0.0060469807
B48: WACC | C48: =Sensitivities!M10 -> -0.033853007 | D48: =Sensitivities!O10 -> 0.037866118
B65: Germany No Pipeline
C66: Low | D66: High
B67: T&S Sensitivity | C67: =Sensitivities!M14 -> -0.116126 | D67: =Sensitivities!O14 -> 0.083553984
B68: Gas Price in €/kwh | C68: =Sensitivities!M15 -> -0.047218728 | D68: =Sensitivities!O15 -> 0.047218728
B69: Electricity Price in €/kwh | C69: =Sensitivities!M16 -> -0.005128132 | D69: =Sensitivities!O16 -> 0.005128132
B70: WACC | C70: =Sensitivities!M17 -> -0.028708987 | D70: =Sensitivities!O17 -> 0.032108735
B88: Denmark Pipeline
C89: Low | D89: High
B90: Gas Price in €/kwh | C90: =Sensitivities!M21 -> -0.077569338 | D90: =Sensitivities!O21 -> 0.077574421
B91: Electricity Price in €/kwh | C91: =Sensitivities!M22 -> -0.0047419861 | D91: =Sensitivities!O22 -> 0.0047419861
B92: WACC | C92: =Sensitivities!M23 -> -0.040151866 | D92: =Sensitivities!O23 -> 0.04503108
B110: Denmark No Pipeline
C111: Low | D111: High
B112: Gas Price in €/kwh | C112: =Sensitivities!M27 -> -0.077290405 | D112: =Sensitivities!O27 -> 0.077285341
B113: Electricity Price in €/kwh | C113: =Sensitivities!M28 -> -0.0047246248 | D113: =Sensitivities!O28 -> 0.0047246248
B114: WACC | C114: =Sensitivities!M29 -> -0.040009925 | D114: =Sensitivities!O29 -> 0.044861148

Sheet RQ2
B2: Fixed Policy Parameters | I2: Investment Grant
C4: Germany - Pipeline | D4: Germany - No Pipeline | E4: Denmark - Pipeline | F4: Denmark - No Pipeline | J4: DE pipeline | K4: DE no pipeline | L4: DK pipeline | M4: DK no pipeline
B5: S1 - Baseline | C5: ='Scenario Design'!D15 -> 69.27081 | D5: ='Scenario Design'!L15 -> 69.27081 | E5: ='Scenario Design'!D26 -> 55.66693 | F5: ='Scenario Design'!L26 -> 55.66693 | I5: S3 - Required Grant Coverage (%) | J5: ='Scenario Design'!C39 -> 1.4663375 | K5: ='Scenario Design'!D39 -> 1.5238099 | L5: ='Scenario Design'!E39 -> 1.0384102 | M5: ='Scenario Design'!F39 -> 1.0412829
B6: S2 - Transport | C6: ='Scenario Design'!D16 -> 162.75029 | D6: ='Scenario Design'!L16 -> 205.38914 | E6: ='Scenario Design'!D27 -> 100.45563 | F6: ='Scenario Design'!L27 -> 101.17819 | I6: S3 - Policy Cost (€) - Grant Coverage | J6: ='Scenario Design'!C40 -> 9.5120992e+08 | K6: ='Scenario Design'!D40 -> 1.2277193e+09 | L6: ='Scenario Design'!E40 -> 5.1948992e+08 | M6: ='Scenario Design'!F40 -> 5.2371682e+08
B7: S3 - Investment Grant | C7: ='Scenario Design'!D17 -> 96.66449 | D7: ='Scenario Design'!L17 -> 127.19889 | E7: ='Scenario Design'!D28 -> 46.04433 | F7: ='Scenario Design'!L28 -> 46.53791 | I7: S6 - Required Grant Coverage (%) - CCfD held at baseline | J7: ='Scenario Design'!C52 -> 1.017133 | K7: ='Scenario Design'!D52 -> 1.1621351 | L7: ='Scenario Design'!E52 -> 0.38670466 | M7: ='Scenario Design'!F52 -> 0.39119999
B8: S4 - CCfD | C8: ='Scenario Design'!D18 -> 117.81555 | D8: ='Scenario Design'!L18 -> 160.45441 | E8: ='Scenario Design'!D29 -> 42.39823 | F8: ='Scenario Design'!L29 -> 43.12079 | I8: S6 - Policy Cost (€) - Grant Coverage | J8: ='Scenario Design'!C53 -> 8.6341172e+08 | K8: ='Scenario Design'!D53 -> 1.1399211e+09 | L8: ='Scenario Design'!E53 -> 4.5836784e+08 | M8: ='Scenario Design'!F53 -> 4.6166482e+08
B9: S5 - T&S Support | C9: ='Scenario Design'!D19 -> 131.12666 | D9: ='Scenario Design'!L19 -> 173.76551 | E9: ='Scenario Design'!D30 -> 69.05294 | F9: ='Scenario Design'!L30 -> 69.7755
B10: S6 - Grant + CCfD | C10: ='Scenario Design'!D20 -> 51.72975 | D10: ='Scenario Design'!L20 -> 82.26415 | E10: ='Scenario Design'!D31 -> -12.01306 | F10: ='Scenario Design'!L31 -> -11.51949
B11: S7 - CCfD + T&S Support | C11: ='Scenario Design'!D21 -> 86.19192 | D11: ='Scenario Design'!L21 -> 128.83078 | E11: ='Scenario Design'!D32 -> 17.59374 | F11: ='Scenario Design'!L32 -> 18.18412
I26: CCfD
J28: DE pipeline | K28: DE no pipeline | L28: DK pipeline | M28: DK no pipeline
I29: S4 - Required CCFD subsidy (€/t) - For Germany implied payment per ton | J29: ='Scenario Design'!C42 -> 217.40177 | K29: ='Scenario Design'!D42 -> 270.16665 | L29: ='Scenario Design'!E42 -> 99.906883 | M29: ='Scenario Design'!F42 -> 100.56394
I30: S4 - Policy Cost (€) - CCfD subsidy | J30: ='Scenario Design'!C43 -> 8.5383768e+08 | K30: ='Scenario Design'!D43 -> 1.0610698e+09 | L30: ='Scenario Design'!E43 -> 5.1053774e+08 | M30: ='Scenario Design'!F43 -> 5.1389537e+08
I31: S6 - Required CCFD subsidy (€/t) - Grant held at 50% coverage and for Germany implied payment per ton | J31: ='Scenario Design'!C55 -> 111.51923 | K31: ='Scenario Design'!D55 -> 146.74594 | L31: ='Scenario Design'!E55 -> 41.113422 | M31: ='Scenario Design'!F55 -> 41.554137
I32: S6 - Policy Cost (€) - CCfD strike | J32: ='Scenario Design'!C56 -> 7.623367e+08 | K32: ='Scenario Design'!D56 -> 9.7918473e+08 | L32: ='Scenario Design'!E56 -> 4.6023231e+08 | M32: ='Scenario Design'!F56 -> 4.63824e+08
I33: S7 - Required CCFD strike/subsidy (€/t) - T&S subsidy held at baseline and for Germany implied payment per ton | J33: ='Scenario Design'!C58 -> 180.91844 | K33: ='Scenario Design'!D58 -> 233.68332 | L33: ='Scenario Design'!E58 -> 71.867124 | M33: ='Scenario Design'!F58 -> 72.524177
I34: S7 - Policy Cost (€) - CCfD strike | J34: ='Scenario Design'!C59 -> 8.5383768e+08 | K34: ='Scenario Design'!D59 -> 1.0610698e+09 | L34: ='Scenario Design'!E59 -> 5.1053774e+08 | M34: ='Scenario Design'!F59 -> 5.1389537e+08
I53: T&S subsidy
J55: DE pipeline | K55: DE no pipeline | L55: DK pipeline | M55: DK no pipeline
I56: S5 - Required T&S subsidy (€/t) | J56: ='Scenario Design'!C44 -> 178.76803 | K56: ='Scenario Design'!D44 -> 222.15623 | L56: ='Scenario Design'!E44 -> 109.01815 | M56: ='Scenario Design'!F44 -> 109.74124
I57: S5 - Policy Cost (€) - T&S subsidy | J57: ='Scenario Design'!C45 -> 8.5383768e+08 | K57: ='Scenario Design'!D45 -> 1.0610698e+09 | L57: ='Scenario Design'!E45 -> 5.2069603e+08 | M57: ='Scenario Design'!F45 -> 5.2414966e+08
I58: S7 - Required T&S subsidy (€/t) - CCfD held at baseline | J58: ='Scenario Design'!C60 -> 136.14034 | K58: ='Scenario Design'!D60 -> 179.52855 | L58: ='Scenario Design'!E60 -> 51.548551 | M58: ='Scenario Design'!F60 -> 52.271639
I59: S7 - Policy Cost (€) - T&S subsidy | J59: ='Scenario Design'!C61 -> 8.5383768e+08 | K59: ='Scenario Design'!D61 -> 1.0610698e+09 | L59: ='Scenario Design'!E61 -> 5.1111731e+08 | M59: ='Scenario Design'!F61 -> 5.1457095e+08
J63: DE pipeline | K63: DE no pipeline | L63: DK pipeline | M63: DK no pipeline
I64: S3 - Required Grant Coverage (%) | J64: ='Scenario Design'!C39 -> 1.4663375 | K64: ='Scenario Design'!D39 -> 1.5238099 | L64: ='Scenario Design'!E39 -> 1.0384102 | M64: ='Scenario Design'!F39 -> 1.0412829
I65: S3 - Policy Cost (€) - Grant Coverage | J65: ='Scenario Design'!C40 -> 9.5120992e+08 | K65: ='Scenario Design'!D40 -> 1.2277193e+09 | L65: ='Scenario Design'!E40 -> 5.1948992e+08 | M65: ='Scenario Design'!F40 -> 5.2371682e+08
I66: S4 - Required CCFD subsidy (implied payment) (€/t) | J66: ='Scenario Design'!C42 -> 217.40177 | K66: ='Scenario Design'!D42 -> 270.16665 | L66: ='Scenario Design'!E42 -> 99.906883 | M66: ='Scenario Design'!F42 -> 100.56394
I67: S4 - Policy Cost (€) - CCfD subsidy | J67: ='Scenario Design'!C43 -> 8.5383768e+08 | K67: ='Scenario Design'!D43 -> 1.0610698e+09 | L67: ='Scenario Design'!E43 -> 5.1053774e+08 | M67: ='Scenario Design'!F43 -> 5.1389537e+08
I68: S5 - Required T&S subsidy (€/t) | J68: ='Scenario Design'!C44 -> 178.76803 | K68: ='Scenario Design'!D44 -> 222.15623 | L68: ='Scenario Design'!E44 -> 109.01815 | M68: ='Scenario Design'!F44 -> 109.74124
I69: S5 - Policy Cost (€) - T&S subsidy | J69: ='Scenario Design'!C45 -> 8.5383768e+08 | K69: ='Scenario Design'!D45 -> 1.0610698e+09 | L69: ='Scenario Design'!E45 -> 5.2069603e+08 | M69: ='Scenario Design'!F45 -> 5.2414966e+08
I70: S6 - Required Grant Coverage (%) | J70: ='Scenario Design'!C52 -> 1.017133 | K70: ='Scenario Design'!D52 -> 1.1621351 | L70: ='Scenario Design'!E52 -> 0.38670466 | M70: ='Scenario Design'!F52 -> 0.39119999
I71: S6 - Policy Cost (€) - Grant Coverage | J71: ='Scenario Design'!C53 -> 8.6341172e+08 | K71: ='Scenario Design'!D53 -> 1.1399211e+09 | L71: ='Scenario Design'!E53 -> 4.5836784e+08 | M71: ='Scenario Design'!F53 -> 4.6166482e+08
I72: S6 - Required CCFD subsidy (impled payment) (€/t) | J72: ='Scenario Design'!C55 -> 111.51923 | K72: ='Scenario Design'!D55 -> 146.74594 | L72: ='Scenario Design'!E55 -> 41.113422 | M72: ='Scenario Design'!F55 -> 41.554137
I73: S6 - Policy Cost (€) - CCfD strike | J73: ='Scenario Design'!C56 -> 7.623367e+08 | K73: ='Scenario Design'!D56 -> 9.7918473e+08 | L73: ='Scenario Design'!E56 -> 4.6023231e+08 | M73: ='Scenario Design'!F56 -> 4.63824e+08
I74: S7 - Required CCFD strike/subsidy (€/t) | J74: ='Scenario Design'!C58 -> 180.91844 | K74: ='Scenario Design'!D58 -> 233.68332 | L74: ='Scenario Design'!E58 -> 71.867124 | M74: ='Scenario Design'!F58 -> 72.524177
I75: S7 - Policy Cost (€) - CCfD strike | J75: ='Scenario Design'!C59 -> 8.5383768e+08 | K75: ='Scenario Design'!D59 -> 1.0610698e+09 | L75: ='Scenario Design'!E59 -> 5.1053774e+08 | M75: ='Scenario Design'!F59 -> 5.1389537e+08
I76: S7 - Required T&S subsidy (€/t) | J76: ='Scenario Design'!C60 -> 136.14034 | K76: ='Scenario Design'!D60 -> 179.52855 | L76: ='Scenario Design'!E60 -> 51.548551 | M76: ='Scenario Design'!F60 -> 52.271639
I77: S7 - Policy Cost (€) - T&S subsidy | J77: ='Scenario Design'!C61 -> 8.5383768e+08 | K77: ='Scenario Design'!D61 -> 1.0610698e+09 | L77: ='Scenario Design'!E61 -> 5.1111731e+08 | M77: ='Scenario Design'!F61 -> 5.1457095e+08

Sheet Cement Production
C3: Avoided Emissions - Capture | D3: Avoided Emissions - Full Chain | H3: Premium to Production Price
B4: Denmark | C4: 605683.52 | D4: 586488.13 | F4: Germany capture P+CCS | G4: =C14+C25 -> 147.03542 | H4: =(G4-C25)/C25 -> 0.79844437
B5: Germany | C5: 601586.04 | D5: 582390.65 | F5: Denmark capture P+CCS | G5: =C15+C26 -> 147.8795 | H5: =(G5-C26)/C26 -> 0.87186867
B7: Clinker/Cement Factor | C7: 0.737 | F7: Germany pipeline P + CCS | G7: =C17+C25 -> 187.59507 | H7: =(G7-C25)/C25 -> 1.2945444
B8: Total cement production | C8: ='Input Parameters'!D8/'Cement Production'!C7 -> 1309467.5 | F8: Germany no pipeline P + CCS | G8: =C18+C25 -> 206.55892 | H8: =(G8-C25)/C25 -> 1.5264983
F9: Denmark pipeline P + CCS | G9: =C19+C26 -> 167.12331 | H9: =(G9-C26)/C26 -> 1.1154582
C10: Cement emission factor - capture | D10: Cement emission factor - full chain
B11: Denmark | C11: =C4/C8 -> 0.46254186 | D11: =D4/C8 -> 0.44788293
B12: Germany | C12: =C5/C8 -> 0.45941274 | D12: =D5/C8 -> 0.44475382
B14: Germany capture uplift | C14: ='Scenario Design'!C15*'Cement Production'!C12 -> 65.278416
B15: Denmark capture uplift | C15: ='Scenario Design'!C26*'Cement Production'!C11 -> 68.878496 | H15: Premium to current price
F16: Germany capture P+CCS | G16: =C14+C25 -> 147.03542 | H16: =(G16-C30)/C30 -> 0.23963305
B17: Germany pipeline uplift | C17: ='Scenario Design'!C16*'Cement Production'!D12 -> 105.83807 | F17: Denmark capture P+CCS | G17: =C26+C15 -> 147.8795 | H17: =(G17-C34)/C34 -> -0.17783152
B18: Germany no pipeline uplift | C18: ='Scenario Design'!K16*'Cement Production'!D12 -> 124.80192
B19: Denmark pipeline uplift | C19: ='Scenario Design'!C27*'Cement Production'!D11 -> 88.122311 | F19: Germany pipeline P + CCS | G19: =C25+C17 -> 187.59507 | H19: =(G19-C30)/C30 -> 0.58158523
F20: Germany no pipeline P + CCS | G20: =C25+C18 -> 206.55892 | H20: =(G20-C30)/C30 -> 0.74146661
B21: Gallego Davila Production Price 2021 | C21: 52 | F21: Denmark pipeline P + CCS | G21: =C19+C26 -> 167.12331 | H21: =(G21-C34)/C34 -> -0.070841314
B22: Germany PPI | C22: =C45 -> 1.57225 | F22: Denmark pipeline P + CCS to German Price | G22: =C19+C26 -> 167.12331 | H22: =(G22-C30)/C30 -> 0.40899101
B23: Europe PPI | C23: =C44 -> 1.51925
B25: Germany Production Price 2024 | C25: =C21*C22 -> 81.757
B26: Denmark Production Price 2024 | C26: =C21*C23 -> 79.001
B28: Germany Sold Quantity in tons 2024 | C28: =11181090000/1000 -> 11181090
B29: Germany Sold Value 2024 | C29: 1326212000
B30: Germany Price per quantity | C30: =C29/C28 -> 118.61205
B32: Denmark Sold Quantity in tons 2024 | C32: =1990653633/1000 -> 1990653.6
B33: Denmark Sold Value 2024 | C33: 358049310
B34: Denmark Price per quantity | C34: =C33/C32 -> 179.8652
B37: PPI
B38: TIME | C38: 2021-01 | E38: 2021-02 | G38: 2021-03 | I38: 2021-04 | K38: 2021-05 | M38: 2021-06 | O38: 2021-07 | Q38: 2021-08 | S38: 2021-09 | U38: 2021-10 | W38: 2021-11 | Y38: 2021-12 | AA38: 2022-01 | AC38: 2022-02 | AE38: 2022-03 | AG38: 2022-04 | AI38: 2022-05 | AK38: 2022-06 | AM38: 2022-07 | AO38: 2022-08 | AQ38: 2022-09 | AS38: 2022-10 | AU38: 2022-11 | AW38: 2022-12 | AY38: 2023-01 | BA38: 2023-02 | BC38: 2023-03 | BE38: 2023-04 | BG38: 2023-05 | BI38: 2023-06 | BK38: 2023-07 | BM38: 2023-08 | BO38: 2023-09 | BQ38: 2023-10 | BS38: 2023-11 | BU38: 2023-12 | BW38: 2024-01 | BY38: 2024-02 | CA38: 2024-03 | CC38: 2024-04 | CE38: 2024-05 | CG38: 2024-06 | CI38: 2024-07 | CK38: 2024-08 | CM38: 2024-09 | CO38: 2024-10 | CQ38: 2024-11 | CS38: 2024-12
B39: GEO (Labels)
B40: Euro area – 20 countries (2023-2025) | C40: 99 | E40: 99.9 | G40: 99.5 | I40: 99.5 | K40: 99.6 | M40: 99.8 | O40: 99.7 | Q40: 100.5 | S40: 100.6 | U40: 100.6 | W40: 100.5 | Y40: 100.9 | AA40: 109.3 | AC40: 110.6 | AE40: 110.5 | AG40: 114.3 | AI40: 122.2 | AK40: 124.6 | AM40: 126.7 | AO40: 126.9 | AQ40: 128.2 | AS40: 130 | AU40: 133 | AW40: 134.2 | AY40: 144.3 | BA40: 150.4 | BC40: 150.4 | BE40: 150.3 | BG40: 150.6 | BI40: 150.7 | BK40: 150 | BM40: 149.2 | BO40: 149.4 | BQ40: 149.5 | BS40: 149.1 | BU40: 149.4 | BW40: 151.4 | BY40: 152.9 | CA40: 153.9 | CC40: 153.8 | CE40: 152.8 | CG40: 151.5 | CI40: 151.5 | CK40: 151.5 | CM40: 151.7 | CO40: 151.2 | CQ40: 150.5 | CS40: 150.4
B41: Germany | C41: 99 | E41: 99.2 | G41: 99.1 | I41: 99.6 | K41: 99.7 | M41: 100.1 | O41: 100 | Q41: 101.3 | S41: 100.7 | U41: 100.5 | W41: 100.5 | Y41: 100.5 | AA41: 102.1 | AC41: 104 | AE41: 103.9 | AG41: 111.4 | AI41: 118.7 | AK41: 120.5 | AM41: 122.8 | AO41: 123 | AQ41: 126.3 | AS41: 127.4 | AU41: 125.6 | AW41: 126.8 | AY41: 144.4 | BA41: 157.2 | BC41: 157.9 | BE41: 158.5 | BG41: 157.4 | BI41: 158.2 | BK41: 156.3 | BM41: 155.3 | BO41: 155.5 | BQ41: 155.2 | BS41: 155.4 | BU41: 157 | BW41: 156.7 | BY41: 159.7 | CA41: 160.6 | CC41: 159.5 | CE41: 157.5 | CG41: 155.9 | CI41: 155.5 | CK41: 155.5 | CM41: 156.9 | CO41: 156.5 | CQ41: 156.5 | CS41: 155.9
B44: Average PPI Euro Area 2024 | C44: =AVERAGE(BW40:CT40)/100 -> 1.51925
B45: Average PPI Germany 2024 | C45: =AVERAGE(BW41:CT41)/100 -> 1.57225
