Workbook
Name Additional_Commissioning_Costs: 'Step 2.3 - Data Input (CapEx)'!$F$18
Name Additional_Component_Costs: 'Step 2.4 - Data Input (OpEx)'!$F$92
Name Additional_Ongoing_Property_Costs: 'Step 2.4 - Data Input (OpEx)'!$F$33
Name Additional_Special_Costs: 'Step 2.4 - Data Input (OpEx)'!$F$11
Name Administrative_Overhead: 'Step 2.1 - Data Input (General)'!$F$8
Name Annual_Depreciation: 'Step 2.1 - Data Input (General)'!$F$9
Name Annual_Efficiency_Increase_Automated_Labour: 'Step 2.4 - Data Input (OpEx)'!$F$18
Name Annual_Efficiency_Increase_Backward_Logistics: 'Step 2.4 - Data Input (OpEx)'!$F$19
Name Annual_Efficiency_Increase_Forward_Logistics: 'Step 2.4 - Data Input (OpEx)'!$F$20
Name Annual_Efficiency_Increase_Manual_Labour: 'Step 2.4 - Data Input (OpEx)'!$F$17
Name Annual_Price_Rental_Contract: 'Step 2.2 - Data Input (Revenue)'!$F$16
Name Annual_Price_Trend_Electricity: 'Step 2.4 - Data Input (OpEx)'!$F$16
Name Annual_Price_Trend_Heating: 'Step 2.4 - Data Input (OpEx)'!$F$15
Name Annual_Price_Trend_Virgin_Materials: 'Step 2.4 - Data Input (OpEx)'!$F$14
Name Automated_Labour_Assembly: 'Step 2.4 - Data Input (OpEx)'!$F$90
Name Automated_Labour_Cleaning: 'Step 2.4 - Data Input (OpEx)'!$F$79
Name Automated_Labour_Disassembly: 'Step 2.4 - Data Input (OpEx)'!$F$65
Name Automated_Labour_Dismantling: 'Step 2.4 - Data Input (OpEx)'!$F$54
Name Automated_Labour_Identification___Sorting: 'Step 2.4 - Data Input (OpEx)'!$F$59
Name Automated_Labour_Inspection: 'Step 2.4 - Data Input (OpEx)'!$F$70
Name Automated_Labour_Linear_Production: 'Step 2.4 - Data Input (OpEx)'!$F$39
Name Automated_Labour_Restoring: 'Step 2.4 - Data Input (OpEx)'!$F$84
Name Automated_Labour_Testing: 'Step 2.4 - Data Input (OpEx)'!$F$97
Name Base_Costs_Electricity: 'Step 2.4 - Data Input (OpEx)'!$F$26
Name Base_Costs_Heating: 'Step 2.4 - Data Input (OpEx)'!$F$23
Name Basic_Rent: 'Step 2.4 - Data Input (OpEx)'!$F$31
Name BL_Distance_Core_Acquisition_Site: 'Step 2.4 - Data Input (OpEx)'!$F$45
Name BL_Distance_Customer: 'Step 2.4 - Data Input (OpEx)'!$F$44
Name BL_Flat_Rate: 'Step 2.4 - Data Input (OpEx)'!$F$43
Name BL_KM_Cost: 'Step 2.4 - Data Input (OpEx)'!$F$46
Name BL_Packaging_Cost: 'Step 2.4 - Data Input (OpEx)'!$F$47
Name BL_Shipment_Cost: 'Step 2.4 - Data Input (OpEx)'!$F$48
Name BL_Type: 'Step 2.1 - Data Input (General)'!$F$21
Name Calculator_Code: 'Step 2.2 - Data Input (Revenue)'!#REF!
Name Calculator_Code: 'Step 2.3 - Data Input (CapEx)'!#REF!
Name Calculator_Code: 'Step 2.4 - Data Input (OpEx)'!#REF!
Name Calculator_Code: 'Step 2.1 - Data Input (General)'!#REF!
Name Certification_Costs: 'Step 2.4 - Data Input (OpEx)'!$F$98
Name Commissioning_Costs_Research___Development: 'Step 2.3 - Data Input (CapEx)'!$F$15
Name Commissioning_Time_Administration: 'Step 2.3 - Data Input (CapEx)'!$F$16
Name Commissioning_Time_Production_Staff: 'Step 2.3 - Data Input (CapEx)'!$F$17
Name Consumption_Cost_Electricity: 'Step 2.4 - Data Input (OpEx)'!$F$28
Name Consumption_Cost_Heating: 'Step 2.4 - Data Input (OpEx)'!$F$25
Name Core_Premium: 'Step 2.4 - Data Input (OpEx)'!$F$49
Name Core_Reuse_Rate: 'Step 2.1 - Data Input (General)'!$F$24
Name Corporate_Tax_Rate: 'Step 2.1 - Data Input (General)'!$F$6
Name Debt_Capital: 'Step 2.1 - Data Input (General)'!$F$16
Name Discount_Rate: 'Step 2.1 - Data Input (General)'!$F$7
Name Disposal_Cost_Component: 'Step 2.4 - Data Input (OpEx)'!$F$74
Name Disposal_Cost_Core: 'Step 2.4 - Data Input (OpEx)'!$F$60
Name Disposal_Cost_Linear_Production: 'Step 2.4 - Data Input (OpEx)'!$F$37
Name Energy_Consumption_Electricity: 'Step 2.4 - Data Input (OpEx)'!$F$27
Name Energy_Consumption_Heating: 'Step 2.4 - Data Input (OpEx)'!$F$24
Name FL_Average_Journey_Number: 'Step 2.4 - Data Input (OpEx)'!$F$104
Name FL_Distance_Customer: 'Step 2.4 - Data Input (OpEx)'!$F$103
Name FL_Flat_Rate: 'Step 2.4 - Data Input (OpEx)'!$F$102
Name FL_KM_Cost: 'Step 2.4 - Data Input (OpEx)'!$F$105
Name FL_Packaging_Cost: 'Step 2.4 - Data Input (OpEx)'!$F$106
Name FL_Shipment_Cost: 'Step 2.4 - Data Input (OpEx)'!$F$107
Name FL_Type: 'Step 2.1 - Data Input (General)'!$F$22

Sheet Start
C3: CE Business Case Calculator v1.1 powered by R-evolve
C6: Welcome!
C8: Introduction The CE Business Case Calculator is an Excel-based tool designed to assist companies in the economic evaluation of circular economy business models (CBMs). It enables a structured and transparent assessment of financial viability by modelling revenue streams, capital and operating expenditures (CapEX, OpEx) as well as financing costs in detail. The tool provides a clear and visually intuitive graphical representation of the results as an output. The current version (v1.1) of the calculator, developed by the Wuppertal Institute as part of the R-evolve project, covers the following CBMs, including several sub-strategies: Repair, Reuse, Refurbish, Remanufacture, Repurpose, Recycle and Rental. It also enables the parallel calculation and comparison of several scenarios, such as different sales markets or forecasts. Further features and business models will be included in future updates. This tool has been carefully developed and tested. However, minor errors cannot be entirely ruled out. Please note that we accept no liability for any misrepresentations or miscalculations, nor for decisions made on the basis of the results. We welcome your feedback to help us further improve and refine the calculator (see Contact). How to use the tool The calculator follows a clear three-step structure to guide users through the analysis: Step 1: By answering a short questionnaire, a case is selected and the tool is pre-configured to meet your specific requirements. Step 2: Starting with general financial figures (2.1), the tool guides you through the data entry for revenue (2.2), CapEx (2.3) and OpEx (2.4). Step 3: Based on the input, results are prepared automatically, focusing on key financial indicators and detailed cost analyses. The tool provides both an in-depth assessment of the base case (3.1) and an optional comparison with up to three scenarios (3.2). Calculation: All calculations are carried out in the calculation sheets and should not be altered to ensure the integrity of the tool. License This tool is published under the Creative Commons Attribution (CC BY) license: https://creativecommons.org/licenses/by/4.0/ Authors: Niklas Hoffmann, Martin Perau | Contact: niklas.hoffmann@wupperinst.org DOI: 10.5281/zenodo.20799159 22.06.2026
P36: This work has recived founding from the European Union's Horizon Europe research and innovation programme under GA nº101182221.

Sheet Step 1 - Case Selection
C3: Step 1 - Case Selection
C6: 1. Instructions
D7: You will be asked to answer a few questions about your company and the business case you are interested in. This serves to preset the calculator so that you get the best possible results with as little data entry as possible. To ensure an accurate and complete analysis, all highlighted questions must be answered. Where available, use the drop-down menus to answer. Manually overwriting data in this table will cause an error in the calculator!
D12: Company Name: | J12: Test Company
D14: Case Name: | J14: Test Case
D16: Short Case Description: | J16: …
C20: 2. Questionaire
D21: The following questions determine the basic configuration of the calculator. Depending on your answers, further detailed questions may appear, which must also be answered in this case. Conversely, greyed-out questions can be ignored. The results of the questionnaire have a significant influence on which data must be collected in Step 2. The term 'core' refers to a returned/retrieved item intended to be reprocessed and (or) resold.
D25: What type of business case would you like to calculate?
E27: What R-strategy (s.b.) does your business case follow or support?
F29: Do you sell a service or a product (incl. component)?
G31: What subtype service strategy do you employ?
F33: How many cores are required per output instance (e.g. per remanufactured product)? | W33: *usually it is 1
F35: What percentage of cores is discarded because they are not suitable for use? | W35: *fill in manually
F37: Do you pay a premium for the take back of cores?
E39: Does backward logistic play a relevant role in your business case?
F41: How do you want to calculate your backwards logistic?
G43: What model does your backwards logistic follow?
H45: Do you employ a direct or multi-stage pickup system?
H47: Are returns already sorted before being transported to the processing site?
E49: Do you receive public funding or other subsidies for realising this business case?
D51: How do you want to calculate your forward logistic?
E53: What model does your forward logistic follow?
D55: Does the implementation of this business case require major investments (CapEx)?
E57: Is a loan being taken out to cover (a part) of this investment costs?
D59: How many years should be considered for this business case analysis?
D61: Should depreciation be taken into account for this analysis?
C64: R-strategies: Repair: Repair of defective product so it can be used with its original function; Reuse: Reuse by another customer of discarded product which is still in good condition and fulfils its original function; Refurbishment: Restore an old product and bring it up to date; Remanufacturing: Use parts of discarded product in a new (!) product with the same function; Repurpose: Use discarded product or its parts in a new (!) product with a different function; Recycling: Process materials to obtain the same (high grade) or lower (low grade) quality; Rental: Offering a product as a service in exchange for receiving regular payments

Sheet Step 2.1 - Data Input (General)
B2: Step 2.1 - Data Input (General Data)
B3: Instructions If you completed the questionnaire in Step 1, you can now enter the data required to calculate your case. Fields that are greyed out are not relevant to your case. You can start with the Overall Financial Figures. You always have to fill out the "Base Case" (Column F). The calculation of additional scenarios (G - I) is optional. Core vs. Product: In the following, the word "core" is frequently used to describe a commodity that is taken back as input material for a CE business case (e.g. a used furniture item). The aim is to distinguish it clearly from a "product" that is an output of production and gets sold.
B4: Category | C4: Name | D4: Remark | E4: Calculator Code | F4: Base Case | G4: Scenario I | H4: Scenario II | I4: Scenario III | J4: Unit
B5: Basic Parameters
C6: Corporate Tax Rate | D6: on profits | E6: Corporate Tax Rate | J6: %
C7: Discount Rate | E7: Discount Rate | J7: %
C8: Administrative Overhead | E8: Administrative Overhead | J8: %
C9: Annual Depreciation | E9: Annual Depreciation | J9: €
B11: Public Funding
C12: One Time Public Funding | E12: Public Funding Initial | J12: €
C13: Annual Public Funding | E13: Public Funding Annual | J13: € / Year
B15: Financing Costs
C16: Debt Capital | E16: Debt Capital | J16: €
C17: Loan Term | E17: Loan Term | J17: Years
C18: Yearly Interest Cost | D18: only interest, not repayment | E18: Yearly Interest Cost | J18: € / Year
B20: Imported Values (Don't change)
C21: Backward Logistic Type | D21: 1 = Direct Pick-up; 2 = Multi Stage w/o sorting; 3 = Multi Stage with Sorting; 4 = Shipment | E21: BL Type | F21: {=IFERROR(_xlfn.IFS(AND('Step 1 - Case Selection'!V43="Company-Led Pickup", 'Step 1 - Case Selection'!V45="Direct Transport"), 1, AND('Step 1 - Case Selection'!V43="Company-Led Pickup", 'Step 1 - Case Selection'!V45="Multi Stage System", 'Step 1 - Case Selection'!V47="No"), 2, AND('Step 1 - Case Selection'!V43="Company-Led Pickup", 'Step 1 - Case Selection'!V45="Multi Stage System", 'Step 1 - Case Selection'!V47="Yes"), 3, 'Step 1 - Case Selection'!V43="Customer-Led Return", 4),0)} -> 0
C22: Forward Logistic Type | D22: 1 = Delivery, 2 = Shipment, 3 = Repair Service Team | E22: FL Type | F22: {=IFERROR(_xlfn.IFS('Step 1 - Case Selection'!V31="Customer-Site Service", 3, 'Step 1 - Case Selection'!V53="Delivery Service", 1, 'Step 1 - Case Selection'!V53="Shipment (e.g. postal)", 2),0)} -> 0
C23: Required Cores per Business Instance (e.g. Production, Repair) | D23: without considering waste; usually 1 | E23: Required Input Cores | F23: =IF('Step 1 - Case Selection'!V33=0, 1, 'Step 1 - Case Selection'!V33) -> 1 | G23: =IF('Step 1 - Case Selection'!V33=0, 1, 'Step 1 - Case Selection'!V33) -> 1 | H23: =IF('Step 1 - Case Selection'!V33=0, 1, 'Step 1 - Case Selection'!V33) -> 1 | I23: =IF('Step 1 - Case Selection'!V33=0, 1, 'Step 1 - Case Selection'!V33) -> 1 | J23: Cores / Product
C24: Share of Useable Cores | D24: for Rental: after the renting period | E24: Core Reuse Rate | F24: =IF('Step 1 - Case Selection'!V35=0, 1, 1-'Step 1 - Case Selection'!V35) -> 1 | G24: =IF('Step 1 - Case Selection'!V35=0, 1, 1-'Step 1 - Case Selection'!V35) -> 1 | H24: =IF('Step 1 - Case Selection'!V35=0, 1, 1-'Step 1 - Case Selection'!V35) -> 1 | I24: =IF('Step 1 - Case Selection'!V35=0, 1, 1-'Step 1 - Case Selection'!V35) -> 1 | J24: %

Sheet Step 2.2 - Data Input (Revenue)
B2: Step 2.2 - Data Input (Revenue)
B3: Instructions If you completed the questionnaire in Step 1, you can now enter the data required to calculate your case. Fields that are greyed out are not relevant to your case. You can now proceed with Revenue related information. You always have to fill out the "Base Case" (Column F). The calculation of additional scenarios (G - I) is optional. Core vs. Product: In the following, the word “core” is frequently used to describe a commodity that is taken back as input material for a CE business case (e.g. a used furniture item). The aim is to distinguish it clearly from a "product" that is an output of production and gets sold.
B4: Category | C4: Name | D4: Remark | E4: Calculator Code | F4: Base Case | G4: Scenario I | H4: Scenario II | I4: Scenario III | J4: Unit
B5: Sales
C6: Price per Product | D6: net price; including all aditional (service) fees passed onto the customer | E6: Price Product | J6: € / Product
C7: Price per Unit of Material | D7: net price; including all aditional (service) fees passed onto the customer | E7: Price Material for Recycling | J7: € / Mass (t OR kg)
C8: Price per Service (e.g. Repair, Refurbishment) | D8: net price; including all aditional (service) fees passed onto the customer | E8: Price Service | J8: € / Product
C9: Sales in Year 1 | E9: Sales Year 1 | J9: Products OR Mass (t OR kg)
C10: Sales in Year 2 | E10: Sales Year 2 | J10: Products OR Mass (t OR kg)
C11: Sales in Year 3 | E11: Sales Year 3 | J11: Products OR Mass (t OR kg)
C12: Sales in Year 4 | E12: Sales Year 4 | J12: Products OR Mass (t OR kg)
C13: Sales in Year 5 | E13: Sales Year 5 | J13: Products OR Mass (t OR kg)
B15: Rental Agreements
C16: Annual Price per Rented Product | D16: net price | E16: Annual Price Rental Contract | J16: € / Contract
C17: Average Duration of Rental Contract | D17: one month corresponds to approx. 0,083 years | E17: Rental Contract Duration | J17: Years
C18: Newly Rented Products in Year 1 | D18: this only concerns new contracts, not ongoing ones | E18: New Rental Contracts Year 1 | J18: Contracts
C19: Newly Rented Products in Year 2 | D19: this only concerns new contracts, not ongoing ones | E19: New Rental Contracts Year 2 | J19: Contracts
C20: Newly Rented Products in Year 3 | D20: this only concerns new contracts, not ongoing ones | E20: New Rental Contracts Year 3 | J20: Contracts
C21: Newly Rented Products in Year 4 | D21: this only concerns new contracts, not ongoing ones | E21: New Rental Contracts Year 4 | J21: Contracts
C22: Newly Rented Products in Year 5 | D22: this only concerns new contracts, not ongoing ones | E22: New Rental Contracts Year 5 | J22: Contracts

Sheet Step 2.3 - Data Input (CapEx)
B2: Step 2.3 - Data Input (CapEx)
B3: Instructions If you completed the questionnaire in Step 1, you can now enter the data required to calculate your case. Fields that are greyed out are not relevant to your case. You can now proceed with CapEx related information. You always have to fill out the "Base Case" (Column F). The calculation of additional scenarios (G - I) is optional. Core vs. Product: In the following, the word “core” is frequently used to describe a commodity that is taken back as input material for a CE business case (e.g. a used furniture item). The aim is to distinguish it clearly from a "product" that is an output of production and gets sold.
B4: Category | C4: Name | D4: Remark | E4: Calculator Code | F4: Base Case | G4: Scenario I | H4: Scenario II | I4: Scenario III | J4: Unit
B5: Assets
C6: Investments in Land or Buildings | E6: Invest Land/Building | J6: €
C7: Investments in Technical Equipment and Machinery | E7: Invest Technical Equipment/Machinery | J7: €
C8: Investments in Office Equipment | E8: Invest Office Equipment | J8: €
C9: Investments in Patents & Licences | E9: Invest Patents/Licences | J9: €
C10: Investments in Certificates | E10: Invest Certificates | J10: €
C11: Investments in Software | E11: Invest Software | J11: €
C12: Investments in Equity Holdings | E12: Invest Equity Holdings | J12: €
B14: Commissioning Costs
C15: Research and Development Costs | E15: Commissioning Costs Research & Development | J15: €
C16: Required Time for Commissioning (Administration) | D16: incl. training and hiring | E16: Commissioning Time Administration | J16: h
C17: Required Time for Commissioning (Working Staff) | D17: incl. training | E17: Commissioning Time Production Staff | J17: h
C18: Additional Commissioning Costs | E18: Additional Commissioning Costs | J18: €

Sheet Step 2.4 - Data Input (OpEx)
B2: Step 2.4 - Data Input (OpEx)
B3: Instructions If you completed the questionnaire in Step 1, you can now enter the data required to calculate your case. Fields that are greyed out are not relevant to your case. You can finish with OpEx related information. You always have to fill out the "Base Case" (Column F). The calculation of additional scenarios (G - I) is optional. Core vs. Product: In the following, the word “core” is frequently used to describe a commodity that is taken back as input material for a CE business case (e.g. a used furniture item). The aim is to distinguish it clearly from a "product" that is an output of production and gets sold.
B4: Category | C4: Name | D4: Remark | E4: Calculator Code | F4: Base Case | G4: Scenario I | H4: Scenario II | I4: Scenario III | J4: Unit
B5: Overarching Values
C6: Average Hourly Rate of non-Administrative Staff | D6: e.g. production | E6: Hourly Rate Production Staff | J6: € / h
C7: Average Hourly Rate Administrative Staff | E7: Hourly Rate Administration | J7: € / h
C8: Average Hourly Machine Costs | D8: wear (and energy if possible) | E8: Hourly Rate Machines | J8: € / h
C9: Average Material per Core | D9: this refers to the average quantity (kg / t) of material that can be derived from a dismantled product and sold | E9: Output Core Material for Recycling | J9: kg / Core OR t / Core
C10: Production or Aquisition Cost of a Product for Rental | E10: Total Cost Rental Product | J10: € / Product
C11: Special Costs not included in the Calculator | E11: Additional Special Costs | J11: € / Year
B13: Trends
C14: Annual Price Trend of Virgin Materials | D14: without considering general inflation | E14: Annual Price Trend Virgin Materials | J14: % / Year
C15: Annual Price Trend of Heating | D15: without considering general inflation | E15: Annual Price Trend Heating | J15: % / Year
C16: Annual Price Trend of Electricity | D16: without considering general inflation | E16: Annual Price Trend Electricity | J16: % / Year
C17: Annual Efficiency Increase of Manual Labour | E17: Annual Efficiency Increase Manual Labour | J17: % / Year
C18: Annual Efficiency Increase of Automated Labour | E18: Annual Efficiency Increase Automated Labour | J18: % / Year
C19: Annual Efficiency Increase of Backward Logistics | E19: Annual Efficiency Increase Backward Logistics | J19: % / Year
C20: Annual Efficiency Increase of Forward Logistics | E20: Annual Efficiency Increase Forward Logistics | J20: % / Year
B22: Energy Costs
C23: Fixed Basic Costs for Heating | D23: if electricity is used for heating, it must not be listed twice here | E23: Base Costs Heating | J23: € / Year
C24: Energy Consumption Heating | E24: Energy Consumption Heating | J24: kWh / Year
C25: Consumption Costs for Heating per k/Wh | E25: Consumption Cost Heating | J25: € / kWh
C26: Fixed Basic Costs for Electricity | D26: if the energy consumption of machines is already included in “Average Hourly Machine Costs”, it must not be entered here again | E26: Base Costs Electricity | J26: € / Year
C27: Energy Consumption Electricity | E27: Energy Consumption Electricity | J27: kWh / Year
C28: Consumption Costs for Electricity per k/Wh | E28: Consumption Cost Electricity | J28: € / kWh
B30: Property Costs
C31: Basic Rent | E31: Basic Rent | J31: € / Year
C32: Property Insurance | E32: Property Insurance | J32: € / Year
C33: Additional Ongoing Property Costs | E33: Additional Ongoing Property Costs | J33: € / Year
B35: Linear Production
C36: Material Cost for Linear Production | E36: Material Cost Linear Production | J36: € / Product
C37: Disposal Cost in Linear Production | E37: Disposal Cost Linear Production | J37: € / Product
C38: Manual Working Hours in the Linear Production Process | E38: Manual Labour Linear Production | J38: h / Product
C39: Automated Working Hours in the Linear Production Process | E39: Automated Labour Linear Production | J39: h / Product
C40: Additional Linear Production Costs | E40: Special Costs Linear Production | J40: € / Year
B42: Backward Logistics: The core is transported from its current location to a processing facility.
C43: Average Pick-up Cost (Flat Rate) | E43: BL Flat Rate | J43: € / Core
C44: Average Distance from Company Site to Pickup Location | D44: if you employ a multi-stage logistics approach, calculate the distance between your core aquisition site and the customer | E44: BL Distance Customer | J44: km
C45: Distance between Core-Acquisition and Processing Site | E45: BL Distance Core-Acquisition Site | J45: km
C46: Transportation Cost per KM | E46: BL KM Cost | J46: € / (km * Core)
C47: Packaging Costs per Core | E47: BL Packaging Cost | J47: € / Unit
C48: Shipment Cost per Core | D48: if you compensate the seller for the shipment | E48: BL Shipment Cost | J48: € / Core
C49: Core-Premium | E49: Core-Premium | J49: € / Core
C50: Additional Backward Logistic Costs | E50: Special Costs Backward Logistics | J50: € / Year
B52: Dismantling: The core is prepared for transport at its current location (e.g.demounted).
C53: Manual Working Hours in Dismantling | E53: Manual Labour Dismantling | J53: h / Core
C54: Automated Working Hours in Dismantling | E54: Automated Labour Dismantling | J54: h / Core
C55: Additional Dismantling Costs | E55: Special Costs Dismantling | J55: € / Year
B57: Identification & Sorting: The returned core is registered to determine the product identity. In a subsequent or simultaneous sorting process, the core is evaluated and sorted regarding product identity, condition and effort required for processing.
C58: Manual Working Hours in Identification & Sorting | E58: Manual Labour Identification & Sorting | J58: h / Core
C59: Automated Working Hours in Identification & Sorting | E59: Automated Labour Identification & Sorting | J59: h / Core
C60: Disposal Cost for a not useable Core | E60: Disposal Cost Core | J60: € / Core
C61: Additional Identification & Sorting Costs | E61: Special Costs Identification & Sorting | J61: € / Year
B63: Disassembly: The core is disassembled into individual components either completely or to a defined.
C64: Manual Working Hours in Disassembly | E64: Manual Labour Disassembly | J64: h / Core
C65: Automated Working Hours in Disassembly | E65: Automated Labour Disassembly | J65: h / Core
C66: Additional Disassembly Costs | E66: Special Costs Disassembly | J66: € / Year
B68: Inspection: The disassembled components are inspected and tested to ensure they are suitable for further processing. The inspection can be carried out visually and/or by means of measuring methods.
C69: Manual Working Hours in Inspection | E69: Manual Labour Inspection | J69: h / Core
C70: Automated Working Hours in Inspection | E70: Automated Labour Inspection | J70: h / Core
C71: Number of not-reusable Components per Core | D71: not necessarily broken, but by definition not reusable (e.g. due to warranty or connection type) | E71: Not-Reusable Components | J71: Components / Core
C72: Number of theoretically reusable Components per Core | E72: Reusable Components | J72: Components / Core
C73: Scrap Rate | D73: with regard to theoretically reusable components | E73: Scrap Rate | J73: %
C74: Disposal Cost for not usebale Components | E74: Disposal Cost Component | J74: € / Component
C75: Additional Inspection Costs | E75: Special Costs Inspection | J75: € / Year
B77: Cleaning: The disassembled components or even entire cores are freed from (foreign) substances.
C78: Manual Working Hours in Cleaning | E78: Manual Labour Cleaning | J78: h / Core
C79: Automated Working Hours in Cleaning | E79: Automated Labour Cleaning | J79: h / Core
C80: Additional Cleaning Costs | E80: Special Costs Cleaning | J80: € / Year
B82: Restoring: The components (or core) are restored in terms of functionality and visual appearance.
C83: Total Manual Working Hours in Restoring | E83: Manual Labour Restoring | J83: h / Core
C84: Total Automated Working Hours in Restoring | E84: Automated Labour Restoring | J84: h / Core
C85: Average Material Costs in Restoring | E85: Material Cost Restoring | J85: € / Core
C86: Additional Restoring Costs | E86: Special Costs Restoring | J86: € / Year
B88: Assembly: The processed components are assembled togetherwith any necessary new parts. By using new components, it is also possible to upgrade to a technical standard that exceed the original performance.
C89: Manual Working Hours in Assembly | E89: Manual Labour Assembly | J89: h / Product
C90: Automated Working Hours in Assembly | E90: Automated Labour Assembly | J90: h / Product
C91: Average Cost for Spare Parts | E91: Spare Part Costs | J91: € / Product
C92: Average Cost für additional Components | E92: Additional Component Costs | J92: € / Product
C93: Additional Assembly Costs | E93: Special Costs Assembly | J93: € / Year
B95: Testing: The quality of the new product is ensured either by testing and inspection procedures or by controlling all process parameters. If necessary, certification is performed.
C96: Manual Working Hours in Testing | E96: Manual Labour Testing | J96: h / Product
C97: Automated Working Hours in Testing | E97: Automated Labour Testing | J97: h / Product
C98: Certification Costs on Product Level | E98: Certification Costs | J98: € / Product
C99: Additional Testing Costs | E99: Special Costs Testing | J99: € / Year
B101: Forward Logistics: The product, component or material is transported to a customer (e.g. end customer, retailer).
C102: Average Delivery Cost (Flat Rate) | E102: FL Flat Rate | J102: € / Core
C103: Average Distance from Company Site to Customer | E103: FL Distance Customer | J103: km
C104: Average Number of Trips for one Service Order | E104: FL Average Journey Number | J104: Journeys / Sale
C105: Transportation Cost per KM | E105: FL KM Cost | J105: € / (km * Product)
C106: Packaging Costs per Product | E106: FL Packaging Cost | J106: € / Product
C107: Shipment Cost per Product | E107: FL Shipment Cost | J107: € / Product
C108: Additional Forward Logistic Costs | E108: Special Costs Forward Logistics | J108: € / Year

Sheet Step 3.1 - Base Case Results
B2: CE Business Case Calculator | Q2: =IF('Step 1 - Case Selection'!J12="","",'Step 1 - Case Selection'!J12) -> Test Company
C4: Case name: | G4: =IF('Step 1 - Case Selection'!J14="","",'Step 1 - Case Selection'!J14) -> Test Case | V4: =TODAY() -> 46195
B6: Core KPIs (before / after taxes)
C8: Net Present Value | Q8: Internal Rate of Return | AE8: Dynamic Payback Period
C9: ='Calculation (BC)'!G148 -> 0 | H9: / | I9: ='Calculation (BC)'!G157 -> 0 | Q9: ='Calculation (BC)'!G150 -> #NUM! | V9: / | W9: ='Calculation (BC)'!G159 -> #NUM! | AE9: ="ca. " & ROUND('Calculation (BC)'!G153,1) & " Years" -> #VALUE! | AJ9: / | AK9: ="ca. " & ROUND('Calculation (BC)'!G162,1) & " Years" -> #VALUE!
W12: Margin Breakdown (first year | before taxes)
X14: Ø Total Cost per Sales Unit | AG14: = | AH14: ='Calculation (BC)'!I139/Sales_Year_1 -> #DIV/0!
X15: Net Price per Sales Unit | AG15: = | AH15: =Price_Product+Price_Material_for_Recycling+Price_Service -> 0
X17: Ø Margin per Sales Unit | AG17: = | AH17: =AH15-AH14 -> #DIV/0!
B35: CE Business Case Calculator | Q35: =IF('Step 1 - Case Selection'!J12="","",'Step 1 - Case Selection'!J12) -> Test Company
C37: Case name: | G37: =IF('Step 1 - Case Selection'!J14="","",'Step 1 - Case Selection'!J14) -> Test Case | V37: =TODAY() -> 46195

Sheet Step 3.2 - Scenario Analysis
B2: CE Business Case Calculator | Q2: =IF('Step 1 - Case Selection'!J12="","",'Step 1 - Case Selection'!J12) -> Test Company
C4: Case name: | G4: =IF('Step 1 - Case Selection'!J14="","",'Step 1 - Case Selection'!J14) -> Test Case | V4: =TODAY() -> 46195
AB6: KPI Comparison
AC8: Net Present Value
AC9: Base Case | AJ9: S1 | AL9: S2 | AN9: S3
AC10: ='Calculation (BC)'!G157 -> 0 | AJ10: =IF('Calculation (sI)'!F155 = 0, "/", ('Calculation (sI)'!F155 - 'Calculation (BC)'!G157)/'Calculation (BC)'!G157) -> / | AL10: =IF('Calculation (sII)'!F155 = 0, "/", ('Calculation (sII)'!F155 - 'Calculation (BC)'!G157)/'Calculation (BC)'!G157) -> / | AN10: =IF('Calculation (sIII)'!F155=0,"/",('Calculation (sIII)'!F155-'Calculation (BC)'!G157)/'Calculation (BC)'!G157) -> /
AC12: Internal Rate of Return
AC13: Base Case | AJ13: S1 | AL13: S2 | AN13: S3
AC14: ='Calculation (BC)'!G159 -> #NUM! | AJ14: =IFERROR(('Calculation (sI)'!F157 - 'Calculation (BC)'!G159)/'Calculation (BC)'!G159,"/") -> / | AL14: =IFERROR(('Calculation (sII)'!F157 - 'Calculation (BC)'!G159)/'Calculation (BC)'!G159,"/") -> / | AN14: =IFERROR(('Calculation (sIII)'!F157 - 'Calculation (BC)'!G159)/'Calculation (BC)'!G159,"/") -> /
AC16: Dynamic Payback Period
AC17: Base Case | AJ17: S1 | AL17: S2 | AN17: S3
AC18: ="ca. " & ROUND('Calculation (BC)'!G162,1) & " Years" -> #VALUE! | AJ18: =IFERROR(('Calculation (sI)'!F160 - 'Calculation (BC)'!G162)/'Calculation (BC)'!G162, "/") -> / | AL18: =IFERROR(('Calculation (sII)'!F160 - 'Calculation (BC)'!G162)/'Calculation (BC)'!G162, "/") -> / | AN18: =IFERROR(('Calculation (sIII)'!F160 - 'Calculation (BC)'!G162)/'Calculation (BC)'!G162, "/") -> /

Sheet Calculation (BC)
A1: Type | B1: Category | C1: Sub-Categoy | D1: Auxiliary Calculations | E1: Calculation Formular | F1: Unit | G1: Total Value | H1: Year 0 - Value | I1: Year 1 - Value | J1: Year 2 - Value | K1: Year 3 - Value | L1: Year 4 - Value | M1: Year 5 - Value | N1: After | O1: Auxiliary Column
A2: Income Flows | E2: Total Income Flow (SUM) | F2: € | G2: =SUM(H2:M2) -> 0 | H2: =SUM(H4,H13) -> 0 | I2: =SUM(I4,I13) -> 0 | J2: =SUM(J4,J13) -> 0 | K2: =SUM(K4,K13) -> 0 | L2: =SUM(L4,L13) -> 0 | M2: =SUM(M4,M13) -> 0
B4: Revenue | E4: SUM of all Revenue from Business Activities | F4: € | G4: =SUM(H4:M4) -> 0 | I4: =SUM(I5+I9) -> 0 | J4: =SUM(J5+J9) -> 0 | K4: =SUM(K5+K9) -> 0 | L4: =SUM(L5+L9) -> 0 | M4: =SUM(M5+M9) -> 0
C5: Sales Revenue | E5: SUM of all Sales Revenue from Product, Material and Service Sales | F5: € | G5: =SUM(H5:M5) -> 0 | I5: =SUM(I6:I8) -> 0 | J5: =SUM(J6:J8) -> 0 | K5: =SUM(K6:K8) -> 0 | L5: =SUM(L6:L8) -> 0 | M5: =SUM(M6:M8) -> 0
D6: Product Sales Revenue | E6: Sales_Year_t*Price_Product | F6: € | G6: =SUM(H6:M6) -> 0 | I6: =Sales_Year_1*Price_Product -> 0 | J6: =Sales_Year_2*Price_Product -> 0 | K6: =Sales_Year_3*Price_Product -> 0 | L6: =Sales_Year_4*Price_Product -> 0 | M6: =Sales_Year_5*Price_Product -> 0
D7: Materials for Recycling Sales Revenue | E7: Sales_Year_t*Price_Material_for_Recycling | F7: € | G7: =SUM(H7:M7) -> 0 | I7: =Sales_Year_1*Price_Material_for_Recycling -> 0 | J7: =Sales_Year_2*Price_Material_for_Recycling -> 0 | K7: =Sales_Year_3*Price_Material_for_Recycling -> 0 | L7: =Sales_Year_4*Price_Material_for_Recycling -> 0 | M7: =Sales_Year_5*Price_Material_for_Recycling -> 0
D8: Service Sales Revenue | E8: Sales_Year_t*Price_Service | F8: € | G8: =SUM(H8:M8) -> 0 | I8: =Sales_Year_1*Price_Service -> 0 | J8: =Sales_Year_2*Price_Service -> 0 | K8: =Sales_Year_3*Price_Service -> 0 | L8: =Sales_Year_4*Price_Service -> 0 | M8: =Sales_Year_5*Price_Service -> 0
C9: Rental Agreements Revenue | E9: x10*Annual_Price_Rental_Contract | F9: € | G9: =SUM(H9:M9) -> 0 | I9: =I10*Annual_Price_Rental_Contract -> 0 | J9: =J10*Annual_Price_Rental_Contract -> 0 | K9: =K10*Annual_Price_Rental_Contract -> 0 | L9: =L10*Annual_Price_Rental_Contract -> 0 | M9: =M10*Annual_Price_Rental_Contract -> 0
D10: Active Rental Agreements | E10: IF query of Rental_Contract_Duration followed by SUM of all active Agreements per Year | F10: I | I10: =New_Rental_Contracts_Year_1 -> 0 | J10: =IF(Rental_Contract_Duration>1,New_Rental_Contracts_Year_1+New_Rental_Contracts_Year_2,New_Rental_Contracts_Year_2) -> 0 | K10: {=_xlfn.IFS(Rental_Contract_Duration>2, New_Rental_Contracts_Year_1+New_Rental_Contracts_Year_2+New_Rental_Contracts_Year_3,Rental_Contract_Duration>1,New_Rental_Contracts_Year_2+New_Rental_Contracts_Year_3, Rental_Contract_Duration<=1, New_Rental_Contracts_Year_3)} -> 0 | L10: {=_xlfn.IFS(Rental_Contract_Duration>3, New_Rental_Contracts_Year_1+New_Rental_Contracts_Year_2+New_Rental_Contracts_Year_3+ New_Rental_Contracts_Year_4, Rental_Contract_Duration>2,New_Rental_Contracts_Year_2+New_Rental_Contracts_Year_3+New_Rental_Contracts_Year_4, Rental_Contract_Duration>1, New_Rental_Contracts_Year_3+New_Rental_Contracts_Year_4, Rental_Contract_Duration<=1, New_Rental_Contracts_Year_4)} -> 0 | M10: {=_xlfn.IFS(Rental_Contract_Duration>4, New_Rental_Contracts_Year_1+New_Rental_Contracts_Year_2+New_Rental_Contracts_Year_3+ New_Rental_Contracts_Year_4+New_Rental_Contracts_Year_5, Rental_Contract_Duration>3,New_Rental_Contracts_Year_2+New_Rental_Contracts_Year_3+New_Rental_Contracts_Year_4+New_Rental_Contracts_Year_5, Rental_Contract_Duration>2, New_Rental_Contracts_Year_3+New_Rental_Contracts_Year_4+New_Rental_Contracts_Year_5, Rental_Contract_Duration>1, New_Rental_Contracts_Year_4+New_Rental_Contracts_Year_5,Rental_Contract_Duration<=1, New_Rental_Contracts_Year_5)} -> 0
D11: Residual Value after Period of Review | E11: IF query of Rental_Contract_Duration for years >5 (SUM) | F11: € | G11: =SUM(H11:N11) -> 0 | N11: {=_xlfn.IFS(Rental_Contract_Duration>5, ((Rental_Contract_Duration-5)*New_Rental_Contracts_Year_1+(Rental_Contract_Duration-4)*New_Rental_Contracts_Year_2+(Rental_Contract_Duration-3)*New_Rental_Contracts_Year_3+(Rental_Contract_Duration-2)*New_Rental_Contracts_Year_4+(Rental_Contract_Duration-1)*New_Rental_Contracts_Year_5)*Annual_Price_Rental_Contract, Rental_Contract_Duration>4, ((Rental_Contract_Duration-4)*New_Rental_Contracts_Year_2+(Rental_Contract_Duration-3)*New_Rental_Contracts_Year_3+(Rental_Contract_Duration-2)*New_Rental_Contracts_Year_4+(Rental_Contract_Duration-1)*New_Rental_Contracts_Year_5)*Annual_Price_Rental_Contract, Rental_Contract_Duration>3, ((Rental_Contract_Duration-3)*New_Rental_Contracts_Year_3+(Rental_Contract_Duration-2)*New_Rental_Contracts_Year_4+(Rental_Contract_Duration-1)*New_Rental_Contracts_Year_5)*Annual_Price_Rental_Contract, Rental_Contract_Duration>2,((Rental_Contract_Duration-2)*New_Rental_Contracts_Year_4+(Rental_Contract_Duration-1)*New_Rental_Contracts_Year_5)*Annual_Price_Rental_Contract, Rental_Contract_Duration>1, (Rental_Contract_Duration-1)*New_Rental_Contracts_Year_5*Annual_Price_Rental_Contract, Rental_Contract_Duration<=1, 0)} -> 0
B13: Other positive balance sheet positions | E13: Total other positive positions (SUM) | F13: € | G13: =SUM(H13:M13) -> 0 | H13: =SUM(H14:H15) -> 0 | I13: =SUM(I14:I15) -> 0 | J13: =SUM(J14:J15) -> 0 | K13: =SUM(K14:K15) -> 0 | L13: =SUM(L14:L15) -> 0 | M13: =SUM(M14:M15) -> 0
C14: Loans | E14: Debt_Capital | F14: € | G14: =SUM(H14:M14) -> 0 | H14: =Debt_Capital -> 0
C15: Subsidies | E15: Public_Funding_Initial // Public_Funding_Annual | F15: € | G15: =SUM(H15:M15) -> 0 | H15: =Public_Funding_Initial -> 0 | I15: =Public_Funding_Annual -> 0 | J15: =Public_Funding_Annual -> 0 | K15: =Public_Funding_Annual -> 0 | L15: =Public_Funding_Annual -> 0 | M15: =Public_Funding_Annual -> 0
A17: CapEx | E17: Total CapEx (SUM) | F17: € | G17: =SUM(H17:M17) -> 0 | H17: =SUM(H19+H24) -> 0
B19: Assets | E19: SUM of all CapEX into Assets | G19: =SUM(H19:M19) -> 0 | H19: =SUM(H20:H22) -> 0
C20: Tangible Assets | E20: SUM(Invest_Land_Building+Invest_Technical_Equipment_Machinery+Invest_Office_Equipment) | F20: € | G20: =SUM(H20:M20) -> 0 | H20: =SUM(Invest_Land_Building+Invest_Technical_Equipment_Machinery+Invest_Office_Equipment) -> 0
C21: Intangible Assets | E21: SUM(Invest_Certificates+Invest_Patents_Licences+Invest_Software) | F21: € | G21: =SUM(H21:M21) -> 0 | H21: =SUM(Invest_Certificates+Invest_Patents_Licences+Invest_Software) -> 0
C22: Equity Holdings | E22: Invest_Equity_Holdings | F22: € | G22: =SUM(H22:M22) -> 0 | H22: =Invest_Equity_Holdings -> 0
B24: Comissioning Costs | E24: SUM of all Comissioning Costs | F24: € | G24: =SUM(H24:M24) -> 0 | H24: =SUM(H25:H28) -> 0
C25: Administrative Staff Costs | E25: Commissioning_Time_Administration_Year*Hourly_Rate_Administration | F25: € | G25: =SUM(H25:M25) -> 0 | H25: =Commissioning_Time_Administration*Hourly_Rate_Administration -> 0
C26: Production Staff Costs | E26: Commissioning_Time_Production_Staff_Year*Hourly_Rate_Production_Staff | F26: € | G26: =SUM(H26:M26) -> 0 | H26: =Commissioning_Time_Production_Staff*Hourly_Rate_Production_Staff -> 0
C27: Research and Development | E27: Commissioning_Costs_Research___Development | F27: € | G27: =SUM(H27:M27) -> 0 | H27: =Commissioning_Costs_Research___Development -> 0
C28: Other Comissioning Costs | E28: Additional_Commissioning_Costs_Year | F28: € | G28: =SUM(H28:M28) -> 0 | H28: =Additional_Commissioning_Costs -> 0
A30: OpEx | E30: Total OpEx (SUM) | F30: € | G30: =SUM(H30:M30) -> 0 | I30: =SUM(I32:I33) -> 0 | J30: =SUM(J32:J33) -> 0 | K30: =SUM(K32:K33) -> 0 | L30: =SUM(L32:L33) -> 0 | M30: =SUM(M32:M33) -> 0
B32: Administrative Overhead | E32: x% Mark-Up on other OpEx | F32: € | G32: =SUM(H32:M32) -> 0 | I32: =SUM(I33*Administrative_Overhead) -> 0 | J32: =SUM(J33*Administrative_Overhead) -> 0 | K32: =SUM(K33*Administrative_Overhead) -> 0 | L32: =SUM(L33*Administrative_Overhead) -> 0 | M32: =SUM(M33*Administrative_Overhead) -> 0
D33: Subtotal OpEx | E33: Total OpEx Subtotal (SUM)+Additional_Special_Costs | F33: € | I33: =SUM(I35,I37,I41,I47,I70,I74,I79,I83,I89,I93,I98,I103,I108)+Additional_Special_Costs -> 0 | J33: =SUM(J35,J37,J41,J47,J70,J74,J79,J83,J89,J93,J98,J103,J108)+Additional_Special_Costs -> 0 | K33: =SUM(K35,K37,K41,K47,K70,K74,K79,K83,K89,K93,K98,K103,K108)+Additional_Special_Costs -> 0 | L33: =SUM(L35,L37,L41,L47,L70,L74,L79,L83,L89,L93,L98,L103,L108)+Additional_Special_Costs -> 0 | M33: =SUM(M35,M37,M41,M47,M70,M74,M79,M83,M89,M93,M98,M103,M108)+Additional_Special_Costs -> 0
B35: Property Costs (exc. Energy) | E35: Basic_Rent+Property_Insurance+Additional_Ongoing_Property_Costs | F35: € | G35: =SUM(H35:M35) -> 0 | I35: =Basic_Rent+Property_Insurance+Additional_Ongoing_Property_Costs -> 0 | J35: =Basic_Rent+Property_Insurance+Additional_Ongoing_Property_Costs -> 0 | K35: =Basic_Rent+Property_Insurance+Additional_Ongoing_Property_Costs -> 0 | L35: =Basic_Rent+Property_Insurance+Additional_Ongoing_Property_Costs -> 0 | M35: =Basic_Rent+Property_Insurance+Additional_Ongoing_Property_Costs -> 0
B37: Energy Costs | E37: SUM of all Energy Costs | F37: € | G37: =SUM(H37:M37) -> 0 | I37: =SUM(I38:I39) -> 0 | J37: =SUM(J38:J39) -> 0 | K37: =SUM(K38:K39) -> 0 | L37: =SUM(L38:L39) -> 0 | M37: =SUM(M38:M39) -> 0
C38: Electricity | E38: (Base_Costs_Electricity+Energy_Consumption_Electricity*Consumption_Cost_Electricity)*(1+Annual_Price_Trend_Electricity)^t-1 | F38: € | G38: =SUM(H38:M38) -> 0 | I38: =(Base_Costs_Electricity+Energy_Consumption_Electricity*Consumption_Cost_Electricity)*(1+Annual_Price_Trend_Electricity)^0 -> 0 | J38: =(Base_Costs_Electricity+Energy_Consumption_Electricity*Consumption_Cost_Electricity)*(1+Annual_Price_Trend_Electricity)^1 -> 0 | K38: =(Base_Costs_Electricity+Energy_Consumption_Electricity*Consumption_Cost_Electricity)*(1+Annual_Price_Trend_Electricity)^2 -> 0 | L38: =(Base_Costs_Electricity+Energy_Consumption_Electricity*Consumption_Cost_Electricity)*(1+Annual_Price_Trend_Electricity)^3 -> 0 | M38: =(Base_Costs_Electricity+Energy_Consumption_Electricity*Consumption_Cost_Electricity)*(1+Annual_Price_Trend_Electricity)^4 -> 0
C39: Heating (Oil, Gas) | E39: (Base_Costs_Heating+Energy_Consumption_Heating*Consumption_Cost_Heating)*(1+Annual_Price_Trend_Heating)^t-1 | F39: € | G39: =SUM(H39:M39) -> 0 | I39: =(Base_Costs_Heating+Energy_Consumption_Heating*Consumption_Cost_Heating)*(1+Annual_Price_Trend_Heating)^0 -> 0 | J39: =(Base_Costs_Heating+Energy_Consumption_Heating*Consumption_Cost_Heating)*(1+Annual_Price_Trend_Heating)^1 -> 0 | K39: =(Base_Costs_Heating+Energy_Consumption_Heating*Consumption_Cost_Heating)*(1+Annual_Price_Trend_Heating)^2 -> 0 | L39: =(Base_Costs_Heating+Energy_Consumption_Heating*Consumption_Cost_Heating)*(1+Annual_Price_Trend_Heating)^3 -> 0 | M39: =(Base_Costs_Heating+Energy_Consumption_Heating*Consumption_Cost_Heating)*(1+Annual_Price_Trend_Heating)^4 -> 0
B41: Linear Production Base Case | E41: SUM of Costs in Linear Production + Special_Costs_Linear_Production | F41: € | G41: =SUM(H41:M41) -> 0 | I41: =SUM(I42:I45)+Special_Costs_Linear_Production -> 0 | J41: =SUM(J42:J45)+Special_Costs_Linear_Production -> 0 | K41: =SUM(K42:K45)+Special_Costs_Linear_Production -> 0 | L41: =SUM(L42:L45)+Special_Costs_Linear_Production -> 0 | M41: =SUM(M42:M45)+Special_Costs_Linear_Production -> 0
C42: Material Costs | E42: Sales_Year_t*Material_Cost_Linear_Production*(1+Annual_Price_Trend_Virgin_Materials)^t-1 | F42: € | G42: =SUM(H42:M42) -> 0 | I42: =Sales_Year_1*Material_Cost_Linear_Production*(1+Annual_Price_Trend_Virgin_Materials)^0 -> 0 | J42: =Sales_Year_2*Material_Cost_Linear_Production*(1+Annual_Price_Trend_Virgin_Materials)^1 -> 0 | K42: =Sales_Year_3*Material_Cost_Linear_Production*(1+Annual_Price_Trend_Virgin_Materials)^2 -> 0 | L42: =Sales_Year_4*Material_Cost_Linear_Production*(1+Annual_Price_Trend_Virgin_Materials)^3 -> 0 | M42: =Sales_Year_5*Material_Cost_Linear_Production*(1+Annual_Price_Trend_Virgin_Materials)^4 -> 0
C43: Disposal Costs | E43: Sales_Year_t*Disposal_Cost_Linear_Production | F43: € | G43: =SUM(H43:M43) -> 0 | I43: =Sales_Year_1*Disposal_Cost_Linear_Production -> 0 | J43: =Sales_Year_2*Disposal_Cost_Linear_Production -> 0 | K43: =Sales_Year_3*Disposal_Cost_Linear_Production -> 0 | L43: =Sales_Year_4*Disposal_Cost_Linear_Production -> 0 | M43: =Sales_Year_5*Disposal_Cost_Linear_Production -> 0
C44: Personel Costs | E44: Sales_Year_t*(Manual_Labour_Linear_Production*Hourly_Rate_Production_Staff)*(1-Annual_Efficiency_Increase_Manual_Labour)^t-1 | F44: € | G44: =SUM(H44:M44) -> 0 | I44: =Sales_Year_1*(Manual_Labour_Linear_Production*Hourly_Rate_Production_Staff)*(1-Annual_Efficiency_Increase_Manual_Labour)^0 -> 0 | J44: =Sales_Year_2*(Manual_Labour_Linear_Production*Hourly_Rate_Production_Staff)*(1-Annual_Efficiency_Increase_Manual_Labour)^1 -> 0 | K44: =Sales_Year_3*(Manual_Labour_Linear_Production*Hourly_Rate_Production_Staff)*(1-Annual_Efficiency_Increase_Manual_Labour)^2 -> 0 | L44: =Sales_Year_4*(Manual_Labour_Linear_Production*Hourly_Rate_Production_Staff)*(1-Annual_Efficiency_Increase_Manual_Labour)^3 -> 0 | M44: =Sales_Year_5*(Manual_Labour_Linear_Production*Hourly_Rate_Production_Staff)*(1-Annual_Efficiency_Increase_Manual_Labour)^4 -> 0
C45: Machine Costs | E45: Sales_Year_t*(Automated_Labour_Total_Linear_Production_Process*Hourly_Rate_Machines)*(1-Annual_Efficiency_Increase_Automated_Labour)^t-1 | F45: € | G45: =SUM(H45:M45) -> 0 | I45: =Sales_Year_1*(Automated_Labour_Linear_Production*Hourly_Rate_Machines)*(1-Annual_Efficiency_Increase_Automated_Labour)^0 -> 0 | J45: =Sales_Year_2*(Automated_Labour_Linear_Production*Hourly_Rate_Machines)*(1-Annual_Efficiency_Increase_Automated_Labour)^1 -> 0 | K45: =Sales_Year_3*(Automated_Labour_Linear_Production*Hourly_Rate_Machines)*(1-Annual_Efficiency_Increase_Automated_Labour)^2 -> 0 | L45: =Sales_Year_4*(Automated_Labour_Linear_Production*Hourly_Rate_Machines)*(1-Annual_Efficiency_Increase_Automated_Labour)^3 -> 0 | M45: =Sales_Year_5*(Automated_Labour_Linear_Production*Hourly_Rate_Machines)*(1-Annual_Efficiency_Increase_Automated_Labour)^4 -> 0
B47: Backward Logistics | E47: IF query on Billing Type followed by SUM of Costs for Backward Logistic + Core Premium + Special_Costs_Backward_Logistic | F47: € | G47: =SUM(H47:M47) -> 0 | I47: =IF('Step 1 - Case Selection'!V41="as a Flat Rate",I48+I54+Special_Costs_Backward_Logistics,SUM(I48,I55,I61,I68)+Special_Costs_Backward_Logistics) -> 0 | J47: =IF('Step 1 - Case Selection'!V41="as a Flat Rate",J48+J54+Special_Costs_Backward_Logistics,SUM(J48,J55,J61,J68)+Special_Costs_Backward_Logistics) -> 0 | K47: =IF('Step 1 - Case Selection'!V41="as a Flat Rate",K48+K54+Special_Costs_Backward_Logistics,SUM(K48,K55,K61,K68)+Special_Costs_Backward_Logistics) -> 0 | L47: =IF('Step 1 - Case Selection'!V41="as a Flat Rate",L48+L54+Special_Costs_Backward_Logistics,SUM(L48,L55,L61,L68)+Special_Costs_Backward_Logistics) -> 0 | M47: =IF('Step 1 - Case Selection'!V41="as a Flat Rate",M48+M54+Special_Costs_Backward_Logistics,SUM(M48,M55,M61,M68)+Special_Costs_Backward_Logistics) -> 0
D48: Core Premiums | E48: Core_Premium*(x49+x51) | F48: € | G48: =SUM(H48:M48) -> 0 | I48: =Core_Premium*(I49+I51) -> 0 | J48: =Core_Premium*(J49+J51) -> 0 | K48: =Core_Premium*(K49+K51) -> 0 | L48: =Core_Premium*(L49+L51) -> 0 | M48: =Core_Premium*(M49+M51) -> 0
D49: Required Cores Product Basis (before Sorting) | E49: ROUND(IF('Step 1 - Case Selection'!V27<>"Recycle"; Sales_Year_t/Core_Reuse_Rate*Required_Input_Cores);0) | F49: I | I49: =ROUND(IF('Step 1 - Case Selection'!V27<>"Recycle", Sales_Year_1/Core_Reuse_Rate*Required_Input_Cores),0) -> 0 | J49: =ROUND(IF('Step 1 - Case Selection'!V27<>"Recycle", Sales_Year_2/Core_Reuse_Rate*Required_Input_Cores),0) -> 0 | K49: =ROUND(IF('Step 1 - Case Selection'!V27<>"Recycle", Sales_Year_3/Core_Reuse_Rate*Required_Input_Cores),0) -> 0 | L49: =ROUND(IF('Step 1 - Case Selection'!V27<>"Recycle", Sales_Year_4/Core_Reuse_Rate*Required_Input_Cores),0) -> 0 | M49: =ROUND(IF('Step 1 - Case Selection'!V27<>"Recycle", Sales_Year_5/Core_Reuse_Rate*Required_Input_Cores),0) -> 0
D50: Required Cores Product Basis (after Sorting) | E50: ROUND(IF('Step 1 - Case Selection'!V27<>"Recycle"; Sales_Year_t*Required_Input_Cores);0) | F50: I | I50: =ROUND(IF('Step 1 - Case Selection'!V27<>"Recycle", Sales_Year_1*Required_Input_Cores),0) -> 0 | J50: =ROUND(IF('Step 1 - Case Selection'!V27<>"Recycle", Sales_Year_2*Required_Input_Cores),0) -> 0 | K50: =ROUND(IF('Step 1 - Case Selection'!V27<>"Recycle", Sales_Year_3*Required_Input_Cores),0) -> 0 | L50: =ROUND(IF('Step 1 - Case Selection'!V27<>"Recycle", Sales_Year_4*Required_Input_Cores),0) -> 0 | M50: =ROUND(IF('Step 1 - Case Selection'!V27<>"Recycle", Sales_Year_5*Required_Input_Cores),0) -> 0
D51: Required Cores Material Basis (before Sorting) | E51: ROUND(IF('Step 1 - Case Selection'!V27="Recycle"; Sales_Year_t/Output_Core_Material_for_Recycling/Core_Reuse_Rate; 0);0) | F51: I | I51: =ROUND(IF('Step 1 - Case Selection'!V27="Recycle", Sales_Year_1/Output_Core_Material_for_Recycling/Core_Reuse_Rate, 0),0) -> 0 | J51: =ROUND(IF('Step 1 - Case Selection'!V27="Recycle", Sales_Year_2/Output_Core_Material_for_Recycling/Core_Reuse_Rate, 0),0) -> 0 | K51: =ROUND(IF('Step 1 - Case Selection'!V27="Recycle", Sales_Year_3/Output_Core_Material_for_Recycling/Core_Reuse_Rate, 0),0) -> 0 | L51: =ROUND(IF('Step 1 - Case Selection'!V27="Recycle", Sales_Year_4/Output_Core_Material_for_Recycling/Core_Reuse_Rate, 0),0) -> 0 | M51: =ROUND(IF('Step 1 - Case Selection'!V27="Recycle", Sales_Year_5/Output_Core_Material_for_Recycling/Core_Reuse_Rate, 0),0) -> 0
D52: Required Cores Material Basis (after Sorting) | E52: ROUND(IF('Step 1 - Case Selection'!V27="Recycle"; Sales_Year_t/Output_Core_Material_for_Recycling; 0);0) | F52: I | I52: =ROUND(IF('Step 1 - Case Selection'!V27="Recycle", Sales_Year_1/Output_Core_Material_for_Recycling, 0),0) -> 0 | J52: =ROUND(IF('Step 1 - Case Selection'!V27="Recycle", Sales_Year_2/Output_Core_Material_for_Recycling, 0),0) -> 0 | K52: =ROUND(IF('Step 1 - Case Selection'!V27="Recycle", Sales_Year_3/Output_Core_Material_for_Recycling, 0),0) -> 0 | L52: =ROUND(IF('Step 1 - Case Selection'!V27="Recycle", Sales_Year_4/Output_Core_Material_for_Recycling, 0),0) -> 0 | M52: =ROUND(IF('Step 1 - Case Selection'!V27="Recycle", Sales_Year_5/Output_Core_Material_for_Recycling, 0),0) -> 0
D53: Ending Rental Agreements | E53: Inverse IF query of New_Rental_Contracts_Year_t | F53: I | I53: =IF('Step 1 - Case Selection'!V59<1, 0, IF(Rental_Contract_Duration<=1, New_Rental_Contracts_Year_1, 0)) -> 0 | J53: {=IF('Step 1 - Case Selection'!V59<2, 0, _xlfn.IFS(Rental_Contract_Duration<=1, New_Rental_Contracts_Year_2, Rental_Contract_Duration<=2, New_Rental_Contracts_Year_1, Rental_Contract_Duration>2, 0))} -> 0 | K53: {=IF('Step 1 - Case Selection'!V59<3, 0, _xlfn.IFS(Rental_Contract_Duration<=1, New_Rental_Contracts_Year_3, Rental_Contract_Duration<=2, New_Rental_Contracts_Year_2, Rental_Contract_Duration<=3, New_Rental_Contracts_Year_1, Rental_Contract_Duration>3, 0))} -> 0 | L53: {=IF('Step 1 - Case Selection'!V59<4, 0, _xlfn.IFS(Rental_Contract_Duration<=1, New_Rental_Contracts_Year_4, Rental_Contract_Duration<=2, New_Rental_Contracts_Year_3, Rental_Contract_Duration<=3, New_Rental_Contracts_Year_2, Rental_Contract_Duration<=4, New_Rental_Contracts_Year_1, Rental_Contract_Duration>4, 0))} -> 0 | M53: {=IF('Step 1 - Case Selection'!V59<5, 0, _xlfn.IFS(Rental_Contract_Duration<=1, New_Rental_Contracts_Year_5, Rental_Contract_Duration<=2, New_Rental_Contracts_Year_4, Rental_Contract_Duration<=3, New_Rental_Contracts_Year_3, Rental_Contract_Duration<=4, New_Rental_Contracts_Year_2, Rental_Contract_Duration<=5, New_Rental_Contracts_Year_1,Rental_Contract_Duration>5, 0))} -> 0 | N53: =SUM(New_Rental_Contracts_Year_1+New_Rental_Contracts_Year_2+New_Rental_Contracts_Year_3+New_Rental_Contracts_Year_4+New_Rental_Contracts_Year_5-(SUM(I53:M53))) -> 0
C54: Optional Flat Rate Calculation | E54: BL_Flat_Rate*(x49+x51+x53) | F54: € | G54: =SUM(H54:M54) -> 0 | I54: =BL_Flat_Rate*(I49+I51+I53) -> 0 | J54: =BL_Flat_Rate*(J49+J51+J53) -> 0 | K54: =BL_Flat_Rate*(K49+K51+K53) -> 0 | L54: =BL_Flat_Rate*(L49+L51+L53) -> 0 | M54: =BL_Flat_Rate*(M49+M51+M53) -> 0
C55: Backwards Logistic Sales | E55: SUM of all Costs for Backward Logistic in relation to Sales | F55: € | G55: =SUM(H55:M55) -> 0 | I55: =SUM(I56:I60) -> 0 | J55: =SUM(J56:J60) -> 0 | K55: =SUM(K56:K60) -> 0 | L55: =SUM(L56:L60) -> 0 | M55: =SUM(M56:M60) -> 0
D56: Costs for Direct Pick-Up System | E56: IF(BL_Type=1;(x49+x51)*(BL_Distance_Customer*BL_KM_Cost)*(1-Annual_Efficiency_Increase_Backward_Logistics)^t-1;0) | F56: € | G56: =SUM(H56:M56) -> 0 | I56: =IF(BL_Type=1,(I49+I51)*(BL_Distance_Customer*BL_KM_Cost)*(1-Annual_Efficiency_Increase_Backward_Logistics)^0,0) -> 0 | J56: =IF(BL_Type=1,(J49+J51)*(BL_Distance_Customer*BL_KM_Cost)*(1-Annual_Efficiency_Increase_Backward_Logistics)^1,0) -> 0 | K56: =IF(BL_Type=1,(K49+K51)*(BL_Distance_Customer*BL_KM_Cost)*(1-Annual_Efficiency_Increase_Backward_Logistics)^2,0) -> 0 | L56: =IF(BL_Type=1,(L49+L51)*(BL_Distance_Customer*BL_KM_Cost)*(1-Annual_Efficiency_Increase_Backward_Logistics)^3,0) -> 0 | M56: =IF(BL_Type=1,(M49+M51)*(BL_Distance_Customer*BL_KM_Cost)*(1-Annual_Efficiency_Increase_Backward_Logistics)^4,0) -> 0
D57: Costs for Multi-Step Pick-Up System / Step 1 (to CAS) | E57: IF(OR(BL_Type=2;BL_Type=3);(x49+x51)*(BL_Distance_Customer*BL_KM_Cost)*(1-Annual_Efficiency_Increase_Backward_Logistics)^t-1;0) | F57: € | G57: =SUM(H57:M57) -> 0 | I57: =IF(OR(BL_Type=2,BL_Type=3),(I49+I51)*(BL_Distance_Customer*BL_KM_Cost)*(1-Annual_Efficiency_Increase_Backward_Logistics)^0,0) -> 0 | J57: =IF(OR(BL_Type=2,BL_Type=3),(J49+J51)*(BL_Distance_Customer*BL_KM_Cost)*(1-Annual_Efficiency_Increase_Backward_Logistics)^1,0) -> 0 | K57: =IF(OR(BL_Type=2,BL_Type=3),(K49+K51)*(BL_Distance_Customer*BL_KM_Cost)*(1-Annual_Efficiency_Increase_Backward_Logistics)^2,0) -> 0 | L57: =IF(OR(BL_Type=2,BL_Type=3),(L49+L51)*(BL_Distance_Customer*BL_KM_Cost)*(1-Annual_Efficiency_Increase_Backward_Logistics)^3,0) -> 0 | M57: =IF(OR(BL_Type=2,BL_Type=3),(M49+M51)*(BL_Distance_Customer*BL_KM_Cost)*(1-Annual_Efficiency_Increase_Backward_Logistics)^4,0) -> 0
D58: Costs for Multi-Step Pick-Up System / Step 2 (to PS; no Sorting at CAS) | E58: IF(BL_Type=2;(x49+x51)*(BL_Distance_Core_Acquisition_Site*BL_KM_Cost)*(1-Annual_Efficiency_Increase_Backward_Logistics)^t-1;0) | F58: € | G58: =SUM(H58:M58) -> 0 | I58: =IF(BL_Type=2,(I49+I51)*(BL_Distance_Core_Acquisition_Site*BL_KM_Cost)*(1-Annual_Efficiency_Increase_Backward_Logistics)^0,0) -> 0 | J58: =IF(BL_Type=2,(J49+J51)*(BL_Distance_Core_Acquisition_Site*BL_KM_Cost)*(1-Annual_Efficiency_Increase_Backward_Logistics)^1,0) -> 0 | K58: =IF(BL_Type=2,(K49+K51)*(BL_Distance_Core_Acquisition_Site*BL_KM_Cost)*(1-Annual_Efficiency_Increase_Backward_Logistics)^2,0) -> 0 | L58: =IF(BL_Type=2,(L49+L51)*(BL_Distance_Core_Acquisition_Site*BL_KM_Cost)*(1-Annual_Efficiency_Increase_Backward_Logistics)^3,0) -> 0 | M58: =IF(BL_Type=2,(M49+M51)*(BL_Distance_Core_Acquisition_Site*BL_KM_Cost)*(1-Annual_Efficiency_Increase_Backward_Logistics)^4,0) -> 0
D59: Costs for Multi-Step Pick-Up System / Step 2 (to PS; Sorting at CAS) | E59: IF(BL_Type=3;(x50+x52)*(BL_Distance_Core_Acquisition_Site*BL_KM_Cost)*(1-Annual_Efficiency_Increase_Backward_Logistics)^t-1;0) | F59: € | G59: =SUM(H59:M59) -> 0 | I59: =IF(BL_Type=3,(I50+I52)*(BL_Distance_Core_Acquisition_Site*BL_KM_Cost)*(1-Annual_Efficiency_Increase_Backward_Logistics)^0,0) -> 0 | J59: =IF(BL_Type=3,(J50+J52)*(BL_Distance_Core_Acquisition_Site*BL_KM_Cost)*(1-Annual_Efficiency_Increase_Backward_Logistics)^1,0) -> 0 | K59: =IF(BL_Type=3,(K50+K52)*(BL_Distance_Core_Acquisition_Site*BL_KM_Cost)*(1-Annual_Efficiency_Increase_Backward_Logistics)^2,0) -> 0 | L59: =IF(BL_Type=3,(L50+L52)*(BL_Distance_Core_Acquisition_Site*BL_KM_Cost)*(1-Annual_Efficiency_Increase_Backward_Logistics)^3,0) -> 0 | M59: =IF(BL_Type=3,(M50+M52)*(BL_Distance_Core_Acquisition_Site*BL_KM_Cost)*(1-Annual_Efficiency_Increase_Backward_Logistics)^4,0) -> 0
D60: Costs for Shipment of Cores | E60: IF(BL_Type=4;(x49+x51)*(BL_Shipment_Cost);0) | F60: € | G60: =SUM(H60:M60) -> 0 | I60: =IF(BL_Type=4,(I49+I51)*(BL_Shipment_Cost),0) -> 0 | J60: =IF(BL_Type=4,(J49+J51)*(BL_Shipment_Cost),0) -> 0 | K60: =IF(BL_Type=4,(K49+K51)*(BL_Shipment_Cost),0) -> 0 | L60: =IF(BL_Type=4,(L49+L51)*(BL_Shipment_Cost),0) -> 0 | M60: =IF(BL_Type=4,(M49+M51)*(BL_Shipment_Cost),0) -> 0
C61: Backwards Logistic at the End of Rental Agreements | E61: SUM of all Costs for Backward Logistic in relation to Ending Rental Agreements | F61: € | G61: =SUM(H61:M61) -> 0 | I61: =SUM(I62:I66) -> 0 | J61: =SUM(J62:J66) -> 0 | K61: =SUM(K62:K66) -> 0 | L61: =SUM(L62:L66) -> 0 | M61: =SUM(M62:M66) -> 0
D62: Costs for Direct Pick-Up System | E62: IF(BL_Type=1;x53*(BL_Distance_Customer*BL_KM_Cost)*(1-Annual_Efficiency_Increase_Backward_Logistics)^t-1;0) | F62: € | G62: =SUM(H62:M62) -> 0 | I62: =IF(BL_Type=1,I53*(BL_Distance_Customer*BL_KM_Cost)*(1-Annual_Efficiency_Increase_Backward_Logistics)^0,0) -> 0 | J62: =IF(BL_Type=1,J53*(BL_Distance_Customer*BL_KM_Cost)*(1-Annual_Efficiency_Increase_Backward_Logistics)^1,0) -> 0 | K62: =IF(BL_Type=1,K53*(BL_Distance_Customer*BL_KM_Cost)*(1-Annual_Efficiency_Increase_Backward_Logistics)^2,0) -> 0 | L62: =IF(BL_Type=1,L53*(BL_Distance_Customer*BL_KM_Cost)*(1-Annual_Efficiency_Increase_Backward_Logistics)^3,0) -> 0 | M62: =IF(BL_Type=1,M53*(BL_Distance_Customer*BL_KM_Cost)*(1-Annual_Efficiency_Increase_Backward_Logistics)^4,0) -> 0 | N62: =IF(BL_Type=1,N53*(BL_Distance_Customer*BL_KM_Cost)*(1-Annual_Efficiency_Increase_Backward_Logistics)^5,0) -> 0
D63: Costs for Multi-Step Pick-Up System / Step 1 (to CAS) | E63: IF(OR(BL_Type=2;BL_Type=3);x53*(BL_Distance_Customer*BL_KM_Cost)*(1-Annual_Efficiency_Increase_Backward_Logistics)^t-1;0) | F63: € | G63: =SUM(H63:M63) -> 0 | I63: =IF(OR(BL_Type=2,BL_Type=3),I53*(BL_Distance_Customer*BL_KM_Cost)*(1-Annual_Efficiency_Increase_Backward_Logistics)^0,0) -> 0 | J63: =IF(OR(BL_Type=2,BL_Type=3),J53*(BL_Distance_Customer*BL_KM_Cost)*(1-Annual_Efficiency_Increase_Backward_Logistics)^1,0) -> 0 | K63: =IF(OR(BL_Type=2,BL_Type=3),K53*(BL_Distance_Customer*BL_KM_Cost)*(1-Annual_Efficiency_Increase_Backward_Logistics)^2,0) -> 0 | L63: =IF(OR(BL_Type=2,BL_Type=3),L53*(BL_Distance_Customer*BL_KM_Cost)*(1-Annual_Efficiency_Increase_Backward_Logistics)^3,0) -> 0 | M63: =IF(OR(BL_Type=2,BL_Type=3),M53*(BL_Distance_Customer*BL_KM_Cost)*(1-Annual_Efficiency_Increase_Backward_Logistics)^4,0) -> 0 | N63: =IF(OR(BL_Type=2,BL_Type=3),N53*(BL_Distance_Customer*BL_KM_Cost)*(1-Annual_Efficiency_Increase_Backward_Logistics)^5,0) -> 0
D64: Costs for Multi-Step Pick-Up System / Step 2 (to PS; no Sorting at CAS) | E64: IF(BL_Type=2;x53*(BL_Distance_Core_Acquisition_Site*BL_KM_Cost)*(1-Annual_Efficiency_Increase_Backward_Logistics)^t-1;0) | F64: € | G64: =SUM(H64:M64) -> 0 | I64: =IF(BL_Type=2,I53*(BL_Distance_Core_Acquisition_Site*BL_KM_Cost)*(1-Annual_Efficiency_Increase_Backward_Logistics)^0,0) -> 0 | J64: =IF(BL_Type=2,J53*(BL_Distance_Core_Acquisition_Site*BL_KM_Cost)*(1-Annual_Efficiency_Increase_Backward_Logistics)^1,0) -> 0 | K64: =IF(BL_Type=2,K53*(BL_Distance_Core_Acquisition_Site*BL_KM_Cost)*(1-Annual_Efficiency_Increase_Backward_Logistics)^2,0) -> 0 | L64: =IF(BL_Type=2,L53*(BL_Distance_Core_Acquisition_Site*BL_KM_Cost)*(1-Annual_Efficiency_Increase_Backward_Logistics)^3,0) -> 0 | M64: =IF(BL_Type=2,M53*(BL_Distance_Core_Acquisition_Site*BL_KM_Cost)*(1-Annual_Efficiency_Increase_Backward_Logistics)^4,0) -> 0 | N64: =IF(BL_Type=2,N53*(BL_Distance_Core_Acquisition_Site*BL_KM_Cost)*(1-Annual_Efficiency_Increase_Backward_Logistics)^5,0) -> 0
D65: Costs for Multi-Step Pick-Up System / Step 2 (to PS; Sorting at CAS) | E65: IF(BL_Type=3;x53*Core_Reuse_Rate*(BL_Distance_Core_Acquisition_Site*BL_KM_Cost)*(1-Annual_Efficiency_Increase_Backward_Logistics)^t-1;0) | F65: € | G65: =SUM(H65:M65) -> 0 | I65: =IF(BL_Type=3,I53*Core_Reuse_Rate*(BL_Distance_Core_Acquisition_Site*BL_KM_Cost)*(1-Annual_Efficiency_Increase_Backward_Logistics)^0,0) -> 0 | J65: =IF(BL_Type=3,J53*Core_Reuse_Rate*(BL_Distance_Core_Acquisition_Site*BL_KM_Cost)*(1-Annual_Efficiency_Increase_Backward_Logistics)^1,0) -> 0 | K65: =IF(BL_Type=3,K53*Core_Reuse_Rate*(BL_Distance_Core_Acquisition_Site*BL_KM_Cost)*(1-Annual_Efficiency_Increase_Backward_Logistics)^2,0) -> 0 | L65: =IF(BL_Type=3,L53*Core_Reuse_Rate*(BL_Distance_Core_Acquisition_Site*BL_KM_Cost)*(1-Annual_Efficiency_Increase_Backward_Logistics)^3,0) -> 0 | M65: =IF(BL_Type=3,M53*Core_Reuse_Rate*(BL_Distance_Core_Acquisition_Site*BL_KM_Cost)*(1-Annual_Efficiency_Increase_Backward_Logistics)^4,0) -> 0 | N65: =IF(BL_Type=3,N53*Core_Reuse_Rate*(BL_Distance_Core_Acquisition_Site*BL_KM_Cost)*(1-Annual_Efficiency_Increase_Backward_Logistics)^5,0) -> 0
D66: Costs for Shipment of Cores | E66: IF(BL_Type=4;x53*(BL_Shipment_Cost);0) | F66: € | G66: =SUM(H66:M66) -> 0 | I66: =IF(BL_Type=4,I53*(BL_Shipment_Cost),0) -> 0 | J66: =IF(BL_Type=4,J53*(BL_Shipment_Cost),0) -> 0 | K66: =IF(BL_Type=4,K53*(BL_Shipment_Cost),0) -> 0 | L66: =IF(BL_Type=4,L53*(BL_Shipment_Cost),0) -> 0 | M66: =IF(BL_Type=4,M53*(BL_Shipment_Cost),0) -> 0 | N66: =IF(BL_Type=4,N53*(BL_Shipment_Cost),0) -> 0
D67: Pending Backward Logistics Costs after Year 5 | E67: SUM of Rental Agreements ending after Year 5*Corresponding Backward Logistic Costs | F67: € | G67: =SUM(H67:M67) -> 0 | N67: =SUM(N62:N66) -> 0
C68: Packaging Costs | E68: BL_Packaging_Cost*(x49+x51+x53) | F68: € | G68: =SUM(H68:M68) -> 0 | I68: =BL_Packaging_Cost*(I49+I51+I53) -> 0 | J68: =BL_Packaging_Cost*(J49+J51+J53) -> 0 | K68: =BL_Packaging_Cost*(K49+K51+K53) -> 0 | L68: =BL_Packaging_Cost*(L49+L51+L53) -> 0 | M68: =BL_Packaging_Cost*(M49+M51+M53) -> 0
B70: Dismantling | E70: SUM of Costs for Dismantling + Special_Costs_Dismantling | F70: € | G70: =SUM(H70:M70) -> 0 | I70: =SUM(I71:I72)+Special_Costs_Dismantling -> 0 | J70: =SUM(J71:J72)+Special_Costs_Dismantling -> 0 | K70: =SUM(K71:K72)+Special_Costs_Dismantling -> 0 | L70: =SUM(L71:L72)+Special_Costs_Dismantling -> 0 | M70: =SUM(M71:M72)+Special_Costs_Dismantling -> 0
C71: Personel Costs | E71: Manual_Labour_Dismantling*Hourly_Rate_Production_Staff*(x49+x51)*(1-Annual_Efficiency_Increase_Manual_Labour)^t-1 | F71: € | G71: =SUM(H71:M71) -> 0 | I71: =Manual_Labour_Dismantling*Hourly_Rate_Production_Staff*(I49+I51)*(1-Annual_Efficiency_Increase_Manual_Labour)^0 -> 0 | J71: =Manual_Labour_Dismantling*Hourly_Rate_Production_Staff*(J49+J51)*(1-Annual_Efficiency_Increase_Manual_Labour)^1 -> 0 | K71: =Manual_Labour_Dismantling*Hourly_Rate_Production_Staff*(K49+K51)*(1-Annual_Efficiency_Increase_Manual_Labour)^2 -> 0 | L71: =Manual_Labour_Dismantling*Hourly_Rate_Production_Staff*(L49+L51)*(1-Annual_Efficiency_Increase_Manual_Labour)^3 -> 0 | M71: =Manual_Labour_Dismantling*Hourly_Rate_Production_Staff*(M49+M51)*(1-Annual_Efficiency_Increase_Manual_Labour)^4 -> 0
C72: Machine Costs | E72: Automated_Labour_Dismantling*Hourly_Rate_Machines*(x49+x51)*(1-Annual_Efficiency_Increase_Automated_Labour)^t-1 | F72: € | G72: =SUM(H72:M72) -> 0 | I72: =Automated_Labour_Dismantling*Hourly_Rate_Machines*(I49+I51)*(1-Annual_Efficiency_Increase_Automated_Labour)^0 -> 0 | J72: =Automated_Labour_Dismantling*Hourly_Rate_Machines*(J49+J51)*(1-Annual_Efficiency_Increase_Automated_Labour)^1 -> 0 | K72: =Automated_Labour_Dismantling*Hourly_Rate_Machines*(K49+K51)*(1-Annual_Efficiency_Increase_Automated_Labour)^2 -> 0 | L72: =Automated_Labour_Dismantling*Hourly_Rate_Machines*(L49+L51)*(1-Annual_Efficiency_Increase_Automated_Labour)^3 -> 0 | M72: =Automated_Labour_Dismantling*Hourly_Rate_Machines*(M49+M51)*(1-Annual_Efficiency_Increase_Automated_Labour)^4 -> 0
B74: Identification and Sorting | E74: SUM of Costs for Identification & Sorting + Special_Costs_Identification___Sorting | F74: € | G74: =SUM(H74:M74) -> 0 | I74: =SUM(I75:I77)+Special_Costs_Identification___Sorting -> 0 | J74: =SUM(J75:J77)+Special_Costs_Identification___Sorting -> 0 | K74: =SUM(K75:K77)+Special_Costs_Identification___Sorting -> 0 | L74: =SUM(L75:L77)+Special_Costs_Identification___Sorting -> 0 | M74: =SUM(M75:M77)+Special_Costs_Identification___Sorting -> 0
C75: Personel Costs | E75: Manual_Labour_Identification___Sorting*Hourly_Rate_Production_Staff*(x49+x51)*(1-Annual_Efficiency_Increase_Manual_Labour)^t-1 | F75: € | G75: =SUM(H75:M75) -> 0 | I75: =Manual_Labour_Identification___Sorting*Hourly_Rate_Production_Staff*(I49+I51)*(1-Annual_Efficiency_Increase_Manual_Labour)^0 -> 0 | J75: =Manual_Labour_Identification___Sorting*Hourly_Rate_Production_Staff*(J49+J51)*(1-Annual_Efficiency_Increase_Manual_Labour)^1 -> 0 | K75: =Manual_Labour_Identification___Sorting*Hourly_Rate_Production_Staff*(K49+K51)*(1-Annual_Efficiency_Increase_Manual_Labour)^2 -> 0 | L75: =Manual_Labour_Identification___Sorting*Hourly_Rate_Production_Staff*(L49+L51)*(1-Annual_Efficiency_Increase_Manual_Labour)^3 -> 0 | M75: =Manual_Labour_Identification___Sorting*Hourly_Rate_Production_Staff*(M49+M51)*(1-Annual_Efficiency_Increase_Manual_Labour)^4 -> 0
C76: Machine Costs | E76: Automated_Labour_Identification___Sorting*Hourly_Rate_Machines*(x49+x51)*(1-Annual_Efficiency_Increase_Automated_Labour)^t-1 | F76: € | G76: =SUM(H76:M76) -> 0 | I76: =Automated_Labour_Identification___Sorting*Hourly_Rate_Machines*(I49+I51)*(1-Annual_Efficiency_Increase_Automated_Labour)^0 -> 0 | J76: =Automated_Labour_Identification___Sorting*Hourly_Rate_Machines*(J49+J51)*(1-Annual_Efficiency_Increase_Automated_Labour)^1 -> 0 | K76: =Automated_Labour_Identification___Sorting*Hourly_Rate_Machines*(K49+K51)*(1-Annual_Efficiency_Increase_Automated_Labour)^2 -> 0 | L76: =Automated_Labour_Identification___Sorting*Hourly_Rate_Machines*(L49+L51)*(1-Annual_Efficiency_Increase_Automated_Labour)^3 -> 0 | M76: =Automated_Labour_Identification___Sorting*Hourly_Rate_Machines*(M49+M51)*(1-Annual_Efficiency_Increase_Automated_Labour)^4 -> 0
C77: Disposal Costs Cores | E77: Disposal_Cost_Core*((x49-x50)+(x51-x52)) | F77: € | G77: =SUM(H77:M77) -> 0 | I77: =Disposal_Cost_Core*((I49-I50)+(I51-I52)) -> 0 | J77: =Disposal_Cost_Core*((J49-J50)+(J51-J52)) -> 0 | K77: =Disposal_Cost_Core*((K49-K50)+(K51-K52)) -> 0 | L77: =Disposal_Cost_Core*((L49-L50)+(L51-L52)) -> 0 | M77: =Disposal_Cost_Core*((M49-M50)+(M51-M52)) -> 0
B79: Disassembly | E79: SUM of Costs for Disassembly + Special_Costs_Disassembly | F79: € | G79: =SUM(H79:M79) -> 0 | I79: =SUM(I80:I81)+Special_Costs_Disassembly -> 0 | J79: =SUM(J80:J81)+Special_Costs_Disassembly -> 0 | K79: =SUM(K80:K81)+Special_Costs_Disassembly -> 0 | L79: =SUM(L80:L81)+Special_Costs_Disassembly -> 0 | M79: =SUM(M80:M81)+Special_Costs_Disassembly -> 0
C80: Personel Costs | E80: Manual_Labour_Disassembly*Hourly_Rate_Production_Staff*(x50+x52)*(1-Annual_Efficiency_Increase_Manual_Labour)^t-1 | F80: € | G80: =SUM(H80:M80) -> 0 | I80: =Manual_Labour_Disassembly*Hourly_Rate_Production_Staff*(I50+I52)*(1-Annual_Efficiency_Increase_Manual_Labour)^0 -> 0 | J80: =Manual_Labour_Disassembly*Hourly_Rate_Production_Staff*(J50+J52)*(1-Annual_Efficiency_Increase_Manual_Labour)^1 -> 0 | K80: =Manual_Labour_Disassembly*Hourly_Rate_Production_Staff*(K50+K52)*(1-Annual_Efficiency_Increase_Manual_Labour)^2 -> 0 | L80: =Manual_Labour_Disassembly*Hourly_Rate_Production_Staff*(L50+L52)*(1-Annual_Efficiency_Increase_Manual_Labour)^3 -> 0 | M80: =Manual_Labour_Disassembly*Hourly_Rate_Production_Staff*(M50+M52)*(1-Annual_Efficiency_Increase_Manual_Labour)^4 -> 0
C81: Machine Costs | E81: Automated_Labour_Disassembly*Hourly_Rate_Machines*(x50+x52)*(1-Annual_Efficiency_Increase_Automated_Labour)^t-1 | F81: € | G81: =SUM(H81:M81) -> 0 | I81: =Automated_Labour_Disassembly*Hourly_Rate_Machines*(I50+I52)*(1-Annual_Efficiency_Increase_Automated_Labour)^0 -> 0 | J81: =Automated_Labour_Disassembly*Hourly_Rate_Machines*(J50+J52)*(1-Annual_Efficiency_Increase_Automated_Labour)^1 -> 0 | K81: =Automated_Labour_Disassembly*Hourly_Rate_Machines*(K50+K52)*(1-Annual_Efficiency_Increase_Automated_Labour)^2 -> 0 | L81: =Automated_Labour_Disassembly*Hourly_Rate_Machines*(L50+L52)*(1-Annual_Efficiency_Increase_Automated_Labour)^3 -> 0 | M81: =Automated_Labour_Disassembly*Hourly_Rate_Machines*(M50+M52)*(1-Annual_Efficiency_Increase_Automated_Labour)^4 -> 0
B83: Inspection | E83: Total Costs for Inspection + Special_Costs_Inspection | F83: € | G83: =SUM(H83:M83) -> 0 | I83: =SUM(I84:I87)+Special_Costs_Inspection -> 0 | J83: =SUM(J84:J87)+Special_Costs_Inspection -> 0 | K83: =SUM(K84:K87)+Special_Costs_Inspection -> 0 | L83: =SUM(L84:L87)+Special_Costs_Inspection -> 0 | M83: =SUM(M84:M87)+Special_Costs_Inspection -> 0
C84: Personel Costs | E84: Manual_Labour_Inspection*Hourly_Rate_Production_Staff*(x50)*(1-Annual_Efficiency_Increase_Manual_Labour)^t-1 | F84: € | G84: =SUM(H84:M84) -> 0 | I84: =Manual_Labour_Inspection*Hourly_Rate_Production_Staff*(I50)*(1-Annual_Efficiency_Increase_Manual_Labour)^0 -> 0 | J84: =Manual_Labour_Inspection*Hourly_Rate_Production_Staff*(J50)*(1-Annual_Efficiency_Increase_Manual_Labour)^1 -> 0 | K84: =Manual_Labour_Inspection*Hourly_Rate_Production_Staff*(K50)*(1-Annual_Efficiency_Increase_Manual_Labour)^2 -> 0 | L84: =Manual_Labour_Inspection*Hourly_Rate_Production_Staff*(L50)*(1-Annual_Efficiency_Increase_Manual_Labour)^3 -> 0 | M84: =Manual_Labour_Inspection*Hourly_Rate_Production_Staff*(M50)*(1-Annual_Efficiency_Increase_Manual_Labour)^4 -> 0
C85: Machine Costs | E85: Automated_Labour_Inspection*Hourly_Rate_Machines*(x50)*(1-Annual_Efficiency_Increase_Automated_Labour)^t-1 | F85: € | G85: =SUM(H85:M85) -> 0 | I85: =Automated_Labour_Inspection*Hourly_Rate_Machines*(I50)*(1-Annual_Efficiency_Increase_Automated_Labour)^0 -> 0 | J85: =Automated_Labour_Inspection*Hourly_Rate_Machines*(J50)*(1-Annual_Efficiency_Increase_Automated_Labour)^1 -> 0 | K85: =Automated_Labour_Inspection*Hourly_Rate_Machines*(K50)*(1-Annual_Efficiency_Increase_Automated_Labour)^2 -> 0 | L85: =Automated_Labour_Inspection*Hourly_Rate_Machines*(L50)*(1-Annual_Efficiency_Increase_Automated_Labour)^3 -> 0 | M85: =Automated_Labour_Inspection*Hourly_Rate_Machines*(M50)*(1-Annual_Efficiency_Increase_Automated_Labour)^4 -> 0
C86: Disposal Costs Scrap Components | E86: Disposal_Cost_Component*Scrap_Rate*Reusable_Components*(x50+x52) | F86: € | G86: =SUM(H86:M86) -> 0 | I86: =Disposal_Cost_Component*Scrap_Rate*Reusable_Components*(I50+I52) -> 0 | J86: =Disposal_Cost_Component*Scrap_Rate*Reusable_Components*(J50+J52) -> 0 | K86: =Disposal_Cost_Component*Scrap_Rate*Reusable_Components*(K50+K52) -> 0 | L86: =Disposal_Cost_Component*Scrap_Rate*Reusable_Components*(L50+L52) -> 0 | M86: =Disposal_Cost_Component*Scrap_Rate*Reusable_Components*(M50+M52) -> 0
C87: Disposal Costs Not Reusable Components | E87: Disposal_Cost_Component*Not_Reusable_Components*(x50+x52) | F87: € | G87: =SUM(H87:M87) -> 0 | I87: =Disposal_Cost_Component*Not_Reusable_Components*(I50+I52) -> 0 | J87: =Disposal_Cost_Component*Not_Reusable_Components*(J50+J52) -> 0 | K87: =Disposal_Cost_Component*Not_Reusable_Components*(K50+K52) -> 0 | L87: =Disposal_Cost_Component*Not_Reusable_Components*(L50+L52) -> 0 | M87: =Disposal_Cost_Component*Not_Reusable_Components*(M50+M52) -> 0
B89: Cleaning | E89: SUM of Costs for Cleaning + Special_Costs_Cleaning | F89: € | G89: =SUM(H89:M89) -> 0 | I89: =SUM(I90:I91)+Special_Costs_Cleaning -> 0 | J89: =SUM(J90:J91)+Special_Costs_Cleaning -> 0 | K89: =SUM(K90:K91)+Special_Costs_Cleaning -> 0 | L89: =SUM(L90:L91)+Special_Costs_Cleaning -> 0 | M89: =SUM(M90:M91)+Special_Costs_Cleaning -> 0
C90: Personel Costs | E90: Manual_Labour_Cleaning*Hourly_Rate_Production_Staff*(x50)*(1-Annual_Efficiency_Increase_Manual_Labour)^t-1 | F90: € | G90: =SUM(H90:M90) -> 0 | I90: =Manual_Labour_Cleaning*Hourly_Rate_Production_Staff*(I50)*(1-Annual_Efficiency_Increase_Manual_Labour)^0 -> 0 | J90: =Manual_Labour_Cleaning*Hourly_Rate_Production_Staff*(J50)*(1-Annual_Efficiency_Increase_Manual_Labour)^1 -> 0 | K90: =Manual_Labour_Cleaning*Hourly_Rate_Production_Staff*(K50)*(1-Annual_Efficiency_Increase_Manual_Labour)^2 -> 0 | L90: =Manual_Labour_Cleaning*Hourly_Rate_Production_Staff*(L50)*(1-Annual_Efficiency_Increase_Manual_Labour)^3 -> 0 | M90: =Manual_Labour_Cleaning*Hourly_Rate_Production_Staff*(M50)*(1-Annual_Efficiency_Increase_Manual_Labour)^4 -> 0
C91: Machine Costs | E91: Automated_Labour_Cleaning*Hourly_Rate_Machines*(x50)*(1-Annual_Efficiency_Increase_Automated_Labour)^t-1 | F91: € | G91: =SUM(H91:M91) -> 0 | I91: =Automated_Labour_Cleaning*Hourly_Rate_Machines*(I50)*(1-Annual_Efficiency_Increase_Automated_Labour)^0 -> 0 | J91: =Automated_Labour_Cleaning*Hourly_Rate_Machines*(J50)*(1-Annual_Efficiency_Increase_Automated_Labour)^1 -> 0 | K91: =Automated_Labour_Cleaning*Hourly_Rate_Machines*(K50)*(1-Annual_Efficiency_Increase_Automated_Labour)^2 -> 0 | L91: =Automated_Labour_Cleaning*Hourly_Rate_Machines*(L50)*(1-Annual_Efficiency_Increase_Automated_Labour)^3 -> 0 | M91: =Automated_Labour_Cleaning*Hourly_Rate_Machines*(M50)*(1-Annual_Efficiency_Increase_Automated_Labour)^4 -> 0
B93: Restoring | E93: SUM of Costs for Restoring + Special_Costs_Restoring | F93: € | G93: =SUM(H93:M93) -> 0 | I93: =SUM(I94:I96)+Special_Costs_Restoring -> 0 | J93: =SUM(J94:J96)+Special_Costs_Restoring -> 0 | K93: =SUM(K94:K96)+Special_Costs_Restoring -> 0 | L93: =SUM(L94:L96)+Special_Costs_Restoring -> 0 | M93: =SUM(M94:M96)+Special_Costs_Restoring -> 0
C94: Personel Costs | E94: Manual_Labour_Restoring*Hourly_Rate_Production_Staff*(x50)*(1-Annual_Efficiency_Increase_Manual_Labour)^t-1 | F94: € | G94: =SUM(H94:M94) -> 0 | I94: =Manual_Labour_Restoring*Hourly_Rate_Production_Staff*(I50)*(1-Annual_Efficiency_Increase_Manual_Labour)^0 -> 0 | J94: =Manual_Labour_Restoring*Hourly_Rate_Production_Staff*(J50)*(1-Annual_Efficiency_Increase_Manual_Labour)^1 -> 0 | K94: =Manual_Labour_Restoring*Hourly_Rate_Production_Staff*(K50)*(1-Annual_Efficiency_Increase_Manual_Labour)^2 -> 0 | L94: =Manual_Labour_Restoring*Hourly_Rate_Production_Staff*(L50)*(1-Annual_Efficiency_Increase_Manual_Labour)^3 -> 0 | M94: =Manual_Labour_Restoring*Hourly_Rate_Production_Staff*(M50)*(1-Annual_Efficiency_Increase_Manual_Labour)^4 -> 0
C95: Machine Costs | E95: Automated_Labour_Restoring*Hourly_Rate_Machines*(x50)*(1-Annual_Efficiency_Increase_Automated_Labour)^t-1 | F95: € | G95: =SUM(H95:M95) -> 0 | I95: =Automated_Labour_Restoring*Hourly_Rate_Machines*(I50)*(1-Annual_Efficiency_Increase_Automated_Labour)^0 -> 0 | J95: =Automated_Labour_Restoring*Hourly_Rate_Machines*(J50)*(1-Annual_Efficiency_Increase_Automated_Labour)^1 -> 0 | K95: =Automated_Labour_Restoring*Hourly_Rate_Machines*(K50)*(1-Annual_Efficiency_Increase_Automated_Labour)^2 -> 0 | L95: =Automated_Labour_Restoring*Hourly_Rate_Machines*(L50)*(1-Annual_Efficiency_Increase_Automated_Labour)^3 -> 0 | M95: =Automated_Labour_Restoring*Hourly_Rate_Machines*(M50)*(1-Annual_Efficiency_Increase_Automated_Labour)^4 -> 0
C96: Material Costs (e.g. Paints) | E96: Material_Cost_Restoring*x50*(1+Annual_Price_Trend_Virgin_Materials)^t-1 | F96: € | G96: =SUM(H96:M96) -> 0 | I96: =Material_Cost_Restoring*I50*(1+Annual_Price_Trend_Virgin_Materials)^0 -> 0 | J96: =Material_Cost_Restoring*J50*(1+Annual_Price_Trend_Virgin_Materials)^1 -> 0 | K96: =Material_Cost_Restoring*K50*(1+Annual_Price_Trend_Virgin_Materials)^2 -> 0 | L96: =Material_Cost_Restoring*L50*(1+Annual_Price_Trend_Virgin_Materials)^3 -> 0 | M96: =Material_Cost_Restoring*M50*(1+Annual_Price_Trend_Virgin_Materials)^4 -> 0
B98: Assembly | E98: SUM of Costs for Assembly + Special_Costs_Assembly | F98: € | G98: =SUM(H98:M98) -> 0 | I98: =SUM(I99:I101)+Special_Costs_Assembly -> 0 | J98: =SUM(J99:J101)+Special_Costs_Assembly -> 0 | K98: =SUM(K99:K101)+Special_Costs_Assembly -> 0 | L98: =SUM(L99:L101)+Special_Costs_Assembly -> 0 | M98: =SUM(M99:M101)+Special_Costs_Assembly -> 0
C99: Personel Costs | E99: Manual_Labour_Assembly*Hourly_Rate_Production_Staff*(Sales_Year_t)*(1-Annual_Efficiency_Increase_Manual_Labour)^t-1 | F99: € | G99: =SUM(H99:M99) -> 0 | I99: =Manual_Labour_Assembly*Hourly_Rate_Production_Staff*(Sales_Year_1)*(1-Annual_Efficiency_Increase_Manual_Labour)^0 -> 0 | J99: =Manual_Labour_Assembly*Hourly_Rate_Production_Staff*(Sales_Year_2)*(1-Annual_Efficiency_Increase_Manual_Labour)^1 -> 0 | K99: =Manual_Labour_Assembly*Hourly_Rate_Production_Staff*(Sales_Year_3)*(1-Annual_Efficiency_Increase_Manual_Labour)^2 -> 0 | L99: =Manual_Labour_Assembly*Hourly_Rate_Production_Staff*(Sales_Year_4)*(1-Annual_Efficiency_Increase_Manual_Labour)^3 -> 0 | M99: =Manual_Labour_Assembly*Hourly_Rate_Production_Staff*(Sales_Year_5)*(1-Annual_Efficiency_Increase_Manual_Labour)^4 -> 0
C100: Machine Costs | E100: Automated_Labour_Assembly*Hourly_Rate_Machines*(Sales_Year_t)*(1-Annual_Efficiency_Increase_Automated_Labour)^t-1 | F100: € | G100: =SUM(H100:M100) -> 0 | I100: =Automated_Labour_Assembly*Hourly_Rate_Machines*(Sales_Year_1)*(1-Annual_Efficiency_Increase_Automated_Labour)^0 -> 0 | J100: =Automated_Labour_Assembly*Hourly_Rate_Machines*(Sales_Year_2)*(1-Annual_Efficiency_Increase_Automated_Labour)^1 -> 0 | K100: =Automated_Labour_Assembly*Hourly_Rate_Machines*(Sales_Year_3)*(1-Annual_Efficiency_Increase_Automated_Labour)^2 -> 0 | L100: =Automated_Labour_Assembly*Hourly_Rate_Machines*(Sales_Year_4)*(1-Annual_Efficiency_Increase_Automated_Labour)^3 -> 0 | M100: =Automated_Labour_Assembly*Hourly_Rate_Machines*(Sales_Year_5)*(1-Annual_Efficiency_Increase_Automated_Labour)^4 -> 0
C101: Material Costs (e.g. Spare Parts) | E101: (Spare_Part_Costs+Additional_Component_Costs)*Sales_Year_t*(1+Annual_Price_Trend_Virgin_Materials)^t-1 | F101: € | G101: =SUM(H101:M101) -> 0 | I101: =(Spare_Part_Costs+Additional_Component_Costs)*Sales_Year_1*(1+Annual_Price_Trend_Virgin_Materials)^0 -> 0 | J101: =(Spare_Part_Costs+Additional_Component_Costs)*Sales_Year_2*(1+Annual_Price_Trend_Virgin_Materials)^1 -> 0 | K101: =(Spare_Part_Costs+Additional_Component_Costs)*Sales_Year_3*(1+Annual_Price_Trend_Virgin_Materials)^2 -> 0 | L101: =(Spare_Part_Costs+Additional_Component_Costs)*Sales_Year_4*(1+Annual_Price_Trend_Virgin_Materials)^3 -> 0 | M101: =(Spare_Part_Costs+Additional_Component_Costs)*Sales_Year_5*(1+Annual_Price_Trend_Virgin_Materials)^4 -> 0
B103: Testing | E103: SUM of Costs for Testing + Special_Costs_Testing | F103: € | G103: =SUM(H103:M103) -> 0 | I103: =SUM(I104:I105)+Special_Costs_Testing -> 0 | J103: =SUM(J104:J105)+Special_Costs_Testing -> 0 | K103: =SUM(K104:K105)+Special_Costs_Testing -> 0 | L103: =SUM(L104:L105)+Special_Costs_Testing -> 0 | M103: =SUM(M104:M105)+Special_Costs_Testing -> 0
C104: Personel Costs | E104: Manual_Labour_Testing*Hourly_Rate_Production_Staff*(Sales_Year_t)*(1-Annual_Efficiency_Increase_Manual_Labour)^t-1 | F104: € | G104: =SUM(H104:M104) -> 0 | I104: =Manual_Labour_Testing*Hourly_Rate_Production_Staff*(Sales_Year_1)*(1-Annual_Efficiency_Increase_Manual_Labour)^0 -> 0 | J104: =Manual_Labour_Testing*Hourly_Rate_Production_Staff*(Sales_Year_2)*(1-Annual_Efficiency_Increase_Manual_Labour)^1 -> 0 | K104: =Manual_Labour_Testing*Hourly_Rate_Production_Staff*(Sales_Year_3)*(1-Annual_Efficiency_Increase_Manual_Labour)^2 -> 0 | L104: =Manual_Labour_Testing*Hourly_Rate_Production_Staff*(Sales_Year_4)*(1-Annual_Efficiency_Increase_Manual_Labour)^3 -> 0 | M104: =Manual_Labour_Testing*Hourly_Rate_Production_Staff*(Sales_Year_5)*(1-Annual_Efficiency_Increase_Manual_Labour)^4 -> 0
C105: Machine Costs | E105: Automated_Labour_Testing*Hourly_Rate_Machines*(Sales_Year_t)*(1-Annual_Efficiency_Increase_Automated_Labour)^t-1 | F105: € | G105: =SUM(H105:M105) -> 0 | I105: =Automated_Labour_Testing*Hourly_Rate_Machines*(Sales_Year_1)*(1-Annual_Efficiency_Increase_Automated_Labour)^0 -> 0 | J105: =Automated_Labour_Testing*Hourly_Rate_Machines*(Sales_Year_2)*(1-Annual_Efficiency_Increase_Automated_Labour)^1 -> 0 | K105: =Automated_Labour_Testing*Hourly_Rate_Machines*(Sales_Year_3)*(1-Annual_Efficiency_Increase_Automated_Labour)^2 -> 0 | L105: =Automated_Labour_Testing*Hourly_Rate_Machines*(Sales_Year_4)*(1-Annual_Efficiency_Increase_Automated_Labour)^3 -> 0 | M105: =Automated_Labour_Testing*Hourly_Rate_Machines*(Sales_Year_5)*(1-Annual_Efficiency_Increase_Automated_Labour)^4 -> 0
C106: Certification Costs | E106: Certification_Costs*Sales_Year_t | F106: € | G106: =SUM(H106:M106) -> 0 | I106: =Certification_Costs*Sales_Year_1 -> 0 | J106: =Certification_Costs*Sales_Year_2 -> 0 | K106: =Certification_Costs*Sales_Year_3 -> 0 | L106: =Certification_Costs*Sales_Year_4 -> 0 | M106: =Certification_Costs*Sales_Year_5 -> 0
B108: Forward Logistics | E108: IF query on Billing Type followed by SUM of Costs for Forward Logistic + Special_Costs_Forward_Logistic | F108: € | G108: =SUM(H108:M108) -> 0 | I108: =IF('Step 1 - Case Selection'!V51="as a Flat Rate",I109+Special_Costs_Forward_Logistics,SUM(I110:I113)+Special_Costs_Forward_Logistics) -> 0 | J108: =IF('Step 1 - Case Selection'!V51="as a Flat Rate",J109+Special_Costs_Forward_Logistics,SUM(J110:J113)+Special_Costs_Forward_Logistics) -> 0 | K108: =IF('Step 1 - Case Selection'!V51="as a Flat Rate",K109+Special_Costs_Forward_Logistics,SUM(K110:K113)+Special_Costs_Forward_Logistics) -> 0 | L108: =IF('Step 1 - Case Selection'!V51="as a Flat Rate",L109+Special_Costs_Forward_Logistics,SUM(L110:L113)+Special_Costs_Forward_Logistics) -> 0 | M108: =IF('Step 1 - Case Selection'!V51="as a Flat Rate",M109+Special_Costs_Forward_Logistics,SUM(M110:M113)+Special_Costs_Forward_Logistics) -> 0
C109: Optional Flat Rate Calculation | E109: FL_Flat_Rate*(Sales_Year_t+New_Rental_Contracts_Year_t) | F109: € | G109: =SUM(H109:M109) -> 0 | I109: =FL_Flat_Rate*(Sales_Year_1+New_Rental_Contracts_Year_1) -> 0 | J109: =FL_Flat_Rate*(Sales_Year_2+New_Rental_Contracts_Year_2) -> 0 | K109: =FL_Flat_Rate*(Sales_Year_3+New_Rental_Contracts_Year_3) -> 0 | L109: =FL_Flat_Rate*(Sales_Year_4+New_Rental_Contracts_Year_4) -> 0 | M109: =FL_Flat_Rate*(Sales_Year_5+New_Rental_Contracts_Year_5) -> 0
C110: Delivery Costs | E110: IF(FL_Type=1;FL_Distance_Customer*FL_KM_Cost*(Sales_Year_t+New_Rental_Contracts_Year_t)*(1-Annual_Efficiency_Increase_Forward_Logistics)^t-1;0) | F110: € | G110: =SUM(H110:M110) -> 0 | I110: =IF(FL_Type=1,FL_Distance_Customer*FL_KM_Cost*(Sales_Year_1+New_Rental_Contracts_Year_1)*(1-Annual_Efficiency_Increase_Forward_Logistics)^0,0) -> 0 | J110: =IF(FL_Type=1, FL_Distance_Customer*FL_KM_Cost*(Sales_Year_2+New_Rental_Contracts_Year_2)*(1-Annual_Efficiency_Increase_Forward_Logistics)^1,0) -> 0 | K110: =IF(FL_Type=1, FL_Distance_Customer*FL_KM_Cost*(Sales_Year_3+New_Rental_Contracts_Year_3)*(1-Annual_Efficiency_Increase_Forward_Logistics)^2,0) -> 0 | L110: =IF(FL_Type=1, FL_Distance_Customer*FL_KM_Cost*(Sales_Year_4+New_Rental_Contracts_Year_4)*(1-Annual_Efficiency_Increase_Forward_Logistics)^3,0) -> 0 | M110: =IF(FL_Type=1, FL_Distance_Customer*FL_KM_Cost*(Sales_Year_5+New_Rental_Contracts_Year_5)*(1-Annual_Efficiency_Increase_Forward_Logistics)^4,0) -> 0
C111: Shipment Costs | E111: IF(FL_Type=2;FL_Shipment_Cost*(Sales_Year_t+New_Rental_Contracts_Year_t);0) | F111: € | G111: =SUM(H111:M111) -> 0 | I111: =IF(FL_Type=2,FL_Shipment_Cost*(Sales_Year_1+New_Rental_Contracts_Year_1),0) -> 0 | J111: =IF(FL_Type=2,FL_Shipment_Cost*(Sales_Year_2+New_Rental_Contracts_Year_2),0) -> 0 | K111: =IF(FL_Type=2,FL_Shipment_Cost*(Sales_Year_3+New_Rental_Contracts_Year_3),0) -> 0 | L111: =IF(FL_Type=2,FL_Shipment_Cost*(Sales_Year_4+New_Rental_Contracts_Year_4),0) -> 0 | M111: =IF(FL_Type=2,FL_Shipment_Cost*(Sales_Year_5+New_Rental_Contracts_Year_5),0) -> 0
C112: Customer Site Repair Logstics | E112: IF(FL_Type=3; FL_Distance_Customer*FL_KM_Cost*Sales_Year_t*FL_Average_Journey_Number*(1-Annual_Efficiency_Increase_Forward_Logistics)^t-1;0) | F112: € | G112: =SUM(H112:M112) -> 0 | I112: =IF(FL_Type=3, FL_Distance_Customer*FL_KM_Cost*Sales_Year_1*FL_Average_Journey_Number*(1-Annual_Efficiency_Increase_Forward_Logistics)^0,0) -> 0 | J112: =IF(FL_Type=3, FL_Distance_Customer*FL_KM_Cost*Sales_Year_2*FL_Average_Journey_Number*(1-Annual_Efficiency_Increase_Forward_Logistics)^1,0) -> 0 | K112: =IF(FL_Type=3, FL_Distance_Customer*FL_KM_Cost*Sales_Year_3*FL_Average_Journey_Number*(1-Annual_Efficiency_Increase_Forward_Logistics)^2,0) -> 0 | L112: =IF(FL_Type=3, FL_Distance_Customer*FL_KM_Cost*Sales_Year_4*FL_Average_Journey_Number*(1-Annual_Efficiency_Increase_Forward_Logistics)^3,0) -> 0 | M112: =IF(FL_Type=3, FL_Distance_Customer*FL_KM_Cost*Sales_Year_5*FL_Average_Journey_Number*(1-Annual_Efficiency_Increase_Forward_Logistics)^4,0) -> 0
C113: Packaging Costs | E113: FL_Packaging_Cost*(Sales_Year_t+New_Rental_Contracts_Year_t) | F113: € | G113: =SUM(H113:M113) -> 0 | I113: =FL_Packaging_Cost*(Sales_Year_1+New_Rental_Contracts_Year_1) -> 0 | J113: =FL_Packaging_Cost*(Sales_Year_2+New_Rental_Contracts_Year_2) -> 0 | K113: =FL_Packaging_Cost*(Sales_Year_3+New_Rental_Contracts_Year_3) -> 0 | L113: =FL_Packaging_Cost*(Sales_Year_4+New_Rental_Contracts_Year_4) -> 0 | M113: =FL_Packaging_Cost*(Sales_Year_5+New_Rental_Contracts_Year_5) -> 0
A115: Financing costs | E115: Total Financing Costs (SUM) | F115: € | G115: =SUM(H115:M115) -> #DIV/0! | I115: =SUM(I117) -> #DIV/0! | J115: =SUM(J117) -> 0 | K115: =SUM(K117) -> 0 | L115: =SUM(L117) -> 0 | M115: =SUM(M117) -> 0
B117: Loans | E117: Total Loan Expenses (SUM) | F117: € | G117: =SUM(I117:M117) -> #DIV/0! | I117: =SUM(I118:I119) -> #DIV/0! | J117: =SUM(J118:J119) -> 0 | K117: =SUM(K118:K119) -> 0 | L117: =SUM(L118:L119) -> 0 | M117: =SUM(M118:M119) -> 0
C118: Repayment Instalment | E118: Debt_Capital/Loan_Term (IF query of Loan-Term) | F118: € | G118: =SUM(I118:M118) -> #DIV/0! | I118: =Debt_Capital/Loan_Term -> #DIV/0! | J118: =IF(Loan_Term>1, Debt_Capital/Loan_Term, 0) -> 0 | K118: =IF(Loan_Term>2, Debt_Capital/Loan_Term, 0) -> 0 | L118: =IF(Loan_Term>3, Debt_Capital/Loan_Term, 0) -> 0 | M118: =IF(Loan_Term>4, Debt_Capital/Loan_Term, 0) -> 0
C119: Interest Cost | E119: Yearly_Interest_Cost (IF query of Loan-Term) | F119: € | G119: =SUM(I119:M119) -> 0 | I119: =Yearly_Interest_Cost -> 0 | J119: =IF(Loan_Term>1, Yearly_Interest_Cost, 0) -> 0 | K119: =IF(Loan_Term>2, Yearly_Interest_Cost, 0) -> 0 | L119: =IF(Loan_Term>3, Yearly_Interest_Cost, 0) -> 0 | M119: =IF(Loan_Term>4, Yearly_Interest_Cost, 0) -> 0
A125: Calculation of Economic Impact (Base Case)
B127: Cash Flow
C128: Total Cash Flow (Gross) | E128: IF query on Period under Review followed by Income Flow (x128) - Outward Flow (x129) | F128: € | H128: =IF('Step 1 - Case Selection'!V55="No",0,H129-H130) -> 0 | I128: =IF('Step 1 - Case Selection'!V59<1,0,I129-I130) -> 0 | J128: =IF('Step 1 - Case Selection'!V59<2,0,J129-J130) -> 0 | K128: =IF('Step 1 - Case Selection'!V59<3,0,K129-K130) -> 0 | L128: =IF('Step 1 - Case Selection'!V59<4,0,L129-L130) -> 0 | M128: =IF('Step 1 - Case Selection'!V59<5,0,M129-M130) -> 0
...

Sheet Calculation (sI)
A1: Type | B1: Category | C1: Sub-Categoy | D1: Auxiliary Calculations | E1: Unit | F1: Total Value | G1: Year 0 - Value | H1: Year 1 - Value | I1: Year 2 - Value | J1: Year 3 - Value | K1: Year 4 - Value | L1: Year 5 - Value | M1: After | N1: Auxiliary Column
A2: Income Flows | E2: € | F2: =SUM(G2:L2) -> 0 | G2: =SUM(G4,G13) -> 0 | H2: =SUM(H4,H13) -> 0 | I2: =SUM(I4,I13) -> 0 | J2: =SUM(J4,J13) -> 0 | K2: =SUM(K4,K13) -> 0 | L2: =SUM(L4,L13) -> 0
B4: Revenue | E4: € | F4: =SUM(G4:L4) -> 0 | H4: =SUM(H5+H9) -> 0 | I4: =SUM(I5+I9) -> 0 | J4: =SUM(J5+J9) -> 0 | K4: =SUM(K5+K9) -> 0 | L4: =SUM(L5+L9) -> 0
C5: Sales Revenue | E5: € | F5: =SUM(G5:L5) -> 0 | H5: =SUM(H6:H8) -> 0 | I5: =SUM(I6:I8) -> 0 | J5: =SUM(J6:J8) -> 0 | K5: =SUM(K6:K8) -> 0 | L5: =SUM(L6:L8) -> 0
D6: Product Sales Revenue | E6: € | F6: =SUM(G6:L6) -> 0 | H6: ='Step 2.2 - Data Input (Revenue)'!G9*'Step 2.2 - Data Input (Revenue)'!G6 -> 0 | I6: ='Step 2.2 - Data Input (Revenue)'!G10*'Step 2.2 - Data Input (Revenue)'!G6 -> 0 | J6: ='Step 2.2 - Data Input (Revenue)'!G11*'Step 2.2 - Data Input (Revenue)'!G6 -> 0 | K6: ='Step 2.2 - Data Input (Revenue)'!G12*'Step 2.2 - Data Input (Revenue)'!G6 -> 0 | L6: ='Step 2.2 - Data Input (Revenue)'!G13*'Step 2.2 - Data Input (Revenue)'!G6 -> 0
D7: Materials for Recycling Sales Revenue | E7: € | F7: =SUM(G7:L7) -> 0 | H7: ='Step 2.2 - Data Input (Revenue)'!G9*'Step 2.2 - Data Input (Revenue)'!G7 -> 0 | I7: ='Step 2.2 - Data Input (Revenue)'!G10*'Step 2.2 - Data Input (Revenue)'!G7 -> 0 | J7: ='Step 2.2 - Data Input (Revenue)'!G11*'Step 2.2 - Data Input (Revenue)'!G7 -> 0 | K7: ='Step 2.2 - Data Input (Revenue)'!G12*'Step 2.2 - Data Input (Revenue)'!G7 -> 0 | L7: ='Step 2.2 - Data Input (Revenue)'!G13*'Step 2.2 - Data Input (Revenue)'!G7 -> 0
D8: Service Sales Revenue | E8: € | F8: =SUM(G8:L8) -> 0 | H8: ='Step 2.2 - Data Input (Revenue)'!G9*'Step 2.2 - Data Input (Revenue)'!G8 -> 0 | I8: ='Step 2.2 - Data Input (Revenue)'!G10*'Step 2.2 - Data Input (Revenue)'!G8 -> 0 | J8: ='Step 2.2 - Data Input (Revenue)'!G11*'Step 2.2 - Data Input (Revenue)'!G8 -> 0 | K8: ='Step 2.2 - Data Input (Revenue)'!G12*'Step 2.2 - Data Input (Revenue)'!G8 -> 0 | L8: ='Step 2.2 - Data Input (Revenue)'!G13*'Step 2.2 - Data Input (Revenue)'!G8 -> 0
C9: Rental Agreements Revenue | E9: € | F9: =SUM(G9:L9) -> 0 | H9: =H10*'Step 2.2 - Data Input (Revenue)'!G16 -> 0 | I9: =I10*'Step 2.2 - Data Input (Revenue)'!G16 -> 0 | J9: =J10*'Step 2.2 - Data Input (Revenue)'!G16 -> 0 | K9: =K10*'Step 2.2 - Data Input (Revenue)'!G16 -> 0 | L9: =L10*'Step 2.2 - Data Input (Revenue)'!G16 -> 0
D10: Active Rental Agreements | E10: I | H10: ='Step 2.2 - Data Input (Revenue)'!G18 -> 0 | I10: =IF('Step 2.2 - Data Input (Revenue)'!G17>1,'Step 2.2 - Data Input (Revenue)'!G18+'Step 2.2 - Data Input (Revenue)'!G19,'Step 2.2 - Data Input (Revenue)'!G19) -> 0 | J10: {=_xlfn.IFS('Step 2.2 - Data Input (Revenue)'!G17>2, 'Step 2.2 - Data Input (Revenue)'!G18+'Step 2.2 - Data Input (Revenue)'!G19+'Step 2.2 - Data Input (Revenue)'!G20,'Step 2.2 - Data Input (Revenue)'!G17>1,'Step 2.2 - Data Input (Revenue)'!G19+'Step 2.2 - Data Input (Revenue)'!G20, 'Step 2.2 - Data Input (Revenue)'!G17<=1, 'Step 2.2 - Data Input (Revenue)'!G20)} -> 0 | K10: {=_xlfn.IFS('Step 2.2 - Data Input (Revenue)'!G17>3, 'Step 2.2 - Data Input (Revenue)'!G18+'Step 2.2 - Data Input (Revenue)'!G19+'Step 2.2 - Data Input (Revenue)'!G20+ 'Step 2.2 - Data Input (Revenue)'!G21, 'Step 2.2 - Data Input (Revenue)'!G17>2,'Step 2.2 - Data Input (Revenue)'!G19+'Step 2.2 - Data Input (Revenue)'!G20+'Step 2.2 - Data Input (Revenue)'!G21, 'Step 2.2 - Data Input (Revenue)'!G17>1, 'Step 2.2 - Data Input (Revenue)'!G20+'Step 2.2 - Data Input (Revenue)'!G21, 'Step 2.2 - Data Input (Revenue)'!G17<=1, 'Step 2.2 - Data Input (Revenue)'!G21)} -> 0 | L10: {=_xlfn.IFS('Step 2.2 - Data Input (Revenue)'!G17>4, 'Step 2.2 - Data Input (Revenue)'!G18+'Step 2.2 - Data Input (Revenue)'!G19+'Step 2.2 - Data Input (Revenue)'!G20+ 'Step 2.2 - Data Input (Revenue)'!G21+'Step 2.2 - Data Input (Revenue)'!G22, 'Step 2.2 - Data Input (Revenue)'!G17>3,'Step 2.2 - Data Input (Revenue)'!G19+'Step 2.2 - Data Input (Revenue)'!G20+'Step 2.2 - Data Input (Revenue)'!G21+'Step 2.2 - Data Input (Revenue)'!G22, 'Step 2.2 - Data Input (Revenue)'!G17>2, 'Step 2.2 - Data Input (Revenue)'!G20+'Step 2.2 - Data Input (Revenue)'!G21+'Step 2.2 - Data Input (Revenue)'!G22, 'Step 2.2 - Data Input (Revenue)'!G17>1, 'Step 2.2 - Data Input (Revenue)'!G21+'Step 2.2 - Data Input (Revenue)'!G22,'Step 2.2 - Data Input (Revenue)'!G17<=1, 'Step 2.2 - Data Input (Revenue)'!G22)} -> 0
D11: Residual Value after Period of Review | E11: € | F11: =SUM(G11:M11) -> 0 | M11: {=_xlfn.IFS('Step 2.2 - Data Input (Revenue)'!G17>5, (('Step 2.2 - Data Input (Revenue)'!G17-5)*'Step 2.2 - Data Input (Revenue)'!G18+('Step 2.2 - Data Input (Revenue)'!G17-4)*'Step 2.2 - Data Input (Revenue)'!G19+('Step 2.2 - Data Input (Revenue)'!G17-3)*'Step 2.2 - Data Input (Revenue)'!G20+('Step 2.2 - Data Input (Revenue)'!G17-2)*'Step 2.2 - Data Input (Revenue)'!G21+('Step 2.2 - Data Input (Revenue)'!G17-1)*'Step 2.2 - Data Input (Revenue)'!G22)*Annual_Price_Rental_Contract, 'Step 2.2 - Data Input (Revenue)'!G17>4, (('Step 2.2 - Data Input (Revenue)'!G17-4)*'Step 2.2 - Data Input (Revenue)'!G19+('Step 2.2 - Data Input (Revenue)'!G17-3)*'Step 2.2 - Data Input (Revenue)'!G20+('Step 2.2 - Data Input (Revenue)'!G17-2)*'Step 2.2 - Data Input (Revenue)'!G21+('Step 2.2 - Data Input (Revenue)'!G17-1)*'Step 2.2 - Data Input (Revenue)'!G22)*Annual_Price_Rental_Contract, 'Step 2.2 - Data Input (Revenue)'!G17>3, (('Step 2.2 - Data Input (Revenue)'!G17-3)*'Step 2.2 - Data Input (Revenue)'!G20+('Step 2.2 - Data Input (Revenue)'!G17-2)*'Step 2.2 - Data Input (Revenue)'!G21+('Step 2.2 - Data Input (Revenue)'!G17-1)*'Step 2.2 - Data Input (Revenue)'!G22)*Annual_Price_Rental_Contract, 'Step 2.2 - Data Input (Revenue)'!G17>2,(('Step 2.2 - Data Input (Revenue)'!G17-2)*'Step 2.2 - Data Input (Revenue)'!G21+('Step 2.2 - Data Input (Revenue)'!G17-1)*'Step 2.2 - Data Input (Revenue)'!G22)*Annual_Price_Rental_Contract, 'Step 2.2 - Data Input (Revenue)'!G17>1, ('Step 2.2 - Data Input (Revenue)'!G17-1)*'Step 2.2 - Data Input (Revenue)'!G22*Annual_Price_Rental_Contract, 'Step 2.2 - Data Input (Revenue)'!G17<=1, 0)} -> 0
B13: Other positive balance sheet positions | E13: € | F13: =SUM(G13:L13) -> 0 | G13: =SUM(G14:G15) -> 0 | H13: =SUM(H14:H15) -> 0 | I13: =SUM(I14:I15) -> 0 | J13: =SUM(J14:J15) -> 0 | K13: =SUM(K14:K15) -> 0 | L13: =SUM(L14:L15) -> 0
C14: Loans | E14: € | F14: =SUM(G14:L14) -> 0 | G14: ='Step 2.1 - Data Input (General)'!G16 -> 0
C15: Subsidies | E15: € | F15: =SUM(G15:L15) -> 0 | G15: ='Step 2.1 - Data Input (General)'!G12 -> 0 | H15: ='Step 2.1 - Data Input (General)'!G13 -> 0 | I15: ='Step 2.1 - Data Input (General)'!G13 -> 0 | J15: ='Step 2.1 - Data Input (General)'!G13 -> 0 | K15: ='Step 2.1 - Data Input (General)'!G13 -> 0 | L15: ='Step 2.1 - Data Input (General)'!G13 -> 0
A17: CapEx | E17: € | F17: =SUM(G17:L17) -> 0 | G17: =SUM(G19+G24) -> 0
B19: Assets | F19: =SUM(G19:L19) -> 0 | G19: =SUM(G20:G22) -> 0
C20: Tangible Assets | E20: € | F20: =SUM(G20:L20) -> 0 | G20: =SUM('Step 2.3 - Data Input (CapEx)'!G6+'Step 2.3 - Data Input (CapEx)'!G7+'Step 2.3 - Data Input (CapEx)'!G8) -> 0
C21: Intangible Assets | E21: € | F21: =SUM(G21:L21) -> 0 | G21: =SUM('Step 2.3 - Data Input (CapEx)'!G9+'Step 2.3 - Data Input (CapEx)'!G10+'Step 2.3 - Data Input (CapEx)'!G11) -> 0
C22: Equity Holdings | E22: € | F22: =SUM(G22:L22) -> 0 | G22: ='Step 2.3 - Data Input (CapEx)'!G12 -> 0
B24: Comissioning Costs | E24: € | F24: =SUM(G24:L24) -> 0 | G24: =SUM(G25:G28) -> 0
C25: Administrative Staff Costs | E25: € | F25: =SUM(G25:L25) -> 0 | G25: ='Step 2.3 - Data Input (CapEx)'!G16*'Step 2.4 - Data Input (OpEx)'!G7 -> 0
C26: Production Staff Costs | E26: € | F26: =SUM(G26:L26) -> 0 | G26: ='Step 2.3 - Data Input (CapEx)'!G17*'Step 2.4 - Data Input (OpEx)'!G6 -> 0
C27: Research and Development | E27: € | F27: =SUM(G27:L27) -> 0 | G27: ='Step 2.3 - Data Input (CapEx)'!G15 -> 0
C28: Other Comissioning Costs | E28: € | F28: =SUM(G28:L28) -> 0 | G28: ='Step 2.3 - Data Input (CapEx)'!G18 -> 0
A30: OpEx | E30: € | F30: =SUM(G30:L30) -> 0 | H30: =SUM(H32:H33) -> 0 | I30: =SUM(I32:I33) -> 0 | J30: =SUM(J32:J33) -> 0 | K30: =SUM(K32:K33) -> 0 | L30: =SUM(L32:L33) -> 0
B32: Administrative Overhead | E32: € | F32: =SUM(G32:L32) -> 0 | H32: =SUM(H33*'Step 2.1 - Data Input (General)'!G8) -> 0 | I32: =SUM(I33*'Step 2.1 - Data Input (General)'!G8) -> 0 | J32: =SUM(J33*'Step 2.1 - Data Input (General)'!G8) -> 0 | K32: =SUM(K33*'Step 2.1 - Data Input (General)'!G8) -> 0 | L32: =SUM(L33*'Step 2.1 - Data Input (General)'!G8) -> 0
D33: Subtotal OpEx | E33: € | H33: =SUM(H35,H37,H41,H47,H70,H74,H79,H83,H89,H93,H98,H103,H108)+'Step 2.4 - Data Input (OpEx)'!G11 -> 0 | I33: =SUM(I35,I37,I41,I47,I70,I74,I79,I83,I89,I93,I98,I103,I108)+'Step 2.4 - Data Input (OpEx)'!G11 -> 0 | J33: =SUM(J35,J37,J41,J47,J70,J74,J79,J83,J89,J93,J98,J103,J108)+'Step 2.4 - Data Input (OpEx)'!G11 -> 0 | K33: =SUM(K35,K37,K41,K47,K70,K74,K79,K83,K89,K93,K98,K103,K108)+'Step 2.4 - Data Input (OpEx)'!G11 -> 0 | L33: =SUM(L35,L37,L41,L47,L70,L74,L79,L83,L89,L93,L98,L103,L108)+'Step 2.4 - Data Input (OpEx)'!G11 -> 0
B35: Property Costs (exc. Energy) | E35: € | F35: =SUM(G35:L35) -> 0 | H35: ='Step 2.4 - Data Input (OpEx)'!G31+'Step 2.4 - Data Input (OpEx)'!G32+'Step 2.4 - Data Input (OpEx)'!G33 -> 0 | I35: ='Step 2.4 - Data Input (OpEx)'!G31+'Step 2.4 - Data Input (OpEx)'!G32+'Step 2.4 - Data Input (OpEx)'!G33 -> 0 | J35: ='Step 2.4 - Data Input (OpEx)'!G31+'Step 2.4 - Data Input (OpEx)'!G32+'Step 2.4 - Data Input (OpEx)'!G33 -> 0 | K35: ='Step 2.4 - Data Input (OpEx)'!G31+'Step 2.4 - Data Input (OpEx)'!G32+'Step 2.4 - Data Input (OpEx)'!G33 -> 0 | L35: ='Step 2.4 - Data Input (OpEx)'!G31+'Step 2.4 - Data Input (OpEx)'!G32+'Step 2.4 - Data Input (OpEx)'!G33 -> 0
B37: Energy Costs | E37: € | F37: =SUM(G37:L37) -> 0 | H37: =SUM(H38:H39) -> 0 | I37: =SUM(I38:I39) -> 0 | J37: =SUM(J38:J39) -> 0 | K37: =SUM(K38:K39) -> 0 | L37: =SUM(L38:L39) -> 0
C38: Electricity | E38: € | F38: =SUM(G38:L38) -> 0 | H38: =('Step 2.4 - Data Input (OpEx)'!G26+'Step 2.4 - Data Input (OpEx)'!G27*'Step 2.4 - Data Input (OpEx)'!G28)*(1+'Step 2.4 - Data Input (OpEx)'!G16)^0 -> 0 | I38: =('Step 2.4 - Data Input (OpEx)'!G26+'Step 2.4 - Data Input (OpEx)'!G27*'Step 2.4 - Data Input (OpEx)'!G28)*(1+'Step 2.4 - Data Input (OpEx)'!G16)^1 -> 0 | J38: =('Step 2.4 - Data Input (OpEx)'!G26+'Step 2.4 - Data Input (OpEx)'!G27*'Step 2.4 - Data Input (OpEx)'!G28)*(1+'Step 2.4 - Data Input (OpEx)'!G16)^2 -> 0 | K38: =('Step 2.4 - Data Input (OpEx)'!G26+'Step 2.4 - Data Input (OpEx)'!G27*'Step 2.4 - Data Input (OpEx)'!G28)*(1+'Step 2.4 - Data Input (OpEx)'!G16)^3 -> 0 | L38: =('Step 2.4 - Data Input (OpEx)'!G26+'Step 2.4 - Data Input (OpEx)'!G27*'Step 2.4 - Data Input (OpEx)'!G28)*(1+'Step 2.4 - Data Input (OpEx)'!G16)^4 -> 0
C39: Heating (Oil, Gas) | E39: € | F39: =SUM(G39:L39) -> 0 | H39: =('Step 2.4 - Data Input (OpEx)'!G23+'Step 2.4 - Data Input (OpEx)'!G24*'Step 2.4 - Data Input (OpEx)'!G25)*(1+'Step 2.4 - Data Input (OpEx)'!G15)^0 -> 0 | I39: =('Step 2.4 - Data Input (OpEx)'!G23+'Step 2.4 - Data Input (OpEx)'!G24*'Step 2.4 - Data Input (OpEx)'!G25)*(1+'Step 2.4 - Data Input (OpEx)'!G15)^1 -> 0 | J39: =('Step 2.4 - Data Input (OpEx)'!G23+'Step 2.4 - Data Input (OpEx)'!G24*'Step 2.4 - Data Input (OpEx)'!G25)*(1+'Step 2.4 - Data Input (OpEx)'!G15)^2 -> 0 | K39: =('Step 2.4 - Data Input (OpEx)'!G23+'Step 2.4 - Data Input (OpEx)'!G24*'Step 2.4 - Data Input (OpEx)'!G25)*(1+'Step 2.4 - Data Input (OpEx)'!G15)^3 -> 0 | L39: =('Step 2.4 - Data Input (OpEx)'!G23+'Step 2.4 - Data Input (OpEx)'!G24*'Step 2.4 - Data Input (OpEx)'!G25)*(1+'Step 2.4 - Data Input (OpEx)'!G15)^4 -> 0
B41: Linear Production Base Case | E41: € | F41: =SUM(G41:L41) -> 0 | H41: =SUM(H42:H45)+'Step 2.4 - Data Input (OpEx)'!G40 -> 0 | I41: =SUM(I42:I45)+'Step 2.4 - Data Input (OpEx)'!G40 -> 0 | J41: =SUM(J42:J45)+'Step 2.4 - Data Input (OpEx)'!G40 -> 0 | K41: =SUM(K42:K45)+'Step 2.4 - Data Input (OpEx)'!G40 -> 0 | L41: =SUM(L42:L45)+'Step 2.4 - Data Input (OpEx)'!G40 -> 0
C42: Material Costs | E42: € | F42: =SUM(G42:L42) -> 0 | H42: ='Step 2.2 - Data Input (Revenue)'!G9*'Step 2.4 - Data Input (OpEx)'!G36*(1+'Step 2.4 - Data Input (OpEx)'!G14)^0 -> 0 | I42: ='Step 2.2 - Data Input (Revenue)'!G10*'Step 2.4 - Data Input (OpEx)'!G36*(1+'Step 2.4 - Data Input (OpEx)'!G14)^1 -> 0 | J42: ='Step 2.2 - Data Input (Revenue)'!G11*'Step 2.4 - Data Input (OpEx)'!G36*(1+'Step 2.4 - Data Input (OpEx)'!G14)^2 -> 0 | K42: ='Step 2.2 - Data Input (Revenue)'!G12*'Step 2.4 - Data Input (OpEx)'!G36*(1+'Step 2.4 - Data Input (OpEx)'!G14)^3 -> 0 | L42: ='Step 2.2 - Data Input (Revenue)'!G13*'Step 2.4 - Data Input (OpEx)'!G36*(1+'Step 2.4 - Data Input (OpEx)'!G14)^4 -> 0
C43: Disposal Costs | E43: € | F43: =SUM(G43:L43) -> 0 | H43: ='Step 2.2 - Data Input (Revenue)'!G9*'Step 2.4 - Data Input (OpEx)'!G37 -> 0 | I43: ='Step 2.2 - Data Input (Revenue)'!G10*'Step 2.4 - Data Input (OpEx)'!G37 -> 0 | J43: ='Step 2.2 - Data Input (Revenue)'!G11*'Step 2.4 - Data Input (OpEx)'!G37 -> 0 | K43: ='Step 2.2 - Data Input (Revenue)'!G12*'Step 2.4 - Data Input (OpEx)'!G37 -> 0 | L43: ='Step 2.2 - Data Input (Revenue)'!G13*'Step 2.4 - Data Input (OpEx)'!G37 -> 0
C44: Personel Costs | E44: € | F44: =SUM(G44:L44) -> 0 | H44: ='Step 2.2 - Data Input (Revenue)'!G9*('Step 2.4 - Data Input (OpEx)'!G38*'Step 2.4 - Data Input (OpEx)'!G6)*(1-'Step 2.4 - Data Input (OpEx)'!G17)^0 -> 0 | I44: ='Step 2.2 - Data Input (Revenue)'!G10*('Step 2.4 - Data Input (OpEx)'!G38*'Step 2.4 - Data Input (OpEx)'!G6)*(1-'Step 2.4 - Data Input (OpEx)'!G17)^1 -> 0 | J44: ='Step 2.2 - Data Input (Revenue)'!G11*('Step 2.4 - Data Input (OpEx)'!G38*'Step 2.4 - Data Input (OpEx)'!G6)*(1-'Step 2.4 - Data Input (OpEx)'!G17)^2 -> 0 | K44: ='Step 2.2 - Data Input (Revenue)'!G12*('Step 2.4 - Data Input (OpEx)'!G38*'Step 2.4 - Data Input (OpEx)'!G6)*(1-'Step 2.4 - Data Input (OpEx)'!G17)^3 -> 0 | L44: ='Step 2.2 - Data Input (Revenue)'!G13*('Step 2.4 - Data Input (OpEx)'!G38*'Step 2.4 - Data Input (OpEx)'!G6)*(1-'Step 2.4 - Data Input (OpEx)'!G17)^4 -> 0
C45: Machine Costs | E45: € | F45: =SUM(G45:L45) -> 0 | H45: ='Step 2.2 - Data Input (Revenue)'!G9*('Step 2.4 - Data Input (OpEx)'!G39*'Step 2.4 - Data Input (OpEx)'!G8)*(1-'Step 2.4 - Data Input (OpEx)'!G18)^0 -> 0 | I45: ='Step 2.2 - Data Input (Revenue)'!G10*('Step 2.4 - Data Input (OpEx)'!G39*'Step 2.4 - Data Input (OpEx)'!G8)*(1-'Step 2.4 - Data Input (OpEx)'!G18)^1 -> 0 | J45: ='Step 2.2 - Data Input (Revenue)'!G11*('Step 2.4 - Data Input (OpEx)'!G39*'Step 2.4 - Data Input (OpEx)'!G8)*(1-'Step 2.4 - Data Input (OpEx)'!G18)^2 -> 0 | K45: ='Step 2.2 - Data Input (Revenue)'!G12*('Step 2.4 - Data Input (OpEx)'!G39*'Step 2.4 - Data Input (OpEx)'!G8)*(1-'Step 2.4 - Data Input (OpEx)'!G18)^3 -> 0 | L45: ='Step 2.2 - Data Input (Revenue)'!G13*('Step 2.4 - Data Input (OpEx)'!G39*'Step 2.4 - Data Input (OpEx)'!G8)*(1-'Step 2.4 - Data Input (OpEx)'!G18)^4 -> 0
B47: Backward Logistics | E47: € | F47: =SUM(G47:L47) -> 0 | H47: =IF('Step 1 - Case Selection'!V41="as a Flat Rate",H48+H54+Special_Costs_Backward_Logistics,SUM(H48,H55,H61,H68)+Special_Costs_Backward_Logistics) -> 0 | I47: =IF('Step 1 - Case Selection'!V41="as a Flat Rate",I48+I54+Special_Costs_Backward_Logistics,SUM(I48,I55,I61,I68)+Special_Costs_Backward_Logistics) -> 0 | J47: =IF('Step 1 - Case Selection'!V41="as a Flat Rate",J48+J54+Special_Costs_Backward_Logistics,SUM(J48,J55,J61,J68)+Special_Costs_Backward_Logistics) -> 0 | K47: =IF('Step 1 - Case Selection'!V41="as a Flat Rate",K48+K54+Special_Costs_Backward_Logistics,SUM(K48,K55,K61,K68)+Special_Costs_Backward_Logistics) -> 0 | L47: =IF('Step 1 - Case Selection'!V41="as a Flat Rate",L48+L54+Special_Costs_Backward_Logistics,SUM(L48,L55,L61,L68)+Special_Costs_Backward_Logistics) -> 0
D48: Core Premiums | E48: € | F48: =SUM(G48:L48) -> 0 | H48: ='Step 2.4 - Data Input (OpEx)'!G49*(H49+H51) -> 0 | I48: ='Step 2.4 - Data Input (OpEx)'!G49*(I49+I51) -> 0 | J48: ='Step 2.4 - Data Input (OpEx)'!G49*(J49+J51) -> 0 | K48: ='Step 2.4 - Data Input (OpEx)'!G49*(K49+K51) -> 0 | L48: ='Step 2.4 - Data Input (OpEx)'!G49*(L49+L51) -> 0
D49: Required Cores Product Basis (before Sorting) | E49: I | H49: =ROUND(IF('Step 1 - Case Selection'!V27<>"Recycle", 'Step 2.2 - Data Input (Revenue)'!G9/'Step 2.1 - Data Input (General)'!G24*'Step 2.1 - Data Input (General)'!G23, 0),0) -> 0 | I49: =ROUND(IF('Step 1 - Case Selection'!V27<>"Recycle", 'Step 2.2 - Data Input (Revenue)'!G10/'Step 2.1 - Data Input (General)'!G24*'Step 2.1 - Data Input (General)'!G23, 0),0) -> 0 | J49: =ROUND(IF('Step 1 - Case Selection'!V27<>"Recycle", 'Step 2.2 - Data Input (Revenue)'!G11/'Step 2.1 - Data Input (General)'!G24*'Step 2.1 - Data Input (General)'!G23, 0),0) -> 0 | K49: =ROUND(IF('Step 1 - Case Selection'!V27<>"Recycle", 'Step 2.2 - Data Input (Revenue)'!G12/'Step 2.1 - Data Input (General)'!G24*'Step 2.1 - Data Input (General)'!G23, 0),0) -> 0 | L49: =ROUND(IF('Step 1 - Case Selection'!V27<>"Recycle", 'Step 2.2 - Data Input (Revenue)'!G13/'Step 2.1 - Data Input (General)'!G24*'Step 2.1 - Data Input (General)'!G23, 0),0) -> 0
D50: Required Cores Product Basis (after Sorting) | E50: I | H50: =ROUND(IF('Step 1 - Case Selection'!V27<>"Recycle", 'Step 2.2 - Data Input (Revenue)'!G9*'Step 2.1 - Data Input (General)'!G23,0),0) -> 0 | I50: =ROUND(IF('Step 1 - Case Selection'!V27<>"Recycle", 'Step 2.2 - Data Input (Revenue)'!G10*'Step 2.1 - Data Input (General)'!G23,0),0) -> 0 | J50: =ROUND(IF('Step 1 - Case Selection'!V27<>"Recycle", 'Step 2.2 - Data Input (Revenue)'!G11*'Step 2.1 - Data Input (General)'!G23,0),0) -> 0 | K50: =ROUND(IF('Step 1 - Case Selection'!V27<>"Recycle", 'Step 2.2 - Data Input (Revenue)'!G12*'Step 2.1 - Data Input (General)'!G23,0),0) -> 0 | L50: =ROUND(IF('Step 1 - Case Selection'!V27<>"Recycle", 'Step 2.2 - Data Input (Revenue)'!G13*'Step 2.1 - Data Input (General)'!G23,0),0) -> 0
D51: Required Cores Material Basis (before Sorting) | E51: I | H51: =ROUND(IF('Step 1 - Case Selection'!V27="Recycle", 'Step 2.2 - Data Input (Revenue)'!G9/'Step 2.4 - Data Input (OpEx)'!G9/'Step 2.1 - Data Input (General)'!G24,0),0) -> 0 | I51: =ROUND(IF('Step 1 - Case Selection'!V27="Recycle", 'Step 2.2 - Data Input (Revenue)'!G10/'Step 2.4 - Data Input (OpEx)'!G9/'Step 2.1 - Data Input (General)'!G24,0),0) -> 0 | J51: =ROUND(IF('Step 1 - Case Selection'!V27="Recycle", 'Step 2.2 - Data Input (Revenue)'!G11/'Step 2.4 - Data Input (OpEx)'!G9/'Step 2.1 - Data Input (General)'!G24,0),0) -> 0 | K51: =ROUND(IF('Step 1 - Case Selection'!V27="Recycle", 'Step 2.2 - Data Input (Revenue)'!G12/'Step 2.4 - Data Input (OpEx)'!G9/'Step 2.1 - Data Input (General)'!G24,0),0) -> 0 | L51: =ROUND(IF('Step 1 - Case Selection'!V27="Recycle", 'Step 2.2 - Data Input (Revenue)'!G13/'Step 2.4 - Data Input (OpEx)'!G9/'Step 2.1 - Data Input (General)'!G24,0),0) -> 0
D52: Required Cores Material Basis (after Sorting) | E52: I | H52: =ROUND(IF('Step 1 - Case Selection'!V27="Recycle", 'Step 2.2 - Data Input (Revenue)'!G9/'Step 2.4 - Data Input (OpEx)'!G9,0),0) -> 0 | I52: =ROUND(IF('Step 1 - Case Selection'!V27="Recycle", 'Step 2.2 - Data Input (Revenue)'!G10/'Step 2.4 - Data Input (OpEx)'!G9,0),0) -> 0 | J52: =ROUND(IF('Step 1 - Case Selection'!V27="Recycle", 'Step 2.2 - Data Input (Revenue)'!G11/'Step 2.4 - Data Input (OpEx)'!G9,0),0) -> 0 | K52: =ROUND(IF('Step 1 - Case Selection'!V27="Recycle", 'Step 2.2 - Data Input (Revenue)'!G12/'Step 2.4 - Data Input (OpEx)'!G9,0),0) -> 0 | L52: =ROUND(IF('Step 1 - Case Selection'!V27="Recycle", 'Step 2.2 - Data Input (Revenue)'!G13/'Step 2.4 - Data Input (OpEx)'!G9,0),0) -> 0
D53: Ending Rental Agreements | E53: I | H53: =IF('Step 2.2 - Data Input (Revenue)'!G17<=1, 'Step 2.2 - Data Input (Revenue)'!G18, 0) -> 0 | I53: {=_xlfn.IFS('Step 2.2 - Data Input (Revenue)'!G17<=1, 'Step 2.2 - Data Input (Revenue)'!G19, 'Step 2.2 - Data Input (Revenue)'!G17<=2, 'Step 2.2 - Data Input (Revenue)'!G18, 'Step 2.2 - Data Input (Revenue)'!G17>2, 0)} -> 0 | J53: {=_xlfn.IFS('Step 2.2 - Data Input (Revenue)'!G17<=1, 'Step 2.2 - Data Input (Revenue)'!G20, 'Step 2.2 - Data Input (Revenue)'!G17<=2, 'Step 2.2 - Data Input (Revenue)'!G19, 'Step 2.2 - Data Input (Revenue)'!G17<=3, 'Step 2.2 - Data Input (Revenue)'!G18, 'Step 2.2 - Data Input (Revenue)'!G17>3, 0)} -> 0 | K53: {=_xlfn.IFS('Step 2.2 - Data Input (Revenue)'!G17<=1, 'Step 2.2 - Data Input (Revenue)'!G21, 'Step 2.2 - Data Input (Revenue)'!G17<=2, 'Step 2.2 - Data Input (Revenue)'!G20, 'Step 2.2 - Data Input (Revenue)'!G17<=3, 'Step 2.2 - Data Input (Revenue)'!G19, 'Step 2.2 - Data Input (Revenue)'!G17<=4, 'Step 2.2 - Data Input (Revenue)'!G18, 'Step 2.2 - Data Input (Revenue)'!G17>4, 0)} -> 0 | L53: {=_xlfn.IFS('Step 2.2 - Data Input (Revenue)'!G17<=1, 'Step 2.2 - Data Input (Revenue)'!G22, 'Step 2.2 - Data Input (Revenue)'!G17<=2, 'Step 2.2 - Data Input (Revenue)'!G21, 'Step 2.2 - Data Input (Revenue)'!G17<=3, 'Step 2.2 - Data Input (Revenue)'!G20, 'Step 2.2 - Data Input (Revenue)'!G17<=4, 'Step 2.2 - Data Input (Revenue)'!G19, 'Step 2.2 - Data Input (Revenue)'!G17<=5, 'Step 2.2 - Data Input (Revenue)'!G18,'Step 2.2 - Data Input (Revenue)'!G17>5, 0)} -> 0 | M53: =SUM('Step 2.2 - Data Input (Revenue)'!G18+'Step 2.2 - Data Input (Revenue)'!G19+'Step 2.2 - Data Input (Revenue)'!G20+'Step 2.2 - Data Input (Revenue)'!G21+'Step 2.2 - Data Input (Revenue)'!G22-(SUM(H53:L53))) -> 0
C54: Optional Flat Rate Calculation | E54: € | F54: =SUM(G54:L54) -> 0 | H54: ='Step 2.4 - Data Input (OpEx)'!G43*(H49+H51+H53) -> 0 | I54: ='Step 2.4 - Data Input (OpEx)'!G43*(I49+I51+I53) -> 0 | J54: ='Step 2.4 - Data Input (OpEx)'!G43*(J49+J51+J53) -> 0 | K54: ='Step 2.4 - Data Input (OpEx)'!G43*(K49+K51+K53) -> 0 | L54: ='Step 2.4 - Data Input (OpEx)'!G43*(L49+L51+L53) -> 0
C55: Backwards Logistic Sales | E55: € | F55: =SUM(G55:L55) -> 0 | H55: =SUM(H56:H60) -> 0 | I55: =SUM(I56:I60) -> 0 | J55: =SUM(J56:J60) -> 0 | K55: =SUM(K56:K60) -> 0 | L55: =SUM(L56:L60) -> 0
D56: Costs for Direct Pick-Up System | E56: € | F56: =SUM(G56:L56) -> 0 | H56: =IF(BL_Type=1,(H49+H51)*('Step 2.4 - Data Input (OpEx)'!G44*'Step 2.4 - Data Input (OpEx)'!G46)*(1-'Step 2.4 - Data Input (OpEx)'!G19)^0,0) -> 0 | I56: =IF(BL_Type=1,(I49+I51)*('Step 2.4 - Data Input (OpEx)'!G44*'Step 2.4 - Data Input (OpEx)'!G46)*(1-'Step 2.4 - Data Input (OpEx)'!G19)^1,0) -> 0 | J56: =IF(BL_Type=1,(J49+J51)*('Step 2.4 - Data Input (OpEx)'!G44*'Step 2.4 - Data Input (OpEx)'!G46)*(1-'Step 2.4 - Data Input (OpEx)'!G19)^2,0) -> 0 | K56: =IF(BL_Type=1,(K49+K51)*('Step 2.4 - Data Input (OpEx)'!G44*'Step 2.4 - Data Input (OpEx)'!G46)*(1-'Step 2.4 - Data Input (OpEx)'!G19)^3,0) -> 0 | L56: =IF(BL_Type=1,(L49+L51)*('Step 2.4 - Data Input (OpEx)'!G44*'Step 2.4 - Data Input (OpEx)'!G46)*(1-'Step 2.4 - Data Input (OpEx)'!G19)^4,0) -> 0
D57: Costs for Multi-Step Pick-Up System / Step 1 (to CAS) | E57: € | F57: =SUM(G57:L57) -> 0 | H57: =IF(OR(BL_Type=2,BL_Type=3),(H49+H51)*('Step 2.4 - Data Input (OpEx)'!G44*'Step 2.4 - Data Input (OpEx)'!G46)*(1-'Step 2.4 - Data Input (OpEx)'!G19)^0,0) -> 0 | I57: =IF(OR(BL_Type=2,BL_Type=3),(I49+I51)*('Step 2.4 - Data Input (OpEx)'!G44*'Step 2.4 - Data Input (OpEx)'!G46)*(1-'Step 2.4 - Data Input (OpEx)'!G19)^1,0) -> 0 | J57: =IF(OR(BL_Type=2,BL_Type=3),(J49+J51)*('Step 2.4 - Data Input (OpEx)'!G44*'Step 2.4 - Data Input (OpEx)'!G46)*(1-'Step 2.4 - Data Input (OpEx)'!G19)^2,0) -> 0 | K57: =IF(OR(BL_Type=2,BL_Type=3),(K49+K51)*('Step 2.4 - Data Input (OpEx)'!G44*'Step 2.4 - Data Input (OpEx)'!G46)*(1-'Step 2.4 - Data Input (OpEx)'!G19)^3,0) -> 0 | L57: =IF(OR(BL_Type=2,BL_Type=3),(L49+L51)*('Step 2.4 - Data Input (OpEx)'!G44*'Step 2.4 - Data Input (OpEx)'!G46)*(1-'Step 2.4 - Data Input (OpEx)'!G19)^4,0) -> 0
D58: Costs for Multi-Step Pick-Up System / Step 2 (to PS; no Sorting at CAS) | E58: € | F58: =SUM(G58:L58) -> 0 | H58: =IF(BL_Type=2,(H49+H51)*('Step 2.4 - Data Input (OpEx)'!G45*'Step 2.4 - Data Input (OpEx)'!G46)*(1-'Step 2.4 - Data Input (OpEx)'!G19)^0,0) -> 0 | I58: =IF(BL_Type=2,(I49+I51)*('Step 2.4 - Data Input (OpEx)'!G45*'Step 2.4 - Data Input (OpEx)'!G46)*(1-'Step 2.4 - Data Input (OpEx)'!G19)^1,0) -> 0 | J58: =IF(BL_Type=2,(J49+J51)*('Step 2.4 - Data Input (OpEx)'!G45*'Step 2.4 - Data Input (OpEx)'!G46)*(1-'Step 2.4 - Data Input (OpEx)'!G19)^2,0) -> 0 | K58: =IF(BL_Type=2,(K49+K51)*('Step 2.4 - Data Input (OpEx)'!G45*'Step 2.4 - Data Input (OpEx)'!G46)*(1-'Step 2.4 - Data Input (OpEx)'!G19)^3,0) -> 0 | L58: =IF(BL_Type=2,(L49+L51)*('Step 2.4 - Data Input (OpEx)'!G45*'Step 2.4 - Data Input (OpEx)'!G46)*(1-'Step 2.4 - Data Input (OpEx)'!G19)^4,0) -> 0
D59: Costs for Multi-Step Pick-Up System / Step 2 (to PS; Sorting at CAS) | E59: € | F59: =SUM(G59:L59) -> 0 | H59: =IF(BL_Type=3,(H50+H52)*('Step 2.4 - Data Input (OpEx)'!G45*'Step 2.4 - Data Input (OpEx)'!G46)*(1-'Step 2.4 - Data Input (OpEx)'!G19)^0,0) -> 0 | I59: =IF(BL_Type=3,(I50+I52)*('Step 2.4 - Data Input (OpEx)'!G45*'Step 2.4 - Data Input (OpEx)'!G46)*(1-'Step 2.4 - Data Input (OpEx)'!G19)^1,0) -> 0 | J59: =IF(BL_Type=3,(J50+J52)*('Step 2.4 - Data Input (OpEx)'!G45*'Step 2.4 - Data Input (OpEx)'!G46)*(1-'Step 2.4 - Data Input (OpEx)'!G19)^2,0) -> 0 | K59: =IF(BL_Type=3,(K50+K52)*('Step 2.4 - Data Input (OpEx)'!G45*'Step 2.4 - Data Input (OpEx)'!G46)*(1-'Step 2.4 - Data Input (OpEx)'!G19)^3,0) -> 0 | L59: =IF(BL_Type=3,(L50+L52)*('Step 2.4 - Data Input (OpEx)'!G45*'Step 2.4 - Data Input (OpEx)'!G46)*(1-'Step 2.4 - Data Input (OpEx)'!G19)^4,0) -> 0
D60: Costs for Shipment of Cores | E60: € | F60: =SUM(G60:L60) -> 0 | H60: =IF(BL_Type=4,(H49+H51)*('Step 2.4 - Data Input (OpEx)'!G48),0) -> 0 | I60: =IF(BL_Type=4,(I49+I51)*('Step 2.4 - Data Input (OpEx)'!G48),0) -> 0 | J60: =IF(BL_Type=4,(J49+J51)*('Step 2.4 - Data Input (OpEx)'!G48),0) -> 0 | K60: =IF(BL_Type=4,(K49+K51)*('Step 2.4 - Data Input (OpEx)'!G48),0) -> 0 | L60: =IF(BL_Type=4,(L49+L51)*('Step 2.4 - Data Input (OpEx)'!G48),0) -> 0
C61: Backwards Logistic at the End of Rental Agreements | E61: € | F61: =SUM(G61:L61) -> 0 | H61: =SUM(H62:H66) -> 0 | I61: =SUM(I62:I66) -> 0 | J61: =SUM(J62:J66) -> 0 | K61: =SUM(K62:K66) -> 0 | L61: =SUM(L62:L66) -> 0
D62: Costs for Direct Pick-Up System | E62: € | F62: =SUM(G62:L62) -> 0 | H62: =IF(BL_Type=1,H53*('Step 2.4 - Data Input (OpEx)'!G44*'Step 2.4 - Data Input (OpEx)'!G46)*(1-'Step 2.4 - Data Input (OpEx)'!G19)^0,0) -> 0 | I62: =IF(BL_Type=1,I53*('Step 2.4 - Data Input (OpEx)'!G44*'Step 2.4 - Data Input (OpEx)'!G46)*(1-'Step 2.4 - Data Input (OpEx)'!G19)^1,0) -> 0 | J62: =IF(BL_Type=1,J53*('Step 2.4 - Data Input (OpEx)'!G44*'Step 2.4 - Data Input (OpEx)'!G46)*(1-'Step 2.4 - Data Input (OpEx)'!G19)^2,0) -> 0 | K62: =IF(BL_Type=1,K53*('Step 2.4 - Data Input (OpEx)'!G44*'Step 2.4 - Data Input (OpEx)'!G46)*(1-'Step 2.4 - Data Input (OpEx)'!G19)^3,0) -> 0 | L62: =IF(BL_Type=1,L53*('Step 2.4 - Data Input (OpEx)'!G44*'Step 2.4 - Data Input (OpEx)'!G46)*(1-'Step 2.4 - Data Input (OpEx)'!G19)^4,0) -> 0 | M62: =IF(BL_Type=1,M53*('Step 2.4 - Data Input (OpEx)'!G44*'Step 2.4 - Data Input (OpEx)'!G46)*(1-'Step 2.4 - Data Input (OpEx)'!G19)^5,0) -> 0
D63: Costs for Multi-Step Pick-Up System / Step 1 (to CAS) | E63: € | F63: =SUM(G63:L63) -> 0 | H63: =IF(OR(BL_Type=2,BL_Type=3),H53*('Step 2.4 - Data Input (OpEx)'!G44*'Step 2.4 - Data Input (OpEx)'!G46)*(1-'Step 2.4 - Data Input (OpEx)'!G19)^0,0) -> 0 | I63: =IF(OR(BL_Type=2,BL_Type=3),I53*('Step 2.4 - Data Input (OpEx)'!G44*'Step 2.4 - Data Input (OpEx)'!G46)*(1-'Step 2.4 - Data Input (OpEx)'!G19)^1,0) -> 0 | J63: =IF(OR(BL_Type=2,BL_Type=3),J53*('Step 2.4 - Data Input (OpEx)'!G44*'Step 2.4 - Data Input (OpEx)'!G46)*(1-'Step 2.4 - Data Input (OpEx)'!G19)^2,0) -> 0 | K63: =IF(OR(BL_Type=2,BL_Type=3),K53*('Step 2.4 - Data Input (OpEx)'!G44*'Step 2.4 - Data Input (OpEx)'!G46)*(1-'Step 2.4 - Data Input (OpEx)'!G19)^3,0) -> 0 | L63: =IF(OR(BL_Type=2,BL_Type=3),L53*('Step 2.4 - Data Input (OpEx)'!G44*'Step 2.4 - Data Input (OpEx)'!G46)*(1-'Step 2.4 - Data Input (OpEx)'!G19)^4,0) -> 0 | M63: =IF(OR(BL_Type=2,BL_Type=3),M53*('Step 2.4 - Data Input (OpEx)'!G44*'Step 2.4 - Data Input (OpEx)'!G46)*(1-'Step 2.4 - Data Input (OpEx)'!G19)^5,0) -> 0
D64: Costs for Multi-Step Pick-Up System / Step 2 (to PS; no Sorting at CAS) | E64: € | F64: =SUM(G64:L64) -> 0 | H64: =IF(BL_Type=2,H53*('Step 2.4 - Data Input (OpEx)'!G45*'Step 2.4 - Data Input (OpEx)'!G46)*(1-'Step 2.4 - Data Input (OpEx)'!G19)^0,0) -> 0 | I64: =IF(BL_Type=2,I53*('Step 2.4 - Data Input (OpEx)'!G45*'Step 2.4 - Data Input (OpEx)'!G46)*(1-'Step 2.4 - Data Input (OpEx)'!G19)^1,0) -> 0 | J64: =IF(BL_Type=2,J53*('Step 2.4 - Data Input (OpEx)'!G45*'Step 2.4 - Data Input (OpEx)'!G46)*(1-'Step 2.4 - Data Input (OpEx)'!G19)^2,0) -> 0 | K64: =IF(BL_Type=2,K53*('Step 2.4 - Data Input (OpEx)'!G45*'Step 2.4 - Data Input (OpEx)'!G46)*(1-'Step 2.4 - Data Input (OpEx)'!G19)^3,0) -> 0 | L64: =IF(BL_Type=2,L53*('Step 2.4 - Data Input (OpEx)'!G45*'Step 2.4 - Data Input (OpEx)'!G46)*(1-'Step 2.4 - Data Input (OpEx)'!G19)^4,0) -> 0 | M64: =IF(BL_Type=2,M53*('Step 2.4 - Data Input (OpEx)'!G45*'Step 2.4 - Data Input (OpEx)'!G46)*(1-'Step 2.4 - Data Input (OpEx)'!G19)^5,0) -> 0
D65: Costs for Multi-Step Pick-Up System / Step 2 (to PS; Sorting at CAS) | E65: € | F65: =SUM(G65:L65) -> 0 | H65: =IF(BL_Type=3,H53*'Step 2.1 - Data Input (General)'!G24*('Step 2.4 - Data Input (OpEx)'!G45*'Step 2.4 - Data Input (OpEx)'!G46)*(1-'Step 2.4 - Data Input (OpEx)'!G19)^0,0) -> 0 | I65: =IF(BL_Type=3,I53*'Step 2.1 - Data Input (General)'!G24*('Step 2.4 - Data Input (OpEx)'!G45*'Step 2.4 - Data Input (OpEx)'!G46)*(1-'Step 2.4 - Data Input (OpEx)'!G19)^1,0) -> 0 | J65: =IF(BL_Type=3,J53*'Step 2.1 - Data Input (General)'!G24*('Step 2.4 - Data Input (OpEx)'!G45*'Step 2.4 - Data Input (OpEx)'!G46)*(1-'Step 2.4 - Data Input (OpEx)'!G19)^2,0) -> 0 | K65: =IF(BL_Type=3,K53*'Step 2.1 - Data Input (General)'!G24*('Step 2.4 - Data Input (OpEx)'!G45*'Step 2.4 - Data Input (OpEx)'!G46)*(1-'Step 2.4 - Data Input (OpEx)'!G19)^3,0) -> 0 | L65: =IF(BL_Type=3,L53*'Step 2.1 - Data Input (General)'!G24*('Step 2.4 - Data Input (OpEx)'!G45*'Step 2.4 - Data Input (OpEx)'!G46)*(1-'Step 2.4 - Data Input (OpEx)'!G19)^4,0) -> 0 | M65: =IF(BL_Type=3,M53*'Step 2.1 - Data Input (General)'!G24*('Step 2.4 - Data Input (OpEx)'!G45*'Step 2.4 - Data Input (OpEx)'!G46)*(1-'Step 2.4 - Data Input (OpEx)'!G19)^5,0) -> 0
D66: Costs for Shipment of Cores | E66: € | F66: =SUM(G66:L66) -> 0 | H66: =IF(BL_Type=4,H53*('Step 2.4 - Data Input (OpEx)'!G48),0) -> 0 | I66: =IF(BL_Type=4,I53*('Step 2.4 - Data Input (OpEx)'!G48),0) -> 0 | J66: =IF(BL_Type=4,J53*('Step 2.4 - Data Input (OpEx)'!G48),0) -> 0 | K66: =IF(BL_Type=4,K53*('Step 2.4 - Data Input (OpEx)'!G48),0) -> 0 | L66: =IF(BL_Type=4,L53*('Step 2.4 - Data Input (OpEx)'!G48),0) -> 0 | M66: =IF(BL_Type=4,M53*('Step 2.4 - Data Input (OpEx)'!G48),0) -> 0
D67: Pending Backward Logistics Costs after Year 5 | E67: € | F67: =SUM(G67:L67) -> 0 | M67: =SUM(M62:M66) -> 0
C68: Packaging Costs | E68: € | F68: =SUM(G68:L68) -> 0 | H68: ='Step 2.4 - Data Input (OpEx)'!G47*(H49+H51+H53) -> 0 | I68: ='Step 2.4 - Data Input (OpEx)'!G47*(I49+I51+I53) -> 0 | J68: ='Step 2.4 - Data Input (OpEx)'!G47*(J49+J51+J53) -> 0 | K68: ='Step 2.4 - Data Input (OpEx)'!G47*(K49+K51+K53) -> 0 | L68: ='Step 2.4 - Data Input (OpEx)'!G47*(L49+L51+L53) -> 0
B70: Dismantling | E70: € | F70: =SUM(G70:L70) -> 0 | H70: =SUM(H71:H72)+'Step 2.4 - Data Input (OpEx)'!G55 -> 0 | I70: =SUM(I71:I72)+'Step 2.4 - Data Input (OpEx)'!G55 -> 0 | J70: =SUM(J71:J72)+'Step 2.4 - Data Input (OpEx)'!G55 -> 0 | K70: =SUM(K71:K72)+'Step 2.4 - Data Input (OpEx)'!G55 -> 0 | L70: =SUM(L71:L72)+'Step 2.4 - Data Input (OpEx)'!G55 -> 0
C71: Personel Costs | E71: € | F71: =SUM(G71:L71) -> 0 | H71: ='Step 2.4 - Data Input (OpEx)'!G53*'Step 2.4 - Data Input (OpEx)'!G6*(H49+H51)*(1-'Step 2.4 - Data Input (OpEx)'!G17)^0 -> 0 | I71: ='Step 2.4 - Data Input (OpEx)'!G53*'Step 2.4 - Data Input (OpEx)'!G6*(I49+I51)*(1-'Step 2.4 - Data Input (OpEx)'!G17)^1 -> 0 | J71: ='Step 2.4 - Data Input (OpEx)'!G53*'Step 2.4 - Data Input (OpEx)'!G6*(J49+J51)*(1-'Step 2.4 - Data Input (OpEx)'!G17)^2 -> 0 | K71: ='Step 2.4 - Data Input (OpEx)'!G53*'Step 2.4 - Data Input (OpEx)'!G6*(K49+K51)*(1-'Step 2.4 - Data Input (OpEx)'!G17)^3 -> 0 | L71: ='Step 2.4 - Data Input (OpEx)'!G53*'Step 2.4 - Data Input (OpEx)'!G6*(L49+L51)*(1-'Step 2.4 - Data Input (OpEx)'!G17)^4 -> 0
C72: Machine Costs | E72: € | F72: =SUM(G72:L72) -> 0 | H72: ='Step 2.4 - Data Input (OpEx)'!G54*'Step 2.4 - Data Input (OpEx)'!G8*(H49+H51)*(1-'Step 2.4 - Data Input (OpEx)'!G18)^0 -> 0 | I72: ='Step 2.4 - Data Input (OpEx)'!G54*'Step 2.4 - Data Input (OpEx)'!G8*(I49+I51)*(1-'Step 2.4 - Data Input (OpEx)'!G18)^1 -> 0 | J72: ='Step 2.4 - Data Input (OpEx)'!G54*'Step 2.4 - Data Input (OpEx)'!G8*(J49+J51)*(1-'Step 2.4 - Data Input (OpEx)'!G18)^2 -> 0 | K72: ='Step 2.4 - Data Input (OpEx)'!G54*'Step 2.4 - Data Input (OpEx)'!G8*(K49+K51)*(1-'Step 2.4 - Data Input (OpEx)'!G18)^3 -> 0 | L72: ='Step 2.4 - Data Input (OpEx)'!G54*'Step 2.4 - Data Input (OpEx)'!G8*(L49+L51)*(1-'Step 2.4 - Data Input (OpEx)'!G18)^4 -> 0
B74: Identification and Sorting | E74: € | F74: =SUM(G74:L74) -> 0 | H74: =SUM(H75:H77)+'Step 2.4 - Data Input (OpEx)'!G61 -> 0 | I74: =SUM(I75:I77)+'Step 2.4 - Data Input (OpEx)'!G61 -> 0 | J74: =SUM(J75:J77)+'Step 2.4 - Data Input (OpEx)'!G61 -> 0 | K74: =SUM(K75:K77)+'Step 2.4 - Data Input (OpEx)'!G61 -> 0 | L74: =SUM(L75:L77)+'Step 2.4 - Data Input (OpEx)'!G61 -> 0
C75: Personel Costs | E75: € | F75: =SUM(G75:L75) -> 0 | H75: ='Step 2.4 - Data Input (OpEx)'!G58*'Step 2.4 - Data Input (OpEx)'!G6*(H49+H51)*(1-'Step 2.4 - Data Input (OpEx)'!G17)^0 -> 0 | I75: ='Step 2.4 - Data Input (OpEx)'!G58*'Step 2.4 - Data Input (OpEx)'!G6*(I49+I51)*(1-'Step 2.4 - Data Input (OpEx)'!G17)^1 -> 0 | J75: ='Step 2.4 - Data Input (OpEx)'!G58*'Step 2.4 - Data Input (OpEx)'!G6*(J49+J51)*(1-'Step 2.4 - Data Input (OpEx)'!G17)^2 -> 0 | K75: ='Step 2.4 - Data Input (OpEx)'!G58*'Step 2.4 - Data Input (OpEx)'!G6*(K49+K51)*(1-'Step 2.4 - Data Input (OpEx)'!G17)^3 -> 0 | L75: ='Step 2.4 - Data Input (OpEx)'!G58*'Step 2.4 - Data Input (OpEx)'!G6*(L49+L51)*(1-'Step 2.4 - Data Input (OpEx)'!G17)^4 -> 0
C76: Machine Costs | E76: € | F76: =SUM(G76:L76) -> 0 | H76: ='Step 2.4 - Data Input (OpEx)'!G59*'Step 2.4 - Data Input (OpEx)'!G8*(H49+H51)*(1-'Step 2.4 - Data Input (OpEx)'!G18)^0 -> 0 | I76: ='Step 2.4 - Data Input (OpEx)'!G59*'Step 2.4 - Data Input (OpEx)'!G8*(I49+I51)*(1-'Step 2.4 - Data Input (OpEx)'!G18)^1 -> 0 | J76: ='Step 2.4 - Data Input (OpEx)'!G59*'Step 2.4 - Data Input (OpEx)'!G8*(J49+J51)*(1-'Step 2.4 - Data Input (OpEx)'!G18)^2 -> 0 | K76: ='Step 2.4 - Data Input (OpEx)'!G59*'Step 2.4 - Data Input (OpEx)'!G8*(K49+K51)*(1-'Step 2.4 - Data Input (OpEx)'!G18)^3 -> 0 | L76: ='Step 2.4 - Data Input (OpEx)'!G59*'Step 2.4 - Data Input (OpEx)'!G8*(L49+L51)*(1-'Step 2.4 - Data Input (OpEx)'!G18)^4 -> 0
C77: Disposal Costs Cores | E77: € | F77: =SUM(G77:L77) -> 0 | H77: ='Step 2.4 - Data Input (OpEx)'!G60*((H49-H50)+(H51-H52)) -> 0 | I77: ='Step 2.4 - Data Input (OpEx)'!G60*((I49-I50)+(I51-I52)) -> 0 | J77: ='Step 2.4 - Data Input (OpEx)'!G60*((J49-J50)+(J51-J52)) -> 0 | K77: ='Step 2.4 - Data Input (OpEx)'!G60*((K49-K50)+(K51-K52)) -> 0 | L77: ='Step 2.4 - Data Input (OpEx)'!G60*((L49-L50)+(L51-L52)) -> 0
B79: Disassembly | E79: € | F79: =SUM(G79:L79) -> 0 | H79: =SUM(H80:H81)+'Step 2.4 - Data Input (OpEx)'!G66 -> 0 | I79: =SUM(I80:I81)+'Step 2.4 - Data Input (OpEx)'!G66 -> 0 | J79: =SUM(J80:J81)+'Step 2.4 - Data Input (OpEx)'!G66 -> 0 | K79: =SUM(K80:K81)+'Step 2.4 - Data Input (OpEx)'!G66 -> 0 | L79: =SUM(L80:L81)+'Step 2.4 - Data Input (OpEx)'!G66 -> 0
C80: Personel Costs | E80: € | F80: =SUM(G80:L80) -> 0 | H80: ='Step 2.4 - Data Input (OpEx)'!G64*'Step 2.4 - Data Input (OpEx)'!G6*(H50+H52)*(1-'Step 2.4 - Data Input (OpEx)'!G17)^0 -> 0 | I80: ='Step 2.4 - Data Input (OpEx)'!G64*'Step 2.4 - Data Input (OpEx)'!G6*(I50+I52)*(1-'Step 2.4 - Data Input (OpEx)'!G17)^1 -> 0 | J80: ='Step 2.4 - Data Input (OpEx)'!G64*'Step 2.4 - Data Input (OpEx)'!G6*(J50+J52)*(1-'Step 2.4 - Data Input (OpEx)'!G17)^2 -> 0 | K80: ='Step 2.4 - Data Input (OpEx)'!G64*'Step 2.4 - Data Input (OpEx)'!G6*(K50+K52)*(1-'Step 2.4 - Data Input (OpEx)'!G17)^3 -> 0 | L80: ='Step 2.4 - Data Input (OpEx)'!G64*'Step 2.4 - Data Input (OpEx)'!G6*(L50+L52)*(1-'Step 2.4 - Data Input (OpEx)'!G17)^4 -> 0
C81: Machine Costs | E81: € | F81: =SUM(G81:L81) -> 0 | H81: ='Step 2.4 - Data Input (OpEx)'!G65*'Step 2.4 - Data Input (OpEx)'!G8*(H50+H52)*(1-'Step 2.4 - Data Input (OpEx)'!G18)^0 -> 0 | I81: ='Step 2.4 - Data Input (OpEx)'!G65*'Step 2.4 - Data Input (OpEx)'!G8*(I50+I52)*(1-'Step 2.4 - Data Input (OpEx)'!G18)^1 -> 0 | J81: ='Step 2.4 - Data Input (OpEx)'!G65*'Step 2.4 - Data Input (OpEx)'!G8*(J50+J52)*(1-'Step 2.4 - Data Input (OpEx)'!G18)^2 -> 0 | K81: ='Step 2.4 - Data Input (OpEx)'!G65*'Step 2.4 - Data Input (OpEx)'!G8*(K50+K52)*(1-'Step 2.4 - Data Input (OpEx)'!G18)^3 -> 0 | L81: ='Step 2.4 - Data Input (OpEx)'!G65*'Step 2.4 - Data Input (OpEx)'!G8*(L50+L52)*(1-'Step 2.4 - Data Input (OpEx)'!G18)^4 -> 0
B83: Inspection | E83: € | F83: =SUM(G83:L83) -> 0 | H83: =SUM(H84:H87)+'Step 2.4 - Data Input (OpEx)'!G75 -> 0 | I83: =SUM(I84:I87)+'Step 2.4 - Data Input (OpEx)'!G75 -> 0 | J83: =SUM(J84:J87)+'Step 2.4 - Data Input (OpEx)'!G75 -> 0 | K83: =SUM(K84:K87)+'Step 2.4 - Data Input (OpEx)'!G75 -> 0 | L83: =SUM(L84:L87)+'Step 2.4 - Data Input (OpEx)'!G75 -> 0
C84: Personel Costs | E84: € | F84: =SUM(G84:L84) -> 0 | H84: ='Step 2.4 - Data Input (OpEx)'!G69*'Step 2.4 - Data Input (OpEx)'!G6*(H50)*(1-'Step 2.4 - Data Input (OpEx)'!G17)^0 -> 0 | I84: ='Step 2.4 - Data Input (OpEx)'!G69*'Step 2.4 - Data Input (OpEx)'!G6*(I50)*(1-'Step 2.4 - Data Input (OpEx)'!G17)^1 -> 0 | J84: ='Step 2.4 - Data Input (OpEx)'!G69*'Step 2.4 - Data Input (OpEx)'!G6*(J50)*(1-'Step 2.4 - Data Input (OpEx)'!G17)^2 -> 0 | K84: ='Step 2.4 - Data Input (OpEx)'!G69*'Step 2.4 - Data Input (OpEx)'!G6*(K50)*(1-'Step 2.4 - Data Input (OpEx)'!G17)^3 -> 0 | L84: ='Step 2.4 - Data Input (OpEx)'!G69*'Step 2.4 - Data Input (OpEx)'!G6*(L50)*(1-'Step 2.4 - Data Input (OpEx)'!G17)^4 -> 0
C85: Machine Costs | E85: € | F85: =SUM(G85:L85) -> 0 | H85: ='Step 2.4 - Data Input (OpEx)'!G70*'Step 2.4 - Data Input (OpEx)'!G8*(H50)*(1-'Step 2.4 - Data Input (OpEx)'!G18)^0 -> 0 | I85: ='Step 2.4 - Data Input (OpEx)'!G70*'Step 2.4 - Data Input (OpEx)'!G8*(I50)*(1-'Step 2.4 - Data Input (OpEx)'!G18)^1 -> 0 | J85: ='Step 2.4 - Data Input (OpEx)'!G70*'Step 2.4 - Data Input (OpEx)'!G8*(J50)*(1-'Step 2.4 - Data Input (OpEx)'!G18)^2 -> 0 | K85: ='Step 2.4 - Data Input (OpEx)'!G70*'Step 2.4 - Data Input (OpEx)'!G8*(K50)*(1-'Step 2.4 - Data Input (OpEx)'!G18)^3 -> 0 | L85: ='Step 2.4 - Data Input (OpEx)'!G70*'Step 2.4 - Data Input (OpEx)'!G8*(L50)*(1-'Step 2.4 - Data Input (OpEx)'!G18)^4 -> 0
C86: Disposal Costs Scrap Components | E86: € | F86: =SUM(G86:L86) -> 0 | H86: ='Step 2.4 - Data Input (OpEx)'!G74*'Step 2.4 - Data Input (OpEx)'!G73*'Step 2.4 - Data Input (OpEx)'!G72*(H50+H52) -> 0 | I86: ='Step 2.4 - Data Input (OpEx)'!G74*'Step 2.4 - Data Input (OpEx)'!G73*'Step 2.4 - Data Input (OpEx)'!G72*(I50+I52) -> 0 | J86: ='Step 2.4 - Data Input (OpEx)'!G74*'Step 2.4 - Data Input (OpEx)'!G73*'Step 2.4 - Data Input (OpEx)'!G72*(J50+J52) -> 0 | K86: ='Step 2.4 - Data Input (OpEx)'!G74*'Step 2.4 - Data Input (OpEx)'!G73*'Step 2.4 - Data Input (OpEx)'!G72*(K50+K52) -> 0 | L86: ='Step 2.4 - Data Input (OpEx)'!G74*'Step 2.4 - Data Input (OpEx)'!G73*'Step 2.4 - Data Input (OpEx)'!G72*(L50+L52) -> 0
C87: Disposal Costs Not Reusable Components | E87: € | F87: =SUM(G87:L87) -> 0 | H87: ='Step 2.4 - Data Input (OpEx)'!G74*'Step 2.4 - Data Input (OpEx)'!G71*(H50+H52) -> 0 | I87: ='Step 2.4 - Data Input (OpEx)'!G74*'Step 2.4 - Data Input (OpEx)'!G71*(I50+I52) -> 0 | J87: ='Step 2.4 - Data Input (OpEx)'!G74*'Step 2.4 - Data Input (OpEx)'!G71*(J50+J52) -> 0 | K87: ='Step 2.4 - Data Input (OpEx)'!G74*'Step 2.4 - Data Input (OpEx)'!G71*(K50+K52) -> 0 | L87: ='Step 2.4 - Data Input (OpEx)'!G74*'Step 2.4 - Data Input (OpEx)'!G71*(L50+L52) -> 0
B89: Cleaning | E89: € | F89: =SUM(G89:L89) -> 0 | H89: =SUM(H90:H91)+'Step 2.4 - Data Input (OpEx)'!G80 -> 0 | I89: =SUM(I90:I91)+'Step 2.4 - Data Input (OpEx)'!G80 -> 0 | J89: =SUM(J90:J91)+'Step 2.4 - Data Input (OpEx)'!G80 -> 0 | K89: =SUM(K90:K91)+'Step 2.4 - Data Input (OpEx)'!G80 -> 0 | L89: =SUM(L90:L91)+'Step 2.4 - Data Input (OpEx)'!G80 -> 0
C90: Personel Costs | E90: € | F90: =SUM(G90:L90) -> 0 | H90: ='Step 2.4 - Data Input (OpEx)'!G78*'Step 2.4 - Data Input (OpEx)'!G6*(H50)*(1-'Step 2.4 - Data Input (OpEx)'!G17)^0 -> 0 | I90: ='Step 2.4 - Data Input (OpEx)'!G78*'Step 2.4 - Data Input (OpEx)'!G6*(I50)*(1-'Step 2.4 - Data Input (OpEx)'!G17)^1 -> 0 | J90: ='Step 2.4 - Data Input (OpEx)'!G78*'Step 2.4 - Data Input (OpEx)'!G6*(J50)*(1-'Step 2.4 - Data Input (OpEx)'!G17)^2 -> 0 | K90: ='Step 2.4 - Data Input (OpEx)'!G78*'Step 2.4 - Data Input (OpEx)'!G6*(K50)*(1-'Step 2.4 - Data Input (OpEx)'!G17)^3 -> 0 | L90: ='Step 2.4 - Data Input (OpEx)'!G78*'Step 2.4 - Data Input (OpEx)'!G6*(L50)*(1-'Step 2.4 - Data Input (OpEx)'!G17)^4 -> 0
C91: Machine Costs | E91: € | F91: =SUM(G91:L91) -> 0 | H91: ='Step 2.4 - Data Input (OpEx)'!G79*'Step 2.4 - Data Input (OpEx)'!G8*(H50)*(1-'Step 2.4 - Data Input (OpEx)'!G18)^0 -> 0 | I91: ='Step 2.4 - Data Input (OpEx)'!G79*'Step 2.4 - Data Input (OpEx)'!G8*(I50)*(1-'Step 2.4 - Data Input (OpEx)'!G18)^1 -> 0 | J91: ='Step 2.4 - Data Input (OpEx)'!G79*'Step 2.4 - Data Input (OpEx)'!G8*(J50)*(1-'Step 2.4 - Data Input (OpEx)'!G18)^2 -> 0 | K91: ='Step 2.4 - Data Input (OpEx)'!G79*'Step 2.4 - Data Input (OpEx)'!G8*(K50)*(1-'Step 2.4 - Data Input (OpEx)'!G18)^3 -> 0 | L91: ='Step 2.4 - Data Input (OpEx)'!G79*'Step 2.4 - Data Input (OpEx)'!G8*(L50)*(1-'Step 2.4 - Data Input (OpEx)'!G18)^4 -> 0
B93: Restoring | E93: € | F93: =SUM(G93:L93) -> 0 | H93: =SUM(H94:H96)+'Step 2.4 - Data Input (OpEx)'!G86 -> 0 | I93: =SUM(I94:I96)+'Step 2.4 - Data Input (OpEx)'!G86 -> 0 | J93: =SUM(J94:J96)+'Step 2.4 - Data Input (OpEx)'!G86 -> 0 | K93: =SUM(K94:K96)+'Step 2.4 - Data Input (OpEx)'!G86 -> 0 | L93: =SUM(L94:L96)+'Step 2.4 - Data Input (OpEx)'!G86 -> 0
C94: Personel Costs | E94: € | F94: =SUM(G94:L94) -> 0 | H94: ='Step 2.4 - Data Input (OpEx)'!G83*'Step 2.4 - Data Input (OpEx)'!G6*(H50)*(1-'Step 2.4 - Data Input (OpEx)'!G17)^0 -> 0 | I94: ='Step 2.4 - Data Input (OpEx)'!G89*'Step 2.4 - Data Input (OpEx)'!G6*(I50)*(1-'Step 2.4 - Data Input (OpEx)'!G17)^1 -> 0 | J94: ='Step 2.4 - Data Input (OpEx)'!G83*'Step 2.4 - Data Input (OpEx)'!G6*(J50)*(1-'Step 2.4 - Data Input (OpEx)'!G17)^2 -> 0 | K94: ='Step 2.4 - Data Input (OpEx)'!G83*'Step 2.4 - Data Input (OpEx)'!G6*(K50)*(1-'Step 2.4 - Data Input (OpEx)'!G17)^3 -> 0 | L94: ='Step 2.4 - Data Input (OpEx)'!G83*'Step 2.4 - Data Input (OpEx)'!G6*(L50)*(1-'Step 2.4 - Data Input (OpEx)'!G17)^4 -> 0
C95: Machine Costs | E95: € | F95: =SUM(G95:L95) -> 0 | H95: =Automated_Labour_Restoring*'Step 2.4 - Data Input (OpEx)'!G8*(H50)*(1-'Step 2.4 - Data Input (OpEx)'!G18)^0 -> 0 | I95: ='Step 2.4 - Data Input (OpEx)'!G84*'Step 2.4 - Data Input (OpEx)'!G8*(I50)*(1-'Step 2.4 - Data Input (OpEx)'!G18)^1 -> 0 | J95: ='Step 2.4 - Data Input (OpEx)'!G84*'Step 2.4 - Data Input (OpEx)'!G8*(J50)*(1-'Step 2.4 - Data Input (OpEx)'!G18)^2 -> 0 | K95: ='Step 2.4 - Data Input (OpEx)'!G84*'Step 2.4 - Data Input (OpEx)'!G8*(K50)*(1-'Step 2.4 - Data Input (OpEx)'!G18)^3 -> 0 | L95: ='Step 2.4 - Data Input (OpEx)'!G84*'Step 2.4 - Data Input (OpEx)'!G8*(L50)*(1-'Step 2.4 - Data Input (OpEx)'!G18)^4 -> 0
C96: Material Costs (e.g. Paints) | E96: € | F96: =SUM(G96:L96) -> 0 | H96: ='Step 2.4 - Data Input (OpEx)'!G85*H50*(1+'Step 2.4 - Data Input (OpEx)'!G14)^0 -> 0 | I96: ='Step 2.4 - Data Input (OpEx)'!G85*I50*(1+'Step 2.4 - Data Input (OpEx)'!G14)^1 -> 0 | J96: ='Step 2.4 - Data Input (OpEx)'!G85*J50*(1+'Step 2.4 - Data Input (OpEx)'!G14)^2 -> 0 | K96: ='Step 2.4 - Data Input (OpEx)'!G85*K50*(1+'Step 2.4 - Data Input (OpEx)'!G14)^3 -> 0 | L96: ='Step 2.4 - Data Input (OpEx)'!G85*L50*(1+'Step 2.4 - Data Input (OpEx)'!G14)^4 -> 0
B98: Assembly | E98: € | F98: =SUM(G98:L98) -> 0 | H98: =SUM(H99:H101)+'Step 2.4 - Data Input (OpEx)'!G93 -> 0 | I98: =SUM(I99:I101)+'Step 2.4 - Data Input (OpEx)'!G93 -> 0 | J98: =SUM(J99:J101)+'Step 2.4 - Data Input (OpEx)'!G93 -> 0 | K98: =SUM(K99:K101)+'Step 2.4 - Data Input (OpEx)'!G93 -> 0 | L98: =SUM(L99:L101)+'Step 2.4 - Data Input (OpEx)'!G93 -> 0
C99: Personel Costs | E99: € | F99: =SUM(G99:L99) -> 0 | H99: ='Step 2.4 - Data Input (OpEx)'!G89*'Step 2.4 - Data Input (OpEx)'!G6*('Step 2.2 - Data Input (Revenue)'!G9)*(1-'Step 2.4 - Data Input (OpEx)'!G17)^0 -> 0 | I99: ='Step 2.4 - Data Input (OpEx)'!G89*'Step 2.4 - Data Input (OpEx)'!G6*('Step 2.2 - Data Input (Revenue)'!G10)*(1-'Step 2.4 - Data Input (OpEx)'!G17)^1 -> 0 | J99: ='Step 2.4 - Data Input (OpEx)'!G89*'Step 2.4 - Data Input (OpEx)'!G6*('Step 2.2 - Data Input (Revenue)'!G11)*(1-'Step 2.4 - Data Input (OpEx)'!G17)^2 -> 0 | K99: ='Step 2.4 - Data Input (OpEx)'!G89*'Step 2.4 - Data Input (OpEx)'!G6*('Step 2.2 - Data Input (Revenue)'!G12)*(1-'Step 2.4 - Data Input (OpEx)'!G17)^3 -> 0 | L99: ='Step 2.4 - Data Input (OpEx)'!G89*'Step 2.4 - Data Input (OpEx)'!G6*('Step 2.2 - Data Input (Revenue)'!G13)*(1-'Step 2.4 - Data Input (OpEx)'!G17)^4 -> 0
C100: Machine Costs | E100: € | F100: =SUM(G100:L100) -> 0 | H100: ='Step 2.4 - Data Input (OpEx)'!G90*'Step 2.4 - Data Input (OpEx)'!G8*('Step 2.2 - Data Input (Revenue)'!G9)*(1-'Step 2.4 - Data Input (OpEx)'!G18)^0 -> 0 | I100: ='Step 2.4 - Data Input (OpEx)'!G90*'Step 2.4 - Data Input (OpEx)'!G8*('Step 2.2 - Data Input (Revenue)'!G10)*(1-'Step 2.4 - Data Input (OpEx)'!G18)^1 -> 0 | J100: ='Step 2.4 - Data Input (OpEx)'!G90*'Step 2.4 - Data Input (OpEx)'!G8*('Step 2.2 - Data Input (Revenue)'!G11)*(1-'Step 2.4 - Data Input (OpEx)'!G18)^2 -> 0 | K100: ='Step 2.4 - Data Input (OpEx)'!G90*'Step 2.4 - Data Input (OpEx)'!G8*('Step 2.2 - Data Input (Revenue)'!G12)*(1-'Step 2.4 - Data Input (OpEx)'!G18)^3 -> 0 | L100: ='Step 2.4 - Data Input (OpEx)'!G90*'Step 2.4 - Data Input (OpEx)'!G8*('Step 2.2 - Data Input (Revenue)'!G13)*(1-'Step 2.4 - Data Input (OpEx)'!G18)^4 -> 0
C101: Material Costs (e.g. Spare Parts) | E101: € | F101: =SUM(G101:L101) -> 0 | H101: =('Step 2.4 - Data Input (OpEx)'!G91+'Step 2.4 - Data Input (OpEx)'!G92)*'Step 2.2 - Data Input (Revenue)'!G9*(1+'Step 2.4 - Data Input (OpEx)'!G14)^0 -> 0 | I101: =('Step 2.4 - Data Input (OpEx)'!G91+'Step 2.4 - Data Input (OpEx)'!G92)*'Step 2.2 - Data Input (Revenue)'!G10*(1+'Step 2.4 - Data Input (OpEx)'!G14)^1 -> 0 | J101: =('Step 2.4 - Data Input (OpEx)'!G91+'Step 2.4 - Data Input (OpEx)'!G92)*'Step 2.2 - Data Input (Revenue)'!G11*(1+'Step 2.4 - Data Input (OpEx)'!G14)^2 -> 0 | K101: =('Step 2.4 - Data Input (OpEx)'!G91+'Step 2.4 - Data Input (OpEx)'!G92)*'Step 2.2 - Data Input (Revenue)'!G12*(1+'Step 2.4 - Data Input (OpEx)'!G14)^3 -> 0 | L101: =('Step 2.4 - Data Input (OpEx)'!G91+'Step 2.4 - Data Input (OpEx)'!G92)*'Step 2.2 - Data Input (Revenue)'!G13*(1+'Step 2.4 - Data Input (OpEx)'!G14)^4 -> 0
B103: Testing | E103: € | F103: =SUM(G103:L103) -> 0 | H103: =SUM(H104:H105)+'Step 2.4 - Data Input (OpEx)'!G99 -> 0 | I103: =SUM(I104:I105)+'Step 2.4 - Data Input (OpEx)'!G99 -> 0 | J103: =SUM(J104:J105)+'Step 2.4 - Data Input (OpEx)'!G99 -> 0 | K103: =SUM(K104:K105)+'Step 2.4 - Data Input (OpEx)'!G99 -> 0 | L103: =SUM(L104:L105)+'Step 2.4 - Data Input (OpEx)'!G99 -> 0
C104: Personel Costs | E104: € | F104: =SUM(G104:L104) -> 0 | H104: ='Step 2.4 - Data Input (OpEx)'!G96*'Step 2.4 - Data Input (OpEx)'!G6*('Step 2.2 - Data Input (Revenue)'!G9)*(1-'Step 2.4 - Data Input (OpEx)'!G17)^0 -> 0 | I104: ='Step 2.4 - Data Input (OpEx)'!G96*'Step 2.4 - Data Input (OpEx)'!G6*('Step 2.2 - Data Input (Revenue)'!G10)*(1-'Step 2.4 - Data Input (OpEx)'!G17)^1 -> 0 | J104: ='Step 2.4 - Data Input (OpEx)'!G96*'Step 2.4 - Data Input (OpEx)'!G6*('Step 2.2 - Data Input (Revenue)'!G11)*(1-'Step 2.4 - Data Input (OpEx)'!G17)^2 -> 0 | K104: ='Step 2.4 - Data Input (OpEx)'!G96*'Step 2.4 - Data Input (OpEx)'!G6*('Step 2.2 - Data Input (Revenue)'!G12)*(1-'Step 2.4 - Data Input (OpEx)'!G17)^3 -> 0 | L104: ='Step 2.4 - Data Input (OpEx)'!G96*'Step 2.4 - Data Input (OpEx)'!G6*('Step 2.2 - Data Input (Revenue)'!G13)*(1-'Step 2.4 - Data Input (OpEx)'!G17)^4 -> 0
C105: Machine Costs | E105: € | F105: =SUM(G105:L105) -> 0 | H105: ='Step 2.4 - Data Input (OpEx)'!G97*'Step 2.4 - Data Input (OpEx)'!G8*('Step 2.2 - Data Input (Revenue)'!G9)*(1-'Step 2.4 - Data Input (OpEx)'!G18)^0 -> 0 | I105: ='Step 2.4 - Data Input (OpEx)'!G97*'Step 2.4 - Data Input (OpEx)'!G8*('Step 2.2 - Data Input (Revenue)'!G10)*(1-'Step 2.4 - Data Input (OpEx)'!G18)^1 -> 0 | J105: ='Step 2.4 - Data Input (OpEx)'!G97*'Step 2.4 - Data Input (OpEx)'!G8*('Step 2.2 - Data Input (Revenue)'!G11)*(1-'Step 2.4 - Data Input (OpEx)'!G18)^2 -> 0 | K105: ='Step 2.4 - Data Input (OpEx)'!G97*'Step 2.4 - Data Input (OpEx)'!G8*('Step 2.2 - Data Input (Revenue)'!G12)*(1-'Step 2.4 - Data Input (OpEx)'!G18)^3 -> 0 | L105: ='Step 2.4 - Data Input (OpEx)'!G97*'Step 2.4 - Data Input (OpEx)'!G8*('Step 2.2 - Data Input (Revenue)'!G13)*(1-'Step 2.4 - Data Input (OpEx)'!G18)^4 -> 0
C106: Certification Costs | E106: € | F106: =SUM(G106:L106) -> 0 | H106: ='Step 2.4 - Data Input (OpEx)'!G98*'Step 2.2 - Data Input (Revenue)'!G9 -> 0 | I106: ='Step 2.4 - Data Input (OpEx)'!G98*'Step 2.2 - Data Input (Revenue)'!G10 -> 0 | J106: ='Step 2.4 - Data Input (OpEx)'!G98*'Step 2.2 - Data Input (Revenue)'!G11 -> 0 | K106: ='Step 2.4 - Data Input (OpEx)'!G98*'Step 2.2 - Data Input (Revenue)'!G12 -> 0 | L106: ='Step 2.4 - Data Input (OpEx)'!G98*'Step 2.2 - Data Input (Revenue)'!G13 -> 0
B108: Forward Logistics | E108: € | F108: =SUM(G108:L108) -> 0 | H108: =IF('Step 1 - Case Selection'!V51="as a Flat Rate",H109+'Step 2.4 - Data Input (OpEx)'!G108,SUM(H110:H113)+'Step 2.4 - Data Input (OpEx)'!G108) -> 0 | I108: =IF('Step 1 - Case Selection'!V51="as a Flat Rate",I109+'Step 2.4 - Data Input (OpEx)'!G108,SUM(I110:I113)+'Step 2.4 - Data Input (OpEx)'!G108) -> 0 | J108: =IF('Step 1 - Case Selection'!V51="as a Flat Rate",J109+'Step 2.4 - Data Input (OpEx)'!G108,SUM(J110:J113)+'Step 2.4 - Data Input (OpEx)'!G108) -> 0 | K108: =IF('Step 1 - Case Selection'!V51="as a Flat Rate",K109+'Step 2.4 - Data Input (OpEx)'!G108,SUM(K110:K113)+'Step 2.4 - Data Input (OpEx)'!G108) -> 0 | L108: =IF('Step 1 - Case Selection'!V51="as a Flat Rate",L109+'Step 2.4 - Data Input (OpEx)'!G108,SUM(L110:L113)+'Step 2.4 - Data Input (OpEx)'!G108) -> 0
C109: Optional Flat Rate Calculation | E109: € | F109: =SUM(G109:L109) -> 0 | H109: ='Step 2.4 - Data Input (OpEx)'!G102*('Step 2.2 - Data Input (Revenue)'!G9+'Step 2.2 - Data Input (Revenue)'!G18) -> 0 | I109: ='Step 2.4 - Data Input (OpEx)'!G102*('Step 2.2 - Data Input (Revenue)'!G10+'Step 2.2 - Data Input (Revenue)'!G19) -> 0 | J109: ='Step 2.4 - Data Input (OpEx)'!G102*('Step 2.2 - Data Input (Revenue)'!G11+'Step 2.2 - Data Input (Revenue)'!G20) -> 0 | K109: ='Step 2.4 - Data Input (OpEx)'!G102*('Step 2.2 - Data Input (Revenue)'!G12+'Step 2.2 - Data Input (Revenue)'!G21) -> 0 | L109: ='Step 2.4 - Data Input (OpEx)'!G102*('Step 2.2 - Data Input (Revenue)'!G13+'Step 2.2 - Data Input (Revenue)'!G22) -> 0
C110: Delivery Costs | E110: € | F110: =SUM(G110:L110) -> 0 | H110: =IF(FL_Type=1,'Step 2.4 - Data Input (OpEx)'!G103*'Step 2.4 - Data Input (OpEx)'!G105*('Step 2.2 - Data Input (Revenue)'!G9+'Step 2.2 - Data Input (Revenue)'!G18)*(1-'Step 2.4 - Data Input (OpEx)'!G20)^0,0) -> 0 | I110: =IF(FL_Type=1, 'Step 2.4 - Data Input (OpEx)'!G103*'Step 2.4 - Data Input (OpEx)'!G105*('Step 2.2 - Data Input (Revenue)'!G10+'Step 2.2 - Data Input (Revenue)'!G19)*(1-'Step 2.4 - Data Input (OpEx)'!G20)^1,0) -> 0 | J110: =IF(FL_Type=1, 'Step 2.4 - Data Input (OpEx)'!G103*'Step 2.4 - Data Input (OpEx)'!G105*('Step 2.2 - Data Input (Revenue)'!G11+'Step 2.2 - Data Input (Revenue)'!G20)*(1-'Step 2.4 - Data Input (OpEx)'!G20)^2,0) -> 0 | K110: =IF(FL_Type=1, 'Step 2.4 - Data Input (OpEx)'!G103*'Step 2.4 - Data Input (OpEx)'!G105*('Step 2.2 - Data Input (Revenue)'!G12+'Step 2.2 - Data Input (Revenue)'!G21)*(1-'Step 2.4 - Data Input (OpEx)'!G20)^3,0) -> 0 | L110: =IF(FL_Type=1, 'Step 2.4 - Data Input (OpEx)'!G103*'Step 2.4 - Data Input (OpEx)'!G105*('Step 2.2 - Data Input (Revenue)'!G13+'Step 2.2 - Data Input (Revenue)'!G22)*(1-'Step 2.4 - Data Input (OpEx)'!G20)^4,0) -> 0
C111: Shipment Costs | E111: € | F111: =SUM(G111:L111) -> 0 | H111: =IF(FL_Type=2,'Step 2.4 - Data Input (OpEx)'!G107*('Step 2.2 - Data Input (Revenue)'!G9+'Step 2.2 - Data Input (Revenue)'!G18),0) -> 0 | I111: =IF(FL_Type=2,'Step 2.4 - Data Input (OpEx)'!G107*('Step 2.2 - Data Input (Revenue)'!G10+'Step 2.2 - Data Input (Revenue)'!G19),0) -> 0 | J111: =IF(FL_Type=2,'Step 2.4 - Data Input (OpEx)'!G107*('Step 2.2 - Data Input (Revenue)'!G11+'Step 2.2 - Data Input (Revenue)'!G20),0) -> 0 | K111: =IF(FL_Type=2,'Step 2.4 - Data Input (OpEx)'!G107*('Step 2.2 - Data Input (Revenue)'!G12+'Step 2.2 - Data Input (Revenue)'!G21),0) -> 0 | L111: =IF(FL_Type=2,'Step 2.4 - Data Input (OpEx)'!G107*('Step 2.2 - Data Input (Revenue)'!G13+'Step 2.2 - Data Input (Revenue)'!G22),0) -> 0
C112: Customer Site Repair Logstics | E112: € | F112: =SUM(G112:L112) -> 0 | H112: =IF(FL_Type=3, 'Step 2.4 - Data Input (OpEx)'!G103*'Step 2.4 - Data Input (OpEx)'!G105*'Step 2.2 - Data Input (Revenue)'!G9*'Step 2.4 - Data Input (OpEx)'!G104*(1-'Step 2.4 - Data Input (OpEx)'!G20)^0,0) -> 0 | I112: =IF(FL_Type=3, 'Step 2.4 - Data Input (OpEx)'!G103*'Step 2.4 - Data Input (OpEx)'!G105*'Step 2.2 - Data Input (Revenue)'!G10*'Step 2.4 - Data Input (OpEx)'!G104*(1-'Step 2.4 - Data Input (OpEx)'!G20)^1,0) -> 0 | J112: =IF(FL_Type=3, 'Step 2.4 - Data Input (OpEx)'!G103*'Step 2.4 - Data Input (OpEx)'!G105*'Step 2.2 - Data Input (Revenue)'!G11*'Step 2.4 - Data Input (OpEx)'!G104*(1-'Step 2.4 - Data Input (OpEx)'!G20)^2,0) -> 0 | K112: =IF(FL_Type=3, 'Step 2.4 - Data Input (OpEx)'!G103*'Step 2.4 - Data Input (OpEx)'!G105*'Step 2.2 - Data Input (Revenue)'!G12*'Step 2.4 - Data Input (OpEx)'!G104*(1-'Step 2.4 - Data Input (OpEx)'!G20)^3,0) -> 0 | L112: =IF(FL_Type=3, 'Step 2.4 - Data Input (OpEx)'!G103*'Step 2.4 - Data Input (OpEx)'!G105*'Step 2.2 - Data Input (Revenue)'!G13*'Step 2.4 - Data Input (OpEx)'!G104*(1-'Step 2.4 - Data Input (OpEx)'!G20)^4,0) -> 0
C113: Packaging Costs | E113: € | F113: =SUM(G113:L113) -> 0 | H113: ='Step 2.4 - Data Input (OpEx)'!G106*('Step 2.2 - Data Input (Revenue)'!G9+'Step 2.2 - Data Input (Revenue)'!G18) -> 0 | I113: ='Step 2.4 - Data Input (OpEx)'!G106*('Step 2.2 - Data Input (Revenue)'!G10+'Step 2.2 - Data Input (Revenue)'!G19) -> 0 | J113: ='Step 2.4 - Data Input (OpEx)'!G106*('Step 2.2 - Data Input (Revenue)'!G11+'Step 2.2 - Data Input (Revenue)'!G20) -> 0 | K113: ='Step 2.4 - Data Input (OpEx)'!G106*('Step 2.2 - Data Input (Revenue)'!G12+'Step 2.2 - Data Input (Revenue)'!G21) -> 0 | L113: ='Step 2.4 - Data Input (OpEx)'!G106*('Step 2.2 - Data Input (Revenue)'!G13+'Step 2.2 - Data Input (Revenue)'!G22) -> 0
A115: Financing costs | E115: € | F115: =SUM(G115:L115) -> 0 | H115: =SUM(H117) -> 0 | I115: =SUM(I117) -> 0 | J115: =SUM(J117) -> 0 | K115: =SUM(K117) -> 0 | L115: =SUM(L117) -> 0
B117: Loans | E117: € | F117: =SUM(H117:L117) -> 0 | H117: =SUM(H118:H119) -> 0 | I117: =SUM(I118:I119) -> 0 | J117: =SUM(J118:J119) -> 0 | K117: =SUM(K118:K119) -> 0 | L117: =SUM(L118:L119) -> 0
C118: Repayment Instalment | E118: € | F118: =SUM(H118:L118) -> 0 | H118: =IFERROR('Step 2.1 - Data Input (General)'!G16/'Step 2.1 - Data Input (General)'!G17,0) -> 0 | I118: =IF('Step 2.1 - Data Input (General)'!G17>1, 'Step 2.1 - Data Input (General)'!G16/'Step 2.1 - Data Input (General)'!G17, 0) -> 0 | J118: =IF('Step 2.1 - Data Input (General)'!G17>2, 'Step 2.1 - Data Input (General)'!G16/'Step 2.1 - Data Input (General)'!G17, 0) -> 0 | K118: =IF('Step 2.1 - Data Input (General)'!G17>3, 'Step 2.1 - Data Input (General)'!G16/'Step 2.1 - Data Input (General)'!G17, 0) -> 0 | L118: =IF('Step 2.1 - Data Input (General)'!G17>4, 'Step 2.1 - Data Input (General)'!G16/'Step 2.1 - Data Input (General)'!G17, 0) -> 0
C119: Interest Cost | E119: € | F119: =SUM(H119:L119) -> 0 | H119: ='Step 2.1 - Data Input (General)'!G18 -> 0 | I119: =IF('Step 2.1 - Data Input (General)'!G17>1, 'Step 2.1 - Data Input (General)'!G18, 0) -> 0 | J119: =IF('Step 2.1 - Data Input (General)'!G17>2, 'Step 2.1 - Data Input (General)'!G18, 0) -> 0 | K119: =IF('Step 2.1 - Data Input (General)'!G17>3, 'Step 2.1 - Data Input (General)'!G18, 0) -> 0 | L119: =IF('Step 2.1 - Data Input (General)'!G17>4, 'Step 2.1 - Data Input (General)'!G18, 0) -> 0
A125: Calculation of Economic Impact (Scenario I)
B127: Cash Flow
C128: Total Cash Flow (Gross) | E128: € | G128: =IF('Step 1 - Case Selection'!V55="No",0,G129-G130) -> 0 | H128: =IF('Step 1 - Case Selection'!V59<1,0,H129-H130) -> 0 | I128: =IF('Step 1 - Case Selection'!V59<2,0,I129-I130) -> 0 | J128: =IF('Step 1 - Case Selection'!V59<3,0,J129-J130) -> 0 | K128: =IF('Step 1 - Case Selection'!V59<4,0,K129-K130) -> 0 | L128: =IF('Step 1 - Case Selection'!V59<5,0,L129-L130) -> 0
...

Sheet Calculation (sII)
A1: Type | B1: Category | C1: Sub-Categoy | D1: Auxiliary Calculations | E1: Unit | F1: Total Value | G1: Year 0 - Value | H1: Year 1 - Value | I1: Year 2 - Value | J1: Year 3 - Value | K1: Year 4 - Value | L1: Year 5 - Value | M1: After | N1: Auxiliary Column
A2: Income Flows | E2: € | F2: =SUM(G2:L2) -> 0 | G2: =SUM(G4,G13) -> 0 | H2: =SUM(H4,H13) -> 0 | I2: =SUM(I4,I13) -> 0 | J2: =SUM(J4,J13) -> 0 | K2: =SUM(K4,K13) -> 0 | L2: =SUM(L4,L13) -> 0
B4: Revenue | E4: € | F4: =SUM(G4:L4) -> 0 | H4: =SUM(H5+H9) -> 0 | I4: =SUM(I5+I9) -> 0 | J4: =SUM(J5+J9) -> 0 | K4: =SUM(K5+K9) -> 0 | L4: =SUM(L5+L9) -> 0
C5: Sales Revenue | E5: € | F5: =SUM(G5:L5) -> 0 | H5: =SUM(H6:H8) -> 0 | I5: =SUM(I6:I8) -> 0 | J5: =SUM(J6:J8) -> 0 | K5: =SUM(K6:K8) -> 0 | L5: =SUM(L6:L8) -> 0
D6: Product Sales Revenue | E6: € | F6: =SUM(G6:L6) -> 0 | H6: ='Step 2.2 - Data Input (Revenue)'!H9*'Step 2.2 - Data Input (Revenue)'!H6 -> 0 | I6: ='Step 2.2 - Data Input (Revenue)'!H10*'Step 2.2 - Data Input (Revenue)'!H6 -> 0 | J6: ='Step 2.2 - Data Input (Revenue)'!H11*'Step 2.2 - Data Input (Revenue)'!H6 -> 0 | K6: ='Step 2.2 - Data Input (Revenue)'!H12*'Step 2.2 - Data Input (Revenue)'!H6 -> 0 | L6: ='Step 2.2 - Data Input (Revenue)'!H13*'Step 2.2 - Data Input (Revenue)'!H6 -> 0
D7: Materials for Recycling Sales Revenue | E7: € | F7: =SUM(G7:L7) -> 0 | H7: ='Step 2.2 - Data Input (Revenue)'!H9*'Step 2.2 - Data Input (Revenue)'!H7 -> 0 | I7: ='Step 2.2 - Data Input (Revenue)'!H10*'Step 2.2 - Data Input (Revenue)'!H7 -> 0 | J7: ='Step 2.2 - Data Input (Revenue)'!H11*'Step 2.2 - Data Input (Revenue)'!H7 -> 0 | K7: ='Step 2.2 - Data Input (Revenue)'!H12*'Step 2.2 - Data Input (Revenue)'!H7 -> 0 | L7: ='Step 2.2 - Data Input (Revenue)'!H13*'Step 2.2 - Data Input (Revenue)'!H7 -> 0
D8: Service Sales Revenue | E8: € | F8: =SUM(G8:L8) -> 0 | H8: ='Step 2.2 - Data Input (Revenue)'!H9*'Step 2.2 - Data Input (Revenue)'!H8 -> 0 | I8: ='Step 2.2 - Data Input (Revenue)'!H10*'Step 2.2 - Data Input (Revenue)'!H8 -> 0 | J8: ='Step 2.2 - Data Input (Revenue)'!H11*'Step 2.2 - Data Input (Revenue)'!H8 -> 0 | K8: ='Step 2.2 - Data Input (Revenue)'!H12*'Step 2.2 - Data Input (Revenue)'!H8 -> 0 | L8: ='Step 2.2 - Data Input (Revenue)'!H13*'Step 2.2 - Data Input (Revenue)'!H8 -> 0
C9: Rental Agreements Revenue | E9: € | F9: =SUM(G9:L9) -> 0 | H9: =H10*'Step 2.2 - Data Input (Revenue)'!H16 -> 0 | I9: =I10*'Step 2.2 - Data Input (Revenue)'!H16 -> 0 | J9: =J10*'Step 2.2 - Data Input (Revenue)'!H16 -> 0 | K9: =K10*'Step 2.2 - Data Input (Revenue)'!H16 -> 0 | L9: =L10*'Step 2.2 - Data Input (Revenue)'!H16 -> 0
D10: Active Rental Agreements | E10: I | H10: ='Step 2.2 - Data Input (Revenue)'!H18 -> 0 | I10: =IF('Step 2.2 - Data Input (Revenue)'!H17>1,'Step 2.2 - Data Input (Revenue)'!H18+'Step 2.2 - Data Input (Revenue)'!H19,'Step 2.2 - Data Input (Revenue)'!H19) -> 0 | J10: {=_xlfn.IFS('Step 2.2 - Data Input (Revenue)'!H17>2, 'Step 2.2 - Data Input (Revenue)'!H18+'Step 2.2 - Data Input (Revenue)'!H19+'Step 2.2 - Data Input (Revenue)'!H20,'Step 2.2 - Data Input (Revenue)'!H17>1,'Step 2.2 - Data Input (Revenue)'!H19+'Step 2.2 - Data Input (Revenue)'!H20, 'Step 2.2 - Data Input (Revenue)'!H17<=1, 'Step 2.2 - Data Input (Revenue)'!H20)} -> 0 | K10: {=_xlfn.IFS('Step 2.2 - Data Input (Revenue)'!H17>3, 'Step 2.2 - Data Input (Revenue)'!H18+'Step 2.2 - Data Input (Revenue)'!H19+'Step 2.2 - Data Input (Revenue)'!H20+ 'Step 2.2 - Data Input (Revenue)'!H21, 'Step 2.2 - Data Input (Revenue)'!H17>2,'Step 2.2 - Data Input (Revenue)'!H19+'Step 2.2 - Data Input (Revenue)'!H20+'Step 2.2 - Data Input (Revenue)'!H21, 'Step 2.2 - Data Input (Revenue)'!H17>1, 'Step 2.2 - Data Input (Revenue)'!H20+'Step 2.2 - Data Input (Revenue)'!H21, 'Step 2.2 - Data Input (Revenue)'!H17<=1, 'Step 2.2 - Data Input (Revenue)'!H21)} -> 0 | L10: {=_xlfn.IFS('Step 2.2 - Data Input (Revenue)'!H17>4, 'Step 2.2 - Data Input (Revenue)'!H18+'Step 2.2 - Data Input (Revenue)'!H19+'Step 2.2 - Data Input (Revenue)'!H20+ 'Step 2.2 - Data Input (Revenue)'!H21+'Step 2.2 - Data Input (Revenue)'!H22, 'Step 2.2 - Data Input (Revenue)'!H17>3,'Step 2.2 - Data Input (Revenue)'!H19+'Step 2.2 - Data Input (Revenue)'!H20+'Step 2.2 - Data Input (Revenue)'!H21+'Step 2.2 - Data Input (Revenue)'!H22, 'Step 2.2 - Data Input (Revenue)'!H17>2, 'Step 2.2 - Data Input (Revenue)'!H20+'Step 2.2 - Data Input (Revenue)'!H21+'Step 2.2 - Data Input (Revenue)'!H22, 'Step 2.2 - Data Input (Revenue)'!H17>1, 'Step 2.2 - Data Input (Revenue)'!H21+'Step 2.2 - Data Input (Revenue)'!H22,'Step 2.2 - Data Input (Revenue)'!H17<=1, 'Step 2.2 - Data Input (Revenue)'!H22)} -> 0
D11: Residual Value after Period of Review | E11: € | F11: =SUM(G11:M11) -> 0 | M11: {=_xlfn.IFS('Step 2.2 - Data Input (Revenue)'!H17>5, (('Step 2.2 - Data Input (Revenue)'!H17-5)*'Step 2.2 - Data Input (Revenue)'!H18+('Step 2.2 - Data Input (Revenue)'!H17-4)*'Step 2.2 - Data Input (Revenue)'!H19+('Step 2.2 - Data Input (Revenue)'!H17-3)*'Step 2.2 - Data Input (Revenue)'!H20+('Step 2.2 - Data Input (Revenue)'!H17-2)*'Step 2.2 - Data Input (Revenue)'!H21+('Step 2.2 - Data Input (Revenue)'!H17-1)*'Step 2.2 - Data Input (Revenue)'!H22)*Annual_Price_Rental_Contract, 'Step 2.2 - Data Input (Revenue)'!H17>4, (('Step 2.2 - Data Input (Revenue)'!H17-4)*'Step 2.2 - Data Input (Revenue)'!H19+('Step 2.2 - Data Input (Revenue)'!H17-3)*'Step 2.2 - Data Input (Revenue)'!H20+('Step 2.2 - Data Input (Revenue)'!H17-2)*'Step 2.2 - Data Input (Revenue)'!H21+('Step 2.2 - Data Input (Revenue)'!H17-1)*'Step 2.2 - Data Input (Revenue)'!H22)*Annual_Price_Rental_Contract, 'Step 2.2 - Data Input (Revenue)'!H17>3, (('Step 2.2 - Data Input (Revenue)'!H17-3)*'Step 2.2 - Data Input (Revenue)'!H20+('Step 2.2 - Data Input (Revenue)'!H17-2)*'Step 2.2 - Data Input (Revenue)'!H21+('Step 2.2 - Data Input (Revenue)'!H17-1)*'Step 2.2 - Data Input (Revenue)'!H22)*Annual_Price_Rental_Contract, 'Step 2.2 - Data Input (Revenue)'!H17>2,(('Step 2.2 - Data Input (Revenue)'!H17-2)*'Step 2.2 - Data Input (Revenue)'!H21+('Step 2.2 - Data Input (Revenue)'!H17-1)*'Step 2.2 - Data Input (Revenue)'!H22)*Annual_Price_Rental_Contract, 'Step 2.2 - Data Input (Revenue)'!H17>1, ('Step 2.2 - Data Input (Revenue)'!H17-1)*'Step 2.2 - Data Input (Revenue)'!H22*Annual_Price_Rental_Contract, 'Step 2.2 - Data Input (Revenue)'!H17<=1, 0)} -> 0
B13: Other positive balance sheet positions | E13: € | F13: =SUM(G13:L13) -> 0 | G13: =SUM(G14:G15) -> 0 | H13: =SUM(H14:H15) -> 0 | I13: =SUM(I14:I15) -> 0 | J13: =SUM(J14:J15) -> 0 | K13: =SUM(K14:K15) -> 0 | L13: =SUM(L14:L15) -> 0
C14: Loans | E14: € | F14: =SUM(G14:L14) -> 0 | G14: ='Step 2.1 - Data Input (General)'!H16 -> 0
C15: Subsidies | E15: € | F15: =SUM(G15:L15) -> 0 | G15: ='Step 2.1 - Data Input (General)'!H12 -> 0 | H15: ='Step 2.1 - Data Input (General)'!H13 -> 0 | I15: ='Step 2.1 - Data Input (General)'!H13 -> 0 | J15: ='Step 2.1 - Data Input (General)'!H13 -> 0 | K15: ='Step 2.1 - Data Input (General)'!H13 -> 0 | L15: ='Step 2.1 - Data Input (General)'!H13 -> 0
A17: CapEx | E17: € | F17: =SUM(G17:L17) -> 0 | G17: =SUM(G19+G24) -> 0
B19: Assets | F19: =SUM(G19:L19) -> 0 | G19: =SUM(G20:G22) -> 0
C20: Tangible Assets | E20: € | F20: =SUM(G20:L20) -> 0 | G20: =SUM('Step 2.3 - Data Input (CapEx)'!H6+'Step 2.3 - Data Input (CapEx)'!H7+'Step 2.3 - Data Input (CapEx)'!G8) -> 0
C21: Intangible Assets | E21: € | F21: =SUM(G21:L21) -> 0 | G21: =SUM('Step 2.3 - Data Input (CapEx)'!H9+'Step 2.3 - Data Input (CapEx)'!H10+'Step 2.3 - Data Input (CapEx)'!H11) -> 0
C22: Equity Holdings | E22: € | F22: =SUM(G22:L22) -> 0 | G22: ='Step 2.3 - Data Input (CapEx)'!H12 -> 0
B24: Comissioning Costs | E24: € | F24: =SUM(G24:L24) -> 0 | G24: =SUM(G25:G28) -> 0
C25: Administrative Staff Costs | E25: € | F25: =SUM(G25:L25) -> 0 | G25: ='Step 2.3 - Data Input (CapEx)'!H16*'Step 2.4 - Data Input (OpEx)'!H7 -> 0
C26: Production Staff Costs | E26: € | F26: =SUM(G26:L26) -> 0 | G26: ='Step 2.3 - Data Input (CapEx)'!H17*'Step 2.4 - Data Input (OpEx)'!H6 -> 0
C27: Research and Development | E27: € | F27: =SUM(G27:L27) -> 0 | G27: ='Step 2.3 - Data Input (CapEx)'!H15 -> 0
C28: Other Comissioning Costs | E28: € | F28: =SUM(G28:L28) -> 0 | G28: ='Step 2.3 - Data Input (CapEx)'!H18 -> 0
A30: OpEx | E30: € | F30: =SUM(G30:L30) -> 0 | H30: =SUM(H32:H33) -> 0 | I30: =SUM(I32:I33) -> 0 | J30: =SUM(J32:J33) -> 0 | K30: =SUM(K32:K33) -> 0 | L30: =SUM(L32:L33) -> 0
B32: Administrative Overhead | E32: € | F32: =SUM(G32:L32) -> 0 | H32: =SUM(H33*'Step 2.1 - Data Input (General)'!H8) -> 0 | I32: =SUM(I33*'Step 2.1 - Data Input (General)'!H8) -> 0 | J32: =SUM(J33*'Step 2.1 - Data Input (General)'!H8) -> 0 | K32: =SUM(K33*'Step 2.1 - Data Input (General)'!H8) -> 0 | L32: =SUM(L33*'Step 2.1 - Data Input (General)'!H8) -> 0
D33: Subtotal OpEx | E33: € | H33: =SUM(H35,H37,H41,H47,H70,H74,H79,H83,H89,H93,H98,H103,H108)+'Step 2.4 - Data Input (OpEx)'!H11 -> 0 | I33: =SUM(I35,I37,I41,I47,I70,I74,I79,I83,I89,I93,I98,I103,I108)+'Step 2.4 - Data Input (OpEx)'!H11 -> 0 | J33: =SUM(J35,J37,J41,J47,J70,J74,J79,J83,J89,J93,J98,J103,J108)+'Step 2.4 - Data Input (OpEx)'!H11 -> 0 | K33: =SUM(K35,K37,K41,K47,K70,K74,K79,K83,K89,K93,K98,K103,K108)+'Step 2.4 - Data Input (OpEx)'!H11 -> 0 | L33: =SUM(L35,L37,L41,L47,L70,L74,L79,L83,L89,L93,L98,L103,L108)+'Step 2.4 - Data Input (OpEx)'!H11 -> 0
B35: Property Costs (exc. Energy) | E35: € | F35: =SUM(G35:L35) -> 0 | H35: ='Step 2.4 - Data Input (OpEx)'!H31+'Step 2.4 - Data Input (OpEx)'!H32+'Step 2.4 - Data Input (OpEx)'!H33 -> 0 | I35: ='Step 2.4 - Data Input (OpEx)'!H31+'Step 2.4 - Data Input (OpEx)'!H32+'Step 2.4 - Data Input (OpEx)'!H33 -> 0 | J35: ='Step 2.4 - Data Input (OpEx)'!H31+'Step 2.4 - Data Input (OpEx)'!H32+'Step 2.4 - Data Input (OpEx)'!H33 -> 0 | K35: ='Step 2.4 - Data Input (OpEx)'!H31+'Step 2.4 - Data Input (OpEx)'!H32+'Step 2.4 - Data Input (OpEx)'!H33 -> 0 | L35: ='Step 2.4 - Data Input (OpEx)'!H31+'Step 2.4 - Data Input (OpEx)'!H32+'Step 2.4 - Data Input (OpEx)'!H33 -> 0
B37: Energy Costs | E37: € | F37: =SUM(G37:L37) -> 0 | H37: =SUM(H38:H39) -> 0 | I37: =SUM(I38:I39) -> 0 | J37: =SUM(J38:J39) -> 0 | K37: =SUM(K38:K39) -> 0 | L37: =SUM(L38:L39) -> 0
C38: Electricity | E38: € | F38: =SUM(G38:L38) -> 0 | H38: =('Step 2.4 - Data Input (OpEx)'!H26+'Step 2.4 - Data Input (OpEx)'!H27*'Step 2.4 - Data Input (OpEx)'!H28)*(1+'Step 2.4 - Data Input (OpEx)'!H16)^0 -> 0 | I38: =('Step 2.4 - Data Input (OpEx)'!H26+'Step 2.4 - Data Input (OpEx)'!H27*'Step 2.4 - Data Input (OpEx)'!H28)*(1+'Step 2.4 - Data Input (OpEx)'!H16)^1 -> 0 | J38: =('Step 2.4 - Data Input (OpEx)'!H26+'Step 2.4 - Data Input (OpEx)'!H27*'Step 2.4 - Data Input (OpEx)'!H28)*(1+'Step 2.4 - Data Input (OpEx)'!H16)^2 -> 0 | K38: =('Step 2.4 - Data Input (OpEx)'!H26+'Step 2.4 - Data Input (OpEx)'!H27*'Step 2.4 - Data Input (OpEx)'!H28)*(1+'Step 2.4 - Data Input (OpEx)'!H16)^3 -> 0 | L38: =('Step 2.4 - Data Input (OpEx)'!H26+'Step 2.4 - Data Input (OpEx)'!H27*'Step 2.4 - Data Input (OpEx)'!H28)*(1+'Step 2.4 - Data Input (OpEx)'!H16)^4 -> 0
C39: Heating (Oil, Gas) | E39: € | F39: =SUM(G39:L39) -> 0 | H39: =('Step 2.4 - Data Input (OpEx)'!H23+'Step 2.4 - Data Input (OpEx)'!H24*'Step 2.4 - Data Input (OpEx)'!H25)*(1+'Step 2.4 - Data Input (OpEx)'!H15)^0 -> 0 | I39: =('Step 2.4 - Data Input (OpEx)'!H23+'Step 2.4 - Data Input (OpEx)'!H24*'Step 2.4 - Data Input (OpEx)'!H25)*(1+'Step 2.4 - Data Input (OpEx)'!H15)^1 -> 0 | J39: =('Step 2.4 - Data Input (OpEx)'!H23+'Step 2.4 - Data Input (OpEx)'!H24*'Step 2.4 - Data Input (OpEx)'!H25)*(1+'Step 2.4 - Data Input (OpEx)'!H15)^2 -> 0 | K39: =('Step 2.4 - Data Input (OpEx)'!H23+'Step 2.4 - Data Input (OpEx)'!H24*'Step 2.4 - Data Input (OpEx)'!H25)*(1+'Step 2.4 - Data Input (OpEx)'!H15)^3 -> 0 | L39: =('Step 2.4 - Data Input (OpEx)'!H23+'Step 2.4 - Data Input (OpEx)'!H24*'Step 2.4 - Data Input (OpEx)'!H25)*(1+'Step 2.4 - Data Input (OpEx)'!H15)^4 -> 0
B41: Linear Production Base Case | E41: € | F41: =SUM(G41:L41) -> 0 | H41: =SUM(H42:H45)+'Step 2.4 - Data Input (OpEx)'!H40 -> 0 | I41: =SUM(I42:I45)+'Step 2.4 - Data Input (OpEx)'!H40 -> 0 | J41: =SUM(J42:J45)+'Step 2.4 - Data Input (OpEx)'!H40 -> 0 | K41: =SUM(K42:K45)+'Step 2.4 - Data Input (OpEx)'!H40 -> 0 | L41: =SUM(L42:L45)+'Step 2.4 - Data Input (OpEx)'!H40 -> 0
C42: Material Costs | E42: € | F42: =SUM(G42:L42) -> 0 | H42: ='Step 2.2 - Data Input (Revenue)'!H9*'Step 2.4 - Data Input (OpEx)'!H36*(1+'Step 2.4 - Data Input (OpEx)'!H14)^0 -> 0 | I42: ='Step 2.2 - Data Input (Revenue)'!H10*'Step 2.4 - Data Input (OpEx)'!H36*(1+'Step 2.4 - Data Input (OpEx)'!H14)^1 -> 0 | J42: ='Step 2.2 - Data Input (Revenue)'!H11*'Step 2.4 - Data Input (OpEx)'!H36*(1+'Step 2.4 - Data Input (OpEx)'!H14)^2 -> 0 | K42: ='Step 2.2 - Data Input (Revenue)'!H12*'Step 2.4 - Data Input (OpEx)'!H36*(1+'Step 2.4 - Data Input (OpEx)'!H14)^3 -> 0 | L42: ='Step 2.2 - Data Input (Revenue)'!H13*'Step 2.4 - Data Input (OpEx)'!H36*(1+'Step 2.4 - Data Input (OpEx)'!H14)^4 -> 0
C43: Disposal Costs | E43: € | F43: =SUM(G43:L43) -> 0 | H43: ='Step 2.2 - Data Input (Revenue)'!H9*'Step 2.4 - Data Input (OpEx)'!H37 -> 0 | I43: ='Step 2.2 - Data Input (Revenue)'!H10*'Step 2.4 - Data Input (OpEx)'!H37 -> 0 | J43: ='Step 2.2 - Data Input (Revenue)'!H11*'Step 2.4 - Data Input (OpEx)'!H37 -> 0 | K43: ='Step 2.2 - Data Input (Revenue)'!H12*'Step 2.4 - Data Input (OpEx)'!H37 -> 0 | L43: ='Step 2.2 - Data Input (Revenue)'!H13*'Step 2.4 - Data Input (OpEx)'!H37 -> 0
C44: Personel Costs | E44: € | F44: =SUM(G44:L44) -> 0 | H44: ='Step 2.2 - Data Input (Revenue)'!H9*('Step 2.4 - Data Input (OpEx)'!H38*'Step 2.4 - Data Input (OpEx)'!H6)*(1-'Step 2.4 - Data Input (OpEx)'!H17)^0 -> 0 | I44: ='Step 2.2 - Data Input (Revenue)'!H10*('Step 2.4 - Data Input (OpEx)'!H38*'Step 2.4 - Data Input (OpEx)'!H6)*(1-'Step 2.4 - Data Input (OpEx)'!H17)^1 -> 0 | J44: ='Step 2.2 - Data Input (Revenue)'!H11*('Step 2.4 - Data Input (OpEx)'!H38*'Step 2.4 - Data Input (OpEx)'!H6)*(1-'Step 2.4 - Data Input (OpEx)'!H17)^2 -> 0 | K44: ='Step 2.2 - Data Input (Revenue)'!H12*('Step 2.4 - Data Input (OpEx)'!H38*'Step 2.4 - Data Input (OpEx)'!H6)*(1-'Step 2.4 - Data Input (OpEx)'!H17)^3 -> 0 | L44: ='Step 2.2 - Data Input (Revenue)'!H13*('Step 2.4 - Data Input (OpEx)'!H38*'Step 2.4 - Data Input (OpEx)'!H6)*(1-'Step 2.4 - Data Input (OpEx)'!H17)^4 -> 0
C45: Machine Costs | E45: € | F45: =SUM(G45:L45) -> 0 | H45: ='Step 2.2 - Data Input (Revenue)'!H9*('Step 2.4 - Data Input (OpEx)'!H39*'Step 2.4 - Data Input (OpEx)'!H8)*(1-'Step 2.4 - Data Input (OpEx)'!H18)^0 -> 0 | I45: ='Step 2.2 - Data Input (Revenue)'!H10*('Step 2.4 - Data Input (OpEx)'!H39*'Step 2.4 - Data Input (OpEx)'!H8)*(1-'Step 2.4 - Data Input (OpEx)'!H18)^1 -> 0 | J45: ='Step 2.2 - Data Input (Revenue)'!H11*('Step 2.4 - Data Input (OpEx)'!H39*'Step 2.4 - Data Input (OpEx)'!H8)*(1-'Step 2.4 - Data Input (OpEx)'!H18)^2 -> 0 | K45: ='Step 2.2 - Data Input (Revenue)'!H12*('Step 2.4 - Data Input (OpEx)'!H39*'Step 2.4 - Data Input (OpEx)'!H8)*(1-'Step 2.4 - Data Input (OpEx)'!H18)^3 -> 0 | L45: ='Step 2.2 - Data Input (Revenue)'!H13*('Step 2.4 - Data Input (OpEx)'!H39*'Step 2.4 - Data Input (OpEx)'!H8)*(1-'Step 2.4 - Data Input (OpEx)'!H18)^4 -> 0
B47: Backward Logistics | E47: € | F47: =SUM(G47:L47) -> 0 | H47: =IF('Step 1 - Case Selection'!V41="as a Flat Rate",H48+H54+Special_Costs_Backward_Logistics,SUM(H48,H55,H61,H68)+Special_Costs_Backward_Logistics) -> 0 | I47: =IF('Step 1 - Case Selection'!V41="as a Flat Rate",I48+I54+Special_Costs_Backward_Logistics,SUM(I48,I55,I61,I68)+Special_Costs_Backward_Logistics) -> 0 | J47: =IF('Step 1 - Case Selection'!V41="as a Flat Rate",J48+J54+Special_Costs_Backward_Logistics,SUM(J48,J55,J61,J68)+Special_Costs_Backward_Logistics) -> 0 | K47: =IF('Step 1 - Case Selection'!V41="as a Flat Rate",K48+K54+Special_Costs_Backward_Logistics,SUM(K48,K55,K61,K68)+Special_Costs_Backward_Logistics) -> 0 | L47: =IF('Step 1 - Case Selection'!V41="as a Flat Rate",L48+L54+Special_Costs_Backward_Logistics,SUM(L48,L55,L61,L68)+Special_Costs_Backward_Logistics) -> 0
D48: Core Premiums | E48: € | F48: =SUM(G48:L48) -> 0 | H48: ='Step 2.4 - Data Input (OpEx)'!H49*(H49+H51) -> 0 | I48: ='Step 2.4 - Data Input (OpEx)'!H49*(I49+I51) -> 0 | J48: ='Step 2.4 - Data Input (OpEx)'!H49*(J49+J51) -> 0 | K48: ='Step 2.4 - Data Input (OpEx)'!H49*(K49+K51) -> 0 | L48: ='Step 2.4 - Data Input (OpEx)'!H49*(L49+L51) -> 0
D49: Required Cores Product Basis (before Sorting) | E49: I | H49: =ROUND(IF('Step 1 - Case Selection'!V27<>"Recycle", 'Step 2.2 - Data Input (Revenue)'!H9/'Step 2.1 - Data Input (General)'!H24*'Step 2.1 - Data Input (General)'!H23, 0),0) -> 0 | I49: =ROUND(IF('Step 1 - Case Selection'!V27<>"Recycle", 'Step 2.2 - Data Input (Revenue)'!H10/'Step 2.1 - Data Input (General)'!H24*'Step 2.1 - Data Input (General)'!H23, 0),0) -> 0 | J49: =ROUND(IF('Step 1 - Case Selection'!V27<>"Recycle", 'Step 2.2 - Data Input (Revenue)'!H11/'Step 2.1 - Data Input (General)'!H24*'Step 2.1 - Data Input (General)'!H23, 0),0) -> 0 | K49: =ROUND(IF('Step 1 - Case Selection'!V27<>"Recycle", 'Step 2.2 - Data Input (Revenue)'!H12/'Step 2.1 - Data Input (General)'!H24*'Step 2.1 - Data Input (General)'!H23, 0),0) -> 0 | L49: =ROUND(IF('Step 1 - Case Selection'!V27<>"Recycle", 'Step 2.2 - Data Input (Revenue)'!H13/'Step 2.1 - Data Input (General)'!H24*'Step 2.1 - Data Input (General)'!H23, 0),0) -> 0
D50: Required Cores Product Basis (after Sorting) | E50: I | H50: =ROUND(IF('Step 1 - Case Selection'!V27<>"Recycle", 'Step 2.2 - Data Input (Revenue)'!H9*'Step 2.1 - Data Input (General)'!H23,0),0) -> 0 | I50: =ROUND(IF('Step 1 - Case Selection'!V27<>"Recycle", 'Step 2.2 - Data Input (Revenue)'!H10*'Step 2.1 - Data Input (General)'!H23,0),0) -> 0 | J50: =ROUND(IF('Step 1 - Case Selection'!V27<>"Recycle", 'Step 2.2 - Data Input (Revenue)'!H11*'Step 2.1 - Data Input (General)'!H23,0),0) -> 0 | K50: =ROUND(IF('Step 1 - Case Selection'!V27<>"Recycle", 'Step 2.2 - Data Input (Revenue)'!H12*'Step 2.1 - Data Input (General)'!H23,0),0) -> 0 | L50: =ROUND(IF('Step 1 - Case Selection'!V27<>"Recycle", 'Step 2.2 - Data Input (Revenue)'!H13*'Step 2.1 - Data Input (General)'!H23,0),0) -> 0
D51: Required Cores Material Basis (before Sorting) | E51: I | H51: =ROUND(IF('Step 1 - Case Selection'!V27="Recycle", 'Step 2.2 - Data Input (Revenue)'!H9/'Step 2.4 - Data Input (OpEx)'!H9/'Step 2.1 - Data Input (General)'!H24,0),0) -> 0 | I51: =ROUND(IF('Step 1 - Case Selection'!V27="Recycle", 'Step 2.2 - Data Input (Revenue)'!H10/'Step 2.4 - Data Input (OpEx)'!H9/'Step 2.1 - Data Input (General)'!H24,0),0) -> 0 | J51: =ROUND(IF('Step 1 - Case Selection'!V27="Recycle", 'Step 2.2 - Data Input (Revenue)'!H11/'Step 2.4 - Data Input (OpEx)'!H9/'Step 2.1 - Data Input (General)'!H24,0),0) -> 0 | K51: =ROUND(IF('Step 1 - Case Selection'!V27="Recycle", 'Step 2.2 - Data Input (Revenue)'!H12/'Step 2.4 - Data Input (OpEx)'!H9/'Step 2.1 - Data Input (General)'!H24,0),0) -> 0 | L51: =ROUND(IF('Step 1 - Case Selection'!V27="Recycle", 'Step 2.2 - Data Input (Revenue)'!H13/'Step 2.4 - Data Input (OpEx)'!H9/'Step 2.1 - Data Input (General)'!H24,0),0) -> 0
D52: Required Cores Material Basis (after Sorting) | E52: I | H52: =ROUND(IF('Step 1 - Case Selection'!V27="Recycle", 'Step 2.2 - Data Input (Revenue)'!H9/'Step 2.4 - Data Input (OpEx)'!H9,0),0) -> 0 | I52: =ROUND(IF('Step 1 - Case Selection'!V27="Recycle", 'Step 2.2 - Data Input (Revenue)'!H10/'Step 2.4 - Data Input (OpEx)'!H9,0),0) -> 0 | J52: =ROUND(IF('Step 1 - Case Selection'!V27="Recycle", 'Step 2.2 - Data Input (Revenue)'!H11/'Step 2.4 - Data Input (OpEx)'!H9,0),0) -> 0 | K52: =ROUND(IF('Step 1 - Case Selection'!V27="Recycle", 'Step 2.2 - Data Input (Revenue)'!H12/'Step 2.4 - Data Input (OpEx)'!H9,0),0) -> 0 | L52: =ROUND(IF('Step 1 - Case Selection'!V27="Recycle", 'Step 2.2 - Data Input (Revenue)'!H13/'Step 2.4 - Data Input (OpEx)'!H9,0),0) -> 0
D53: Ending Rental Agreements | E53: I | H53: =IF('Step 2.2 - Data Input (Revenue)'!H17<=1, 'Step 2.2 - Data Input (Revenue)'!H18, 0) -> 0 | I53: {=_xlfn.IFS('Step 2.2 - Data Input (Revenue)'!H17<=1, 'Step 2.2 - Data Input (Revenue)'!H19, 'Step 2.2 - Data Input (Revenue)'!H17<=2, 'Step 2.2 - Data Input (Revenue)'!H18, 'Step 2.2 - Data Input (Revenue)'!H17>2, 0)} -> 0 | J53: {=_xlfn.IFS('Step 2.2 - Data Input (Revenue)'!H17<=1, 'Step 2.2 - Data Input (Revenue)'!H20, 'Step 2.2 - Data Input (Revenue)'!H17<=2, 'Step 2.2 - Data Input (Revenue)'!H19, 'Step 2.2 - Data Input (Revenue)'!H17<=3, 'Step 2.2 - Data Input (Revenue)'!H18, 'Step 2.2 - Data Input (Revenue)'!H17>3, 0)} -> 0 | K53: {=_xlfn.IFS('Step 2.2 - Data Input (Revenue)'!H17<=1, 'Step 2.2 - Data Input (Revenue)'!H21, 'Step 2.2 - Data Input (Revenue)'!H17<=2, 'Step 2.2 - Data Input (Revenue)'!H20, 'Step 2.2 - Data Input (Revenue)'!H17<=3, 'Step 2.2 - Data Input (Revenue)'!H19, 'Step 2.2 - Data Input (Revenue)'!H17<=4, 'Step 2.2 - Data Input (Revenue)'!H18, 'Step 2.2 - Data Input (Revenue)'!H17>4, 0)} -> 0 | L53: {=_xlfn.IFS('Step 2.2 - Data Input (Revenue)'!H17<=1, 'Step 2.2 - Data Input (Revenue)'!H22, 'Step 2.2 - Data Input (Revenue)'!H17<=2, 'Step 2.2 - Data Input (Revenue)'!H21, 'Step 2.2 - Data Input (Revenue)'!H17<=3, 'Step 2.2 - Data Input (Revenue)'!H20, 'Step 2.2 - Data Input (Revenue)'!H17<=4, 'Step 2.2 - Data Input (Revenue)'!H19, 'Step 2.2 - Data Input (Revenue)'!H17<=5, 'Step 2.2 - Data Input (Revenue)'!H18,'Step 2.2 - Data Input (Revenue)'!H17>5, 0)} -> 0 | M53: =SUM('Step 2.2 - Data Input (Revenue)'!H18+'Step 2.2 - Data Input (Revenue)'!H19+'Step 2.2 - Data Input (Revenue)'!H20+'Step 2.2 - Data Input (Revenue)'!H21+'Step 2.2 - Data Input (Revenue)'!H22-(SUM(H53:L53))) -> 0
C54: Optional Flat Rate Calculation | E54: € | F54: =SUM(G54:L54) -> 0 | H54: ='Step 2.4 - Data Input (OpEx)'!H43*(H49+H51+H53) -> 0 | I54: ='Step 2.4 - Data Input (OpEx)'!H43*(I49+I51+I53) -> 0 | J54: ='Step 2.4 - Data Input (OpEx)'!H43*(J49+J51+J53) -> 0 | K54: ='Step 2.4 - Data Input (OpEx)'!H43*(K49+K51+K53) -> 0 | L54: ='Step 2.4 - Data Input (OpEx)'!H43*(L49+L51+L53) -> 0
C55: Backwards Logistic Sales | E55: € | F55: =SUM(G55:L55) -> 0 | H55: =SUM(H56:H60) -> 0 | I55: =SUM(I56:I60) -> 0 | J55: =SUM(J56:J60) -> 0 | K55: =SUM(K56:K60) -> 0 | L55: =SUM(L56:L60) -> 0
D56: Costs for Direct Pick-Up System | E56: € | F56: =SUM(G56:L56) -> 0 | H56: =IF(BL_Type=1,(H49+H51)*('Step 2.4 - Data Input (OpEx)'!H44*'Step 2.4 - Data Input (OpEx)'!H46)*(1-'Step 2.4 - Data Input (OpEx)'!H19)^0,0) -> 0 | I56: =IF(BL_Type=1,(I49+I51)*('Step 2.4 - Data Input (OpEx)'!H44*'Step 2.4 - Data Input (OpEx)'!H46)*(1-'Step 2.4 - Data Input (OpEx)'!H19)^1,0) -> 0 | J56: =IF(BL_Type=1,(J49+J51)*('Step 2.4 - Data Input (OpEx)'!H44*'Step 2.4 - Data Input (OpEx)'!H46)*(1-'Step 2.4 - Data Input (OpEx)'!H19)^2,0) -> 0 | K56: =IF(BL_Type=1,(K49+K51)*('Step 2.4 - Data Input (OpEx)'!H44*'Step 2.4 - Data Input (OpEx)'!H46)*(1-'Step 2.4 - Data Input (OpEx)'!H19)^3,0) -> 0 | L56: =IF(BL_Type=1,(L49+L51)*('Step 2.4 - Data Input (OpEx)'!H44*'Step 2.4 - Data Input (OpEx)'!H46)*(1-'Step 2.4 - Data Input (OpEx)'!H19)^4,0) -> 0
D57: Costs for Multi-Step Pick-Up System / Step 1 (to CAS) | E57: € | F57: =SUM(G57:L57) -> 0 | H57: =IF(OR(BL_Type=2,BL_Type=3),(H49+H51)*('Step 2.4 - Data Input (OpEx)'!H44*'Step 2.4 - Data Input (OpEx)'!H46)*(1-'Step 2.4 - Data Input (OpEx)'!H19)^0,0) -> 0 | I57: =IF(OR(BL_Type=2,BL_Type=3),(I49+I51)*('Step 2.4 - Data Input (OpEx)'!H44*'Step 2.4 - Data Input (OpEx)'!H46)*(1-'Step 2.4 - Data Input (OpEx)'!H19)^1,0) -> 0 | J57: =IF(OR(BL_Type=2,BL_Type=3),(J49+J51)*('Step 2.4 - Data Input (OpEx)'!H44*'Step 2.4 - Data Input (OpEx)'!H46)*(1-'Step 2.4 - Data Input (OpEx)'!H19)^2,0) -> 0 | K57: =IF(OR(BL_Type=2,BL_Type=3),(K49+K51)*('Step 2.4 - Data Input (OpEx)'!H44*'Step 2.4 - Data Input (OpEx)'!H46)*(1-'Step 2.4 - Data Input (OpEx)'!H19)^3,0) -> 0 | L57: =IF(OR(BL_Type=2,BL_Type=3),(L49+L51)*('Step 2.4 - Data Input (OpEx)'!H44*'Step 2.4 - Data Input (OpEx)'!H46)*(1-'Step 2.4 - Data Input (OpEx)'!H19)^4,0) -> 0
D58: Costs for Multi-Step Pick-Up System / Step 2 (to PS; no Sorting at CAS) | E58: € | F58: =SUM(G58:L58) -> 0 | H58: =IF(BL_Type=2,(H49+H51)*('Step 2.4 - Data Input (OpEx)'!H45*'Step 2.4 - Data Input (OpEx)'!H46)*(1-'Step 2.4 - Data Input (OpEx)'!H19)^0,0) -> 0 | I58: =IF(BL_Type=2,(I49+I51)*('Step 2.4 - Data Input (OpEx)'!H45*'Step 2.4 - Data Input (OpEx)'!H46)*(1-'Step 2.4 - Data Input (OpEx)'!H19)^1,0) -> 0 | J58: =IF(BL_Type=2,(J49+J51)*('Step 2.4 - Data Input (OpEx)'!H45*'Step 2.4 - Data Input (OpEx)'!H46)*(1-'Step 2.4 - Data Input (OpEx)'!H19)^2,0) -> 0 | K58: =IF(BL_Type=2,(K49+K51)*('Step 2.4 - Data Input (OpEx)'!H45*'Step 2.4 - Data Input (OpEx)'!H46)*(1-'Step 2.4 - Data Input (OpEx)'!H19)^3,0) -> 0 | L58: =IF(BL_Type=2,(L49+L51)*('Step 2.4 - Data Input (OpEx)'!H45*'Step 2.4 - Data Input (OpEx)'!H46)*(1-'Step 2.4 - Data Input (OpEx)'!H19)^4,0) -> 0
D59: Costs for Multi-Step Pick-Up System / Step 2 (to PS; Sorting at CAS) | E59: € | F59: =SUM(G59:L59) -> 0 | H59: =IF(BL_Type=3,(H50+H52)*('Step 2.4 - Data Input (OpEx)'!H45*'Step 2.4 - Data Input (OpEx)'!H46)*(1-'Step 2.4 - Data Input (OpEx)'!H19)^0,0) -> 0 | I59: =IF(BL_Type=3,(I50+I52)*('Step 2.4 - Data Input (OpEx)'!H45*'Step 2.4 - Data Input (OpEx)'!H46)*(1-'Step 2.4 - Data Input (OpEx)'!H19)^1,0) -> 0 | J59: =IF(BL_Type=3,(J50+J52)*('Step 2.4 - Data Input (OpEx)'!H45*'Step 2.4 - Data Input (OpEx)'!H46)*(1-'Step 2.4 - Data Input (OpEx)'!H19)^2,0) -> 0 | K59: =IF(BL_Type=3,(K50+K52)*('Step 2.4 - Data Input (OpEx)'!H45*'Step 2.4 - Data Input (OpEx)'!H46)*(1-'Step 2.4 - Data Input (OpEx)'!H19)^3,0) -> 0 | L59: =IF(BL_Type=3,(L50+L52)*('Step 2.4 - Data Input (OpEx)'!H45*'Step 2.4 - Data Input (OpEx)'!H46)*(1-'Step 2.4 - Data Input (OpEx)'!H19)^4,0) -> 0
D60: Costs for Shipment of Cores | E60: € | F60: =SUM(G60:L60) -> 0 | H60: =IF(BL_Type=4,(H49+H51)*('Step 2.4 - Data Input (OpEx)'!H48),0) -> 0 | I60: =IF(BL_Type=4,(I49+I51)*('Step 2.4 - Data Input (OpEx)'!H48),0) -> 0 | J60: =IF(BL_Type=4,(J49+J51)*('Step 2.4 - Data Input (OpEx)'!H48),0) -> 0 | K60: =IF(BL_Type=4,(K49+K51)*('Step 2.4 - Data Input (OpEx)'!H48),0) -> 0 | L60: =IF(BL_Type=4,(L49+L51)*('Step 2.4 - Data Input (OpEx)'!H48),0) -> 0
C61: Backwards Logistic at the End of Rental Agreements | E61: € | F61: =SUM(G61:L61) -> 0 | H61: =SUM(H62:H66) -> 0 | I61: =SUM(I62:I66) -> 0 | J61: =SUM(J62:J66) -> 0 | K61: =SUM(K62:K66) -> 0 | L61: =SUM(L62:L66) -> 0
D62: Costs for Direct Pick-Up System | E62: € | F62: =SUM(G62:L62) -> 0 | H62: =IF(BL_Type=1,H53*('Step 2.4 - Data Input (OpEx)'!H44*'Step 2.4 - Data Input (OpEx)'!H46)*(1-'Step 2.4 - Data Input (OpEx)'!H19)^0,0) -> 0 | I62: =IF(BL_Type=1,I53*('Step 2.4 - Data Input (OpEx)'!H44*'Step 2.4 - Data Input (OpEx)'!H46)*(1-'Step 2.4 - Data Input (OpEx)'!H19)^1,0) -> 0 | J62: =IF(BL_Type=1,J53*('Step 2.4 - Data Input (OpEx)'!H44*'Step 2.4 - Data Input (OpEx)'!H46)*(1-'Step 2.4 - Data Input (OpEx)'!H19)^2,0) -> 0 | K62: =IF(BL_Type=1,K53*('Step 2.4 - Data Input (OpEx)'!H44*'Step 2.4 - Data Input (OpEx)'!H46)*(1-'Step 2.4 - Data Input (OpEx)'!H19)^3,0) -> 0 | L62: =IF(BL_Type=1,L53*('Step 2.4 - Data Input (OpEx)'!H44*'Step 2.4 - Data Input (OpEx)'!H46)*(1-'Step 2.4 - Data Input (OpEx)'!H19)^4,0) -> 0 | M62: =IF(BL_Type=1,M53*('Step 2.4 - Data Input (OpEx)'!H44*'Step 2.4 - Data Input (OpEx)'!H46)*(1-'Step 2.4 - Data Input (OpEx)'!H19)^5,0) -> 0
D63: Costs for Multi-Step Pick-Up System / Step 1 (to CAS) | E63: € | F63: =SUM(G63:L63) -> 0 | H63: =IF(OR(BL_Type=2,BL_Type=3),H53*('Step 2.4 - Data Input (OpEx)'!H44*'Step 2.4 - Data Input (OpEx)'!H46)*(1-'Step 2.4 - Data Input (OpEx)'!H19)^0,0) -> 0 | I63: =IF(OR(BL_Type=2,BL_Type=3),I53*('Step 2.4 - Data Input (OpEx)'!H44*'Step 2.4 - Data Input (OpEx)'!H46)*(1-'Step 2.4 - Data Input (OpEx)'!H19)^1,0) -> 0 | J63: =IF(OR(BL_Type=2,BL_Type=3),J53*('Step 2.4 - Data Input (OpEx)'!H44*'Step 2.4 - Data Input (OpEx)'!H46)*(1-'Step 2.4 - Data Input (OpEx)'!H19)^2,0) -> 0 | K63: =IF(OR(BL_Type=2,BL_Type=3),K53*('Step 2.4 - Data Input (OpEx)'!H44*'Step 2.4 - Data Input (OpEx)'!H46)*(1-'Step 2.4 - Data Input (OpEx)'!H19)^3,0) -> 0 | L63: =IF(OR(BL_Type=2,BL_Type=3),L53*('Step 2.4 - Data Input (OpEx)'!H44*'Step 2.4 - Data Input (OpEx)'!H46)*(1-'Step 2.4 - Data Input (OpEx)'!H19)^4,0) -> 0 | M63: =IF(OR(BL_Type=2,BL_Type=3),M53*('Step 2.4 - Data Input (OpEx)'!H44*'Step 2.4 - Data Input (OpEx)'!H46)*(1-'Step 2.4 - Data Input (OpEx)'!H19)^5,0) -> 0
D64: Costs for Multi-Step Pick-Up System / Step 2 (to PS; no Sorting at CAS) | E64: € | F64: =SUM(G64:L64) -> 0 | H64: =IF(BL_Type=2,H53*('Step 2.4 - Data Input (OpEx)'!H45*'Step 2.4 - Data Input (OpEx)'!H46)*(1-'Step 2.4 - Data Input (OpEx)'!H19)^0,0) -> 0 | I64: =IF(BL_Type=2,I53*('Step 2.4 - Data Input (OpEx)'!H45*'Step 2.4 - Data Input (OpEx)'!H46)*(1-'Step 2.4 - Data Input (OpEx)'!H19)^1,0) -> 0 | J64: =IF(BL_Type=2,J53*('Step 2.4 - Data Input (OpEx)'!H45*'Step 2.4 - Data Input (OpEx)'!H46)*(1-'Step 2.4 - Data Input (OpEx)'!H19)^2,0) -> 0 | K64: =IF(BL_Type=2,K53*('Step 2.4 - Data Input (OpEx)'!H45*'Step 2.4 - Data Input (OpEx)'!H46)*(1-'Step 2.4 - Data Input (OpEx)'!H19)^3,0) -> 0 | L64: =IF(BL_Type=2,L53*('Step 2.4 - Data Input (OpEx)'!H45*'Step 2.4 - Data Input (OpEx)'!H46)*(1-'Step 2.4 - Data Input (OpEx)'!H19)^4,0) -> 0 | M64: =IF(BL_Type=2,M53*('Step 2.4 - Data Input (OpEx)'!H45*'Step 2.4 - Data Input (OpEx)'!H46)*(1-'Step 2.4 - Data Input (OpEx)'!H19)^5,0) -> 0
D65: Costs for Multi-Step Pick-Up System / Step 2 (to PS; Sorting at CAS) | E65: € | F65: =SUM(G65:L65) -> 0 | H65: =IF(BL_Type=3,H53*'Step 2.1 - Data Input (General)'!H24*('Step 2.4 - Data Input (OpEx)'!H45*'Step 2.4 - Data Input (OpEx)'!H46)*(1-'Step 2.4 - Data Input (OpEx)'!H19)^0,0) -> 0 | I65: =IF(BL_Type=3,I53*'Step 2.1 - Data Input (General)'!H24*('Step 2.4 - Data Input (OpEx)'!H45*'Step 2.4 - Data Input (OpEx)'!H46)*(1-'Step 2.4 - Data Input (OpEx)'!H19)^1,0) -> 0 | J65: =IF(BL_Type=3,J53*'Step 2.1 - Data Input (General)'!H24*('Step 2.4 - Data Input (OpEx)'!H45*'Step 2.4 - Data Input (OpEx)'!H46)*(1-'Step 2.4 - Data Input (OpEx)'!H19)^2,0) -> 0 | K65: =IF(BL_Type=3,K53*'Step 2.1 - Data Input (General)'!H24*('Step 2.4 - Data Input (OpEx)'!H45*'Step 2.4 - Data Input (OpEx)'!H46)*(1-'Step 2.4 - Data Input (OpEx)'!H19)^3,0) -> 0 | L65: =IF(BL_Type=3,L53*'Step 2.1 - Data Input (General)'!H24*('Step 2.4 - Data Input (OpEx)'!H45*'Step 2.4 - Data Input (OpEx)'!H46)*(1-'Step 2.4 - Data Input (OpEx)'!H19)^4,0) -> 0 | M65: =IF(BL_Type=3,M53*'Step 2.1 - Data Input (General)'!H24*('Step 2.4 - Data Input (OpEx)'!H45*'Step 2.4 - Data Input (OpEx)'!H46)*(1-'Step 2.4 - Data Input (OpEx)'!H19)^5,0) -> 0
D66: Costs for Shipment of Cores | E66: € | F66: =SUM(G66:L66) -> 0 | H66: =IF(BL_Type=4,H53*('Step 2.4 - Data Input (OpEx)'!H48),0) -> 0 | I66: =IF(BL_Type=4,I53*('Step 2.4 - Data Input (OpEx)'!H48),0) -> 0 | J66: =IF(BL_Type=4,J53*('Step 2.4 - Data Input (OpEx)'!H48),0) -> 0 | K66: =IF(BL_Type=4,K53*('Step 2.4 - Data Input (OpEx)'!H48),0) -> 0 | L66: =IF(BL_Type=4,L53*('Step 2.4 - Data Input (OpEx)'!H48),0) -> 0 | M66: =IF(BL_Type=4,M53*('Step 2.4 - Data Input (OpEx)'!H48),0) -> 0
D67: Pending Backward Logistics Costs after Year 5 | E67: € | F67: =SUM(G67:L67) -> 0 | M67: =SUM(M62:M66) -> 0
C68: Packaging Costs | E68: € | F68: =SUM(G68:L68) -> 0 | H68: ='Step 2.4 - Data Input (OpEx)'!H47*(H49+H51+H53) -> 0 | I68: ='Step 2.4 - Data Input (OpEx)'!H47*(I49+I51+I53) -> 0 | J68: ='Step 2.4 - Data Input (OpEx)'!H47*(J49+J51+J53) -> 0 | K68: ='Step 2.4 - Data Input (OpEx)'!H47*(K49+K51+K53) -> 0 | L68: ='Step 2.4 - Data Input (OpEx)'!H47*(L49+L51+L53) -> 0
B70: Dismantling | E70: € | F70: =SUM(G70:L70) -> 0 | H70: =SUM(H71:H72)+'Step 2.4 - Data Input (OpEx)'!H55 -> 0 | I70: =SUM(I71:I72)+'Step 2.4 - Data Input (OpEx)'!H55 -> 0 | J70: =SUM(J71:J72)+'Step 2.4 - Data Input (OpEx)'!H55 -> 0 | K70: =SUM(K71:K72)+'Step 2.4 - Data Input (OpEx)'!H55 -> 0 | L70: =SUM(L71:L72)+'Step 2.4 - Data Input (OpEx)'!H55 -> 0
C71: Personel Costs | E71: € | F71: =SUM(G71:L71) -> 0 | H71: ='Step 2.4 - Data Input (OpEx)'!H53*'Step 2.4 - Data Input (OpEx)'!H6*(H49+H51)*(1-'Step 2.4 - Data Input (OpEx)'!H17)^0 -> 0 | I71: ='Step 2.4 - Data Input (OpEx)'!H53*'Step 2.4 - Data Input (OpEx)'!H6*(I49+I51)*(1-'Step 2.4 - Data Input (OpEx)'!H17)^1 -> 0 | J71: ='Step 2.4 - Data Input (OpEx)'!H53*'Step 2.4 - Data Input (OpEx)'!H6*(J49+J51)*(1-'Step 2.4 - Data Input (OpEx)'!H17)^2 -> 0 | K71: ='Step 2.4 - Data Input (OpEx)'!H53*'Step 2.4 - Data Input (OpEx)'!H6*(K49+K51)*(1-'Step 2.4 - Data Input (OpEx)'!H17)^3 -> 0 | L71: ='Step 2.4 - Data Input (OpEx)'!H53*'Step 2.4 - Data Input (OpEx)'!H6*(L49+L51)*(1-'Step 2.4 - Data Input (OpEx)'!H17)^4 -> 0
C72: Machine Costs | E72: € | F72: =SUM(G72:L72) -> 0 | H72: ='Step 2.4 - Data Input (OpEx)'!H54*'Step 2.4 - Data Input (OpEx)'!H8*(H49+H51)*(1-'Step 2.4 - Data Input (OpEx)'!H18)^0 -> 0 | I72: ='Step 2.4 - Data Input (OpEx)'!H54*'Step 2.4 - Data Input (OpEx)'!H8*(I49+I51)*(1-'Step 2.4 - Data Input (OpEx)'!H18)^1 -> 0 | J72: ='Step 2.4 - Data Input (OpEx)'!H54*'Step 2.4 - Data Input (OpEx)'!H8*(J49+J51)*(1-'Step 2.4 - Data Input (OpEx)'!H18)^2 -> 0 | K72: ='Step 2.4 - Data Input (OpEx)'!H54*'Step 2.4 - Data Input (OpEx)'!H8*(K49+K51)*(1-'Step 2.4 - Data Input (OpEx)'!H18)^3 -> 0 | L72: ='Step 2.4 - Data Input (OpEx)'!H54*'Step 2.4 - Data Input (OpEx)'!H8*(L49+L51)*(1-'Step 2.4 - Data Input (OpEx)'!H18)^4 -> 0
B74: Identification and Sorting | E74: € | F74: =SUM(G74:L74) -> 0 | H74: =SUM(H75:H77)+'Step 2.4 - Data Input (OpEx)'!H61 -> 0 | I74: =SUM(I75:I77)+'Step 2.4 - Data Input (OpEx)'!H61 -> 0 | J74: =SUM(J75:J77)+'Step 2.4 - Data Input (OpEx)'!H61 -> 0 | K74: =SUM(K75:K77)+'Step 2.4 - Data Input (OpEx)'!H61 -> 0 | L74: =SUM(L75:L77)+'Step 2.4 - Data Input (OpEx)'!H61 -> 0
C75: Personel Costs | E75: € | F75: =SUM(G75:L75) -> 0 | H75: ='Step 2.4 - Data Input (OpEx)'!H58*'Step 2.4 - Data Input (OpEx)'!H6*(H49+H51)*(1-'Step 2.4 - Data Input (OpEx)'!H17)^0 -> 0 | I75: ='Step 2.4 - Data Input (OpEx)'!H58*'Step 2.4 - Data Input (OpEx)'!H6*(I49+I51)*(1-'Step 2.4 - Data Input (OpEx)'!H17)^1 -> 0 | J75: ='Step 2.4 - Data Input (OpEx)'!H58*'Step 2.4 - Data Input (OpEx)'!H6*(J49+J51)*(1-'Step 2.4 - Data Input (OpEx)'!H17)^2 -> 0 | K75: ='Step 2.4 - Data Input (OpEx)'!H58*'Step 2.4 - Data Input (OpEx)'!H6*(K49+K51)*(1-'Step 2.4 - Data Input (OpEx)'!H17)^3 -> 0 | L75: ='Step 2.4 - Data Input (OpEx)'!H58*'Step 2.4 - Data Input (OpEx)'!H6*(L49+L51)*(1-'Step 2.4 - Data Input (OpEx)'!H17)^4 -> 0
C76: Machine Costs | E76: € | F76: =SUM(G76:L76) -> 0 | H76: ='Step 2.4 - Data Input (OpEx)'!H59*'Step 2.4 - Data Input (OpEx)'!H8*(H49+H51)*(1-'Step 2.4 - Data Input (OpEx)'!H18)^0 -> 0 | I76: ='Step 2.4 - Data Input (OpEx)'!H59*'Step 2.4 - Data Input (OpEx)'!H8*(I49+I51)*(1-'Step 2.4 - Data Input (OpEx)'!H18)^1 -> 0 | J76: ='Step 2.4 - Data Input (OpEx)'!H59*'Step 2.4 - Data Input (OpEx)'!H8*(J49+J51)*(1-'Step 2.4 - Data Input (OpEx)'!H18)^2 -> 0 | K76: ='Step 2.4 - Data Input (OpEx)'!H59*'Step 2.4 - Data Input (OpEx)'!H8*(K49+K51)*(1-'Step 2.4 - Data Input (OpEx)'!H18)^3 -> 0 | L76: ='Step 2.4 - Data Input (OpEx)'!H59*'Step 2.4 - Data Input (OpEx)'!H8*(L49+L51)*(1-'Step 2.4 - Data Input (OpEx)'!H18)^4 -> 0
C77: Disposal Costs Cores | E77: € | F77: =SUM(G77:L77) -> 0 | H77: ='Step 2.4 - Data Input (OpEx)'!H60*((H49-H50)+(H51-H52)) -> 0 | I77: ='Step 2.4 - Data Input (OpEx)'!H60*((I49-I50)+(I51-I52)) -> 0 | J77: ='Step 2.4 - Data Input (OpEx)'!H60*((J49-J50)+(J51-J52)) -> 0 | K77: ='Step 2.4 - Data Input (OpEx)'!H60*((K49-K50)+(K51-K52)) -> 0 | L77: ='Step 2.4 - Data Input (OpEx)'!H60*((L49-L50)+(L51-L52)) -> 0
B79: Disassembly | E79: € | F79: =SUM(G79:L79) -> 0 | H79: =SUM(H80:H81)+'Step 2.4 - Data Input (OpEx)'!H66 -> 0 | I79: =SUM(I80:I81)+'Step 2.4 - Data Input (OpEx)'!H66 -> 0 | J79: =SUM(J80:J81)+'Step 2.4 - Data Input (OpEx)'!H66 -> 0 | K79: =SUM(K80:K81)+'Step 2.4 - Data Input (OpEx)'!H66 -> 0 | L79: =SUM(L80:L81)+'Step 2.4 - Data Input (OpEx)'!H66 -> 0
C80: Personel Costs | E80: € | F80: =SUM(G80:L80) -> 0 | H80: ='Step 2.4 - Data Input (OpEx)'!H64*'Step 2.4 - Data Input (OpEx)'!H6*(H50+H52)*(1-'Step 2.4 - Data Input (OpEx)'!H17)^0 -> 0 | I80: ='Step 2.4 - Data Input (OpEx)'!H64*'Step 2.4 - Data Input (OpEx)'!H6*(I50+I52)*(1-'Step 2.4 - Data Input (OpEx)'!H17)^1 -> 0 | J80: ='Step 2.4 - Data Input (OpEx)'!H64*'Step 2.4 - Data Input (OpEx)'!H6*(J50+J52)*(1-'Step 2.4 - Data Input (OpEx)'!H17)^2 -> 0 | K80: ='Step 2.4 - Data Input (OpEx)'!H64*'Step 2.4 - Data Input (OpEx)'!H6*(K50+K52)*(1-'Step 2.4 - Data Input (OpEx)'!H17)^3 -> 0 | L80: ='Step 2.4 - Data Input (OpEx)'!H64*'Step 2.4 - Data Input (OpEx)'!H6*(L50+L52)*(1-'Step 2.4 - Data Input (OpEx)'!H17)^4 -> 0
C81: Machine Costs | E81: € | F81: =SUM(G81:L81) -> 0 | H81: ='Step 2.4 - Data Input (OpEx)'!H65*'Step 2.4 - Data Input (OpEx)'!H8*(H50+H52)*(1-'Step 2.4 - Data Input (OpEx)'!H18)^0 -> 0 | I81: ='Step 2.4 - Data Input (OpEx)'!H65*'Step 2.4 - Data Input (OpEx)'!H8*(I50+I52)*(1-'Step 2.4 - Data Input (OpEx)'!H18)^1 -> 0 | J81: ='Step 2.4 - Data Input (OpEx)'!H65*'Step 2.4 - Data Input (OpEx)'!H8*(J50+J52)*(1-'Step 2.4 - Data Input (OpEx)'!H18)^2 -> 0 | K81: ='Step 2.4 - Data Input (OpEx)'!H65*'Step 2.4 - Data Input (OpEx)'!H8*(K50+K52)*(1-'Step 2.4 - Data Input (OpEx)'!H18)^3 -> 0 | L81: ='Step 2.4 - Data Input (OpEx)'!H65*'Step 2.4 - Data Input (OpEx)'!H8*(L50+L52)*(1-'Step 2.4 - Data Input (OpEx)'!H18)^4 -> 0
B83: Inspection | E83: € | F83: =SUM(G83:L83) -> 0 | H83: =SUM(H84:H87)+'Step 2.4 - Data Input (OpEx)'!H75 -> 0 | I83: =SUM(I84:I87)+'Step 2.4 - Data Input (OpEx)'!H75 -> 0 | J83: =SUM(J84:J87)+'Step 2.4 - Data Input (OpEx)'!H75 -> 0 | K83: =SUM(K84:K87)+'Step 2.4 - Data Input (OpEx)'!H75 -> 0 | L83: =SUM(L84:L87)+'Step 2.4 - Data Input (OpEx)'!H75 -> 0
C84: Personel Costs | E84: € | F84: =SUM(G84:L84) -> 0 | H84: ='Step 2.4 - Data Input (OpEx)'!H69*'Step 2.4 - Data Input (OpEx)'!H6*(H50)*(1-'Step 2.4 - Data Input (OpEx)'!H17)^0 -> 0 | I84: ='Step 2.4 - Data Input (OpEx)'!H69*'Step 2.4 - Data Input (OpEx)'!H6*(I50)*(1-'Step 2.4 - Data Input (OpEx)'!H17)^1 -> 0 | J84: ='Step 2.4 - Data Input (OpEx)'!H69*'Step 2.4 - Data Input (OpEx)'!H6*(J50)*(1-'Step 2.4 - Data Input (OpEx)'!H17)^2 -> 0 | K84: ='Step 2.4 - Data Input (OpEx)'!H69*'Step 2.4 - Data Input (OpEx)'!H6*(K50)*(1-'Step 2.4 - Data Input (OpEx)'!H17)^3 -> 0 | L84: ='Step 2.4 - Data Input (OpEx)'!H69*'Step 2.4 - Data Input (OpEx)'!H6*(L50)*(1-'Step 2.4 - Data Input (OpEx)'!H17)^4 -> 0
C85: Machine Costs | E85: € | F85: =SUM(G85:L85) -> 0 | H85: ='Step 2.4 - Data Input (OpEx)'!H70*'Step 2.4 - Data Input (OpEx)'!H8*(H50)*(1-'Step 2.4 - Data Input (OpEx)'!H18)^0 -> 0 | I85: ='Step 2.4 - Data Input (OpEx)'!H70*'Step 2.4 - Data Input (OpEx)'!H8*(I50)*(1-'Step 2.4 - Data Input (OpEx)'!H18)^1 -> 0 | J85: ='Step 2.4 - Data Input (OpEx)'!H70*'Step 2.4 - Data Input (OpEx)'!H8*(J50)*(1-'Step 2.4 - Data Input (OpEx)'!H18)^2 -> 0 | K85: ='Step 2.4 - Data Input (OpEx)'!H70*'Step 2.4 - Data Input (OpEx)'!H8*(K50)*(1-'Step 2.4 - Data Input (OpEx)'!H18)^3 -> 0 | L85: ='Step 2.4 - Data Input (OpEx)'!H70*'Step 2.4 - Data Input (OpEx)'!H8*(L50)*(1-'Step 2.4 - Data Input (OpEx)'!H18)^4 -> 0
C86: Disposal Costs Scrap Components | E86: € | F86: =SUM(G86:L86) -> 0 | H86: ='Step 2.4 - Data Input (OpEx)'!H74*'Step 2.4 - Data Input (OpEx)'!H73*'Step 2.4 - Data Input (OpEx)'!H72*(H50+H52) -> 0 | I86: ='Step 2.4 - Data Input (OpEx)'!H74*'Step 2.4 - Data Input (OpEx)'!H73*'Step 2.4 - Data Input (OpEx)'!H72*(I50+I52) -> 0 | J86: ='Step 2.4 - Data Input (OpEx)'!H74*'Step 2.4 - Data Input (OpEx)'!H73*'Step 2.4 - Data Input (OpEx)'!H72*(J50+J52) -> 0 | K86: ='Step 2.4 - Data Input (OpEx)'!H74*'Step 2.4 - Data Input (OpEx)'!H73*'Step 2.4 - Data Input (OpEx)'!H72*(K50+K52) -> 0 | L86: ='Step 2.4 - Data Input (OpEx)'!H74*'Step 2.4 - Data Input (OpEx)'!H73*'Step 2.4 - Data Input (OpEx)'!H72*(L50+L52) -> 0
C87: Disposal Costs Not Reusable Components | E87: € | F87: =SUM(G87:L87) -> 0 | H87: ='Step 2.4 - Data Input (OpEx)'!H74*'Step 2.4 - Data Input (OpEx)'!H71*(H50+H52) -> 0 | I87: ='Step 2.4 - Data Input (OpEx)'!H74*'Step 2.4 - Data Input (OpEx)'!H71*(I50+I52) -> 0 | J87: ='Step 2.4 - Data Input (OpEx)'!H74*'Step 2.4 - Data Input (OpEx)'!H71*(J50+J52) -> 0 | K87: ='Step 2.4 - Data Input (OpEx)'!H74*'Step 2.4 - Data Input (OpEx)'!H71*(K50+K52) -> 0 | L87: ='Step 2.4 - Data Input (OpEx)'!H74*'Step 2.4 - Data Input (OpEx)'!H71*(L50+L52) -> 0
B89: Cleaning | E89: € | F89: =SUM(G89:L89) -> 0 | H89: =SUM(H90:H91)+'Step 2.4 - Data Input (OpEx)'!H80 -> 0 | I89: =SUM(I90:I91)+'Step 2.4 - Data Input (OpEx)'!H80 -> 0 | J89: =SUM(J90:J91)+'Step 2.4 - Data Input (OpEx)'!H80 -> 0 | K89: =SUM(K90:K91)+'Step 2.4 - Data Input (OpEx)'!H80 -> 0 | L89: =SUM(L90:L91)+'Step 2.4 - Data Input (OpEx)'!H80 -> 0
C90: Personel Costs | E90: € | F90: =SUM(G90:L90) -> 0 | H90: ='Step 2.4 - Data Input (OpEx)'!H78*'Step 2.4 - Data Input (OpEx)'!H6*(H50)*(1-'Step 2.4 - Data Input (OpEx)'!H17)^0 -> 0 | I90: ='Step 2.4 - Data Input (OpEx)'!H78*'Step 2.4 - Data Input (OpEx)'!H6*(I50)*(1-'Step 2.4 - Data Input (OpEx)'!H17)^1 -> 0 | J90: ='Step 2.4 - Data Input (OpEx)'!H78*'Step 2.4 - Data Input (OpEx)'!H6*(J50)*(1-'Step 2.4 - Data Input (OpEx)'!H17)^2 -> 0 | K90: ='Step 2.4 - Data Input (OpEx)'!H78*'Step 2.4 - Data Input (OpEx)'!H6*(K50)*(1-'Step 2.4 - Data Input (OpEx)'!H17)^3 -> 0 | L90: ='Step 2.4 - Data Input (OpEx)'!H78*'Step 2.4 - Data Input (OpEx)'!H6*(L50)*(1-'Step 2.4 - Data Input (OpEx)'!H17)^4 -> 0
C91: Machine Costs | E91: € | F91: =SUM(G91:L91) -> 0 | H91: ='Step 2.4 - Data Input (OpEx)'!H79*'Step 2.4 - Data Input (OpEx)'!H8*(H50)*(1-'Step 2.4 - Data Input (OpEx)'!H18)^0 -> 0 | I91: ='Step 2.4 - Data Input (OpEx)'!H79*'Step 2.4 - Data Input (OpEx)'!H8*(I50)*(1-'Step 2.4 - Data Input (OpEx)'!H18)^1 -> 0 | J91: ='Step 2.4 - Data Input (OpEx)'!H79*'Step 2.4 - Data Input (OpEx)'!H8*(J50)*(1-'Step 2.4 - Data Input (OpEx)'!H18)^2 -> 0 | K91: ='Step 2.4 - Data Input (OpEx)'!H79*'Step 2.4 - Data Input (OpEx)'!H8*(K50)*(1-'Step 2.4 - Data Input (OpEx)'!H18)^3 -> 0 | L91: ='Step 2.4 - Data Input (OpEx)'!H79*'Step 2.4 - Data Input (OpEx)'!H8*(L50)*(1-'Step 2.4 - Data Input (OpEx)'!H18)^4 -> 0
B93: Restoring | E93: € | F93: =SUM(G93:L93) -> 0 | H93: =SUM(H94:H96)+'Step 2.4 - Data Input (OpEx)'!H86 -> 0 | I93: =SUM(I94:I96)+'Step 2.4 - Data Input (OpEx)'!H86 -> 0 | J93: =SUM(J94:J96)+'Step 2.4 - Data Input (OpEx)'!H86 -> 0 | K93: =SUM(K94:K96)+'Step 2.4 - Data Input (OpEx)'!H86 -> 0 | L93: =SUM(L94:L96)+'Step 2.4 - Data Input (OpEx)'!H86 -> 0
C94: Personel Costs | E94: € | F94: =SUM(G94:L94) -> 0 | H94: ='Step 2.4 - Data Input (OpEx)'!H83*'Step 2.4 - Data Input (OpEx)'!H6*(H50)*(1-'Step 2.4 - Data Input (OpEx)'!H17)^0 -> 0 | I94: ='Step 2.4 - Data Input (OpEx)'!H89*'Step 2.4 - Data Input (OpEx)'!H6*(I50)*(1-'Step 2.4 - Data Input (OpEx)'!H17)^1 -> 0 | J94: ='Step 2.4 - Data Input (OpEx)'!H83*'Step 2.4 - Data Input (OpEx)'!H6*(J50)*(1-'Step 2.4 - Data Input (OpEx)'!H17)^2 -> 0 | K94: ='Step 2.4 - Data Input (OpEx)'!H83*'Step 2.4 - Data Input (OpEx)'!H6*(K50)*(1-'Step 2.4 - Data Input (OpEx)'!H17)^3 -> 0 | L94: ='Step 2.4 - Data Input (OpEx)'!H83*'Step 2.4 - Data Input (OpEx)'!H6*(L50)*(1-'Step 2.4 - Data Input (OpEx)'!H17)^4 -> 0
C95: Machine Costs | E95: € | F95: =SUM(G95:L95) -> 0 | H95: =Automated_Labour_Restoring*'Step 2.4 - Data Input (OpEx)'!H8*(H50)*(1-'Step 2.4 - Data Input (OpEx)'!H18)^0 -> 0 | I95: ='Step 2.4 - Data Input (OpEx)'!H84*'Step 2.4 - Data Input (OpEx)'!H8*(I50)*(1-'Step 2.4 - Data Input (OpEx)'!H18)^1 -> 0 | J95: ='Step 2.4 - Data Input (OpEx)'!H84*'Step 2.4 - Data Input (OpEx)'!H8*(J50)*(1-'Step 2.4 - Data Input (OpEx)'!H18)^2 -> 0 | K95: ='Step 2.4 - Data Input (OpEx)'!H84*'Step 2.4 - Data Input (OpEx)'!H8*(K50)*(1-'Step 2.4 - Data Input (OpEx)'!H18)^3 -> 0 | L95: ='Step 2.4 - Data Input (OpEx)'!H84*'Step 2.4 - Data Input (OpEx)'!H8*(L50)*(1-'Step 2.4 - Data Input (OpEx)'!H18)^4 -> 0
C96: Material Costs (e.g. Paints) | E96: € | F96: =SUM(G96:L96) -> 0 | H96: ='Step 2.4 - Data Input (OpEx)'!H85*H50*(1+'Step 2.4 - Data Input (OpEx)'!H14)^0 -> 0 | I96: ='Step 2.4 - Data Input (OpEx)'!H85*I50*(1+'Step 2.4 - Data Input (OpEx)'!H14)^1 -> 0 | J96: ='Step 2.4 - Data Input (OpEx)'!H85*J50*(1+'Step 2.4 - Data Input (OpEx)'!H14)^2 -> 0 | K96: ='Step 2.4 - Data Input (OpEx)'!H85*K50*(1+'Step 2.4 - Data Input (OpEx)'!H14)^3 -> 0 | L96: ='Step 2.4 - Data Input (OpEx)'!H85*L50*(1+'Step 2.4 - Data Input (OpEx)'!H14)^4 -> 0
B98: Assembly | E98: € | F98: =SUM(G98:L98) -> 0 | H98: =SUM(H99:H101)+'Step 2.4 - Data Input (OpEx)'!H93 -> 0 | I98: =SUM(I99:I101)+'Step 2.4 - Data Input (OpEx)'!H93 -> 0 | J98: =SUM(J99:J101)+'Step 2.4 - Data Input (OpEx)'!H93 -> 0 | K98: =SUM(K99:K101)+'Step 2.4 - Data Input (OpEx)'!H93 -> 0 | L98: =SUM(L99:L101)+'Step 2.4 - Data Input (OpEx)'!H93 -> 0
C99: Personel Costs | E99: € | F99: =SUM(G99:L99) -> 0 | H99: ='Step 2.4 - Data Input (OpEx)'!H89*'Step 2.4 - Data Input (OpEx)'!H6*('Step 2.2 - Data Input (Revenue)'!H9)*(1-'Step 2.4 - Data Input (OpEx)'!H17)^0 -> 0 | I99: ='Step 2.4 - Data Input (OpEx)'!H89*'Step 2.4 - Data Input (OpEx)'!H6*('Step 2.2 - Data Input (Revenue)'!H10)*(1-'Step 2.4 - Data Input (OpEx)'!H17)^1 -> 0 | J99: ='Step 2.4 - Data Input (OpEx)'!H89*'Step 2.4 - Data Input (OpEx)'!H6*('Step 2.2 - Data Input (Revenue)'!H11)*(1-'Step 2.4 - Data Input (OpEx)'!H17)^2 -> 0 | K99: ='Step 2.4 - Data Input (OpEx)'!H89*'Step 2.4 - Data Input (OpEx)'!H6*('Step 2.2 - Data Input (Revenue)'!H12)*(1-'Step 2.4 - Data Input (OpEx)'!H17)^3 -> 0 | L99: ='Step 2.4 - Data Input (OpEx)'!H89*'Step 2.4 - Data Input (OpEx)'!H6*('Step 2.2 - Data Input (Revenue)'!H13)*(1-'Step 2.4 - Data Input (OpEx)'!H17)^4 -> 0
C100: Machine Costs | E100: € | F100: =SUM(G100:L100) -> 0 | H100: ='Step 2.4 - Data Input (OpEx)'!H90*'Step 2.4 - Data Input (OpEx)'!H8*('Step 2.2 - Data Input (Revenue)'!H9)*(1-'Step 2.4 - Data Input (OpEx)'!H18)^0 -> 0 | I100: ='Step 2.4 - Data Input (OpEx)'!H90*'Step 2.4 - Data Input (OpEx)'!H8*('Step 2.2 - Data Input (Revenue)'!H10)*(1-'Step 2.4 - Data Input (OpEx)'!H18)^1 -> 0 | J100: ='Step 2.4 - Data Input (OpEx)'!H90*'Step 2.4 - Data Input (OpEx)'!H8*('Step 2.2 - Data Input (Revenue)'!H11)*(1-'Step 2.4 - Data Input (OpEx)'!H18)^2 -> 0 | K100: ='Step 2.4 - Data Input (OpEx)'!H90*'Step 2.4 - Data Input (OpEx)'!H8*('Step 2.2 - Data Input (Revenue)'!H12)*(1-'Step 2.4 - Data Input (OpEx)'!H18)^3 -> 0 | L100: ='Step 2.4 - Data Input (OpEx)'!H90*'Step 2.4 - Data Input (OpEx)'!H8*('Step 2.2 - Data Input (Revenue)'!H13)*(1-'Step 2.4 - Data Input (OpEx)'!H18)^4 -> 0
C101: Material Costs (e.g. Spare Parts) | E101: € | F101: =SUM(G101:L101) -> 0 | H101: =('Step 2.4 - Data Input (OpEx)'!H91+'Step 2.4 - Data Input (OpEx)'!H92)*'Step 2.2 - Data Input (Revenue)'!H9*(1+'Step 2.4 - Data Input (OpEx)'!H14)^0 -> 0 | I101: =('Step 2.4 - Data Input (OpEx)'!H91+'Step 2.4 - Data Input (OpEx)'!H92)*'Step 2.2 - Data Input (Revenue)'!H10*(1+'Step 2.4 - Data Input (OpEx)'!H14)^1 -> 0 | J101: =('Step 2.4 - Data Input (OpEx)'!H91+'Step 2.4 - Data Input (OpEx)'!H92)*'Step 2.2 - Data Input (Revenue)'!H11*(1+'Step 2.4 - Data Input (OpEx)'!H14)^2 -> 0 | K101: =('Step 2.4 - Data Input (OpEx)'!H91+'Step 2.4 - Data Input (OpEx)'!H92)*'Step 2.2 - Data Input (Revenue)'!H12*(1+'Step 2.4 - Data Input (OpEx)'!H14)^3 -> 0 | L101: =('Step 2.4 - Data Input (OpEx)'!H91+'Step 2.4 - Data Input (OpEx)'!H92)*'Step 2.2 - Data Input (Revenue)'!H13*(1+'Step 2.4 - Data Input (OpEx)'!H14)^4 -> 0
B103: Testing | E103: € | F103: =SUM(G103:L103) -> 0 | H103: =SUM(H104:H105)+'Step 2.4 - Data Input (OpEx)'!H99 -> 0 | I103: =SUM(I104:I105)+'Step 2.4 - Data Input (OpEx)'!H99 -> 0 | J103: =SUM(J104:J105)+'Step 2.4 - Data Input (OpEx)'!H99 -> 0 | K103: =SUM(K104:K105)+'Step 2.4 - Data Input (OpEx)'!H99 -> 0 | L103: =SUM(L104:L105)+'Step 2.4 - Data Input (OpEx)'!H99 -> 0
C104: Personel Costs | E104: € | F104: =SUM(G104:L104) -> 0 | H104: ='Step 2.4 - Data Input (OpEx)'!H96*'Step 2.4 - Data Input (OpEx)'!H6*('Step 2.2 - Data Input (Revenue)'!H9)*(1-'Step 2.4 - Data Input (OpEx)'!H17)^0 -> 0 | I104: ='Step 2.4 - Data Input (OpEx)'!H96*'Step 2.4 - Data Input (OpEx)'!H6*('Step 2.2 - Data Input (Revenue)'!H10)*(1-'Step 2.4 - Data Input (OpEx)'!H17)^1 -> 0 | J104: ='Step 2.4 - Data Input (OpEx)'!H96*'Step 2.4 - Data Input (OpEx)'!H6*('Step 2.2 - Data Input (Revenue)'!H11)*(1-'Step 2.4 - Data Input (OpEx)'!H17)^2 -> 0 | K104: ='Step 2.4 - Data Input (OpEx)'!H96*'Step 2.4 - Data Input (OpEx)'!H6*('Step 2.2 - Data Input (Revenue)'!H12)*(1-'Step 2.4 - Data Input (OpEx)'!H17)^3 -> 0 | L104: ='Step 2.4 - Data Input (OpEx)'!H96*'Step 2.4 - Data Input (OpEx)'!H6*('Step 2.2 - Data Input (Revenue)'!H13)*(1-'Step 2.4 - Data Input (OpEx)'!H17)^4 -> 0
C105: Machine Costs | E105: € | F105: =SUM(G105:L105) -> 0 | H105: ='Step 2.4 - Data Input (OpEx)'!H97*'Step 2.4 - Data Input (OpEx)'!H8*('Step 2.2 - Data Input (Revenue)'!H9)*(1-'Step 2.4 - Data Input (OpEx)'!H18)^0 -> 0 | I105: ='Step 2.4 - Data Input (OpEx)'!H97*'Step 2.4 - Data Input (OpEx)'!H8*('Step 2.2 - Data Input (Revenue)'!H10)*(1-'Step 2.4 - Data Input (OpEx)'!H18)^1 -> 0 | J105: ='Step 2.4 - Data Input (OpEx)'!H97*'Step 2.4 - Data Input (OpEx)'!H8*('Step 2.2 - Data Input (Revenue)'!H11)*(1-'Step 2.4 - Data Input (OpEx)'!H18)^2 -> 0 | K105: ='Step 2.4 - Data Input (OpEx)'!H97*'Step 2.4 - Data Input (OpEx)'!H8*('Step 2.2 - Data Input (Revenue)'!H12)*(1-'Step 2.4 - Data Input (OpEx)'!H18)^3 -> 0 | L105: ='Step 2.4 - Data Input (OpEx)'!H97*'Step 2.4 - Data Input (OpEx)'!H8*('Step 2.2 - Data Input (Revenue)'!H13)*(1-'Step 2.4 - Data Input (OpEx)'!H18)^4 -> 0
C106: Certification Costs | E106: € | F106: =SUM(G106:L106) -> 0 | H106: ='Step 2.4 - Data Input (OpEx)'!H98*'Step 2.2 - Data Input (Revenue)'!H9 -> 0 | I106: ='Step 2.4 - Data Input (OpEx)'!H98*'Step 2.2 - Data Input (Revenue)'!H10 -> 0 | J106: ='Step 2.4 - Data Input (OpEx)'!H98*'Step 2.2 - Data Input (Revenue)'!H11 -> 0 | K106: ='Step 2.4 - Data Input (OpEx)'!H98*'Step 2.2 - Data Input (Revenue)'!H12 -> 0 | L106: ='Step 2.4 - Data Input (OpEx)'!H98*'Step 2.2 - Data Input (Revenue)'!H13 -> 0
B108: Forward Logistics | E108: € | F108: =SUM(G108:L108) -> 0 | H108: =IF('Step 1 - Case Selection'!V51="as a Flat Rate",H109+'Step 2.4 - Data Input (OpEx)'!H108,SUM(H110:H113)+'Step 2.4 - Data Input (OpEx)'!H108) -> 0 | I108: =IF('Step 1 - Case Selection'!V51="as a Flat Rate",I109+'Step 2.4 - Data Input (OpEx)'!H108,SUM(I110:I113)+'Step 2.4 - Data Input (OpEx)'!H108) -> 0 | J108: =IF('Step 1 - Case Selection'!V51="as a Flat Rate",J109+'Step 2.4 - Data Input (OpEx)'!H108,SUM(J110:J113)+'Step 2.4 - Data Input (OpEx)'!H108) -> 0 | K108: =IF('Step 1 - Case Selection'!V51="as a Flat Rate",K109+'Step 2.4 - Data Input (OpEx)'!H108,SUM(K110:K113)+'Step 2.4 - Data Input (OpEx)'!H108) -> 0 | L108: =IF('Step 1 - Case Selection'!V51="as a Flat Rate",L109+'Step 2.4 - Data Input (OpEx)'!H108,SUM(L110:L113)+'Step 2.4 - Data Input (OpEx)'!H108) -> 0
C109: Optional Flat Rate Calculation | E109: € | F109: =SUM(G109:L109) -> 0 | H109: ='Step 2.4 - Data Input (OpEx)'!H102*('Step 2.2 - Data Input (Revenue)'!H9+'Step 2.2 - Data Input (Revenue)'!H18) -> 0 | I109: ='Step 2.4 - Data Input (OpEx)'!H102*('Step 2.2 - Data Input (Revenue)'!H10+'Step 2.2 - Data Input (Revenue)'!H19) -> 0 | J109: ='Step 2.4 - Data Input (OpEx)'!H102*('Step 2.2 - Data Input (Revenue)'!H11+'Step 2.2 - Data Input (Revenue)'!H20) -> 0 | K109: ='Step 2.4 - Data Input (OpEx)'!H102*('Step 2.2 - Data Input (Revenue)'!H12+'Step 2.2 - Data Input (Revenue)'!H21) -> 0 | L109: ='Step 2.4 - Data Input (OpEx)'!H102*('Step 2.2 - Data Input (Revenue)'!H13+'Step 2.2 - Data Input (Revenue)'!H22) -> 0
C110: Delivery Costs | E110: € | F110: =SUM(G110:L110) -> 0 | H110: =IF(FL_Type=1,'Step 2.4 - Data Input (OpEx)'!H103*'Step 2.4 - Data Input (OpEx)'!H105*('Step 2.2 - Data Input (Revenue)'!H9+'Step 2.2 - Data Input (Revenue)'!H18)*(1-'Step 2.4 - Data Input (OpEx)'!H20)^0,0) -> 0 | I110: =IF(FL_Type=1, 'Step 2.4 - Data Input (OpEx)'!H103*'Step 2.4 - Data Input (OpEx)'!H105*('Step 2.2 - Data Input (Revenue)'!H10+'Step 2.2 - Data Input (Revenue)'!H19)*(1-'Step 2.4 - Data Input (OpEx)'!H20)^1,0) -> 0 | J110: =IF(FL_Type=1, 'Step 2.4 - Data Input (OpEx)'!H103*'Step 2.4 - Data Input (OpEx)'!H105*('Step 2.2 - Data Input (Revenue)'!H11+'Step 2.2 - Data Input (Revenue)'!H20)*(1-'Step 2.4 - Data Input (OpEx)'!H20)^2,0) -> 0 | K110: =IF(FL_Type=1, 'Step 2.4 - Data Input (OpEx)'!H103*'Step 2.4 - Data Input (OpEx)'!H105*('Step 2.2 - Data Input (Revenue)'!H12+'Step 2.2 - Data Input (Revenue)'!H21)*(1-'Step 2.4 - Data Input (OpEx)'!H20)^3,0) -> 0 | L110: =IF(FL_Type=1, 'Step 2.4 - Data Input (OpEx)'!H103*'Step 2.4 - Data Input (OpEx)'!H105*('Step 2.2 - Data Input (Revenue)'!H13+'Step 2.2 - Data Input (Revenue)'!H22)*(1-'Step 2.4 - Data Input (OpEx)'!H20)^4,0) -> 0
C111: Shipment Costs | E111: € | F111: =SUM(G111:L111) -> 0 | H111: =IF(FL_Type=2,'Step 2.4 - Data Input (OpEx)'!H107*('Step 2.2 - Data Input (Revenue)'!H9+'Step 2.2 - Data Input (Revenue)'!H18),0) -> 0 | I111: =IF(FL_Type=2,'Step 2.4 - Data Input (OpEx)'!H107*('Step 2.2 - Data Input (Revenue)'!H10+'Step 2.2 - Data Input (Revenue)'!H19),0) -> 0 | J111: =IF(FL_Type=2,'Step 2.4 - Data Input (OpEx)'!H107*('Step 2.2 - Data Input (Revenue)'!H11+'Step 2.2 - Data Input (Revenue)'!H20),0) -> 0 | K111: =IF(FL_Type=2,'Step 2.4 - Data Input (OpEx)'!H107*('Step 2.2 - Data Input (Revenue)'!H12+'Step 2.2 - Data Input (Revenue)'!H21),0) -> 0 | L111: =IF(FL_Type=2,'Step 2.4 - Data Input (OpEx)'!H107*('Step 2.2 - Data Input (Revenue)'!H13+'Step 2.2 - Data Input (Revenue)'!H22),0) -> 0
C112: Customer Site Repair Logstics | E112: € | F112: =SUM(G112:L112) -> 0 | H112: =IF(FL_Type=3, 'Step 2.4 - Data Input (OpEx)'!H103*'Step 2.4 - Data Input (OpEx)'!H105*'Step 2.2 - Data Input (Revenue)'!H9*'Step 2.4 - Data Input (OpEx)'!H104*(1-'Step 2.4 - Data Input (OpEx)'!H20)^0,0) -> 0 | I112: =IF(FL_Type=3, 'Step 2.4 - Data Input (OpEx)'!H103*'Step 2.4 - Data Input (OpEx)'!H105*'Step 2.2 - Data Input (Revenue)'!H10*'Step 2.4 - Data Input (OpEx)'!H104*(1-'Step 2.4 - Data Input (OpEx)'!H20)^1,0) -> 0 | J112: =IF(FL_Type=3, 'Step 2.4 - Data Input (OpEx)'!H103*'Step 2.4 - Data Input (OpEx)'!H105*'Step 2.2 - Data Input (Revenue)'!H11*'Step 2.4 - Data Input (OpEx)'!H104*(1-'Step 2.4 - Data Input (OpEx)'!H20)^2,0) -> 0 | K112: =IF(FL_Type=3, 'Step 2.4 - Data Input (OpEx)'!H103*'Step 2.4 - Data Input (OpEx)'!H105*'Step 2.2 - Data Input (Revenue)'!H12*'Step 2.4 - Data Input (OpEx)'!H104*(1-'Step 2.4 - Data Input (OpEx)'!H20)^3,0) -> 0 | L112: =IF(FL_Type=3, 'Step 2.4 - Data Input (OpEx)'!H103*'Step 2.4 - Data Input (OpEx)'!H105*'Step 2.2 - Data Input (Revenue)'!H13*'Step 2.4 - Data Input (OpEx)'!H104*(1-'Step 2.4 - Data Input (OpEx)'!H20)^4,0) -> 0
C113: Packaging Costs | E113: € | F113: =SUM(G113:L113) -> 0 | H113: ='Step 2.4 - Data Input (OpEx)'!H106*('Step 2.2 - Data Input (Revenue)'!H9+'Step 2.2 - Data Input (Revenue)'!H18) -> 0 | I113: ='Step 2.4 - Data Input (OpEx)'!H106*('Step 2.2 - Data Input (Revenue)'!H10+'Step 2.2 - Data Input (Revenue)'!H19) -> 0 | J113: ='Step 2.4 - Data Input (OpEx)'!H106*('Step 2.2 - Data Input (Revenue)'!H11+'Step 2.2 - Data Input (Revenue)'!H20) -> 0 | K113: ='Step 2.4 - Data Input (OpEx)'!H106*('Step 2.2 - Data Input (Revenue)'!H12+'Step 2.2 - Data Input (Revenue)'!H21) -> 0 | L113: ='Step 2.4 - Data Input (OpEx)'!H106*('Step 2.2 - Data Input (Revenue)'!H13+'Step 2.2 - Data Input (Revenue)'!H22) -> 0
A115: Financing costs | E115: € | F115: =SUM(G115:L115) -> 0 | H115: =SUM(H117) -> 0 | I115: =SUM(I117) -> 0 | J115: =SUM(J117) -> 0 | K115: =SUM(K117) -> 0 | L115: =SUM(L117) -> 0
B117: Loans | E117: € | F117: =SUM(H117:L117) -> 0 | H117: =SUM(H118:H119) -> 0 | I117: =SUM(I118:I119) -> 0 | J117: =SUM(J118:J119) -> 0 | K117: =SUM(K118:K119) -> 0 | L117: =SUM(L118:L119) -> 0
